Workbook
Name ADRESSE: #REF!
Name COMPTE_TRESORERIE: PARAMETRES!$G$18:$G$29
Name DOCUMENT: PARAMETRES!#REF!
Name ENTITE: PARAMETRES!$A$4:$A$11
Name ID_BC_UNIQUE: 'CARNET CDE FATURE PFO 2025'!$E$6:$E$303
Name ID_BC_UNIQUE: 'CARNET DE COMMANDE'!$D$6:$D$350
Name Montant_BC: 'CARNET CDE FATURE PFO 2025'!$G$5:INDEX('CARNET CDE FATURE PFO 2025'!$F:$F,COUNTA('CARNET CDE FATURE PFO 2025'!$F:$F)+4)
Name Montant_BC: 'CARNET DE COMMANDE'!$I$5:INDEX('CARNET DE COMMANDE'!$E:$E,COUNTA('CARNET DE COMMANDE'!$E:$E)+4)
Name N°_BC: Tableau5[ACTIONS A MENER]
Name N°_BC: #REF!
Name NCC: #REF!
Name Nom_BC: 'CARNET CDE FATURE PFO 2025'!$C$5:INDEX('CARNET CDE FATURE PFO 2025'!$D:$D,COUNTA('CARNET CDE FATURE PFO 2025'!$D:$D)+4)
Name Nom_BC: 'CARNET DE COMMANDE'!#REF!:INDEX('CARNET DE COMMANDE'!#REF!,COUNTA('CARNET DE COMMANDE'!#REF!)+4)
Name NOM_CLIENT: 'CLIENTS-CREANCES'!$B$5:$B$21
Name Nom_TClient: #REF!
Name RAISON: #REF!
Name SIEGE: #REF!
Name SIM_GROUP: PARAMETRES!$A$5:$A$9
Name TELEPHONE: #REF!
Name TYPE_DE_BON_DE_COMMANDE_CLIENT: PARAMETRES!#REF!

Sheet PARAMETRES
G1: CONDITION DE REGLEMENT CLIENTS | K1: ACTION DE RECOUVREMENT
A3: ENTITE | C3: CODE PROJET | D3: PROJET/CHANTIER | G3: CLIENT | H3: CONDITION DE PAIEMENT | I3: N° BC | K3: NOMBRE DE JOUR DE RETARD | L3: ACTIONS A MENER
A4: KENAM S | C4: 654R8002 | D4: VRD UNIVERSITE ODIENNE TX | G4: PFO | H4: 30 JOURS DATE DE RECEPTION | I4: LOCATION ENGIN ACHAT FER BETON, GRAVIER, SABLE | K4: 10 | L4: FAIRE 1ERE RELANCE
A5: BTTP | C5: 006G4101 | D5: ATELIER SONGON CHARGES ACT LOCAT° | G5: KOIRA BTP | H5: 30 JOURS DATE DE RECEPTION | I5: ACHAT FER BETON | K5: 20 | L5: FAIRE 2EME RELANCE
A6: DG_FF | C6: 007G4101 | D6: ATELIER DIVO CHARGE ACT LOC EXT | G6: KOIRA BTP | H6: 15 JOURS MAX DATE DE RECEPTION | I6: LOCATION ENGINN | K6: 35 | L6: FAIRE 3EME RELANCE
C7: 009G4101 | D7: ATELIER BOUAKE CHARGE ACT LOCAT° EXT | G7: AFRIK BETON | H7: 40 JOURS DATE DE RECEPTION | I7: LOCATION CAMION PLATEAU | K7: 60 | L7: OUVRIR UN LITIGE
C8: 010G4101 | D8: ATELIER COTIERE CHARGES ACT LOCAT° EXT | G8: SOGENA
C9: 011G4101 | D9: ATELIER DABAKALA CHARGRES ACT LOC E | G9: M IBRAHIM SALHAB
C10: 015G3114 | D10: ATELIER KONG CHARGE ACT LOCATION | G10: KOIRA SA | H10: 30 JOURS DATE DE RECEPTION | I10: ACHAT FER BETON
C11: 015G4101 | D11: ATELIER KONG CHARGE ACT LOCAT° EXT | G11: BETEC-CI | H11: 30 JOURS DATE DE RECEPTION | K11: INTERVALLE BALANCE
C12: 016G4101 | D12: ATELIER BINGERVILLE SM LOCATION EXTERNES | G12: SCORE | H12: 30 JOURS DATE DE RECEPTION | I12: ACHAT MATERIAUX
C13: 017G4101 | D13: ATELIER PETIT NASS. KT SM LOCAT° | G13: SOGIMAS | K13: NOMBRE DE JOUR DE RETARD | L13: INTERVALLE DE BALANCE | M13: Colonne1
C14: 018G4101 | D14: ATELIER KORHOGO SM LOCATION EXTERNES | K14: 0 | L14: [0;29]
C15: 019G3110 | D15: ATELIER ODIENNE CHARGE FG PRESTATAIRE | L15: 30 | M15: [30;59]
C16: 019G4101 | D16: ATELIER ODIENNE CHARGE ACT LOC EXT | L16: 60 | M16: [60;89]
C17: 019R4101 | D17: ATELIER ODIENNE CHARGE ACT LOC EXT | G17: COMPTE TRESORERIE | H17: TYPE MONNAIE | I17: NATURE DE LA MONNAIE | L17: 90 | M17: [90;120]
C18: 021G4101 | D18: SNA PEDRO SOUBRE LOCATION EXTERNE | G18: BDU | H18: SCRIPTURALE | I18: CHEQUE_VIREMENT_CARTE | L18: 120 | M18: >120
C19: 022G4101 | D19: SOUBRE LOCATION EXTERNES POUR LE SE | G19: BDU | H19: SCRIPTURALE | I19: CHEQUE_VIREMENT_CARTE
C20: 170R2101 | D20: FERMETURE AKOUEDO-TX REMOD V. P. CANNIVEAUX | G20: BICICI | H20: SCRIPTURALE | I20: CHEQUE_VIREMENT_CARTE
C21: 251B0206 | D21: VILLA 20 GROS ŒUVRE MACONNERIE | G21: NSIA | H21: SCRIPTURALE | I21: CHEQUE_VIREMENT_CARTE
C22: 252B0209 | D22: REHAB. TOUR C GROS ŒUVRE M. OE | G22: ECOBANK | H22: SCRIPTURALE | I22: CHEQUE_VIREMENT_CARTE
C23: 252B0402 | D23: REHAB. TOUR C CHARPENTE COUVERTURE M | G23: UBA | H23: FIDUCIAIRE | I23: BILLET_ESPECES | K23: Terminologie correcte selon la situation
C24: 255R1001 | D24: TX PROLONGEMENT BD MITTERAND-INST ENTREP | G24: CAISSE | H24: ELECTRONIQUE | I24: TRANSACTIONS VIA APPLICATION
C25: 255R8002 | D25: TX PROLONGEMENT BD MITTERAND-TX MAD ENGIN | G25: CAISSE | H25: ELECTRONIQUE | I25: TRANSACTIONS VIA APPLICATION | K25: Situation réelle | L25: Terme professionnel
C26: 257B0001 | D26: COMPLEXE RES KONG RES KONG GLE FRS | G26: BDU | K26: Échue et non payée | L26: IMPAYÉE
C27: 257B0003 | D27: COMPLEXE RES KONG GLE INST CHANT | G27: BICICI | K27: Échue et partiellement payée | L27: PARTIELLEMENT IMPAYÉE ou PAIEMENT PARTIEL
C28: 257B0005 | D28: COMPLEXE RES. KONG GLE | G28: NSIA | K28: Non échue | L28: NON ÉCHUE
C29: 257B0101 | D29: COMPLEXE RESIDENTIEL-KONG-AMENAGEMENT EXT TERRASSEMENT | G29: SGCI | K29: Totalement payée | L29: PAYÉE
C30: 257B0104 | D30: COMPLEXE RESIDENTIEL KONG-VRD VOIRIE CHE | K30: Annulée | L30: FACTURE ANNULÉE
C31: 257B0105 | D31: COMPLEXE RES KONG AMENAGT EX RESEA E
C32: 257B0109 | D32: COMPLEXE RES. KONG AMENGT EXT P
C33: 257B0200 | D33: COMPLEXE RESIDENTIEL-KONG GROS ŒUVRE GL
C34: 257B0203 | D34: COMPLEXE RESIDENTIEL KONG-GROS ŒUVRE FONDATION
C35: 257B0206 | D35: COMPLEXE RES. KONG GROS ŒUVRE MACO
C36: 257B0207 | D36: COMPLEXE RESIDENTIEL KONG-GROS ŒUVRE M.O
C37: 257B0209 | D37: COMPLEXE RESIDENTIEL-KONG-GROS ŒUVRE DRAINAGE
C38: 257B0403 | D38: COMPLEXE RESIDENTIEL KONG-CHARPENTE COUVERTURE BOIS-05 VILLAS FAMILLE
C39: 257B0504 | D39: COMPLEXE RES. KONG REVT FASCADES M.
C40: 257B0801 | D40: COMPLEXE RES. KONG CLOISON DOUBLAGE
C41: 261B0200 | D41: MUSEE DE COCODY GROS ŒUVRE GL
C42: 305R8002 | D42: ROUTE DABAKALA-KONG TX MAD ENGIN
... C62: 444B1802 | D62: UNIVERSITE D'ODIENNE DEBOURS CENT
C64: Total | D64: =SUBTOTAL(103,Tableau24[PROJET/CHANTIER]) -> 59

Sheet CLIENTS-CREANCES
M1: PERIODE DEFINIE | N1: 45658 | O1: 46387
A2: =+"LISTE DES CLIENTS ET DES CREANCES "&YEAR($O$1) -> LISTE DES CLIENTS ET DES CREANCES 2026
A4: ENTITE | B4: NOM CLIENT | C4: CATEGORIE | D4: NUMERO | E4: REGIME FISCALE | F4: BOITE POSTALE | G4: LOCALISATION | H4: TELEPHONE | I4: ACTIVITE | J4: CORRESPONDANT | K4: SOLDE REPORTE | L4: SOLDE N-1 | M4: MONTANT DU | N4: MONTANT RECOUVRE | O4: SOLDE N
A5: KENAM S | B5: AFRIK BETON | C5: ENTREPRISE | F5: 01 BP 5676 ABIDJAN 01 | G5: Abidjan, Yopougon, Zone industrielle, Lots N°14, 14 bis et N°564, Ilot N°56, | H5: 27 21 22 22 21 | L5: =+SUMIFS(Tableau6[NET A PAYER],Tableau6[CLIENT],Tableau1[[#This Row],[NOM CLIENT]],Tableau6[DATE DE FACTURATION],"<"&'CLIENTS-CREANCES'!$N$1)-SUMIFS(Tableau6[MONTANT PAYE],Tableau6[CLIENT],Tableau1[[#This Row],[NOM CLIENT]],Tableau6[DATE DE FACTURATION],"<"&'CLIENTS-CREANCES'!$N$1) -> 0 | M5: =SUMIFS(Tableau6[NET A PAYER],Tableau6[CLIENT],Tableau1[[#This Row],[NOM CLIENT]],Tableau6[DATE DE FACTURATION],">="&'CLIENTS-CREANCES'!$N$1,Tableau6[DATE DE FACTURATION],"<="&'CLIENTS-CREANCES'!$O$1) -> 4519400 | N5: =SUMIFS(Tableau3[MONTANT TTC],Tableau3[CLIENTS],Tableau1[[#This Row],[NOM CLIENT]],Tableau3[[DATE DE PAIEMENT ]],">="&'CLIENTS-CREANCES'!$N$1,Tableau3[[DATE DE PAIEMENT ]],"<="&'CLIENTS-CREANCES'!$O$1) -> 4519400 | O5: =+SUMIFS(Tableau6[NET A PAYER],Tableau6[CLIENT],Tableau1[[#This Row],[NOM CLIENT]],Tableau6[DATE DE DEPOT],"<="&'CLIENTS-CREANCES'!$O$1)-SUMIFS(Tableau3[MONTANT TTC],Tableau3[CLIENTS],Tableau1[[#This Row],[NOM CLIENT]],Tableau3[[DATE DE PAIEMENT ]],"<="&'CLIENTS-CREANCES'!$O$1) -> 0
A6: KENAM S | B6: BETEC-CI | C6: ENTREPRISE | D6: 1600297 K | F6: 16 BP 387 ABIDJAN 16 | G6: SOCOPRIX – RIVIERA TRIANGLE – IMMEUBLE TECHNIBAT 1er Etage | H6: 27 22 54 54 41 | I6: GENIE CIVIL | L6: =+SUMIFS(Tableau6[NET A PAYER],Tableau6[CLIENT],Tableau1[[#This Row],[NOM CLIENT]],Tableau6[DATE DE FACTURATION],"<"&'CLIENTS-CREANCES'!$N$1)-SUMIFS(Tableau6[MONTANT PAYE],Tableau6[CLIENT],Tableau1[[#This Row],[NOM CLIENT]],Tableau6[DATE DE FACTURATION],"<"&'CLIENTS-CREANCES'!$N$1) -> 0 | M6: =SUMIFS(Tableau6[NET A PAYER],Tableau6[CLIENT],Tableau1[[#This Row],[NOM CLIENT]],Tableau6[DATE DE FACTURATION],">="&'CLIENTS-CREANCES'!$N$1,Tableau6[DATE DE FACTURATION],"<="&'CLIENTS-CREANCES'!$O$1) -> 3465070 | N6: =SUMIFS(Tableau3[MONTANT TTC],Tableau3[CLIENTS],Tableau1[[#This Row],[NOM CLIENT]],Tableau3[[DATE DE PAIEMENT ]],">="&'CLIENTS-CREANCES'!$N$1,Tableau3[[DATE DE PAIEMENT ]],"<="&'CLIENTS-CREANCES'!$O$1) -> 3465070 | O6: =+SUMIFS(Tableau6[NET A PAYER],Tableau6[CLIENT],Tableau1[[#This Row],[NOM CLIENT]],Tableau6[DATE DE DEPOT],"<="&'CLIENTS-CREANCES'!$O$1)-SUMIFS(Tableau3[MONTANT TTC],Tableau3[CLIENTS],Tableau1[[#This Row],[NOM CLIENT]],Tableau3[[DATE DE PAIEMENT ]],"<="&'CLIENTS-CREANCES'!$O$1) -> 0
A7: KENAM S | B7: KOIRA BTP | C7: ENTREPRISE | D7: 1924576 J | F7: 03 BP 2176 ABIDJAN 03 | G7: Abidjan, Vridi Rue Pointe des Fumeurs | H7: 27 21 27 49 80/27 21 27 49 81 | I7: GENIE CIVIL | L7: =+SUMIFS(Tableau6[NET A PAYER],Tableau6[CLIENT],Tableau1[[#This Row],[NOM CLIENT]],Tableau6[DATE DE FACTURATION],"<"&'CLIENTS-CREANCES'!$N$1)-SUMIFS(Tableau6[MONTANT PAYE],Tableau6[CLIENT],Tableau1[[#This Row],[NOM CLIENT]],Tableau6[DATE DE FACTURATION],"<"&'CLIENTS-CREANCES'!$N$1) -> 0 | M7: =SUMIFS(Tableau6[NET A PAYER],Tableau6[CLIENT],Tableau1[[#This Row],[NOM CLIENT]],Tableau6[DATE DE FACTURATION],">="&'CLIENTS-CREANCES'!$N$1,Tableau6[DATE DE FACTURATION],"<="&'CLIENTS-CREANCES'!$O$1) -> 207498939 | N7: =SUMIFS(Tableau3[MONTANT TTC],Tableau3[CLIENTS],Tableau1[[#This Row],[NOM CLIENT]],Tableau3[[DATE DE PAIEMENT ]],">="&'CLIENTS-CREANCES'!$N$1,Tableau3[[DATE DE PAIEMENT ]],"<="&'CLIENTS-CREANCES'!$O$1) -> 200572342 | O7: =+SUMIFS(Tableau6[NET A PAYER],Tableau6[CLIENT],Tableau1[[#This Row],[NOM CLIENT]],Tableau6[DATE DE DEPOT],"<="&'CLIENTS-CREANCES'!$O$1)-SUMIFS(Tableau3[MONTANT TTC],Tableau3[CLIENTS],Tableau1[[#This Row],[NOM CLIENT]],Tableau3[[DATE DE PAIEMENT ]],"<="&'CLIENTS-CREANCES'!$O$1) -> 6926597
A8: KENAM S | B8: KOIRA SA | C8: ENTREPRISE | D8: 0818080 A | F8: 03 BP 2176 Abidjan 03 | G8: Rue des Points aux Fumeurs - Zone Industrielle Vridi | H8: 27 21 27 49 81 | I8: Commerce général de produits importés | L8: =+SUMIFS(Tableau6[NET A PAYER],Tableau6[CLIENT],Tableau1[[#This Row],[NOM CLIENT]],Tableau6[DATE DE FACTURATION],"<"&'CLIENTS-CREANCES'!$N$1)-SUMIFS(Tableau6[MONTANT PAYE],Tableau6[CLIENT],Tableau1[[#This Row],[NOM CLIENT]],Tableau6[DATE DE FACTURATION],"<"&'CLIENTS-CREANCES'!$N$1) -> 0 | M8: =SUMIFS(Tableau6[NET A PAYER],Tableau6[CLIENT],Tableau1[[#This Row],[NOM CLIENT]],Tableau6[DATE DE FACTURATION],">="&'CLIENTS-CREANCES'!$N$1,Tableau6[DATE DE FACTURATION],"<="&'CLIENTS-CREANCES'!$O$1) -> 6926600 | N8: =SUMIFS(Tableau3[MONTANT TTC],Tableau3[CLIENTS],Tableau1[[#This Row],[NOM CLIENT]],Tableau3[[DATE DE PAIEMENT ]],">="&'CLIENTS-CREANCES'!$N$1,Tableau3[[DATE DE PAIEMENT ]],"<="&'CLIENTS-CREANCES'!$O$1) -> 6926600 | O8: =+SUMIFS(Tableau6[NET A PAYER],Tableau6[CLIENT],Tableau1[[#This Row],[NOM CLIENT]],Tableau6[DATE DE DEPOT],"<="&'CLIENTS-CREANCES'!$O$1)-SUMIFS(Tableau3[MONTANT TTC],Tableau3[CLIENTS],Tableau1[[#This Row],[NOM CLIENT]],Tableau3[[DATE DE PAIEMENT ]],"<="&'CLIENTS-CREANCES'!$O$1) -> 0
A9: KENAM S | B9: M IBRAHIM SALHAB | C9: PARTICULIER | L9: =+SUMIFS(Tableau6[NET A PAYER],Tableau6[CLIENT],Tableau1[[#This Row],[NOM CLIENT]],Tableau6[DATE DE FACTURATION],"<"&'CLIENTS-CREANCES'!$N$1)-SUMIFS(Tableau6[MONTANT PAYE],Tableau6[CLIENT],Tableau1[[#This Row],[NOM CLIENT]],Tableau6[DATE DE FACTURATION],"<"&'CLIENTS-CREANCES'!$N$1) -> 0 | M9: =SUMIFS(Tableau6[NET A PAYER],Tableau6[CLIENT],Tableau1[[#This Row],[NOM CLIENT]],Tableau6[DATE DE FACTURATION],">="&'CLIENTS-CREANCES'!$N$1,Tableau6[DATE DE FACTURATION],"<="&'CLIENTS-CREANCES'!$O$1) -> 1711838 | N9: =SUMIFS(Tableau3[MONTANT TTC],Tableau3[CLIENTS],Tableau1[[#This Row],[NOM CLIENT]],Tableau3[[DATE DE PAIEMENT ]],">="&'CLIENTS-CREANCES'!$N$1,Tableau3[[DATE DE PAIEMENT ]],"<="&'CLIENTS-CREANCES'!$O$1) -> 1566766.8 | O9: =+SUMIFS(Tableau6[NET A PAYER],Tableau6[CLIENT],Tableau1[[#This Row],[NOM CLIENT]],Tableau6[DATE DE DEPOT],"<="&'CLIENTS-CREANCES'!$O$1)-SUMIFS(Tableau3[MONTANT TTC],Tableau3[CLIENTS],Tableau1[[#This Row],[NOM CLIENT]],Tableau3[[DATE DE PAIEMENT ]],"<="&'CLIENTS-CREANCES'!$O$1) -> 145071.2
A10: KENAM S | B10: PFO CONSTRUCTION | C10: ENTREPRISE | D10: 1205106 C | E10: RNI | F10: 16 BP 387 ABIDJAN 16 | G10: ABIDJAN COCODY BD LATRILLE APRES SODEMI | H10: 27 22 48 45 45 | I10: GENIE CIVIL | L10: =+SUMIFS(Tableau6[NET A PAYER],Tableau6[CLIENT],Tableau1[[#This Row],[NOM CLIENT]],Tableau6[DATE DE FACTURATION],"<"&'CLIENTS-CREANCES'!$N$1)-SUMIFS(Tableau6[MONTANT PAYE],Tableau6[CLIENT],Tableau1[[#This Row],[NOM CLIENT]],Tableau6[DATE DE FACTURATION],"<"&'CLIENTS-CREANCES'!$N$1) -> 0 | M10: =SUMIFS(Tableau6[NET A PAYER],Tableau6[CLIENT],Tableau1[[#This Row],[NOM CLIENT]],Tableau6[DATE DE FACTURATION],">="&'CLIENTS-CREANCES'!$N$1,Tableau6[DATE DE FACTURATION],"<="&'CLIENTS-CREANCES'!$O$1) -> 2341765664 | N10: =SUMIFS(Tableau3[MONTANT TTC],Tableau3[CLIENTS],Tableau1[[#This Row],[NOM CLIENT]],Tableau3[[DATE DE PAIEMENT ]],">="&'CLIENTS-CREANCES'!$N$1,Tableau3[[DATE DE PAIEMENT ]],"<="&'CLIENTS-CREANCES'!$O$1) -> 2470682140 | O10: =+SUMIFS(Tableau6[NET A PAYER],Tableau6[CLIENT],Tableau1[[#This Row],[NOM CLIENT]],Tableau6[DATE DE DEPOT],"<="&'CLIENTS-CREANCES'!$O$1)-SUMIFS(Tableau3[MONTANT TTC],Tableau3[CLIENTS],Tableau1[[#This Row],[NOM CLIENT]],Tableau3[[DATE DE PAIEMENT ]],"<="&'CLIENTS-CREANCES'!$O$1) -> -128916476
A11: KENAM S | B11: SCORE | C11: ENTREPRISE | D11: 1332571 T | G11: Cocody Angré 7ieme Tranche, Abidjan, Cote d'Ivoire | I11: Route et voirie | L11: =+SUMIFS(Tableau6[NET A PAYER],Tableau6[CLIENT],Tableau1[[#This Row],[NOM CLIENT]],Tableau6[DATE DE FACTURATION],"<"&'CLIENTS-CREANCES'!$N$1)-SUMIFS(Tableau6[MONTANT PAYE],Tableau6[CLIENT],Tableau1[[#This Row],[NOM CLIENT]],Tableau6[DATE DE FACTURATION],"<"&'CLIENTS-CREANCES'!$N$1) -> 0 | M11: =SUMIFS(Tableau6[NET A PAYER],Tableau6[CLIENT],Tableau1[[#This Row],[NOM CLIENT]],Tableau6[DATE DE FACTURATION],">="&'CLIENTS-CREANCES'!$N$1,Tableau6[DATE DE FACTURATION],"<="&'CLIENTS-CREANCES'!$O$1) -> 2336400 | N11: =SUMIFS(Tableau3[MONTANT TTC],Tableau3[CLIENTS],Tableau1[[#This Row],[NOM CLIENT]],Tableau3[[DATE DE PAIEMENT ]],">="&'CLIENTS-CREANCES'!$N$1,Tableau3[[DATE DE PAIEMENT ]],"<="&'CLIENTS-CREANCES'!$O$1) -> 2336400 | O11: =+SUMIFS(Tableau6[NET A PAYER],Tableau6[CLIENT],Tableau1[[#This Row],[NOM CLIENT]],Tableau6[DATE DE DEPOT],"<="&'CLIENTS-CREANCES'!$O$1)-SUMIFS(Tableau3[MONTANT TTC],Tableau3[CLIENTS],Tableau1[[#This Row],[NOM CLIENT]],Tableau3[[DATE DE PAIEMENT ]],"<="&'CLIENTS-CREANCES'!$O$1) -> 0
A12: KENAM S | B12: SOGENA | C12: ENTREPRISE | D12: 1750736 P | E12: RNI | F12: 26 BP 1121 Abidjan 26 | G12: Rue des Brasseurs, Imm. Rive Droite, 3ème étage - Zone 3 | H12: 27 21 22 22 21 | L12: =+SUMIFS(Tableau6[NET A PAYER],Tableau6[CLIENT],Tableau1[[#This Row],[NOM CLIENT]],Tableau6[DATE DE FACTURATION],"<"&'CLIENTS-CREANCES'!$N$1)-SUMIFS(Tableau6[MONTANT PAYE],Tableau6[CLIENT],Tableau1[[#This Row],[NOM CLIENT]],Tableau6[DATE DE FACTURATION],"<"&'CLIENTS-CREANCES'!$N$1) -> 0 | M12: =SUMIFS(Tableau6[NET A PAYER],Tableau6[CLIENT],Tableau1[[#This Row],[NOM CLIENT]],Tableau6[DATE DE FACTURATION],">="&'CLIENTS-CREANCES'!$N$1,Tableau6[DATE DE FACTURATION],"<="&'CLIENTS-CREANCES'!$O$1) -> 2112809 | N12: =SUMIFS(Tableau3[MONTANT TTC],Tableau3[CLIENTS],Tableau1[[#This Row],[NOM CLIENT]],Tableau3[[DATE DE PAIEMENT ]],">="&'CLIENTS-CREANCES'!$N$1,Tableau3[[DATE DE PAIEMENT ]],"<="&'CLIENTS-CREANCES'!$O$1) -> 2283074.6 | O12: =+SUMIFS(Tableau6[NET A PAYER],Tableau6[CLIENT],Tableau1[[#This Row],[NOM CLIENT]],Tableau6[DATE DE DEPOT],"<="&'CLIENTS-CREANCES'!$O$1)-SUMIFS(Tableau3[MONTANT TTC],Tableau3[CLIENTS],Tableau1[[#This Row],[NOM CLIENT]],Tableau3[[DATE DE PAIEMENT ]],"<="&'CLIENTS-CREANCES'!$O$1) -> -170265.6
A13: KENAM S | B13: SOGIMAS | C13: ENTREPRISE | L13: =+SUMIFS(Tableau6[NET A PAYER],Tableau6[CLIENT],Tableau1[[#This Row],[NOM CLIENT]],Tableau6[DATE DE FACTURATION],"<"&'CLIENTS-CREANCES'!$N$1)-SUMIFS(Tableau6[MONTANT PAYE],Tableau6[CLIENT],Tableau1[[#This Row],[NOM CLIENT]],Tableau6[DATE DE FACTURATION],"<"&'CLIENTS-CREANCES'!$N$1) -> 0 | M13: =SUMIFS(Tableau6[NET A PAYER],Tableau6[CLIENT],Tableau1[[#This Row],[NOM CLIENT]],Tableau6[DATE DE FACTURATION],">="&'CLIENTS-CREANCES'!$N$1,Tableau6[DATE DE FACTURATION],"<="&'CLIENTS-CREANCES'!$O$1) -> 0 | N13: =SUMIFS(Tableau3[MONTANT TTC],Tableau3[CLIENTS],Tableau1[[#This Row],[NOM CLIENT]],Tableau3[[DATE DE PAIEMENT ]],">="&'CLIENTS-CREANCES'!$N$1,Tableau3[[DATE DE PAIEMENT ]],"<="&'CLIENTS-CREANCES'!$O$1) -> 0 | O13: =+SUMIFS(Tableau6[NET A PAYER],Tableau6[CLIENT],Tableau1[[#This Row],[NOM CLIENT]],Tableau6[DATE DE DEPOT],"<="&'CLIENTS-CREANCES'!$O$1)-SUMIFS(Tableau3[MONTANT TTC],Tableau3[CLIENTS],Tableau1[[#This Row],[NOM CLIENT]],Tableau3[[DATE DE PAIEMENT ]],"<="&'CLIENTS-CREANCES'!$O$1) -> 0
A14: KENAM S | B14: ETS. MSSZ | C14: ENTREPRISE | D14: 9410647 J | F14: 05 BP 1120 ABIDJAN 05 | H14: 27 22 42 73 48 | L14: =+SUMIFS(Tableau6[NET A PAYER],Tableau6[CLIENT],Tableau1[[#This Row],[NOM CLIENT]],Tableau6[DATE DE FACTURATION],"<"&'CLIENTS-CREANCES'!$N$1)-SUMIFS(Tableau6[MONTANT PAYE],Tableau6[CLIENT],Tableau1[[#This Row],[NOM CLIENT]],Tableau6[DATE DE FACTURATION],"<"&'CLIENTS-CREANCES'!$N$1) -> 0 | M14: =SUMIFS(Tableau6[NET A PAYER],Tableau6[CLIENT],Tableau1[[#This Row],[NOM CLIENT]],Tableau6[DATE DE FACTURATION],">="&'CLIENTS-CREANCES'!$N$1,Tableau6[DATE DE FACTURATION],"<="&'CLIENTS-CREANCES'!$O$1) -> 17369600 | N14: =SUMIFS(Tableau3[MONTANT TTC],Tableau3[CLIENTS],Tableau1[[#This Row],[NOM CLIENT]],Tableau3[[DATE DE PAIEMENT ]],">="&'CLIENTS-CREANCES'!$N$1,Tableau3[[DATE DE PAIEMENT ]],"<="&'CLIENTS-CREANCES'!$O$1) -> 0 | O14: =+SUMIFS(Tableau6[NET A PAYER],Tableau6[CLIENT],Tableau1[[#This Row],[NOM CLIENT]],Tableau6[DATE DE DEPOT],"<="&'CLIENTS-CREANCES'!$O$1)-SUMIFS(Tableau3[MONTANT TTC],Tableau3[CLIENTS],Tableau1[[#This Row],[NOM CLIENT]],Tableau3[[DATE DE PAIEMENT ]],"<="&'CLIENTS-CREANCES'!$O$1) -> 17369600
A15: KENAM S | B15: M BUER | C15: PARTICULIER | L15: =+SUMIFS(Tableau6[NET A PAYER],Tableau6[CLIENT],Tableau1[[#This Row],[NOM CLIENT]],Tableau6[DATE DE FACTURATION],"<"&'CLIENTS-CREANCES'!$N$1)-SUMIFS(Tableau6[MONTANT PAYE],Tableau6[CLIENT],Tableau1[[#This Row],[NOM CLIENT]],Tableau6[DATE DE FACTURATION],"<"&'CLIENTS-CREANCES'!$N$1) -> 0 | M15: =SUMIFS(Tableau6[NET A PAYER],Tableau6[CLIENT],Tableau1[[#This Row],[NOM CLIENT]],Tableau6[DATE DE FACTURATION],">="&'CLIENTS-CREANCES'!$N$1,Tableau6[DATE DE FACTURATION],"<="&'CLIENTS-CREANCES'!$O$1) -> 1645000 | N15: =SUMIFS(Tableau3[MONTANT TTC],Tableau3[CLIENTS],Tableau1[[#This Row],[NOM CLIENT]],Tableau3[[DATE DE PAIEMENT ]],">="&'CLIENTS-CREANCES'!$N$1,Tableau3[[DATE DE PAIEMENT ]],"<="&'CLIENTS-CREANCES'!$O$1) -> 1645000 | O15: =+SUMIFS(Tableau6[NET A PAYER],Tableau6[CLIENT],Tableau1[[#This Row],[NOM CLIENT]],Tableau6[DATE DE DEPOT],"<="&'CLIENTS-CREANCES'!$O$1)-SUMIFS(Tableau3[MONTANT TTC],Tableau3[CLIENTS],Tableau1[[#This Row],[NOM CLIENT]],Tableau3[[DATE DE PAIEMENT ]],"<="&'CLIENTS-CREANCES'!$O$1) -> 0
A16: KENAM S | B16: KHALIF INGENIERIE | C16: ENTREPRISE | F16: 23 BP 2992 ABIDJAN 23 | G16: YOPOUGON NOUVEAU QUARTIER | H16: 07 49 82 12 75 | I16: CONSTRUCTION METALLIQUE, BATIMENT TCE | L16: =+SUMIFS(Tableau6[NET A PAYER],Tableau6[CLIENT],Tableau1[[#This Row],[NOM CLIENT]],Tableau6[DATE DE FACTURATION],"<"&'CLIENTS-CREANCES'!$N$1)-SUMIFS(Tableau6[MONTANT PAYE],Tableau6[CLIENT],Tableau1[[#This Row],[NOM CLIENT]],Tableau6[DATE DE FACTURATION],"<"&'CLIENTS-CREANCES'!$N$1) -> 0 | M16: =SUMIFS(Tableau6[NET A PAYER],Tableau6[CLIENT],Tableau1[[#This Row],[NOM CLIENT]],Tableau6[DATE DE FACTURATION],">="&'CLIENTS-CREANCES'!$N$1,Tableau6[DATE DE FACTURATION],"<="&'CLIENTS-CREANCES'!$O$1) -> 0 | N16: =SUMIFS(Tableau3[MONTANT TTC],Tableau3[CLIENTS],Tableau1[[#This Row],[NOM CLIENT]],Tableau3[[DATE DE PAIEMENT ]],">="&'CLIENTS-CREANCES'!$N$1,Tableau3[[DATE DE PAIEMENT ]],"<="&'CLIENTS-CREANCES'!$O$1) -> 3540000 | O16: =+SUMIFS(Tableau6[NET A PAYER],Tableau6[CLIENT],Tableau1[[#This Row],[NOM CLIENT]],Tableau6[DATE DE DEPOT],"<="&'CLIENTS-CREANCES'!$O$1)-SUMIFS(Tableau3[MONTANT TTC],Tableau3[CLIENTS],Tableau1[[#This Row],[NOM CLIENT]],Tableau3[[DATE DE PAIEMENT ]],"<="&'CLIENTS-CREANCES'!$O$1) -> -3540000
A17: KENAM S | B17: KEDA CERAMIC | C17: ENTREPRISE | L17: =+SUMIFS(Tableau6[NET A PAYER],Tableau6[CLIENT],Tableau1[[#This Row],[NOM CLIENT]],Tableau6[DATE DE FACTURATION],"<"&'CLIENTS-CREANCES'!$N$1)-SUMIFS(Tableau6[MONTANT PAYE],Tableau6[CLIENT],Tableau1[[#This Row],[NOM CLIENT]],Tableau6[DATE DE FACTURATION],"<"&'CLIENTS-CREANCES'!$N$1) -> 0 | M17: =SUMIFS(Tableau6[NET A PAYER],Tableau6[CLIENT],Tableau1[[#This Row],[NOM CLIENT]],Tableau6[DATE DE FACTURATION],">="&'CLIENTS-CREANCES'!$N$1,Tableau6[DATE DE FACTURATION],"<="&'CLIENTS-CREANCES'!$O$1) -> 560000 | N17: =SUMIFS(Tableau3[MONTANT TTC],Tableau3[CLIENTS],Tableau1[[#This Row],[NOM CLIENT]],Tableau3[[DATE DE PAIEMENT ]],">="&'CLIENTS-CREANCES'!$N$1,Tableau3[[DATE DE PAIEMENT ]],"<="&'CLIENTS-CREANCES'!$O$1) -> 0 | O17: =+SUMIFS(Tableau6[NET A PAYER],Tableau6[CLIENT],Tableau1[[#This Row],[NOM CLIENT]],Tableau6[DATE DE DEPOT],"<="&'CLIENTS-CREANCES'!$O$1)-SUMIFS(Tableau3[MONTANT TTC],Tableau3[CLIENTS],Tableau1[[#This Row],[NOM CLIENT]],Tableau3[[DATE DE PAIEMENT ]],"<="&'CLIENTS-CREANCES'!$O$1) -> 0
L18: =+SUMIFS(Tableau6[NET A PAYER],Tableau6[CLIENT],Tableau1[[#This Row],[NOM CLIENT]],Tableau6[DATE DE FACTURATION],"<"&'CLIENTS-CREANCES'!$N$1)-SUMIFS(Tableau6[MONTANT PAYE],Tableau6[CLIENT],Tableau1[[#This Row],[NOM CLIENT]],Tableau6[DATE DE FACTURATION],"<"&'CLIENTS-CREANCES'!$N$1) -> 0 | M18: =SUMIFS(Tableau6[NET A PAYER],Tableau6[CLIENT],Tableau1[[#This Row],[NOM CLIENT]],Tableau6[DATE DE FACTURATION],">="&'CLIENTS-CREANCES'!$N$1,Tableau6[DATE DE FACTURATION],"<="&'CLIENTS-CREANCES'!$O$1) -> 0 | N18: =SUMIFS(Tableau3[MONTANT TTC],Tableau3[CLIENTS],Tableau1[[#This Row],[NOM CLIENT]],Tableau3[[DATE DE PAIEMENT ]],">="&'CLIENTS-CREANCES'!$N$1,Tableau3[[DATE DE PAIEMENT ]],"<="&'CLIENTS-CREANCES'!$O$1) -> 0 | O18: =+SUMIFS(Tableau6[NET A PAYER],Tableau6[CLIENT],Tableau1[[#This Row],[NOM CLIENT]],Tableau6[DATE DE DEPOT],"<="&'CLIENTS-CREANCES'!$O$1)-SUMIFS(Tableau3[MONTANT TTC],Tableau3[CLIENTS],Tableau1[[#This Row],[NOM CLIENT]],Tableau3[[DATE DE PAIEMENT ]],"<="&'CLIENTS-CREANCES'!$O$1) -> 0
L19: =+SUMIFS(Tableau6[NET A PAYER],Tableau6[CLIENT],Tableau1[[#This Row],[NOM CLIENT]],Tableau6[DATE DE FACTURATION],"<"&'CLIENTS-CREANCES'!$N$1)-SUMIFS(Tableau6[MONTANT PAYE],Tableau6[CLIENT],Tableau1[[#This Row],[NOM CLIENT]],Tableau6[DATE DE FACTURATION],"<"&'CLIENTS-CREANCES'!$N$1) -> 0 | M19: =SUMIFS(Tableau6[NET A PAYER],Tableau6[CLIENT],Tableau1[[#This Row],[NOM CLIENT]],Tableau6[DATE DE FACTURATION],">="&'CLIENTS-CREANCES'!$N$1,Tableau6[DATE DE FACTURATION],"<="&'CLIENTS-CREANCES'!$O$1) -> 0 | N19: =SUMIFS(Tableau3[MONTANT TTC],Tableau3[CLIENTS],Tableau1[[#This Row],[NOM CLIENT]],Tableau3[[DATE DE PAIEMENT ]],">="&'CLIENTS-CREANCES'!$N$1,Tableau3[[DATE DE PAIEMENT ]],"<="&'CLIENTS-CREANCES'!$O$1) -> 0 | O19: =+SUMIFS(Tableau6[NET A PAYER],Tableau6[CLIENT],Tableau1[[#This Row],[NOM CLIENT]],Tableau6[DATE DE DEPOT],"<="&'CLIENTS-CREANCES'!$O$1)-SUMIFS(Tableau3[MONTANT TTC],Tableau3[CLIENTS],Tableau1[[#This Row],[NOM CLIENT]],Tableau3[[DATE DE PAIEMENT ]],"<="&'CLIENTS-CREANCES'!$O$1) -> 0
L20: =+SUMIFS(Tableau6[NET A PAYER],Tableau6[CLIENT],Tableau1[[#This Row],[NOM CLIENT]],Tableau6[DATE DE FACTURATION],"<"&'CLIENTS-CREANCES'!$N$1)-SUMIFS(Tableau6[MONTANT PAYE],Tableau6[CLIENT],Tableau1[[#This Row],[NOM CLIENT]],Tableau6[DATE DE FACTURATION],"<"&'CLIENTS-CREANCES'!$N$1) -> 0 | M20: =SUMIFS(Tableau6[NET A PAYER],Tableau6[CLIENT],Tableau1[[#This Row],[NOM CLIENT]],Tableau6[DATE DE FACTURATION],">="&'CLIENTS-CREANCES'!$N$1,Tableau6[DATE DE FACTURATION],"<="&'CLIENTS-CREANCES'!$O$1) -> 0 | N20: =SUMIFS(Tableau3[MONTANT TTC],Tableau3[CLIENTS],Tableau1[[#This Row],[NOM CLIENT]],Tableau3[[DATE DE PAIEMENT ]],">="&'CLIENTS-CREANCES'!$N$1,Tableau3[[DATE DE PAIEMENT ]],"<="&'CLIENTS-CREANCES'!$O$1) -> 0 | O20: =+SUMIFS(Tableau6[NET A PAYER],Tableau6[CLIENT],Tableau1[[#This Row],[NOM CLIENT]],Tableau6[DATE DE DEPOT],"<="&'CLIENTS-CREANCES'!$O$1)-SUMIFS(Tableau3[MONTANT TTC],Tableau3[CLIENTS],Tableau1[[#This Row],[NOM CLIENT]],Tableau3[[DATE DE PAIEMENT ]],"<="&'CLIENTS-CREANCES'!$O$1) -> 0
A21: Total | B21: =SUBTOTAL(103,Tableau1[NOM CLIENT]) -> 13 | L21: =SUBTOTAL(109,Tableau1[SOLDE N-1]) -> 0 | M21: =SUBTOTAL(109,Tableau1[MONTANT DU]) -> 2589911320 | N21: =SUBTOTAL(109,Tableau1[MONTANT RECOUVRE]) -> 2.6975368e+09 | O21: =SUBTOTAL(109,Tableau1[SOLDE N]) -> -1.0818547e+08

Sheet FACTURES
B2: LISTES DES FACTURES
C3: Faire le tri
A4: ENTITE | B4: DATE DE FACTURATION | C4: DATE DE DEPOT | D4: NUM DE FACTURE | E4: CLIENT | F4: DESIGNATION | G4: PROJET/CHANTIER | H4: CODE TVA | I4: MONTANT HT BIEN | J4: MONTANT HT SERVICE | K4: MONTANT HT | L4: ACOMPTE SUR HT | M4: TVA | N4: MONTANT TTC | O4: ACOMPTE SUR TTC | P4: NET A PAYER | Q4: N° BC | R4: MONTANT BC HT | S4: DELAI | T4: DATE LIMITE | U4: JOURS DE RETARD | V4: STATUT | W4: MONTANT PAYE | X4: DATE PAIEMENT | Y4: SOLDE SUR FACTURE | Z4: OBSERVATIONS
A5: KENAM S | B5: 45665 | C5: 45665 | D5: 205 | E5: PFO CONSTRUCTION | F5: LOCATION DE CAMIONS | G5: 305R8002 | H5: TVAF | J5: 20234633 | K5: =+Tableau6[[#This Row],[MONTANT HT BIEN]]+Tableau6[[#This Row],[MONTANT HT SERVICE]] -> 20234633 | L5: 0 | M5: =+IFERROR(IF(Tableau6[[#This Row],[CODE TVA]]="TVAF",Tableau6[[#This Row],[MONTANT HT]]*0.18,0),0) -> 3642233.9 | N5: =Tableau6[[#This Row],[MONTANT HT]]+Tableau6[[#This Row],[TVA]]-Tableau6[[#This Row],[ACOMPTE SUR HT]] -> 23876867 | P5: =+ROUND(Tableau6[[#This Row],[MONTANT TTC]]-Tableau6[[#This Row],[ACOMPTE SUR TTC]],0) -> 23876867 | Q5: BC101017 | R5: =IFERROR(INDEX(Tableau2[[ID BC UNIQUE]:[MONTANT HT VALIDE]],MATCH(Tableau6[[#This Row],[N° BC]],Tableau2[ID BC UNIQUE],0),6),0) -> 20234633 | S5: =IFERROR(INDEX(Tableau2[[DATE]:[DELAIS DE PAIEMENT FACTURES EN JOUR]],MATCH(Tableau6[[#This Row],[N° BC]],Tableau2[ID BC UNIQUE],0),5),0) -> 30 | T5: =IF(ISBLANK(Tableau6[[#This Row],[DATE DE DEPOT]]),"",Tableau6[[#This Row],[DATE DE DEPOT]]+Tableau6[[#This Row],[DELAI]]) -> 45695 | U5: =+IF(AND(W5=0,Tableau6[[#This Row],[DATE LIMITE]]<TODAY()),TODAY()-Tableau6[[#This Row],[DATE LIMITE]],0) -> 0 | V5: =IF(Tableau6[[#This Row],[DATE LIMITE]]>=TODAY(),"NON ECHUE",IF(Tableau6[[#This Row],[MONTANT HT]]<0,IF(ISNUMBER(MATCH(-Tableau6[[#This Row],[MONTANT HT]],Tableau6[MONTANT HT],0)),"AVOIR TOTAL","AVOIR PARTIEL"),IF(AND(ISNUMBER(MATCH(-Tableau6[[#This Row],[MONTANT HT]],Tableau6[MONTANT HT],0)),(Tableau6[[#This Row],[ACOMPTE SUR TTC]]+Tableau6[[#This Row],[MONTANT PAYE]])=0),"FACTURE ANNULEE",IF(Tableau6[[#This Row],[ACOMPTE SUR TTC]]+Tableau6[[#This Row],[MONTANT PAYE]]=0,"ECHUE NON REGLEE",IF(Tableau6[[#This Row],[ACOMPTE SUR TTC]]+Tableau6[[#This Row],[MONTANT PAYE]]=Tableau6[[#This Row],[NET A PAYER]],"PAYE",IF(Tableau6[[#This Row],[ACOMPTE SUR TTC]]+Tableau6[[#This Row],[MONTANT PAYE]]<Tableau6[[#This Row],[NET A PAYER]],"PAIEMENT PARTIEL","TROP PAYE")))))) -> PAYE | W5: =SUMIF(Tableau3[FACTURE],Tableau6[[#This Row],[NUM DE FACTURE]],Tableau3[MONTANT TTC]) -> 23876867 | Y5: =+Tableau6[[#This Row],[NET A PAYER]]-Tableau6[[#This Row],[MONTANT PAYE]] -> 0
A6: KENAM S | B6: 45677 | C6: 45677 | D6: 208 | E6: PFO CONSTRUCTION | F6: LOCATION DE CAMIONS | G6: 348R8002 | H6: TVAF | J6: 3500000 | K6: =+Tableau6[[#This Row],[MONTANT HT BIEN]]+Tableau6[[#This Row],[MONTANT HT SERVICE]] -> 3500000 | L6: 0 | M6: =+IFERROR(IF(Tableau6[[#This Row],[CODE TVA]]="TVAF",Tableau6[[#This Row],[MONTANT HT]]*0.18,0),0) -> 630000 | N6: =Tableau6[[#This Row],[MONTANT HT]]+Tableau6[[#This Row],[TVA]]-Tableau6[[#This Row],[ACOMPTE SUR HT]] -> 4130000 | P6: =+ROUND(Tableau6[[#This Row],[MONTANT TTC]]-Tableau6[[#This Row],[ACOMPTE SUR TTC]],0) -> 4130000 | Q6: BC101167 | R6: =IFERROR(INDEX(Tableau2[[ID BC UNIQUE]:[MONTANT HT VALIDE]],MATCH(Tableau6[[#This Row],[N° BC]],Tableau2[ID BC UNIQUE],0),6),0) -> 3500000 | S6: =IFERROR(INDEX(Tableau2[[DATE]:[DELAIS DE PAIEMENT FACTURES EN JOUR]],MATCH(Tableau6[[#This Row],[N° BC]],Tableau2[ID BC UNIQUE],0),5),0) -> 30 | T6: =IF(ISBLANK(Tableau6[[#This Row],[DATE DE DEPOT]]),"",Tableau6[[#This Row],[DATE DE DEPOT]]+Tableau6[[#This Row],[DELAI]]) -> 45707 | U6: =+IF(AND(W6=0,Tableau6[[#This Row],[DATE LIMITE]]<TODAY()),TODAY()-Tableau6[[#This Row],[DATE LIMITE]],0) -> 0 | V6: =IF(Tableau6[[#This Row],[DATE LIMITE]]>=TODAY(),"NON ECHUE",IF(Tableau6[[#This Row],[MONTANT HT]]<0,IF(ISNUMBER(MATCH(-Tableau6[[#This Row],[MONTANT HT]],Tableau6[MONTANT HT],0)),"AVOIR TOTAL","AVOIR PARTIEL"),IF(AND(ISNUMBER(MATCH(-Tableau6[[#This Row],[MONTANT HT]],Tableau6[MONTANT HT],0)),(Tableau6[[#This Row],[ACOMPTE SUR TTC]]+Tableau6[[#This Row],[MONTANT PAYE]])=0),"FACTURE ANNULEE",IF(Tableau6[[#This Row],[ACOMPTE SUR TTC]]+Tableau6[[#This Row],[MONTANT PAYE]]=0,"ECHUE NON REGLEE",IF(Tableau6[[#This Row],[ACOMPTE SUR TTC]]+Tableau6[[#This Row],[MONTANT PAYE]]=Tableau6[[#This Row],[NET A PAYER]],"PAYE",IF(Tableau6[[#This Row],[ACOMPTE SUR TTC]]+Tableau6[[#This Row],[MONTANT PAYE]]<Tableau6[[#This Row],[NET A PAYER]],"PAIEMENT PARTIEL","TROP PAYE")))))) -> PAYE | W6: =SUMIF(Tableau3[FACTURE],Tableau6[[#This Row],[NUM DE FACTURE]],Tableau3[MONTANT TTC]) -> 4130000 | Y6: =+Tableau6[[#This Row],[NET A PAYER]]-Tableau6[[#This Row],[MONTANT PAYE]] -> 0
A7: KENAM S | B7: 45677 | C7: 45677 | D7: 209 | E7: PFO CONSTRUCTION | F7: LOCATION DE CAMIONS | G7: 348R8002 | H7: TVAF | J7: 720000 | K7: =+Tableau6[[#This Row],[MONTANT HT BIEN]]+Tableau6[[#This Row],[MONTANT HT SERVICE]] -> 720000 | L7: 0 | M7: =+IFERROR(IF(Tableau6[[#This Row],[CODE TVA]]="TVAF",Tableau6[[#This Row],[MONTANT HT]]*0.18,0),0) -> 129600 | N7: =Tableau6[[#This Row],[MONTANT HT]]+Tableau6[[#This Row],[TVA]]-Tableau6[[#This Row],[ACOMPTE SUR HT]] -> 849600 | P7: =+ROUND(Tableau6[[#This Row],[MONTANT TTC]]-Tableau6[[#This Row],[ACOMPTE SUR TTC]],0) -> 849600 | Q7: BC101169 | R7: =IFERROR(INDEX(Tableau2[[ID BC UNIQUE]:[MONTANT HT VALIDE]],MATCH(Tableau6[[#This Row],[N° BC]],Tableau2[ID BC UNIQUE],0),6),0) -> 720000 | S7: =IFERROR(INDEX(Tableau2[[DATE]:[DELAIS DE PAIEMENT FACTURES EN JOUR]],MATCH(Tableau6[[#This Row],[N° BC]],Tableau2[ID BC UNIQUE],0),5),0) -> 30 | T7: =IF(ISBLANK(Tableau6[[#This Row],[DATE DE DEPOT]]),"",Tableau6[[#This Row],[DATE DE DEPOT]]+Tableau6[[#This Row],[DELAI]]) -> 45707 | U7: =+IF(AND(W7=0,Tableau6[[#This Row],[DATE LIMITE]]<TODAY()),TODAY()-Tableau6[[#This Row],[DATE LIMITE]],0) -> 0 | V7: =IF(Tableau6[[#This Row],[DATE LIMITE]]>=TODAY(),"NON ECHUE",IF(Tableau6[[#This Row],[MONTANT HT]]<0,IF(ISNUMBER(MATCH(-Tableau6[[#This Row],[MONTANT HT]],Tableau6[MONTANT HT],0)),"AVOIR TOTAL","AVOIR PARTIEL"),IF(AND(ISNUMBER(MATCH(-Tableau6[[#This Row],[MONTANT HT]],Tableau6[MONTANT HT],0)),(Tableau6[[#This Row],[ACOMPTE SUR TTC]]+Tableau6[[#This Row],[MONTANT PAYE]])=0),"FACTURE ANNULEE",IF(Tableau6[[#This Row],[ACOMPTE SUR TTC]]+Tableau6[[#This Row],[MONTANT PAYE]]=0,"ECHUE NON REGLEE",IF(Tableau6[[#This Row],[ACOMPTE SUR TTC]]+Tableau6[[#This Row],[MONTANT PAYE]]=Tableau6[[#This Row],[NET A PAYER]],"PAYE",IF(Tableau6[[#This Row],[ACOMPTE SUR TTC]]+Tableau6[[#This Row],[MONTANT PAYE]]<Tableau6[[#This Row],[NET A PAYER]],"PAIEMENT PARTIEL","TROP PAYE")))))) -> PAYE | W7: =SUMIF(Tableau3[FACTURE],Tableau6[[#This Row],[NUM DE FACTURE]],Tableau3[MONTANT TTC]) -> 849600 | Y7: =+Tableau6[[#This Row],[NET A PAYER]]-Tableau6[[#This Row],[MONTANT PAYE]] -> 0
A8: KENAM S | B8: 45679 | C8: 45679 | D8: 210 | E8: PFO CONSTRUCTION | F8: VENTE DE MATERIEL | G8: 252B0209 | H8: TVAF | I8: 6064800 | K8: =+Tableau6[[#This Row],[MONTANT HT BIEN]]+Tableau6[[#This Row],[MONTANT HT SERVICE]] -> 6064800 | L8: 0 | M8: =+IFERROR(IF(Tableau6[[#This Row],[CODE TVA]]="TVAF",Tableau6[[#This Row],[MONTANT HT]]*0.18,0),0) -> 1091664 | N8: =Tableau6[[#This Row],[MONTANT HT]]+Tableau6[[#This Row],[TVA]]-Tableau6[[#This Row],[ACOMPTE SUR HT]] -> 7156464 | P8: =+ROUND(Tableau6[[#This Row],[MONTANT TTC]]-Tableau6[[#This Row],[ACOMPTE SUR TTC]],0) -> 7156464 | Q8: BC200691 | R8: =IFERROR(INDEX(Tableau2[[ID BC UNIQUE]:[MONTANT HT VALIDE]],MATCH(Tableau6[[#This Row],[N° BC]],Tableau2[ID BC UNIQUE],0),6),0) -> 6064800 | S8: =IFERROR(INDEX(Tableau2[[DATE]:[DELAIS DE PAIEMENT FACTURES EN JOUR]],MATCH(Tableau6[[#This Row],[N° BC]],Tableau2[ID BC UNIQUE],0),5),0) -> 30 | T8: =IF(ISBLANK(Tableau6[[#This Row],[DATE DE DEPOT]]),"",Tableau6[[#This Row],[DATE DE DEPOT]]+Tableau6[[#This Row],[DELAI]]) -> 45709 | U8: =+IF(AND(W8=0,Tableau6[[#This Row],[DATE LIMITE]]<TODAY()),TODAY()-Tableau6[[#This Row],[DATE LIMITE]],0) -> 0 | V8: =IF(Tableau6[[#This Row],[DATE LIMITE]]>=TODAY(),"NON ECHUE",IF(Tableau6[[#This Row],[MONTANT HT]]<0,IF(ISNUMBER(MATCH(-Tableau6[[#This Row],[MONTANT HT]],Tableau6[MONTANT HT],0)),"AVOIR TOTAL","AVOIR PARTIEL"),IF(AND(ISNUMBER(MATCH(-Tableau6[[#This Row],[MONTANT HT]],Tableau6[MONTANT HT],0)),(Tableau6[[#This Row],[ACOMPTE SUR TTC]]+Tableau6[[#This Row],[MONTANT PAYE]])=0),"FACTURE ANNULEE",IF(Tableau6[[#This Row],[ACOMPTE SUR TTC]]+Tableau6[[#This Row],[MONTANT PAYE]]=0,"ECHUE NON REGLEE",IF(Tableau6[[#This Row],[ACOMPTE SUR TTC]]+Tableau6[[#This Row],[MONTANT PAYE]]=Tableau6[[#This Row],[NET A PAYER]],"PAYE",IF(Tableau6[[#This Row],[ACOMPTE SUR TTC]]+Tableau6[[#This Row],[MONTANT PAYE]]<Tableau6[[#This Row],[NET A PAYER]],"PAIEMENT PARTIEL","TROP PAYE")))))) -> PAYE | W8: =SUMIF(Tableau3[FACTURE],Tableau6[[#This Row],[NUM DE FACTURE]],Tableau3[MONTANT TTC]) -> 7156464 | Y8: =+Tableau6[[#This Row],[NET A PAYER]]-Tableau6[[#This Row],[MONTANT PAYE]] -> 0
A9: KENAM S | B9: 45680 | C9: 45680 | D9: 212 | E9: PFO CONSTRUCTION | F9: LOCATION DE CAMIONS | G9: 257B0209 | H9: TVAF | J9: 540000 | K9: =+Tableau6[[#This Row],[MONTANT HT BIEN]]+Tableau6[[#This Row],[MONTANT HT SERVICE]] -> 540000 | L9: 0 | M9: =+IFERROR(IF(Tableau6[[#This Row],[CODE TVA]]="TVAF",Tableau6[[#This Row],[MONTANT HT]]*0.18,0),0) -> 97200 | N9: =Tableau6[[#This Row],[MONTANT HT]]+Tableau6[[#This Row],[TVA]]-Tableau6[[#This Row],[ACOMPTE SUR HT]] -> 637200 | P9: =+ROUND(Tableau6[[#This Row],[MONTANT TTC]]-Tableau6[[#This Row],[ACOMPTE SUR TTC]],0) -> 637200 | Q9: BC200850 | R9: =IFERROR(INDEX(Tableau2[[ID BC UNIQUE]:[MONTANT HT VALIDE]],MATCH(Tableau6[[#This Row],[N° BC]],Tableau2[ID BC UNIQUE],0),6),0) -> 540000 | S9: =IFERROR(INDEX(Tableau2[[DATE]:[DELAIS DE PAIEMENT FACTURES EN JOUR]],MATCH(Tableau6[[#This Row],[N° BC]],Tableau2[ID BC UNIQUE],0),5),0) -> 30 | T9: =IF(ISBLANK(Tableau6[[#This Row],[DATE DE DEPOT]]),"",Tableau6[[#This Row],[DATE DE DEPOT]]+Tableau6[[#This Row],[DELAI]]) -> 45710 | U9: =+IF(AND(W9=0,Tableau6[[#This Row],[DATE LIMITE]]<TODAY()),TODAY()-Tableau6[[#This Row],[DATE LIMITE]],0) -> 0 | V9: =IF(Tableau6[[#This Row],[DATE LIMITE]]>=TODAY(),"NON ECHUE",IF(Tableau6[[#This Row],[MONTANT HT]]<0,IF(ISNUMBER(MATCH(-Tableau6[[#This Row],[MONTANT HT]],Tableau6[MONTANT HT],0)),"AVOIR TOTAL","AVOIR PARTIEL"),IF(AND(ISNUMBER(MATCH(-Tableau6[[#This Row],[MONTANT HT]],Tableau6[MONTANT HT],0)),(Tableau6[[#This Row],[ACOMPTE SUR TTC]]+Tableau6[[#This Row],[MONTANT PAYE]])=0),"FACTURE ANNULEE",IF(Tableau6[[#This Row],[ACOMPTE SUR TTC]]+Tableau6[[#This Row],[MONTANT PAYE]]=0,"ECHUE NON REGLEE",IF(Tableau6[[#This Row],[ACOMPTE SUR TTC]]+Tableau6[[#This Row],[MONTANT PAYE]]=Tableau6[[#This Row],[NET A PAYER]],"PAYE",IF(Tableau6[[#This Row],[ACOMPTE SUR TTC]]+Tableau6[[#This Row],[MONTANT PAYE]]<Tableau6[[#This Row],[NET A PAYER]],"PAIEMENT PARTIEL","TROP PAYE")))))) -> PAYE | W9: =SUMIF(Tableau3[FACTURE],Tableau6[[#This Row],[NUM DE FACTURE]],Tableau3[MONTANT TTC]) -> 637200 | Y9: =+Tableau6[[#This Row],[NET A PAYER]]-Tableau6[[#This Row],[MONTANT PAYE]] -> 0
A10: KENAM S | B10: 45680 | C10: 45680 | D10: 213 | E10: PFO CONSTRUCTION | F10: LOCATION DE CAMIONS | G10: 257B0207 | H10: TVAF | J10: 1980000 | K10: =+Tableau6[[#This Row],[MONTANT HT BIEN]]+Tableau6[[#This Row],[MONTANT HT SERVICE]] -> 1980000 | L10: 0 | M10: =+IFERROR(IF(Tableau6[[#This Row],[CODE TVA]]="TVAF",Tableau6[[#This Row],[MONTANT HT]]*0.18,0),0) -> 356400 | N10: =Tableau6[[#This Row],[MONTANT HT]]+Tableau6[[#This Row],[TVA]]-Tableau6[[#This Row],[ACOMPTE SUR HT]] -> 2336400 | P10: =+ROUND(Tableau6[[#This Row],[MONTANT TTC]]-Tableau6[[#This Row],[ACOMPTE SUR TTC]],0) -> 2336400 | Q10: BC200851 | R10: =IFERROR(INDEX(Tableau2[[ID BC UNIQUE]:[MONTANT HT VALIDE]],MATCH(Tableau6[[#This Row],[N° BC]],Tableau2[ID BC UNIQUE],0),6),0) -> 1980000 | S10: =IFERROR(INDEX(Tableau2[[DATE]:[DELAIS DE PAIEMENT FACTURES EN JOUR]],MATCH(Tableau6[[#This Row],[N° BC]],Tableau2[ID BC UNIQUE],0),5),0) -> 30 | T10: =IF(ISBLANK(Tableau6[[#This Row],[DATE DE DEPOT]]),"",Tableau6[[#This Row],[DATE DE DEPOT]]+Tableau6[[#This Row],[DELAI]]) -> 45710 | U10: =+IF(AND(W10=0,Tableau6[[#This Row],[DATE LIMITE]]<TODAY()),TODAY()-Tableau6[[#This Row],[DATE LIMITE]],0) -> 0 | V10: =IF(Tableau6[[#This Row],[DATE LIMITE]]>=TODAY(),"NON ECHUE",IF(Tableau6[[#This Row],[MONTANT HT]]<0,IF(ISNUMBER(MATCH(-Tableau6[[#This Row],[MONTANT HT]],Tableau6[MONTANT HT],0)),"AVOIR TOTAL","AVOIR PARTIEL"),IF(AND(ISNUMBER(MATCH(-Tableau6[[#This Row],[MONTANT HT]],Tableau6[MONTANT HT],0)),(Tableau6[[#This Row],[ACOMPTE SUR TTC]]+Tableau6[[#This Row],[MONTANT PAYE]])=0),"FACTURE ANNULEE",IF(Tableau6[[#This Row],[ACOMPTE SUR TTC]]+Tableau6[[#This Row],[MONTANT PAYE]]=0,"ECHUE NON REGLEE",IF(Tableau6[[#This Row],[ACOMPTE SUR TTC]]+Tableau6[[#This Row],[MONTANT PAYE]]=Tableau6[[#This Row],[NET A PAYER]],"PAYE",IF(Tableau6[[#This Row],[ACOMPTE SUR TTC]]+Tableau6[[#This Row],[MONTANT PAYE]]<Tableau6[[#This Row],[NET A PAYER]],"PAIEMENT PARTIEL","TROP PAYE")))))) -> PAYE | W10: =SUMIF(Tableau3[FACTURE],Tableau6[[#This Row],[NUM DE FACTURE]],Tableau3[MONTANT TTC]) -> 2336400 | Y10: =+Tableau6[[#This Row],[NET A PAYER]]-Tableau6[[#This Row],[MONTANT PAYE]] -> 0
A11: KENAM S | B11: 45680 | C11: 45680 | D11: 214 | E11: PFO CONSTRUCTION | F11: LOCATION DE CAMIONS | G11: 257B0207 | H11: TVAF | J11: 2200000 | K11: =+Tableau6[[#This Row],[MONTANT HT BIEN]]+Tableau6[[#This Row],[MONTANT HT SERVICE]] -> 2200000 | L11: 0 | M11: =+IFERROR(IF(Tableau6[[#This Row],[CODE TVA]]="TVAF",Tableau6[[#This Row],[MONTANT HT]]*0.18,0),0) -> 396000 | N11: =Tableau6[[#This Row],[MONTANT HT]]+Tableau6[[#This Row],[TVA]]-Tableau6[[#This Row],[ACOMPTE SUR HT]] -> 2596000 | P11: =+ROUND(Tableau6[[#This Row],[MONTANT TTC]]-Tableau6[[#This Row],[ACOMPTE SUR TTC]],0) -> 2596000 | Q11: BC200852 | R11: =IFERROR(INDEX(Tableau2[[ID BC UNIQUE]:[MONTANT HT VALIDE]],MATCH(Tableau6[[#This Row],[N° BC]],Tableau2[ID BC UNIQUE],0),6),0) -> 2200000 | S11: =IFERROR(INDEX(Tableau2[[DATE]:[DELAIS DE PAIEMENT FACTURES EN JOUR]],MATCH(Tableau6[[#This Row],[N° BC]],Tableau2[ID BC UNIQUE],0),5),0) -> 30 | T11: =IF(ISBLANK(Tableau6[[#This Row],[DATE DE DEPOT]]),"",Tableau6[[#This Row],[DATE DE DEPOT]]+Tableau6[[#This Row],[DELAI]]) -> 45710 | U11: =+IF(AND(W11=0,Tableau6[[#This Row],[DATE LIMITE]]<TODAY()),TODAY()-Tableau6[[#This Row],[DATE LIMITE]],0) -> 0 | V11: =IF(Tableau6[[#This Row],[DATE LIMITE]]>=TODAY(),"NON ECHUE",IF(Tableau6[[#This Row],[MONTANT HT]]<0,IF(ISNUMBER(MATCH(-Tableau6[[#This Row],[MONTANT HT]],Tableau6[MONTANT HT],0)),"AVOIR TOTAL","AVOIR PARTIEL"),IF(AND(ISNUMBER(MATCH(-Tableau6[[#This Row],[MONTANT HT]],Tableau6[MONTANT HT],0)),(Tableau6[[#This Row],[ACOMPTE SUR TTC]]+Tableau6[[#This Row],[MONTANT PAYE]])=0),"FACTURE ANNULEE",IF(Tableau6[[#This Row],[ACOMPTE SUR TTC]]+Tableau6[[#This Row],[MONTANT PAYE]]=0,"ECHUE NON REGLEE",IF(Tableau6[[#This Row],[ACOMPTE SUR TTC]]+Tableau6[[#This Row],[MONTANT PAYE]]=Tableau6[[#This Row],[NET A PAYER]],"PAYE",IF(Tableau6[[#This Row],[ACOMPTE SUR TTC]]+Tableau6[[#This Row],[MONTANT PAYE]]<Tableau6[[#This Row],[NET A PAYER]],"PAIEMENT PARTIEL","TROP PAYE")))))) -> PAYE | W11: =SUMIF(Tableau3[FACTURE],Tableau6[[#This Row],[NUM DE FACTURE]],Tableau3[MONTANT TTC]) -> 2596000 | Y11: =+Tableau6[[#This Row],[NET A PAYER]]-Tableau6[[#This Row],[MONTANT PAYE]] -> 0
A12: KENAM S | B12: 45680 | C12: 45680 | D12: 215 | E12: PFO CONSTRUCTION | F12: LOCATION DE CAMIONS | G12: 257B0209 | H12: TVAF | J12: 1400000 | K12: =+Tableau6[[#This Row],[MONTANT HT BIEN]]+Tableau6[[#This Row],[MONTANT HT SERVICE]] -> 1400000 | L12: 0 | M12: =+IFERROR(IF(Tableau6[[#This Row],[CODE TVA]]="TVAF",Tableau6[[#This Row],[MONTANT HT]]*0.18,0),0) -> 252000 | N12: =Tableau6[[#This Row],[MONTANT HT]]+Tableau6[[#This Row],[TVA]]-Tableau6[[#This Row],[ACOMPTE SUR HT]] -> 1652000 | P12: =+ROUND(Tableau6[[#This Row],[MONTANT TTC]]-Tableau6[[#This Row],[ACOMPTE SUR TTC]],0) -> 1652000 | Q12: BC200853 | R12: =IFERROR(INDEX(Tableau2[[ID BC UNIQUE]:[MONTANT HT VALIDE]],MATCH(Tableau6[[#This Row],[N° BC]],Tableau2[ID BC UNIQUE],0),6),0) -> 1400000 | S12: =IFERROR(INDEX(Tableau2[[DATE]:[DELAIS DE PAIEMENT FACTURES EN JOUR]],MATCH(Tableau6[[#This Row],[N° BC]],Tableau2[ID BC UNIQUE],0),5),0) -> 30 | T12: =IF(ISBLANK(Tableau6[[#This Row],[DATE DE DEPOT]]),"",Tableau6[[#This Row],[DATE DE DEPOT]]+Tableau6[[#This Row],[DELAI]]) -> 45710 | U12: =+IF(AND(W12=0,Tableau6[[#This Row],[DATE LIMITE]]<TODAY()),TODAY()-Tableau6[[#This Row],[DATE LIMITE]],0) -> 0 | V12: =IF(Tableau6[[#This Row],[DATE LIMITE]]>=TODAY(),"NON ECHUE",IF(Tableau6[[#This Row],[MONTANT HT]]<0,IF(ISNUMBER(MATCH(-Tableau6[[#This Row],[MONTANT HT]],Tableau6[MONTANT HT],0)),"AVOIR TOTAL","AVOIR PARTIEL"),IF(AND(ISNUMBER(MATCH(-Tableau6[[#This Row],[MONTANT HT]],Tableau6[MONTANT HT],0)),(Tableau6[[#This Row],[ACOMPTE SUR TTC]]+Tableau6[[#This Row],[MONTANT PAYE]])=0),"FACTURE ANNULEE",IF(Tableau6[[#This Row],[ACOMPTE SUR TTC]]+Tableau6[[#This Row],[MONTANT PAYE]]=0,"ECHUE NON REGLEE",IF(Tableau6[[#This Row],[ACOMPTE SUR TTC]]+Tableau6[[#This Row],[MONTANT PAYE]]=Tableau6[[#This Row],[NET A PAYER]],"PAYE",IF(Tableau6[[#This Row],[ACOMPTE SUR TTC]]+Tableau6[[#This Row],[MONTANT PAYE]]<Tableau6[[#This Row],[NET A PAYER]],"PAIEMENT PARTIEL","TROP PAYE")))))) -> PAYE | W12: =SUMIF(Tableau3[FACTURE],Tableau6[[#This Row],[NUM DE FACTURE]],Tableau3[MONTANT TTC]) -> 1652000 | Y12: =+Tableau6[[#This Row],[NET A PAYER]]-Tableau6[[#This Row],[MONTANT PAYE]] -> 0
A13: KENAM S | B13: 45680 | C13: 45680 | D13: 216 | E13: PFO CONSTRUCTION | F13: LOCATION DE CAMIONS | G13: 257B0209 | H13: TVAF | J13: 1350000 | K13: =+Tableau6[[#This Row],[MONTANT HT BIEN]]+Tableau6[[#This Row],[MONTANT HT SERVICE]] -> 1350000 | L13: 0 | M13: =+IFERROR(IF(Tableau6[[#This Row],[CODE TVA]]="TVAF",Tableau6[[#This Row],[MONTANT HT]]*0.18,0),0) -> 243000 | N13: =Tableau6[[#This Row],[MONTANT HT]]+Tableau6[[#This Row],[TVA]]-Tableau6[[#This Row],[ACOMPTE SUR HT]] -> 1593000 | P13: =+ROUND(Tableau6[[#This Row],[MONTANT TTC]]-Tableau6[[#This Row],[ACOMPTE SUR TTC]],0) -> 1593000 | Q13: BC200854 | R13: =IFERROR(INDEX(Tableau2[[ID BC UNIQUE]:[MONTANT HT VALIDE]],MATCH(Tableau6[[#This Row],[N° BC]],Tableau2[ID BC UNIQUE],0),6),0) -> 1350000 | S13: =IFERROR(INDEX(Tableau2[[DATE]:[DELAIS DE PAIEMENT FACTURES EN JOUR]],MATCH(Tableau6[[#This Row],[N° BC]],Tableau2[ID BC UNIQUE],0),5),0) -> 30 | T13: =IF(ISBLANK(Tableau6[[#This Row],[DATE DE DEPOT]]),"",Tableau6[[#This Row],[DATE DE DEPOT]]+Tableau6[[#This Row],[DELAI]]) -> 45710 | U13: =+IF(AND(W13=0,Tableau6[[#This Row],[DATE LIMITE]]<TODAY()),TODAY()-Tableau6[[#This Row],[DATE LIMITE]],0) -> 0 | V13: =IF(Tableau6[[#This Row],[DATE LIMITE]]>=TODAY(),"NON ECHUE",IF(Tableau6[[#This Row],[MONTANT HT]]<0,IF(ISNUMBER(MATCH(-Tableau6[[#This Row],[MONTANT HT]],Tableau6[MONTANT HT],0)),"AVOIR TOTAL","AVOIR PARTIEL"),IF(AND(ISNUMBER(MATCH(-Tableau6[[#This Row],[MONTANT HT]],Tableau6[MONTANT HT],0)),(Tableau6[[#This Row],[ACOMPTE SUR TTC]]+Tableau6[[#This Row],[MONTANT PAYE]])=0),"FACTURE ANNULEE",IF(Tableau6[[#This Row],[ACOMPTE SUR TTC]]+Tableau6[[#This Row],[MONTANT PAYE]]=0,"ECHUE NON REGLEE",IF(Tableau6[[#This Row],[ACOMPTE SUR TTC]]+Tableau6[[#This Row],[MONTANT PAYE]]=Tableau6[[#This Row],[NET A PAYER]],"PAYE",IF(Tableau6[[#This Row],[ACOMPTE SUR TTC]]+Tableau6[[#This Row],[MONTANT PAYE]]<Tableau6[[#This Row],[NET A PAYER]],"PAIEMENT PARTIEL","TROP PAYE")))))) -> PAYE | W13: =SUMIF(Tableau3[FACTURE],Tableau6[[#This Row],[NUM DE FACTURE]],Tableau3[MONTANT TTC]) -> 1593000 | Y13: =+Tableau6[[#This Row],[NET A PAYER]]-Tableau6[[#This Row],[MONTANT PAYE]] -> 0
A14: KENAM S | B14: 45680 | C14: 45680 | D14: 217 | E14: PFO CONSTRUCTION | F14: LOCATION DE CAMIONS | G14: 257B0200 | H14: TVAF | J14: 3500000 | K14: =+Tableau6[[#This Row],[MONTANT HT BIEN]]+Tableau6[[#This Row],[MONTANT HT SERVICE]] -> 3500000 | L14: 0 | M14: =+IFERROR(IF(Tableau6[[#This Row],[CODE TVA]]="TVAF",Tableau6[[#This Row],[MONTANT HT]]*0.18,0),0) -> 630000 | N14: =Tableau6[[#This Row],[MONTANT HT]]+Tableau6[[#This Row],[TVA]]-Tableau6[[#This Row],[ACOMPTE SUR HT]] -> 4130000 | P14: =+ROUND(Tableau6[[#This Row],[MONTANT TTC]]-Tableau6[[#This Row],[ACOMPTE SUR TTC]],0) -> 4130000 | Q14: BC200855 | R14: =IFERROR(INDEX(Tableau2[[ID BC UNIQUE]:[MONTANT HT VALIDE]],MATCH(Tableau6[[#This Row],[N° BC]],Tableau2[ID BC UNIQUE],0),6),0) -> 3500000 | S14: =IFERROR(INDEX(Tableau2[[DATE]:[DELAIS DE PAIEMENT FACTURES EN JOUR]],MATCH(Tableau6[[#This Row],[N° BC]],Tableau2[ID BC UNIQUE],0),5),0) -> 30 | T14: =IF(ISBLANK(Tableau6[[#This Row],[DATE DE DEPOT]]),"",Tableau6[[#This Row],[DATE DE DEPOT]]+Tableau6[[#This Row],[DELAI]]) -> 45710 | U14: =+IF(AND(W14=0,Tableau6[[#This Row],[DATE LIMITE]]<TODAY()),TODAY()-Tableau6[[#This Row],[DATE LIMITE]],0) -> 0 | V14: =IF(Tableau6[[#This Row],[DATE LIMITE]]>=TODAY(),"NON ECHUE",IF(Tableau6[[#This Row],[MONTANT HT]]<0,IF(ISNUMBER(MATCH(-Tableau6[[#This Row],[MONTANT HT]],Tableau6[MONTANT HT],0)),"AVOIR TOTAL","AVOIR PARTIEL"),IF(AND(ISNUMBER(MATCH(-Tableau6[[#This Row],[MONTANT HT]],Tableau6[MONTANT HT],0)),(Tableau6[[#This Row],[ACOMPTE SUR TTC]]+Tableau6[[#This Row],[MONTANT PAYE]])=0),"FACTURE ANNULEE",IF(Tableau6[[#This Row],[ACOMPTE SUR TTC]]+Tableau6[[#This Row],[MONTANT PAYE]]=0,"ECHUE NON REGLEE",IF(Tableau6[[#This Row],[ACOMPTE SUR TTC]]+Tableau6[[#This Row],[MONTANT PAYE]]=Tableau6[[#This Row],[NET A PAYER]],"PAYE",IF(Tableau6[[#This Row],[ACOMPTE SUR TTC]]+Tableau6[[#This Row],[MONTANT PAYE]]<Tableau6[[#This Row],[NET A PAYER]],"PAIEMENT PARTIEL","TROP PAYE")))))) -> PAYE | W14: =SUMIF(Tableau3[FACTURE],Tableau6[[#This Row],[NUM DE FACTURE]],Tableau3[MONTANT TTC]) -> 4130000 | Y14: =+Tableau6[[#This Row],[NET A PAYER]]-Tableau6[[#This Row],[MONTANT PAYE]] -> 0
A15: KENAM S | B15: 45680 | C15: 45680 | D15: 218 | E15: PFO CONSTRUCTION | F15: LOCATION DE CAMIONS | G15: 257B0203 | H15: TVAF | J15: 540000 | K15: =+Tableau6[[#This Row],[MONTANT HT BIEN]]+Tableau6[[#This Row],[MONTANT HT SERVICE]] -> 540000 | L15: 0 | M15: =+IFERROR(IF(Tableau6[[#This Row],[CODE TVA]]="TVAF",Tableau6[[#This Row],[MONTANT HT]]*0.18,0),0) -> 97200 | N15: =Tableau6[[#This Row],[MONTANT HT]]+Tableau6[[#This Row],[TVA]]-Tableau6[[#This Row],[ACOMPTE SUR HT]] -> 637200 | P15: =+ROUND(Tableau6[[#This Row],[MONTANT TTC]]-Tableau6[[#This Row],[ACOMPTE SUR TTC]],0) -> 637200 | Q15: BC200856 | R15: =IFERROR(INDEX(Tableau2[[ID BC UNIQUE]:[MONTANT HT VALIDE]],MATCH(Tableau6[[#This Row],[N° BC]],Tableau2[ID BC UNIQUE],0),6),0) -> 540000 | S15: =IFERROR(INDEX(Tableau2[[DATE]:[DELAIS DE PAIEMENT FACTURES EN JOUR]],MATCH(Tableau6[[#This Row],[N° BC]],Tableau2[ID BC UNIQUE],0),5),0) -> 30 | T15: =IF(ISBLANK(Tableau6[[#This Row],[DATE DE DEPOT]]),"",Tableau6[[#This Row],[DATE DE DEPOT]]+Tableau6[[#This Row],[DELAI]]) -> 45710 | U15: =+IF(AND(W15=0,Tableau6[[#This Row],[DATE LIMITE]]<TODAY()),TODAY()-Tableau6[[#This Row],[DATE LIMITE]],0) -> 0 | V15: =IF(Tableau6[[#This Row],[DATE LIMITE]]>=TODAY(),"NON ECHUE",IF(Tableau6[[#This Row],[MONTANT HT]]<0,IF(ISNUMBER(MATCH(-Tableau6[[#This Row],[MONTANT HT]],Tableau6[MONTANT HT],0)),"AVOIR TOTAL","AVOIR PARTIEL"),IF(AND(ISNUMBER(MATCH(-Tableau6[[#This Row],[MONTANT HT]],Tableau6[MONTANT HT],0)),(Tableau6[[#This Row],[ACOMPTE SUR TTC]]+Tableau6[[#This Row],[MONTANT PAYE]])=0),"FACTURE ANNULEE",IF(Tableau6[[#This Row],[ACOMPTE SUR TTC]]+Tableau6[[#This Row],[MONTANT PAYE]]=0,"ECHUE NON REGLEE",IF(Tableau6[[#This Row],[ACOMPTE SUR TTC]]+Tableau6[[#This Row],[MONTANT PAYE]]=Tableau6[[#This Row],[NET A PAYER]],"PAYE",IF(Tableau6[[#This Row],[ACOMPTE SUR TTC]]+Tableau6[[#This Row],[MONTANT PAYE]]<Tableau6[[#This Row],[NET A PAYER]],"PAIEMENT PARTIEL","TROP PAYE")))))) -> PAYE | W15: =SUMIF(Tableau3[FACTURE],Tableau6[[#This Row],[NUM DE FACTURE]],Tableau3[MONTANT TTC]) -> 637200 | Y15: =+Tableau6[[#This Row],[NET A PAYER]]-Tableau6[[#This Row],[MONTANT PAYE]] -> 0
A16: KENAM S | B16: 45680 | C16: 45680 | D16: 219 | E16: PFO CONSTRUCTION | F16: LOCATION DE CAMIONS | G16: 257B0209 | H16: TVAF | J16: 4000000 | K16: =+Tableau6[[#This Row],[MONTANT HT BIEN]]+Tableau6[[#This Row],[MONTANT HT SERVICE]] -> 4000000 | L16: 0 | M16: =+IFERROR(IF(Tableau6[[#This Row],[CODE TVA]]="TVAF",Tableau6[[#This Row],[MONTANT HT]]*0.18,0),0) -> 720000 | N16: =Tableau6[[#This Row],[MONTANT HT]]+Tableau6[[#This Row],[TVA]]-Tableau6[[#This Row],[ACOMPTE SUR HT]] -> 4720000 | P16: =+ROUND(Tableau6[[#This Row],[MONTANT TTC]]-Tableau6[[#This Row],[ACOMPTE SUR TTC]],0) -> 4720000 | Q16: BC200857 | R16: =IFERROR(INDEX(Tableau2[[ID BC UNIQUE]:[MONTANT HT VALIDE]],MATCH(Tableau6[[#This Row],[N° BC]],Tableau2[ID BC UNIQUE],0),6),0) -> 4000000 | S16: =IFERROR(INDEX(Tableau2[[DATE]:[DELAIS DE PAIEMENT FACTURES EN JOUR]],MATCH(Tableau6[[#This Row],[N° BC]],Tableau2[ID BC UNIQUE],0),5),0) -> 30 | T16: =IF(ISBLANK(Tableau6[[#This Row],[DATE DE DEPOT]]),"",Tableau6[[#This Row],[DATE DE DEPOT]]+Tableau6[[#This Row],[DELAI]]) -> 45710 | U16: =+IF(AND(W16=0,Tableau6[[#This Row],[DATE LIMITE]]<TODAY()),TODAY()-Tableau6[[#This Row],[DATE LIMITE]],0) -> 0 | V16: =IF(Tableau6[[#This Row],[DATE LIMITE]]>=TODAY(),"NON ECHUE",IF(Tableau6[[#This Row],[MONTANT HT]]<0,IF(ISNUMBER(MATCH(-Tableau6[[#This Row],[MONTANT HT]],Tableau6[MONTANT HT],0)),"AVOIR TOTAL","AVOIR PARTIEL"),IF(AND(ISNUMBER(MATCH(-Tableau6[[#This Row],[MONTANT HT]],Tableau6[MONTANT HT],0)),(Tableau6[[#This Row],[ACOMPTE SUR TTC]]+Tableau6[[#This Row],[MONTANT PAYE]])=0),"FACTURE ANNULEE",IF(Tableau6[[#This Row],[ACOMPTE SUR TTC]]+Tableau6[[#This Row],[MONTANT PAYE]]=0,"ECHUE NON REGLEE",IF(Tableau6[[#This Row],[ACOMPTE SUR TTC]]+Tableau6[[#This Row],[MONTANT PAYE]]=Tableau6[[#This Row],[NET A PAYER]],"PAYE",IF(Tableau6[[#This Row],[ACOMPTE SUR TTC]]+Tableau6[[#This Row],[MONTANT PAYE]]<Tableau6[[#This Row],[NET A PAYER]],"PAIEMENT PARTIEL","TROP PAYE")))))) -> PAYE | W16: =SUMIF(Tableau3[FACTURE],Tableau6[[#This Row],[NUM DE FACTURE]],Tableau3[MONTANT TTC]) -> 4720000 | Y16: =+Tableau6[[#This Row],[NET A PAYER]]-Tableau6[[#This Row],[MONTANT PAYE]] -> 0
A17: KENAM S | B17: 45680 | C17: 45680 | D17: 220 | E17: PFO CONSTRUCTION | F17: LOCATION DE CAMIONS | G17: 257B0207 | H17: TVAF | J17: 400000 | K17: =+Tableau6[[#This Row],[MONTANT HT BIEN]]+Tableau6[[#This Row],[MONTANT HT SERVICE]] -> 400000 | L17: 0 | M17: =+IFERROR(IF(Tableau6[[#This Row],[CODE TVA]]="TVAF",Tableau6[[#This Row],[MONTANT HT]]*0.18,0),0) -> 72000 | N17: =Tableau6[[#This Row],[MONTANT HT]]+Tableau6[[#This Row],[TVA]]-Tableau6[[#This Row],[ACOMPTE SUR HT]] -> 472000 | P17: =+ROUND(Tableau6[[#This Row],[MONTANT TTC]]-Tableau6[[#This Row],[ACOMPTE SUR TTC]],0) -> 472000 | Q17: BC200858 | R17: =IFERROR(INDEX(Tableau2[[ID BC UNIQUE]:[MONTANT HT VALIDE]],MATCH(Tableau6[[#This Row],[N° BC]],Tableau2[ID BC UNIQUE],0),6),0) -> 400000 | S17: =IFERROR(INDEX(Tableau2[[DATE]:[DELAIS DE PAIEMENT FACTURES EN JOUR]],MATCH(Tableau6[[#This Row],[N° BC]],Tableau2[ID BC UNIQUE],0),5),0) -> 30 | T17: =IF(ISBLANK(Tableau6[[#This Row],[DATE DE DEPOT]]),"",Tableau6[[#This Row],[DATE DE DEPOT]]+Tableau6[[#This Row],[DELAI]]) -> 45710 | U17: =+IF(AND(W17=0,Tableau6[[#This Row],[DATE LIMITE]]<TODAY()),TODAY()-Tableau6[[#This Row],[DATE LIMITE]],0) -> 0 | V17: =IF(Tableau6[[#This Row],[DATE LIMITE]]>=TODAY(),"NON ECHUE",IF(Tableau6[[#This Row],[MONTANT HT]]<0,IF(ISNUMBER(MATCH(-Tableau6[[#This Row],[MONTANT HT]],Tableau6[MONTANT HT],0)),"AVOIR TOTAL","AVOIR PARTIEL"),IF(AND(ISNUMBER(MATCH(-Tableau6[[#This Row],[MONTANT HT]],Tableau6[MONTANT HT],0)),(Tableau6[[#This Row],[ACOMPTE SUR TTC]]+Tableau6[[#This Row],[MONTANT PAYE]])=0),"FACTURE ANNULEE",IF(Tableau6[[#This Row],[ACOMPTE SUR TTC]]+Tableau6[[#This Row],[MONTANT PAYE]]=0,"ECHUE NON REGLEE",IF(Tableau6[[#This Row],[ACOMPTE SUR TTC]]+Tableau6[[#This Row],[MONTANT PAYE]]=Tableau6[[#This Row],[NET A PAYER]],"PAYE",IF(Tableau6[[#This Row],[ACOMPTE SUR TTC]]+Tableau6[[#This Row],[MONTANT PAYE]]<Tableau6[[#This Row],[NET A PAYER]],"PAIEMENT PARTIEL","TROP PAYE")))))) -> PAYE | W17: =SUMIF(Tableau3[FACTURE],Tableau6[[#This Row],[NUM DE FACTURE]],Tableau3[MONTANT TTC]) -> 472000 | Y17: =+Tableau6[[#This Row],[NET A PAYER]]-Tableau6[[#This Row],[MONTANT PAYE]] -> 0
A18: KENAM S | B18: 45680 | C18: 45680 | D18: 221 | E18: PFO CONSTRUCTION | F18: LOCATION DE CAMIONS | G18: 257B0203 | H18: TVAF | J18: 1400000 | K18: =+Tableau6[[#This Row],[MONTANT HT BIEN]]+Tableau6[[#This Row],[MONTANT HT SERVICE]] -> 1400000 | L18: 0 | M18: =+IFERROR(IF(Tableau6[[#This Row],[CODE TVA]]="TVAF",Tableau6[[#This Row],[MONTANT HT]]*0.18,0),0) -> 252000 | N18: =Tableau6[[#This Row],[MONTANT HT]]+Tableau6[[#This Row],[TVA]]-Tableau6[[#This Row],[ACOMPTE SUR HT]] -> 1652000 | P18: =+ROUND(Tableau6[[#This Row],[MONTANT TTC]]-Tableau6[[#This Row],[ACOMPTE SUR TTC]],0) -> 1652000 | Q18: BC200839 | R18: =IFERROR(INDEX(Tableau2[[ID BC UNIQUE]:[MONTANT HT VALIDE]],MATCH(Tableau6[[#This Row],[N° BC]],Tableau2[ID BC UNIQUE],0),6),0) -> 1400000 | S18: =IFERROR(INDEX(Tableau2[[DATE]:[DELAIS DE PAIEMENT FACTURES EN JOUR]],MATCH(Tableau6[[#This Row],[N° BC]],Tableau2[ID BC UNIQUE],0),5),0) -> 30 | T18: =IF(ISBLANK(Tableau6[[#This Row],[DATE DE DEPOT]]),"",Tableau6[[#This Row],[DATE DE DEPOT]]+Tableau6[[#This Row],[DELAI]]) -> 45710 | U18: =+IF(AND(W18=0,Tableau6[[#This Row],[DATE LIMITE]]<TODAY()),TODAY()-Tableau6[[#This Row],[DATE LIMITE]],0) -> 0 | V18: =IF(Tableau6[[#This Row],[DATE LIMITE]]>=TODAY(),"NON ECHUE",IF(Tableau6[[#This Row],[MONTANT HT]]<0,IF(ISNUMBER(MATCH(-Tableau6[[#This Row],[MONTANT HT]],Tableau6[MONTANT HT],0)),"AVOIR TOTAL","AVOIR PARTIEL"),IF(AND(ISNUMBER(MATCH(-Tableau6[[#This Row],[MONTANT HT]],Tableau6[MONTANT HT],0)),(Tableau6[[#This Row],[ACOMPTE SUR TTC]]+Tableau6[[#This Row],[MONTANT PAYE]])=0),"FACTURE ANNULEE",IF(Tableau6[[#This Row],[ACOMPTE SUR TTC]]+Tableau6[[#This Row],[MONTANT PAYE]]=0,"ECHUE NON REGLEE",IF(Tableau6[[#This Row],[ACOMPTE SUR TTC]]+Tableau6[[#This Row],[MONTANT PAYE]]=Tableau6[[#This Row],[NET A PAYER]],"PAYE",IF(Tableau6[[#This Row],[ACOMPTE SUR TTC]]+Tableau6[[#This Row],[MONTANT PAYE]]<Tableau6[[#This Row],[NET A PAYER]],"PAIEMENT PARTIEL","TROP PAYE")))))) -> PAYE | W18: =SUMIF(Tableau3[FACTURE],Tableau6[[#This Row],[NUM DE FACTURE]],Tableau3[MONTANT TTC]) -> 1652000 | Y18: =+Tableau6[[#This Row],[NET A PAYER]]-Tableau6[[#This Row],[MONTANT PAYE]] -> 0
A19: KENAM S | B19: 45680 | C19: 45680 | D19: 222 | E19: PFO CONSTRUCTION | F19: LOCATION DE CAMIONS | G19: 257B0200 | H19: TVAF | J19: 3800000 | K19: =+Tableau6[[#This Row],[MONTANT HT BIEN]]+Tableau6[[#This Row],[MONTANT HT SERVICE]] -> 3800000 | L19: 0 | M19: =+IFERROR(IF(Tableau6[[#This Row],[CODE TVA]]="TVAF",Tableau6[[#This Row],[MONTANT HT]]*0.18,0),0) -> 684000 | N19: =Tableau6[[#This Row],[MONTANT HT]]+Tableau6[[#This Row],[TVA]]-Tableau6[[#This Row],[ACOMPTE SUR HT]] -> 4484000 | P19: =+ROUND(Tableau6[[#This Row],[MONTANT TTC]]-Tableau6[[#This Row],[ACOMPTE SUR TTC]],0) -> 4484000 | Q19: BC200840 | R19: =IFERROR(INDEX(Tableau2[[ID BC UNIQUE]:[MONTANT HT VALIDE]],MATCH(Tableau6[[#This Row],[N° BC]],Tableau2[ID BC UNIQUE],0),6),0) -> 3800000 | S19: =IFERROR(INDEX(Tableau2[[DATE]:[DELAIS DE PAIEMENT FACTURES EN JOUR]],MATCH(Tableau6[[#This Row],[N° BC]],Tableau2[ID BC UNIQUE],0),5),0) -> 30 | T19: =IF(ISBLANK(Tableau6[[#This Row],[DATE DE DEPOT]]),"",Tableau6[[#This Row],[DATE DE DEPOT]]+Tableau6[[#This Row],[DELAI]]) -> 45710 | U19: =+IF(AND(W19=0,Tableau6[[#This Row],[DATE LIMITE]]<TODAY()),TODAY()-Tableau6[[#This Row],[DATE LIMITE]],0) -> 0 | V19: =IF(Tableau6[[#This Row],[DATE LIMITE]]>=TODAY(),"NON ECHUE",IF(Tableau6[[#This Row],[MONTANT HT]]<0,IF(ISNUMBER(MATCH(-Tableau6[[#This Row],[MONTANT HT]],Tableau6[MONTANT HT],0)),"AVOIR TOTAL","AVOIR PARTIEL"),IF(AND(ISNUMBER(MATCH(-Tableau6[[#This Row],[MONTANT HT]],Tableau6[MONTANT HT],0)),(Tableau6[[#This Row],[ACOMPTE SUR TTC]]+Tableau6[[#This Row],[MONTANT PAYE]])=0),"FACTURE ANNULEE",IF(Tableau6[[#This Row],[ACOMPTE SUR TTC]]+Tableau6[[#This Row],[MONTANT PAYE]]=0,"ECHUE NON REGLEE",IF(Tableau6[[#This Row],[ACOMPTE SUR TTC]]+Tableau6[[#This Row],[MONTANT PAYE]]=Tableau6[[#This Row],[NET A PAYER]],"PAYE",IF(Tableau6[[#This Row],[ACOMPTE SUR TTC]]+Tableau6[[#This Row],[MONTANT PAYE]]<Tableau6[[#This Row],[NET A PAYER]],"PAIEMENT PARTIEL","TROP PAYE")))))) -> PAYE | W19: =SUMIF(Tableau3[FACTURE],Tableau6[[#This Row],[NUM DE FACTURE]],Tableau3[MONTANT TTC]) -> 4484000 | Y19: =+Tableau6[[#This Row],[NET A PAYER]]-Tableau6[[#This Row],[MONTANT PAYE]] -> 0
A20: KENAM S | B20: 45680 | C20: 45680 | D20: 224 | E20: PFO CONSTRUCTION | F20: LOCATION DE CAMIONS | G20: 257B0200 | H20: TVAF | J20: 2700000 | K20: =+Tableau6[[#This Row],[MONTANT HT BIEN]]+Tableau6[[#This Row],[MONTANT HT SERVICE]] -> 2700000 | L20: 0 | M20: =+IFERROR(IF(Tableau6[[#This Row],[CODE TVA]]="TVAF",Tableau6[[#This Row],[MONTANT HT]]*0.18,0),0) -> 486000 | N20: =Tableau6[[#This Row],[MONTANT HT]]+Tableau6[[#This Row],[TVA]]-Tableau6[[#This Row],[ACOMPTE SUR HT]] -> 3186000 | P20: =+ROUND(Tableau6[[#This Row],[MONTANT TTC]]-Tableau6[[#This Row],[ACOMPTE SUR TTC]],0) -> 3186000 | Q20: BC200841 | R20: =IFERROR(INDEX(Tableau2[[ID BC UNIQUE]:[MONTANT HT VALIDE]],MATCH(Tableau6[[#This Row],[N° BC]],Tableau2[ID BC UNIQUE],0),6),0) -> 2700000 | S20: =IFERROR(INDEX(Tableau2[[DATE]:[DELAIS DE PAIEMENT FACTURES EN JOUR]],MATCH(Tableau6[[#This Row],[N° BC]],Tableau2[ID BC UNIQUE],0),5),0) -> 30 | T20: =IF(ISBLANK(Tableau6[[#This Row],[DATE DE DEPOT]]),"",Tableau6[[#This Row],[DATE DE DEPOT]]+Tableau6[[#This Row],[DELAI]]) -> 45710 | U20: =+IF(AND(W20=0,Tableau6[[#This Row],[DATE LIMITE]]<TODAY()),TODAY()-Tableau6[[#This Row],[DATE LIMITE]],0) -> 0 | V20: =IF(Tableau6[[#This Row],[DATE LIMITE]]>=TODAY(),"NON ECHUE",IF(Tableau6[[#This Row],[MONTANT HT]]<0,IF(ISNUMBER(MATCH(-Tableau6[[#This Row],[MONTANT HT]],Tableau6[MONTANT HT],0)),"AVOIR TOTAL","AVOIR PARTIEL"),IF(AND(ISNUMBER(MATCH(-Tableau6[[#This Row],[MONTANT HT]],Tableau6[MONTANT HT],0)),(Tableau6[[#This Row],[ACOMPTE SUR TTC]]+Tableau6[[#This Row],[MONTANT PAYE]])=0),"FACTURE ANNULEE",IF(Tableau6[[#This Row],[ACOMPTE SUR TTC]]+Tableau6[[#This Row],[MONTANT PAYE]]=0,"ECHUE NON REGLEE",IF(Tableau6[[#This Row],[ACOMPTE SUR TTC]]+Tableau6[[#This Row],[MONTANT PAYE]]=Tableau6[[#This Row],[NET A PAYER]],"PAYE",IF(Tableau6[[#This Row],[ACOMPTE SUR TTC]]+Tableau6[[#This Row],[MONTANT PAYE]]<Tableau6[[#This Row],[NET A PAYER]],"PAIEMENT PARTIEL","TROP PAYE")))))) -> PAYE | W20: =SUMIF(Tableau3[FACTURE],Tableau6[[#This Row],[NUM DE FACTURE]],Tableau3[MONTANT TTC]) -> 3186000 | Y20: =+Tableau6[[#This Row],[NET A PAYER]]-Tableau6[[#This Row],[MONTANT PAYE]] -> 0
... A48: KENAM S | B48: 45686 | C48: 45686 | D48: 254 | E48: PFO CONSTRUCTION | F48: LOCATION DE CAMIONS | G48: 170R2101 | H48: TVAF | J48: 5980000 | K48: =+Tableau6[[#This Row],[MONTANT HT BIEN]]+Tableau6[[#This Row],[MONTANT HT SERVICE]] -> 5980000 | L48: 0 | M48: =+IFERROR(IF(Tableau6[[#This Row],[CODE TVA]]="TVAF",Tableau6[[#This Row],[MONTANT HT]]*0.18,0),0) -> 1076400 | N48: =Tableau6[[#This Row],[MONTANT HT]]+Tableau6[[#This Row],[TVA]]-Tableau6[[#This Row],[ACOMPTE SUR HT]] -> 7056400 | P48: =+ROUND(Tableau6[[#This Row],[MONTANT TTC]]-Tableau6[[#This Row],[ACOMPTE SUR TTC]],0) -> 7056400 | Q48: BC101266 | R48: =IFERROR(INDEX(Tableau2[[ID BC UNIQUE]:[MONTANT HT VALIDE]],MATCH(Tableau6[[#This Row],[N° BC]],Tableau2[ID BC UNIQUE],0),6),0) -> 5980000 | S48: =IFERROR(INDEX(Tableau2[[DATE]:[DELAIS DE PAIEMENT FACTURES EN JOUR]],MATCH(Tableau6[[#This Row],[N° BC]],Tableau2[ID BC UNIQUE],0),5),0) -> 30 | T48: =IF(ISBLANK(Tableau6[[#This Row],[DATE DE DEPOT]]),"",Tableau6[[#This Row],[DATE DE DEPOT]]+Tableau6[[#This Row],[DELAI]]) -> 45716 | U48: =+IF(AND(W48=0,Tableau6[[#This Row],[DATE LIMITE]]<TODAY()),TODAY()-Tableau6[[#This Row],[DATE LIMITE]],0) -> 0 | V48: =IF(Tableau6[[#This Row],[DATE LIMITE]]>=TODAY(),"NON ECHUE",IF(Tableau6[[#This Row],[MONTANT HT]]<0,IF(ISNUMBER(MATCH(-Tableau6[[#This Row],[MONTANT HT]],Tableau6[MONTANT HT],0)),"AVOIR TOTAL","AVOIR PARTIEL"),IF(AND(ISNUMBER(MATCH(-Tableau6[[#This Row],[MONTANT HT]],Tableau6[MONTANT HT],0)),(Tableau6[[#This Row],[ACOMPTE SUR TTC]]+Tableau6[[#This Row],[MONTANT PAYE]])=0),"FACTURE ANNULEE",IF(Tableau6[[#This Row],[ACOMPTE SUR TTC]]+Tableau6[[#This Row],[MONTANT PAYE]]=0,"ECHUE NON REGLEE",IF(Tableau6[[#This Row],[ACOMPTE SUR TTC]]+Tableau6[[#This Row],[MONTANT PAYE]]=Tableau6[[#This Row],[NET A PAYER]],"PAYE",IF(Tableau6[[#This Row],[ACOMPTE SUR TTC]]+Tableau6[[#This Row],[MONTANT PAYE]]<Tableau6[[#This Row],[NET A PAYER]],"PAIEMENT PARTIEL","TROP PAYE")))))) -> PAYE | W48: =SUMIF(Tableau3[FACTURE],Tableau6[[#This Row],[NUM DE FACTURE]],Tableau3[MONTANT TTC]) -> 7056400 | Y48: =+Tableau6[[#This Row],[NET A PAYER]]-Tableau6[[#This Row],[MONTANT PAYE]] -> 0
A49: KENAM S | B49: 45686 | C49: 45686 | D49: 255 | E49: KOIRA BTP | F49: LOCATION DE CAMIONS | G49: 211R3002 | H49: TVAF | J49: 3060000 | K49: =+Tableau6[[#This Row],[MONTANT HT BIEN]]+Tableau6[[#This Row],[MONTANT HT SERVICE]] -> 3060000 | L49: 0 | M49: =+IFERROR(IF(Tableau6[[#This Row],[CODE TVA]]="TVAF",Tableau6[[#This Row],[MONTANT HT]]*0.18,0),0) -> 550800 | N49: =Tableau6[[#This Row],[MONTANT HT]]+Tableau6[[#This Row],[TVA]]-Tableau6[[#This Row],[ACOMPTE SUR HT]] -> 3610800 | P49: =+ROUND(Tableau6[[#This Row],[MONTANT TTC]]-Tableau6[[#This Row],[ACOMPTE SUR TTC]],0) -> 3610800 | R49: =IFERROR(INDEX(Tableau2[[ID BC UNIQUE]:[MONTANT HT VALIDE]],MATCH(Tableau6[[#This Row],[N° BC]],Tableau2[ID BC UNIQUE],0),6),0) -> 0 | S49: =IFERROR(INDEX(Tableau2[[DATE]:[DELAIS DE PAIEMENT FACTURES EN JOUR]],MATCH(Tableau6[[#This Row],[N° BC]],Tableau2[ID BC UNIQUE],0),5),0) -> 0 | T49: =IF(ISBLANK(Tableau6[[#This Row],[DATE DE DEPOT]]),"",Tableau6[[#This Row],[DATE DE DEPOT]]+Tableau6[[#This Row],[DELAI]]) -> 45686 | U49: =+IF(AND(W49=0,Tableau6[[#This Row],[DATE LIMITE]]<TODAY()),TODAY()-Tableau6[[#This Row],[DATE LIMITE]],0) -> 0 | V49: =IF(Tableau6[[#This Row],[DATE LIMITE]]>=TODAY(),"NON ECHUE",IF(Tableau6[[#This Row],[MONTANT HT]]<0,IF(ISNUMBER(MATCH(-Tableau6[[#This Row],[MONTANT HT]],Tableau6[MONTANT HT],0)),"AVOIR TOTAL","AVOIR PARTIEL"),IF(AND(ISNUMBER(MATCH(-Tableau6[[#This Row],[MONTANT HT]],Tableau6[MONTANT HT],0)),(Tableau6[[#This Row],[ACOMPTE SUR TTC]]+Tableau6[[#This Row],[MONTANT PAYE]])=0),"FACTURE ANNULEE",IF(Tableau6[[#This Row],[ACOMPTE SUR TTC]]+Tableau6[[#This Row],[MONTANT PAYE]]=0,"ECHUE NON REGLEE",IF(Tableau6[[#This Row],[ACOMPTE SUR TTC]]+Tableau6[[#This Row],[MONTANT PAYE]]=Tableau6[[#This Row],[NET A PAYER]],"PAYE",IF(Tableau6[[#This Row],[ACOMPTE SUR TTC]]+Tableau6[[#This Row],[MONTANT PAYE]]<Tableau6[[#This Row],[NET A PAYER]],"PAIEMENT PARTIEL","TROP PAYE")))))) -> PAYE | W49: =SUMIF(Tableau3[FACTURE],Tableau6[[#This Row],[NUM DE FACTURE]],Tableau3[MONTANT TTC]) -> 3610800 | X49: 45579 | Y49: =+Tableau6[[#This Row],[NET A PAYER]]-Tableau6[[#This Row],[MONTANT PAYE]] -> 0
A50: KENAM S | B50: 45686 | C50: 45686 | D50: 256 | E50: KOIRA BTP | F50: LOCATION DE CAMIONS | G50: 211R3002 | H50: TVAF | J50: 336538.14 | K50: =+Tableau6[[#This Row],[MONTANT HT BIEN]]+Tableau6[[#This Row],[MONTANT HT SERVICE]] -> 336538.14 | L50: 0 | M50: =+IFERROR(IF(Tableau6[[#This Row],[CODE TVA]]="TVAF",Tableau6[[#This Row],[MONTANT HT]]*0.18,0),0) -> 60576.864 | N50: =Tableau6[[#This Row],[MONTANT HT]]+Tableau6[[#This Row],[TVA]]-Tableau6[[#This Row],[ACOMPTE SUR HT]] -> 397115 | P50: =+ROUND(Tableau6[[#This Row],[MONTANT TTC]]-Tableau6[[#This Row],[ACOMPTE SUR TTC]],0) -> 397115 | R50: =IFERROR(INDEX(Tableau2[[ID BC UNIQUE]:[MONTANT HT VALIDE]],MATCH(Tableau6[[#This Row],[N° BC]],Tableau2[ID BC UNIQUE],0),6),0) -> 0 | S50: =IFERROR(INDEX(Tableau2[[DATE]:[DELAIS DE PAIEMENT FACTURES EN JOUR]],MATCH(Tableau6[[#This Row],[N° BC]],Tableau2[ID BC UNIQUE],0),5),0) -> 0 | T50: =IF(ISBLANK(Tableau6[[#This Row],[DATE DE DEPOT]]),"",Tableau6[[#This Row],[DATE DE DEPOT]]+Tableau6[[#This Row],[DELAI]]) -> 45686 | U50: =+IF(AND(W50=0,Tableau6[[#This Row],[DATE LIMITE]]<TODAY()),TODAY()-Tableau6[[#This Row],[DATE LIMITE]],0) -> 0 | V50: =IF(Tableau6[[#This Row],[DATE LIMITE]]>=TODAY(),"NON ECHUE",IF(Tableau6[[#This Row],[MONTANT HT]]<0,IF(ISNUMBER(MATCH(-Tableau6[[#This Row],[MONTANT HT]],Tableau6[MONTANT HT],0)),"AVOIR TOTAL","AVOIR PARTIEL"),IF(AND(ISNUMBER(MATCH(-Tableau6[[#This Row],[MONTANT HT]],Tableau6[MONTANT HT],0)),(Tableau6[[#This Row],[ACOMPTE SUR TTC]]+Tableau6[[#This Row],[MONTANT PAYE]])=0),"FACTURE ANNULEE",IF(Tableau6[[#This Row],[ACOMPTE SUR TTC]]+Tableau6[[#This Row],[MONTANT PAYE]]=0,"ECHUE NON REGLEE",IF(Tableau6[[#This Row],[ACOMPTE SUR TTC]]+Tableau6[[#This Row],[MONTANT PAYE]]=Tableau6[[#This Row],[NET A PAYER]],"PAYE",IF(Tableau6[[#This Row],[ACOMPTE SUR TTC]]+Tableau6[[#This Row],[MONTANT PAYE]]<Tableau6[[#This Row],[NET A PAYER]],"PAIEMENT PARTIEL","TROP PAYE")))))) -> PAYE | W50: =SUMIF(Tableau3[FACTURE],Tableau6[[#This Row],[NUM DE FACTURE]],Tableau3[MONTANT TTC]) -> 397115 | Y50: =+Tableau6[[#This Row],[NET A PAYER]]-Tableau6[[#This Row],[MONTANT PAYE]] -> 0
A51: KENAM S | B51: 45688 | C51: 45688 | D51: 257 | E51: PFO CONSTRUCTION | F51: LOCATION DE CAMIONS | G51: 170R2101 | H51: TVAF | J51: 3450000 | K51: =+Tableau6[[#This Row],[MONTANT HT BIEN]]+Tableau6[[#This Row],[MONTANT HT SERVICE]] -> 3450000 | L51: 0 | M51: =+IFERROR(IF(Tableau6[[#This Row],[CODE TVA]]="TVAF",Tableau6[[#This Row],[MONTANT HT]]*0.18,0),0) -> 621000 | N51: =Tableau6[[#This Row],[MONTANT HT]]+Tableau6[[#This Row],[TVA]]-Tableau6[[#This Row],[ACOMPTE SUR HT]] -> 4071000 | P51: =+ROUND(Tableau6[[#This Row],[MONTANT TTC]]-Tableau6[[#This Row],[ACOMPTE SUR TTC]],0) -> 4071000 | Q51: BC900010 | R51: =IFERROR(INDEX(Tableau2[[ID BC UNIQUE]:[MONTANT HT VALIDE]],MATCH(Tableau6[[#This Row],[N° BC]],Tableau2[ID BC UNIQUE],0),6),0) -> 3450000 | S51: =IFERROR(INDEX(Tableau2[[DATE]:[DELAIS DE PAIEMENT FACTURES EN JOUR]],MATCH(Tableau6[[#This Row],[N° BC]],Tableau2[ID BC UNIQUE],0),5),0) -> 30 | T51: =IF(ISBLANK(Tableau6[[#This Row],[DATE DE DEPOT]]),"",Tableau6[[#This Row],[DATE DE DEPOT]]+Tableau6[[#This Row],[DELAI]]) -> 45718 | U51: =+IF(AND(W51=0,Tableau6[[#This Row],[DATE LIMITE]]<TODAY()),TODAY()-Tableau6[[#This Row],[DATE LIMITE]],0) -> 0 | V51: =IF(Tableau6[[#This Row],[DATE LIMITE]]>=TODAY(),"NON ECHUE",IF(Tableau6[[#This Row],[MONTANT HT]]<0,IF(ISNUMBER(MATCH(-Tableau6[[#This Row],[MONTANT HT]],Tableau6[MONTANT HT],0)),"AVOIR TOTAL","AVOIR PARTIEL"),IF(AND(ISNUMBER(MATCH(-Tableau6[[#This Row],[MONTANT HT]],Tableau6[MONTANT HT],0)),(Tableau6[[#This Row],[ACOMPTE SUR TTC]]+Tableau6[[#This Row],[MONTANT PAYE]])=0),"FACTURE ANNULEE",IF(Tableau6[[#This Row],[ACOMPTE SUR TTC]]+Tableau6[[#This Row],[MONTANT PAYE]]=0,"ECHUE NON REGLEE",IF(Tableau6[[#This Row],[ACOMPTE SUR TTC]]+Tableau6[[#This Row],[MONTANT PAYE]]=Tableau6[[#This Row],[NET A PAYER]],"PAYE",IF(Tableau6[[#This Row],[ACOMPTE SUR TTC]]+Tableau6[[#This Row],[MONTANT PAYE]]<Tableau6[[#This Row],[NET A PAYER]],"PAIEMENT PARTIEL","TROP PAYE")))))) -> PAYE | W51: =SUMIF(Tableau3[FACTURE],Tableau6[[#This Row],[NUM DE FACTURE]],Tableau3[MONTANT TTC]) -> 4071000 | Y51: =+Tableau6[[#This Row],[NET A PAYER]]-Tableau6[[#This Row],[MONTANT PAYE]] -> 0
A52: KENAM S | B52: 45691 | C52: 45691 | D52: 259 | E52: PFO CONSTRUCTION | F52: VENTE DE MATERIEL | G52: 251B0206 | H52: TVAF | I52: 1534000 | K52: =+Tableau6[[#This Row],[MONTANT HT BIEN]]+Tableau6[[#This Row],[MONTANT HT SERVICE]] -> 1534000 | L52: 0 | M52: =+IFERROR(IF(Tableau6[[#This Row],[CODE TVA]]="TVAF",Tableau6[[#This Row],[MONTANT HT]]*0.18,0),0) -> 276120 | N52: =Tableau6[[#This Row],[MONTANT HT]]+Tableau6[[#This Row],[TVA]]-Tableau6[[#This Row],[ACOMPTE SUR HT]] -> 1810120 | P52: =+ROUND(Tableau6[[#This Row],[MONTANT TTC]]-Tableau6[[#This Row],[ACOMPTE SUR TTC]],0) -> 1810120 | Q52: BC2409263 | R52: =IFERROR(INDEX(Tableau2[[ID BC UNIQUE]:[MONTANT HT VALIDE]],MATCH(Tableau6[[#This Row],[N° BC]],Tableau2[ID BC UNIQUE],0),6),0) -> 1534000 | S52: =IFERROR(INDEX(Tableau2[[DATE]:[DELAIS DE PAIEMENT FACTURES EN JOUR]],MATCH(Tableau6[[#This Row],[N° BC]],Tableau2[ID BC UNIQUE],0),5),0) -> 30 | T52: =IF(ISBLANK(Tableau6[[#This Row],[DATE DE DEPOT]]),"",Tableau6[[#This Row],[DATE DE DEPOT]]+Tableau6[[#This Row],[DELAI]]) -> 45721 | U52: =+IF(AND(W52=0,Tableau6[[#This Row],[DATE LIMITE]]<TODAY()),TODAY()-Tableau6[[#This Row],[DATE LIMITE]],0) -> 0 | V52: =IF(Tableau6[[#This Row],[DATE LIMITE]]>=TODAY(),"NON ECHUE",IF(Tableau6[[#This Row],[MONTANT HT]]<0,IF(ISNUMBER(MATCH(-Tableau6[[#This Row],[MONTANT HT]],Tableau6[MONTANT HT],0)),"AVOIR TOTAL","AVOIR PARTIEL"),IF(AND(ISNUMBER(MATCH(-Tableau6[[#This Row],[MONTANT HT]],Tableau6[MONTANT HT],0)),(Tableau6[[#This Row],[ACOMPTE SUR TTC]]+Tableau6[[#This Row],[MONTANT PAYE]])=0),"FACTURE ANNULEE",IF(Tableau6[[#This Row],[ACOMPTE SUR TTC]]+Tableau6[[#This Row],[MONTANT PAYE]]=0,"ECHUE NON REGLEE",IF(Tableau6[[#This Row],[ACOMPTE SUR TTC]]+Tableau6[[#This Row],[MONTANT PAYE]]=Tableau6[[#This Row],[NET A PAYER]],"PAYE",IF(Tableau6[[#This Row],[ACOMPTE SUR TTC]]+Tableau6[[#This Row],[MONTANT PAYE]]<Tableau6[[#This Row],[NET A PAYER]],"PAIEMENT PARTIEL","TROP PAYE")))))) -> PAYE | W52: =SUMIF(Tableau3[FACTURE],Tableau6[[#This Row],[NUM DE FACTURE]],Tableau3[MONTANT TTC]) -> 1810120 | Y52: =+Tableau6[[#This Row],[NET A PAYER]]-Tableau6[[#This Row],[MONTANT PAYE]] -> 0
A53: KENAM S | B53: 45691 | C53: 45691 | D53: 260 | E53: PFO CONSTRUCTION | F53: VENTE DE MATERIEL | G53: 252B0402 | H53: TVAF | I53: 2602000 | K53: =+Tableau6[[#This Row],[MONTANT HT BIEN]]+Tableau6[[#This Row],[MONTANT HT SERVICE]] -> 2602000 | L53: 0 | M53: =+IFERROR(IF(Tableau6[[#This Row],[CODE TVA]]="TVAF",Tableau6[[#This Row],[MONTANT HT]]*0.18,0),0) -> 468360 | N53: =Tableau6[[#This Row],[MONTANT HT]]+Tableau6[[#This Row],[TVA]]-Tableau6[[#This Row],[ACOMPTE SUR HT]] -> 3070360 | P53: =+ROUND(Tableau6[[#This Row],[MONTANT TTC]]-Tableau6[[#This Row],[ACOMPTE SUR TTC]],0) -> 3070360 | Q53: BC200828 | R53: =IFERROR(INDEX(Tableau2[[ID BC UNIQUE]:[MONTANT HT VALIDE]],MATCH(Tableau6[[#This Row],[N° BC]],Tableau2[ID BC UNIQUE],0),6),0) -> 2602000 | S53: =IFERROR(INDEX(Tableau2[[DATE]:[DELAIS DE PAIEMENT FACTURES EN JOUR]],MATCH(Tableau6[[#This Row],[N° BC]],Tableau2[ID BC UNIQUE],0),5),0) -> 30 | T53: =IF(ISBLANK(Tableau6[[#This Row],[DATE DE DEPOT]]),"",Tableau6[[#This Row],[DATE DE DEPOT]]+Tableau6[[#This Row],[DELAI]]) -> 45721 | U53: =+IF(AND(W53=0,Tableau6[[#This Row],[DATE LIMITE]]<TODAY()),TODAY()-Tableau6[[#This Row],[DATE LIMITE]],0) -> 0 | V53: =IF(Tableau6[[#This Row],[DATE LIMITE]]>=TODAY(),"NON ECHUE",IF(Tableau6[[#This Row],[MONTANT HT]]<0,IF(ISNUMBER(MATCH(-Tableau6[[#This Row],[MONTANT HT]],Tableau6[MONTANT HT],0)),"AVOIR TOTAL","AVOIR PARTIEL"),IF(AND(ISNUMBER(MATCH(-Tableau6[[#This Row],[MONTANT HT]],Tableau6[MONTANT HT],0)),(Tableau6[[#This Row],[ACOMPTE SUR TTC]]+Tableau6[[#This Row],[MONTANT PAYE]])=0),"FACTURE ANNULEE",IF(Tableau6[[#This Row],[ACOMPTE SUR TTC]]+Tableau6[[#This Row],[MONTANT PAYE]]=0,"ECHUE NON REGLEE",IF(Tableau6[[#This Row],[ACOMPTE SUR TTC]]+Tableau6[[#This Row],[MONTANT PAYE]]=Tableau6[[#This Row],[NET A PAYER]],"PAYE",IF(Tableau6[[#This Row],[ACOMPTE SUR TTC]]+Tableau6[[#This Row],[MONTANT PAYE]]<Tableau6[[#This Row],[NET A PAYER]],"PAIEMENT PARTIEL","TROP PAYE")))))) -> PAYE | W53: =SUMIF(Tableau3[FACTURE],Tableau6[[#This Row],[NUM DE FACTURE]],Tableau3[MONTANT TTC]) -> 3070360 | Y53: =+Tableau6[[#This Row],[NET A PAYER]]-Tableau6[[#This Row],[MONTANT PAYE]] -> 0
A54: KENAM S | B54: 45692 | C54: 45692 | D54: 262 | E54: PFO CONSTRUCTION | F54: LOCATION DE CAMION | G54: 257B0209 | H54: TVAF | J54: 3622500 | K54: =+Tableau6[[#This Row],[MONTANT HT BIEN]]+Tableau6[[#This Row],[MONTANT HT SERVICE]] -> 3622500 | L54: 0 | M54: =+IFERROR(IF(Tableau6[[#This Row],[CODE TVA]]="TVAF",Tableau6[[#This Row],[MONTANT HT]]*0.18,0),0) -> 652050 | N54: =Tableau6[[#This Row],[MONTANT HT]]+Tableau6[[#This Row],[TVA]]-Tableau6[[#This Row],[ACOMPTE SUR HT]] -> 4274550 | P54: =+ROUND(Tableau6[[#This Row],[MONTANT TTC]]-Tableau6[[#This Row],[ACOMPTE SUR TTC]],0) -> 4274550 | Q54: BC201021 | R54: =IFERROR(INDEX(Tableau2[[ID BC UNIQUE]:[MONTANT HT VALIDE]],MATCH(Tableau6[[#This Row],[N° BC]],Tableau2[ID BC UNIQUE],0),6),0) -> 3622500 | S54: =IFERROR(INDEX(Tableau2[[DATE]:[DELAIS DE PAIEMENT FACTURES EN JOUR]],MATCH(Tableau6[[#This Row],[N° BC]],Tableau2[ID BC UNIQUE],0),5),0) -> 30 | T54: =IF(ISBLANK(Tableau6[[#This Row],[DATE DE DEPOT]]),"",Tableau6[[#This Row],[DATE DE DEPOT]]+Tableau6[[#This Row],[DELAI]]) -> 45722 | U54: =+IF(AND(W54=0,Tableau6[[#This Row],[DATE LIMITE]]<TODAY()),TODAY()-Tableau6[[#This Row],[DATE LIMITE]],0) -> 0 | V54: =IF(Tableau6[[#This Row],[DATE LIMITE]]>=TODAY(),"NON ECHUE",IF(Tableau6[[#This Row],[MONTANT HT]]<0,IF(ISNUMBER(MATCH(-Tableau6[[#This Row],[MONTANT HT]],Tableau6[MONTANT HT],0)),"AVOIR TOTAL","AVOIR PARTIEL"),IF(AND(ISNUMBER(MATCH(-Tableau6[[#This Row],[MONTANT HT]],Tableau6[MONTANT HT],0)),(Tableau6[[#This Row],[ACOMPTE SUR TTC]]+Tableau6[[#This Row],[MONTANT PAYE]])=0),"FACTURE ANNULEE",IF(Tableau6[[#This Row],[ACOMPTE SUR TTC]]+Tableau6[[#This Row],[MONTANT PAYE]]=0,"ECHUE NON REGLEE",IF(Tableau6[[#This Row],[ACOMPTE SUR TTC]]+Tableau6[[#This Row],[MONTANT PAYE]]=Tableau6[[#This Row],[NET A PAYER]],"PAYE",IF(Tableau6[[#This Row],[ACOMPTE SUR TTC]]+Tableau6[[#This Row],[MONTANT PAYE]]<Tableau6[[#This Row],[NET A PAYER]],"PAIEMENT PARTIEL","TROP PAYE")))))) -> TROP PAYE | W54: =SUMIF(Tableau3[FACTURE],Tableau6[[#This Row],[NUM DE FACTURE]],Tableau3[MONTANT TTC]) -> 4306500 | X54: 45561 | Y54: =+Tableau6[[#This Row],[NET A PAYER]]-Tableau6[[#This Row],[MONTANT PAYE]] -> -31950
A55: KENAM S | B55: 45692 | C55: 45702 | D55: 261 | E55: PFO CONSTRUCTION | F55: LOCATION DE BUS DE TRANSPORT-NOVEMBRE 2024 | G55: 654R7007 | H55: TVANF | J55: 1610000 | K55: =+Tableau6[[#This Row],[MONTANT HT BIEN]]+Tableau6[[#This Row],[MONTANT HT SERVICE]] -> 1610000 | M55: =+IFERROR(IF(Tableau6[[#This Row],[CODE TVA]]="TVAF",Tableau6[[#This Row],[MONTANT HT]]*0.18,0),0) -> 0 | N55: =Tableau6[[#This Row],[MONTANT HT]]+Tableau6[[#This Row],[TVA]]-Tableau6[[#This Row],[ACOMPTE SUR HT]] -> 1610000 | P55: =+ROUND(Tableau6[[#This Row],[MONTANT TTC]]-Tableau6[[#This Row],[ACOMPTE SUR TTC]],0) -> 1610000 | Q55: BC101339 | R55: =IFERROR(INDEX(Tableau2[[ID BC UNIQUE]:[MONTANT HT VALIDE]],MATCH(Tableau6[[#This Row],[N° BC]],Tableau2[ID BC UNIQUE],0),6),0) -> 1610000 | S55: =IFERROR(INDEX(Tableau2[[DATE]:[DELAIS DE PAIEMENT FACTURES EN JOUR]],MATCH(Tableau6[[#This Row],[N° BC]],Tableau2[ID BC UNIQUE],0),5),0) -> 30 | T55: =IF(ISBLANK(Tableau6[[#This Row],[DATE DE DEPOT]]),"",Tableau6[[#This Row],[DATE DE DEPOT]]+Tableau6[[#This Row],[DELAI]]) -> 45732 | U55: =+IF(AND(W55=0,Tableau6[[#This Row],[DATE LIMITE]]<TODAY()),TODAY()-Tableau6[[#This Row],[DATE LIMITE]],0) -> 0 | V55: =IF(Tableau6[[#This Row],[DATE LIMITE]]>=TODAY(),"NON ECHUE",IF(Tableau6[[#This Row],[MONTANT HT]]<0,IF(ISNUMBER(MATCH(-Tableau6[[#This Row],[MONTANT HT]],Tableau6[MONTANT HT],0)),"AVOIR TOTAL","AVOIR PARTIEL"),IF(AND(ISNUMBER(MATCH(-Tableau6[[#This Row],[MONTANT HT]],Tableau6[MONTANT HT],0)),(Tableau6[[#This Row],[ACOMPTE SUR TTC]]+Tableau6[[#This Row],[MONTANT PAYE]])=0),"FACTURE ANNULEE",IF(Tableau6[[#This Row],[ACOMPTE SUR TTC]]+Tableau6[[#This Row],[MONTANT PAYE]]=0,"ECHUE NON REGLEE",IF(Tableau6[[#This Row],[ACOMPTE SUR TTC]]+Tableau6[[#This Row],[MONTANT PAYE]]=Tableau6[[#This Row],[NET A PAYER]],"PAYE",IF(Tableau6[[#This Row],[ACOMPTE SUR TTC]]+Tableau6[[#This Row],[MONTANT PAYE]]<Tableau6[[#This Row],[NET A PAYER]],"PAIEMENT PARTIEL","TROP PAYE")))))) -> PAYE | W55: =SUMIF(Tableau3[FACTURE],Tableau6[[#This Row],[NUM DE FACTURE]],Tableau3[MONTANT TTC]) -> 1610000 | Y55: =+Tableau6[[#This Row],[NET A PAYER]]-Tableau6[[#This Row],[MONTANT PAYE]] -> 0
A56: KENAM S | B56: 45693 | C56: 45693 | D56: 263 | E56: PFO CONSTRUCTION | F56: LOCATION DE CAMIONS | G56: 257B0109 | H56: TVAF | J56: 180000 | K56: =+Tableau6[[#This Row],[MONTANT HT BIEN]]+Tableau6[[#This Row],[MONTANT HT SERVICE]] -> 180000 | L56: 0 | M56: =+IFERROR(IF(Tableau6[[#This Row],[CODE TVA]]="TVAF",Tableau6[[#This Row],[MONTANT HT]]*0.18,0),0) -> 32400 | N56: =Tableau6[[#This Row],[MONTANT HT]]+Tableau6[[#This Row],[TVA]]-Tableau6[[#This Row],[ACOMPTE SUR HT]] -> 212400 | P56: =+ROUND(Tableau6[[#This Row],[MONTANT TTC]]-Tableau6[[#This Row],[ACOMPTE SUR TTC]],0) -> 212400 | Q56: BC201018 | R56: =IFERROR(INDEX(Tableau2[[ID BC UNIQUE]:[MONTANT HT VALIDE]],MATCH(Tableau6[[#This Row],[N° BC]],Tableau2[ID BC UNIQUE],0),6),0) -> 180000 | S56: =IFERROR(INDEX(Tableau2[[DATE]:[DELAIS DE PAIEMENT FACTURES EN JOUR]],MATCH(Tableau6[[#This Row],[N° BC]],Tableau2[ID BC UNIQUE],0),5),0) -> 30 | T56: =IF(ISBLANK(Tableau6[[#This Row],[DATE DE DEPOT]]),"",Tableau6[[#This Row],[DATE DE DEPOT]]+Tableau6[[#This Row],[DELAI]]) -> 45723 | U56: =+IF(AND(W56=0,Tableau6[[#This Row],[DATE LIMITE]]<TODAY()),TODAY()-Tableau6[[#This Row],[DATE LIMITE]],0) -> 0 | V56: =IF(Tableau6[[#This Row],[DATE LIMITE]]>=TODAY(),"NON ECHUE",IF(Tableau6[[#This Row],[MONTANT HT]]<0,IF(ISNUMBER(MATCH(-Tableau6[[#This Row],[MONTANT HT]],Tableau6[MONTANT HT],0)),"AVOIR TOTAL","AVOIR PARTIEL"),IF(AND(ISNUMBER(MATCH(-Tableau6[[#This Row],[MONTANT HT]],Tableau6[MONTANT HT],0)),(Tableau6[[#This Row],[ACOMPTE SUR TTC]]+Tableau6[[#This Row],[MONTANT PAYE]])=0),"FACTURE ANNULEE",IF(Tableau6[[#This Row],[ACOMPTE SUR TTC]]+Tableau6[[#This Row],[MONTANT PAYE]]=0,"ECHUE NON REGLEE",IF(Tableau6[[#This Row],[ACOMPTE SUR TTC]]+Tableau6[[#This Row],[MONTANT PAYE]]=Tableau6[[#This Row],[NET A PAYER]],"PAYE",IF(Tableau6[[#This Row],[ACOMPTE SUR TTC]]+Tableau6[[#This Row],[MONTANT PAYE]]<Tableau6[[#This Row],[NET A PAYER]],"PAIEMENT PARTIEL","TROP PAYE")))))) -> PAYE | W56: =SUMIF(Tableau3[FACTURE],Tableau6[[#This Row],[NUM DE FACTURE]],Tableau3[MONTANT TTC]) -> 212400 | Y56: =+Tableau6[[#This Row],[NET A PAYER]]-Tableau6[[#This Row],[MONTANT PAYE]] -> 0
A57: KENAM S | B57: 45693 | C57: 45693 | D57: 271 | E57: AFRIK BETON | F57: LOCATION DE CAMION | H57: TVAF | J57: 560000 | K57: =+Tableau6[[#This Row],[MONTANT HT BIEN]]+Tableau6[[#This Row],[MONTANT HT SERVICE]] -> 560000 | L57: 0 | M57: =+IFERROR(IF(Tableau6[[#This Row],[CODE TVA]]="TVAF",Tableau6[[#This Row],[MONTANT HT]]*0.18,0),0) -> 100800 | N57: =Tableau6[[#This Row],[MONTANT HT]]+Tableau6[[#This Row],[TVA]]-Tableau6[[#This Row],[ACOMPTE SUR HT]] -> 660800 | P57: =+ROUND(Tableau6[[#This Row],[MONTANT TTC]]-Tableau6[[#This Row],[ACOMPTE SUR TTC]],0) -> 660800 | R57: =IFERROR(INDEX(Tableau2[[ID BC UNIQUE]:[MONTANT HT VALIDE]],MATCH(Tableau6[[#This Row],[N° BC]],Tableau2[ID BC UNIQUE],0),6),0) -> 0 | S57: =IFERROR(INDEX(Tableau2[[DATE]:[DELAIS DE PAIEMENT FACTURES EN JOUR]],MATCH(Tableau6[[#This Row],[N° BC]],Tableau2[ID BC UNIQUE],0),5),0) -> 0 | T57: =IF(ISBLANK(Tableau6[[#This Row],[DATE DE DEPOT]]),"",Tableau6[[#This Row],[DATE DE DEPOT]]+Tableau6[[#This Row],[DELAI]]) -> 45693 | U57: =+IF(AND(W57=0,Tableau6[[#This Row],[DATE LIMITE]]<TODAY()),TODAY()-Tableau6[[#This Row],[DATE LIMITE]],0) -> 0 | V57: =IF(Tableau6[[#This Row],[DATE LIMITE]]>=TODAY(),"NON ECHUE",IF(Tableau6[[#This Row],[MONTANT HT]]<0,IF(ISNUMBER(MATCH(-Tableau6[[#This Row],[MONTANT HT]],Tableau6[MONTANT HT],0)),"AVOIR TOTAL","AVOIR PARTIEL"),IF(AND(ISNUMBER(MATCH(-Tableau6[[#This Row],[MONTANT HT]],Tableau6[MONTANT HT],0)),(Tableau6[[#This Row],[ACOMPTE SUR TTC]]+Tableau6[[#This Row],[MONTANT PAYE]])=0),"FACTURE ANNULEE",IF(Tableau6[[#This Row],[ACOMPTE SUR TTC]]+Tableau6[[#This Row],[MONTANT PAYE]]=0,"ECHUE NON REGLEE",IF(Tableau6[[#This Row],[ACOMPTE SUR TTC]]+Tableau6[[#This Row],[MONTANT PAYE]]=Tableau6[[#This Row],[NET A PAYER]],"PAYE",IF(Tableau6[[#This Row],[ACOMPTE SUR TTC]]+Tableau6[[#This Row],[MONTANT PAYE]]<Tableau6[[#This Row],[NET A PAYER]],"PAIEMENT PARTIEL","TROP PAYE")))))) -> PAYE | W57: =SUMIF(Tableau3[FACTURE],Tableau6[[#This Row],[NUM DE FACTURE]],Tableau3[MONTANT TTC]) -> 660800 | X57: 45579 | Y57: =+Tableau6[[#This Row],[NET A PAYER]]-Tableau6[[#This Row],[MONTANT PAYE]] -> 0
A58: KENAM S | B58: 45694 | C58: 45694 | D58: 269 | E58: PFO CONSTRUCTION | F58: LOCATION DE CAMION | G58: 257B0207 | H58: TVAF | J58: 4500000 | K58: =+Tableau6[[#This Row],[MONTANT HT BIEN]]+Tableau6[[#This Row],[MONTANT HT SERVICE]] -> 4500000 | L58: 0 | M58: =+IFERROR(IF(Tableau6[[#This Row],[CODE TVA]]="TVAF",Tableau6[[#This Row],[MONTANT HT]]*0.18,0),0) -> 810000 | N58: =Tableau6[[#This Row],[MONTANT HT]]+Tableau6[[#This Row],[TVA]]-Tableau6[[#This Row],[ACOMPTE SUR HT]] -> 5310000 | P58: =+ROUND(Tableau6[[#This Row],[MONTANT TTC]]-Tableau6[[#This Row],[ACOMPTE SUR TTC]],0) -> 5310000 | Q58: BC201052 | R58: =IFERROR(INDEX(Tableau2[[ID BC UNIQUE]:[MONTANT HT VALIDE]],MATCH(Tableau6[[#This Row],[N° BC]],Tableau2[ID BC UNIQUE],0),6),0) -> 4500000 | S58: =IFERROR(INDEX(Tableau2[[DATE]:[DELAIS DE PAIEMENT FACTURES EN JOUR]],MATCH(Tableau6[[#This Row],[N° BC]],Tableau2[ID BC UNIQUE],0),5),0) -> 30 | T58: =IF(ISBLANK(Tableau6[[#This Row],[DATE DE DEPOT]]),"",Tableau6[[#This Row],[DATE DE DEPOT]]+Tableau6[[#This Row],[DELAI]]) -> 45724 | U58: =+IF(AND(W58=0,Tableau6[[#This Row],[DATE LIMITE]]<TODAY()),TODAY()-Tableau6[[#This Row],[DATE LIMITE]],0) -> 0 | V58: =IF(Tableau6[[#This Row],[DATE LIMITE]]>=TODAY(),"NON ECHUE",IF(Tableau6[[#This Row],[MONTANT HT]]<0,IF(ISNUMBER(MATCH(-Tableau6[[#This Row],[MONTANT HT]],Tableau6[MONTANT HT],0)),"AVOIR TOTAL","AVOIR PARTIEL"),IF(AND(ISNUMBER(MATCH(-Tableau6[[#This Row],[MONTANT HT]],Tableau6[MONTANT HT],0)),(Tableau6[[#This Row],[ACOMPTE SUR TTC]]+Tableau6[[#This Row],[MONTANT PAYE]])=0),"FACTURE ANNULEE",IF(Tableau6[[#This Row],[ACOMPTE SUR TTC]]+Tableau6[[#This Row],[MONTANT PAYE]]=0,"ECHUE NON REGLEE",IF(Tableau6[[#This Row],[ACOMPTE SUR TTC]]+Tableau6[[#This Row],[MONTANT PAYE]]=Tableau6[[#This Row],[NET A PAYER]],"PAYE",IF(Tableau6[[#This Row],[ACOMPTE SUR TTC]]+Tableau6[[#This Row],[MONTANT PAYE]]<Tableau6[[#This Row],[NET A PAYER]],"PAIEMENT PARTIEL","TROP PAYE")))))) -> PAYE | W58: =SUMIF(Tableau3[FACTURE],Tableau6[[#This Row],[NUM DE FACTURE]],Tableau3[MONTANT TTC]) -> 5310000 | Y58: =+Tableau6[[#This Row],[NET A PAYER]]-Tableau6[[#This Row],[MONTANT PAYE]] -> 0
A59: KENAM S | B59: 45694 | C59: 45694 | D59: 285 | E59: SOGENA | F59: LOCATION DE CAMION | H59: TVAF | J59: 216534.51 | K59: =+Tableau6[[#This Row],[MONTANT HT BIEN]]+Tableau6[[#This Row],[MONTANT HT SERVICE]] -> 216534.51 | L59: 0 | M59: =+IFERROR(IF(Tableau6[[#This Row],[CODE TVA]]="TVAF",Tableau6[[#This Row],[MONTANT HT]]*0.18,0),0) -> 38976.212 | N59: =Tableau6[[#This Row],[MONTANT HT]]+Tableau6[[#This Row],[TVA]]-Tableau6[[#This Row],[ACOMPTE SUR HT]] -> 255510.72 | P59: =+ROUND(Tableau6[[#This Row],[MONTANT TTC]]-Tableau6[[#This Row],[ACOMPTE SUR TTC]],0) -> 255511 | R59: =IFERROR(INDEX(Tableau2[[ID BC UNIQUE]:[MONTANT HT VALIDE]],MATCH(Tableau6[[#This Row],[N° BC]],Tableau2[ID BC UNIQUE],0),6),0) -> 0 | S59: =IFERROR(INDEX(Tableau2[[DATE]:[DELAIS DE PAIEMENT FACTURES EN JOUR]],MATCH(Tableau6[[#This Row],[N° BC]],Tableau2[ID BC UNIQUE],0),5),0) -> 0 | T59: =IF(ISBLANK(Tableau6[[#This Row],[DATE DE DEPOT]]),"",Tableau6[[#This Row],[DATE DE DEPOT]]+Tableau6[[#This Row],[DELAI]]) -> 45694 | U59: =+IF(AND(W59=0,Tableau6[[#This Row],[DATE LIMITE]]<TODAY()),TODAY()-Tableau6[[#This Row],[DATE LIMITE]],0) -> 0 | V59: =IF(Tableau6[[#This Row],[DATE LIMITE]]>=TODAY(),"NON ECHUE",IF(Tableau6[[#This Row],[MONTANT HT]]<0,IF(ISNUMBER(MATCH(-Tableau6[[#This Row],[MONTANT HT]],Tableau6[MONTANT HT],0)),"AVOIR TOTAL","AVOIR PARTIEL"),IF(AND(ISNUMBER(MATCH(-Tableau6[[#This Row],[MONTANT HT]],Tableau6[MONTANT HT],0)),(Tableau6[[#This Row],[ACOMPTE SUR TTC]]+Tableau6[[#This Row],[MONTANT PAYE]])=0),"FACTURE ANNULEE",IF(Tableau6[[#This Row],[ACOMPTE SUR TTC]]+Tableau6[[#This Row],[MONTANT PAYE]]=0,"ECHUE NON REGLEE",IF(Tableau6[[#This Row],[ACOMPTE SUR TTC]]+Tableau6[[#This Row],[MONTANT PAYE]]=Tableau6[[#This Row],[NET A PAYER]],"PAYE",IF(Tableau6[[#This Row],[ACOMPTE SUR TTC]]+Tableau6[[#This Row],[MONTANT PAYE]]<Tableau6[[#This Row],[NET A PAYER]],"PAIEMENT PARTIEL","TROP PAYE")))))) -> PAIEMENT PARTIEL | W59: =SUMIF(Tableau3[FACTURE],Tableau6[[#This Row],[NUM DE FACTURE]],Tableau3[MONTANT TTC]) -> 255510.72 | Y59: =+Tableau6[[#This Row],[NET A PAYER]]-Tableau6[[#This Row],[MONTANT PAYE]] -> 0.28
A60: KENAM S | B60: 45694 | C60: 45694 | D60: 286 | E60: SOGENA | F60: LOCATION DE CAMION | H60: TVAF | J60: 58190.034 | K60: =+Tableau6[[#This Row],[MONTANT HT BIEN]]+Tableau6[[#This Row],[MONTANT HT SERVICE]] -> 58190.034 | L60: 0 | M60: =+IFERROR(IF(Tableau6[[#This Row],[CODE TVA]]="TVAF",Tableau6[[#This Row],[MONTANT HT]]*0.18,0),0) -> 10474.206 | N60: =Tableau6[[#This Row],[MONTANT HT]]+Tableau6[[#This Row],[TVA]]-Tableau6[[#This Row],[ACOMPTE SUR HT]] -> 68664.24 | P60: =+ROUND(Tableau6[[#This Row],[MONTANT TTC]]-Tableau6[[#This Row],[ACOMPTE SUR TTC]],0) -> 68664 | R60: =IFERROR(INDEX(Tableau2[[ID BC UNIQUE]:[MONTANT HT VALIDE]],MATCH(Tableau6[[#This Row],[N° BC]],Tableau2[ID BC UNIQUE],0),6),0) -> 0 | S60: =IFERROR(INDEX(Tableau2[[DATE]:[DELAIS DE PAIEMENT FACTURES EN JOUR]],MATCH(Tableau6[[#This Row],[N° BC]],Tableau2[ID BC UNIQUE],0),5),0) -> 0 | T60: =IF(ISBLANK(Tableau6[[#This Row],[DATE DE DEPOT]]),"",Tableau6[[#This Row],[DATE DE DEPOT]]+Tableau6[[#This Row],[DELAI]]) -> 45694 | U60: =+IF(AND(W60=0,Tableau6[[#This Row],[DATE LIMITE]]<TODAY()),TODAY()-Tableau6[[#This Row],[DATE LIMITE]],0) -> 0 | V60: =IF(Tableau6[[#This Row],[DATE LIMITE]]>=TODAY(),"NON ECHUE",IF(Tableau6[[#This Row],[MONTANT HT]]<0,IF(ISNUMBER(MATCH(-Tableau6[[#This Row],[MONTANT HT]],Tableau6[MONTANT HT],0)),"AVOIR TOTAL","AVOIR PARTIEL"),IF(AND(ISNUMBER(MATCH(-Tableau6[[#This Row],[MONTANT HT]],Tableau6[MONTANT HT],0)),(Tableau6[[#This Row],[ACOMPTE SUR TTC]]+Tableau6[[#This Row],[MONTANT PAYE]])=0),"FACTURE ANNULEE",IF(Tableau6[[#This Row],[ACOMPTE SUR TTC]]+Tableau6[[#This Row],[MONTANT PAYE]]=0,"ECHUE NON REGLEE",IF(Tableau6[[#This Row],[ACOMPTE SUR TTC]]+Tableau6[[#This Row],[MONTANT PAYE]]=Tableau6[[#This Row],[NET A PAYER]],"PAYE",IF(Tableau6[[#This Row],[ACOMPTE SUR TTC]]+Tableau6[[#This Row],[MONTANT PAYE]]<Tableau6[[#This Row],[NET A PAYER]],"PAIEMENT PARTIEL","TROP PAYE")))))) -> TROP PAYE | W60: =SUMIF(Tableau3[FACTURE],Tableau6[[#This Row],[NUM DE FACTURE]],Tableau3[MONTANT TTC]) -> 68664.24 | Y60: =+Tableau6[[#This Row],[NET A PAYER]]-Tableau6[[#This Row],[MONTANT PAYE]] -> -0.24
A61: KENAM S | B61: 45694 | C61: 45694 | D61: 287 | E61: SOGENA | F61: LOCATION DE CAMION | H61: TVAF | J61: 1283651.4 | K61: =+Tableau6[[#This Row],[MONTANT HT BIEN]]+Tableau6[[#This Row],[MONTANT HT SERVICE]] -> 1283651.4 | L61: 0 | M61: =+IFERROR(IF(Tableau6[[#This Row],[CODE TVA]]="TVAF",Tableau6[[#This Row],[MONTANT HT]]*0.18,0),0) -> 231057.25 | N61: =Tableau6[[#This Row],[MONTANT HT]]+Tableau6[[#This Row],[TVA]]-Tableau6[[#This Row],[ACOMPTE SUR HT]] -> 1514708.6 | P61: =+ROUND(Tableau6[[#This Row],[MONTANT TTC]]-Tableau6[[#This Row],[ACOMPTE SUR TTC]],0) -> 1514709 | R61: =IFERROR(INDEX(Tableau2[[ID BC UNIQUE]:[MONTANT HT VALIDE]],MATCH(Tableau6[[#This Row],[N° BC]],Tableau2[ID BC UNIQUE],0),6),0) -> 0 | S61: =IFERROR(INDEX(Tableau2[[DATE]:[DELAIS DE PAIEMENT FACTURES EN JOUR]],MATCH(Tableau6[[#This Row],[N° BC]],Tableau2[ID BC UNIQUE],0),5),0) -> 0 | T61: =IF(ISBLANK(Tableau6[[#This Row],[DATE DE DEPOT]]),"",Tableau6[[#This Row],[DATE DE DEPOT]]+Tableau6[[#This Row],[DELAI]]) -> 45694 | U61: =+IF(AND(W61=0,Tableau6[[#This Row],[DATE LIMITE]]<TODAY()),TODAY()-Tableau6[[#This Row],[DATE LIMITE]],0) -> 0 | V61: =IF(Tableau6[[#This Row],[DATE LIMITE]]>=TODAY(),"NON ECHUE",IF(Tableau6[[#This Row],[MONTANT HT]]<0,IF(ISNUMBER(MATCH(-Tableau6[[#This Row],[MONTANT HT]],Tableau6[MONTANT HT],0)),"AVOIR TOTAL","AVOIR PARTIEL"),IF(AND(ISNUMBER(MATCH(-Tableau6[[#This Row],[MONTANT HT]],Tableau6[MONTANT HT],0)),(Tableau6[[#This Row],[ACOMPTE SUR TTC]]+Tableau6[[#This Row],[MONTANT PAYE]])=0),"FACTURE ANNULEE",IF(Tableau6[[#This Row],[ACOMPTE SUR TTC]]+Tableau6[[#This Row],[MONTANT PAYE]]=0,"ECHUE NON REGLEE",IF(Tableau6[[#This Row],[ACOMPTE SUR TTC]]+Tableau6[[#This Row],[MONTANT PAYE]]=Tableau6[[#This Row],[NET A PAYER]],"PAYE",IF(Tableau6[[#This Row],[ACOMPTE SUR TTC]]+Tableau6[[#This Row],[MONTANT PAYE]]<Tableau6[[#This Row],[NET A PAYER]],"PAIEMENT PARTIEL","TROP PAYE")))))) -> PAIEMENT PARTIEL | W61: =SUMIF(Tableau3[FACTURE],Tableau6[[#This Row],[NUM DE FACTURE]],Tableau3[MONTANT TTC]) -> 1514708.6 | Y61: =+Tableau6[[#This Row],[NET A PAYER]]-Tableau6[[#This Row],[MONTANT PAYE]] -> 0.36
A62: KENAM S | B62: 45694 | C62: 45694 | D62: 288 | E62: SOGENA | F62: LOCATION DE CAMION | G62: NAVIRE_ABK | H62: TVAF | J62: 232140 | K62: =+Tableau6[[#This Row],[MONTANT HT BIEN]]+Tableau6[[#This Row],[MONTANT HT SERVICE]] -> 232140 | L62: 0 | M62: =+IFERROR(IF(Tableau6[[#This Row],[CODE TVA]]="TVAF",Tableau6[[#This Row],[MONTANT HT]]*0.18,0),0) -> 41785.2 | N62: =Tableau6[[#This Row],[MONTANT HT]]+Tableau6[[#This Row],[TVA]]-Tableau6[[#This Row],[ACOMPTE SUR HT]] -> 273925.2 | P62: =+ROUND(Tableau6[[#This Row],[MONTANT TTC]]-Tableau6[[#This Row],[ACOMPTE SUR TTC]],0) -> 273925 | R62: =IFERROR(INDEX(Tableau2[[ID BC UNIQUE]:[MONTANT HT VALIDE]],MATCH(Tableau6[[#This Row],[N° BC]],Tableau2[ID BC UNIQUE],0),6),0) -> 0 | S62: =IFERROR(INDEX(Tableau2[[DATE]:[DELAIS DE PAIEMENT FACTURES EN JOUR]],MATCH(Tableau6[[#This Row],[N° BC]],Tableau2[ID BC UNIQUE],0),5),0) -> 0 | T62: =IF(ISBLANK(Tableau6[[#This Row],[DATE DE DEPOT]]),"",Tableau6[[#This Row],[DATE DE DEPOT]]+Tableau6[[#This Row],[DELAI]]) -> 45694 | U62: =+IF(AND(W62=0,Tableau6[[#This Row],[DATE LIMITE]]<TODAY()),TODAY()-Tableau6[[#This Row],[DATE LIMITE]],0) -> 0 | V62: =IF(Tableau6[[#This Row],[DATE LIMITE]]>=TODAY(),"NON ECHUE",IF(Tableau6[[#This Row],[MONTANT HT]]<0,IF(ISNUMBER(MATCH(-Tableau6[[#This Row],[MONTANT HT]],Tableau6[MONTANT HT],0)),"AVOIR TOTAL","AVOIR PARTIEL"),IF(AND(ISNUMBER(MATCH(-Tableau6[[#This Row],[MONTANT HT]],Tableau6[MONTANT HT],0)),(Tableau6[[#This Row],[ACOMPTE SUR TTC]]+Tableau6[[#This Row],[MONTANT PAYE]])=0),"FACTURE ANNULEE",IF(Tableau6[[#This Row],[ACOMPTE SUR TTC]]+Tableau6[[#This Row],[MONTANT PAYE]]=0,"ECHUE NON REGLEE",IF(Tableau6[[#This Row],[ACOMPTE SUR TTC]]+Tableau6[[#This Row],[MONTANT PAYE]]=Tableau6[[#This Row],[NET A PAYER]],"PAYE",IF(Tableau6[[#This Row],[ACOMPTE SUR TTC]]+Tableau6[[#This Row],[MONTANT PAYE]]<Tableau6[[#This Row],[NET A PAYER]],"PAIEMENT PARTIEL","TROP PAYE")))))) -> TROP PAYE | W62: =SUMIF(Tableau3[FACTURE],Tableau6[[#This Row],[NUM DE FACTURE]],Tableau3[MONTANT TTC]) -> 444191 | Y62: =+Tableau6[[#This Row],[NET A PAYER]]-Tableau6[[#This Row],[MONTANT PAYE]] -> -170266
A63: KENAM S | B63: 45699 | C63: 45699 | D63: 272 | E63: PFO CONSTRUCTION | F63: LOCATION DE CAMION | G63: 342R8002 | H63: TVAF | J63: 2100000 | K63: =+Tableau6[[#This Row],[MONTANT HT BIEN]]+Tableau6[[#This Row],[MONTANT HT SERVICE]] -> 2100000 | L63: 0 | M63: =+IFERROR(IF(Tableau6[[#This Row],[CODE TVA]]="TVAF",Tableau6[[#This Row],[MONTANT HT]]*0.18,0),0) -> 378000 | N63: =Tableau6[[#This Row],[MONTANT HT]]+Tableau6[[#This Row],[TVA]]-Tableau6[[#This Row],[ACOMPTE SUR HT]] -> 2478000 | P63: =+ROUND(Tableau6[[#This Row],[MONTANT TTC]]-Tableau6[[#This Row],[ACOMPTE SUR TTC]],0) -> 2478000 | Q63: BC101444 | R63: =IFERROR(INDEX(Tableau2[[ID BC UNIQUE]:[MONTANT HT VALIDE]],MATCH(Tableau6[[#This Row],[N° BC]],Tableau2[ID BC UNIQUE],0),6),0) -> 2100000 | S63: =IFERROR(INDEX(Tableau2[[DATE]:[DELAIS DE PAIEMENT FACTURES EN JOUR]],MATCH(Tableau6[[#This Row],[N° BC]],Tableau2[ID BC UNIQUE],0),5),0) -> 30 | T63: =IF(ISBLANK(Tableau6[[#This Row],[DATE DE DEPOT]]),"",Tableau6[[#This Row],[DATE DE DEPOT]]+Tableau6[[#This Row],[DELAI]]) -> 45729 | U63: =+IF(AND(W63=0,Tableau6[[#This Row],[DATE LIMITE]]<TODAY()),TODAY()-Tableau6[[#This Row],[DATE LIMITE]],0) -> 0 | V63: =IF(Tableau6[[#This Row],[DATE LIMITE]]>=TODAY(),"NON ECHUE",IF(Tableau6[[#This Row],[MONTANT HT]]<0,IF(ISNUMBER(MATCH(-Tableau6[[#This Row],[MONTANT HT]],Tableau6[MONTANT HT],0)),"AVOIR TOTAL","AVOIR PARTIEL"),IF(AND(ISNUMBER(MATCH(-Tableau6[[#This Row],[MONTANT HT]],Tableau6[MONTANT HT],0)),(Tableau6[[#This Row],[ACOMPTE SUR TTC]]+Tableau6[[#This Row],[MONTANT PAYE]])=0),"FACTURE ANNULEE",IF(Tableau6[[#This Row],[ACOMPTE SUR TTC]]+Tableau6[[#This Row],[MONTANT PAYE]]=0,"ECHUE NON REGLEE",IF(Tableau6[[#This Row],[ACOMPTE SUR TTC]]+Tableau6[[#This Row],[MONTANT PAYE]]=Tableau6[[#This Row],[NET A PAYER]],"PAYE",IF(Tableau6[[#This Row],[ACOMPTE SUR TTC]]+Tableau6[[#This Row],[MONTANT PAYE]]<Tableau6[[#This Row],[NET A PAYER]],"PAIEMENT PARTIEL","TROP PAYE")))))) -> PAYE | W63: =SUMIF(Tableau3[FACTURE],Tableau6[[#This Row],[NUM DE FACTURE]],Tableau3[MONTANT TTC]) -> 2478000 | Y63: =+Tableau6[[#This Row],[NET A PAYER]]-Tableau6[[#This Row],[MONTANT PAYE]] -> 0
A64: KENAM S | B64: 45700 | C64: 45700 | D64: 273 | E64: PFO CONSTRUCTION | F64: LOCATION DE CAMION | G64: 654R8002 | H64: TVANF | J64: 1080000 | K64: =+Tableau6[[#This Row],[MONTANT HT BIEN]]+Tableau6[[#This Row],[MONTANT HT SERVICE]] -> 1080000 | L64: 0 | M64: =+IFERROR(IF(Tableau6[[#This Row],[CODE TVA]]="TVAF",Tableau6[[#This Row],[MONTANT HT]]*0.18,0),0) -> 0 | N64: =Tableau6[[#This Row],[MONTANT HT]]+Tableau6[[#This Row],[TVA]]-Tableau6[[#This Row],[ACOMPTE SUR HT]] -> 1080000 | P64: =+ROUND(Tableau6[[#This Row],[MONTANT TTC]]-Tableau6[[#This Row],[ACOMPTE SUR TTC]],0) -> 1080000 | Q64: BC101465 | R64: =IFERROR(INDEX(Tableau2[[ID BC UNIQUE]:[MONTANT HT VALIDE]],MATCH(Tableau6[[#This Row],[N° BC]],Tableau2[ID BC UNIQUE],0),6),0) -> 1080000 | S64: =IFERROR(INDEX(Tableau2[[DATE]:[DELAIS DE PAIEMENT FACTURES EN JOUR]],MATCH(Tableau6[[#This Row],[N° BC]],Tableau2[ID BC UNIQUE],0),5),0) -> 30 | T64: =IF(ISBLANK(Tableau6[[#This Row],[DATE DE DEPOT]]),"",Tableau6[[#This Row],[DATE DE DEPOT]]+Tableau6[[#This Row],[DELAI]]) -> 45730 | U64: =+IF(AND(W64=0,Tableau6[[#This Row],[DATE LIMITE]]<TODAY()),TODAY()-Tableau6[[#This Row],[DATE LIMITE]],0) -> 0 | V64: =IF(Tableau6[[#This Row],[DATE LIMITE]]>=TODAY(),"NON ECHUE",IF(Tableau6[[#This Row],[MONTANT HT]]<0,IF(ISNUMBER(MATCH(-Tableau6[[#This Row],[MONTANT HT]],Tableau6[MONTANT HT],0)),"AVOIR TOTAL","AVOIR PARTIEL"),IF(AND(ISNUMBER(MATCH(-Tableau6[[#This Row],[MONTANT HT]],Tableau6[MONTANT HT],0)),(Tableau6[[#This Row],[ACOMPTE SUR TTC]]+Tableau6[[#This Row],[MONTANT PAYE]])=0),"FACTURE ANNULEE",IF(Tableau6[[#This Row],[ACOMPTE SUR TTC]]+Tableau6[[#This Row],[MONTANT PAYE]]=0,"ECHUE NON REGLEE",IF(Tableau6[[#This Row],[ACOMPTE SUR TTC]]+Tableau6[[#This Row],[MONTANT PAYE]]=Tableau6[[#This Row],[NET A PAYER]],"PAYE",IF(Tableau6[[#This Row],[ACOMPTE SUR TTC]]+Tableau6[[#This Row],[MONTANT PAYE]]<Tableau6[[#This Row],[NET A PAYER]],"PAIEMENT PARTIEL","TROP PAYE")))))) -> PAYE | W64: =SUMIF(Tableau3[FACTURE],Tableau6[[#This Row],[NUM DE FACTURE]],Tableau3[MONTANT TTC]) -> 1080000 | Y64: =+Tableau6[[#This Row],[NET A PAYER]]-Tableau6[[#This Row],[MONTANT PAYE]] -> 0
A65: KENAM S | B65: 45701 | C65: 45701 | D65: 277 | E65: PFO CONSTRUCTION | F65: LOCATION DE CAMION | G65: 348R8002 | H65: TVAF | J65: 5670000 | K65: =+Tableau6[[#This Row],[MONTANT HT BIEN]]+Tableau6[[#This Row],[MONTANT HT SERVICE]] -> 5670000 | L65: 0 | M65: =+IFERROR(IF(Tableau6[[#This Row],[CODE TVA]]="TVAF",Tableau6[[#This Row],[MONTANT HT]]*0.18,0),0) -> 1020600 | N65: =Tableau6[[#This Row],[MONTANT HT]]+Tableau6[[#This Row],[TVA]]-Tableau6[[#This Row],[ACOMPTE SUR HT]] -> 6690600 | P65: =+ROUND(Tableau6[[#This Row],[MONTANT TTC]]-Tableau6[[#This Row],[ACOMPTE SUR TTC]],0) -> 6690600 | Q65: BC101480 | R65: =IFERROR(INDEX(Tableau2[[ID BC UNIQUE]:[MONTANT HT VALIDE]],MATCH(Tableau6[[#This Row],[N° BC]],Tableau2[ID BC UNIQUE],0),6),0) -> 5670000 | S65: =IFERROR(INDEX(Tableau2[[DATE]:[DELAIS DE PAIEMENT FACTURES EN JOUR]],MATCH(Tableau6[[#This Row],[N° BC]],Tableau2[ID BC UNIQUE],0),5),0) -> 30 | T65: =IF(ISBLANK(Tableau6[[#This Row],[DATE DE DEPOT]]),"",Tableau6[[#This Row],[DATE DE DEPOT]]+Tableau6[[#This Row],[DELAI]]) -> 45731 | U65: =+IF(AND(W65=0,Tableau6[[#This Row],[DATE LIMITE]]<TODAY()),TODAY()-Tableau6[[#This Row],[DATE LIMITE]],0) -> 0 | V65: =IF(Tableau6[[#This Row],[DATE LIMITE]]>=TODAY(),"NON ECHUE",IF(Tableau6[[#This Row],[MONTANT HT]]<0,IF(ISNUMBER(MATCH(-Tableau6[[#This Row],[MONTANT HT]],Tableau6[MONTANT HT],0)),"AVOIR TOTAL","AVOIR PARTIEL"),IF(AND(ISNUMBER(MATCH(-Tableau6[[#This Row],[MONTANT HT]],Tableau6[MONTANT HT],0)),(Tableau6[[#This Row],[ACOMPTE SUR TTC]]+Tableau6[[#This Row],[MONTANT PAYE]])=0),"FACTURE ANNULEE",IF(Tableau6[[#This Row],[ACOMPTE SUR TTC]]+Tableau6[[#This Row],[MONTANT PAYE]]=0,"ECHUE NON REGLEE",IF(Tableau6[[#This Row],[ACOMPTE SUR TTC]]+Tableau6[[#This Row],[MONTANT PAYE]]=Tableau6[[#This Row],[NET A PAYER]],"PAYE",IF(Tableau6[[#This Row],[ACOMPTE SUR TTC]]+Tableau6[[#This Row],[MONTANT PAYE]]<Tableau6[[#This Row],[NET A PAYER]],"PAIEMENT PARTIEL","TROP PAYE")))))) -> PAYE | W65: =SUMIF(Tableau3[FACTURE],Tableau6[[#This Row],[NUM DE FACTURE]],Tableau3[MONTANT TTC]) -> 6690600 | Y65: =+Tableau6[[#This Row],[NET A PAYER]]-Tableau6[[#This Row],[MONTANT PAYE]] -> 0
A66: KENAM S | B66: 45701 | C66: 45701 | D66: 278 | E66: PFO CONSTRUCTION | F66: LOCATION DE CAMION | G66: 348R8002 | H66: TVAF | J66: 2870000 | K66: =+Tableau6[[#This Row],[MONTANT HT BIEN]]+Tableau6[[#This Row],[MONTANT HT SERVICE]] -> 2870000 | L66: 0 | M66: =+IFERROR(IF(Tableau6[[#This Row],[CODE TVA]]="TVAF",Tableau6[[#This Row],[MONTANT HT]]*0.18,0),0) -> 516600 | N66: =Tableau6[[#This Row],[MONTANT HT]]+Tableau6[[#This Row],[TVA]]-Tableau6[[#This Row],[ACOMPTE SUR HT]] -> 3386600 | P66: =+ROUND(Tableau6[[#This Row],[MONTANT TTC]]-Tableau6[[#This Row],[ACOMPTE SUR TTC]],0) -> 3386600 | Q66: BC101360 | R66: =IFERROR(INDEX(Tableau2[[ID BC UNIQUE]:[MONTANT HT VALIDE]],MATCH(Tableau6[[#This Row],[N° BC]],Tableau2[ID BC UNIQUE],0),6),0) -> 2870000 | S66: =IFERROR(INDEX(Tableau2[[DATE]:[DELAIS DE PAIEMENT FACTURES EN JOUR]],MATCH(Tableau6[[#This Row],[N° BC]],Tableau2[ID BC UNIQUE],0),5),0) -> 30 | T66: =IF(ISBLANK(Tableau6[[#This Row],[DATE DE DEPOT]]),"",Tableau6[[#This Row],[DATE DE DEPOT]]+Tableau6[[#This Row],[DELAI]]) -> 45731 | U66: =+IF(AND(W66=0,Tableau6[[#This Row],[DATE LIMITE]]<TODAY()),TODAY()-Tableau6[[#This Row],[DATE LIMITE]],0) -> 0 | V66: =IF(Tableau6[[#This Row],[DATE LIMITE]]>=TODAY(),"NON ECHUE",IF(Tableau6[[#This Row],[MONTANT HT]]<0,IF(ISNUMBER(MATCH(-Tableau6[[#This Row],[MONTANT HT]],Tableau6[MONTANT HT],0)),"AVOIR TOTAL","AVOIR PARTIEL"),IF(AND(ISNUMBER(MATCH(-Tableau6[[#This Row],[MONTANT HT]],Tableau6[MONTANT HT],0)),(Tableau6[[#This Row],[ACOMPTE SUR TTC]]+Tableau6[[#This Row],[MONTANT PAYE]])=0),"FACTURE ANNULEE",IF(Tableau6[[#This Row],[ACOMPTE SUR TTC]]+Tableau6[[#This Row],[MONTANT PAYE]]=0,"ECHUE NON REGLEE",IF(Tableau6[[#This Row],[ACOMPTE SUR TTC]]+Tableau6[[#This Row],[MONTANT PAYE]]=Tableau6[[#This Row],[NET A PAYER]],"PAYE",IF(Tableau6[[#This Row],[ACOMPTE SUR TTC]]+Tableau6[[#This Row],[MONTANT PAYE]]<Tableau6[[#This Row],[NET A PAYER]],"PAIEMENT PARTIEL","TROP PAYE")))))) -> PAYE | W66: =SUMIF(Tableau3[FACTURE],Tableau6[[#This Row],[NUM DE FACTURE]],Tableau3[MONTANT TTC]) -> 3386600 | Y66: =+Tableau6[[#This Row],[NET A PAYER]]-Tableau6[[#This Row],[MONTANT PAYE]] -> 0
A67: KENAM S | B67: 45701 | C67: 45701 | D67: 279 | E67: PFO CONSTRUCTION | F67: LOCATION DE CAMION | G67: 348R8002 | H67: TVAF | J67: 8500000 | K67: =+Tableau6[[#This Row],[MONTANT HT BIEN]]+Tableau6[[#This Row],[MONTANT HT SERVICE]] -> 8500000 | L67: 0 | M67: =+IFERROR(IF(Tableau6[[#This Row],[CODE TVA]]="TVAF",Tableau6[[#This Row],[MONTANT HT]]*0.18,0),0) -> 1530000 | N67: =Tableau6[[#This Row],[MONTANT HT]]+Tableau6[[#This Row],[TVA]]-Tableau6[[#This Row],[ACOMPTE SUR HT]] -> 10030000 | P67: =+ROUND(Tableau6[[#This Row],[MONTANT TTC]]-Tableau6[[#This Row],[ACOMPTE SUR TTC]],0) -> 10030000 | Q67: BC101476 | R67: =IFERROR(INDEX(Tableau2[[ID BC UNIQUE]:[MONTANT HT VALIDE]],MATCH(Tableau6[[#This Row],[N° BC]],Tableau2[ID BC UNIQUE],0),6),0) -> 8500000 | S67: =IFERROR(INDEX(Tableau2[[DATE]:[DELAIS DE PAIEMENT FACTURES EN JOUR]],MATCH(Tableau6[[#This Row],[N° BC]],Tableau2[ID BC UNIQUE],0),5),0) -> 30 | T67: =IF(ISBLANK(Tableau6[[#This Row],[DATE DE DEPOT]]),"",Tableau6[[#This Row],[DATE DE DEPOT]]+Tableau6[[#This Row],[DELAI]]) -> 45731 | U67: =+IF(AND(W67=0,Tableau6[[#This Row],[DATE LIMITE]]<TODAY()),TODAY()-Tableau6[[#This Row],[DATE LIMITE]],0) -> 0 | V67: =IF(Tableau6[[#This Row],[DATE LIMITE]]>=TODAY(),"NON ECHUE",IF(Tableau6[[#This Row],[MONTANT HT]]<0,IF(ISNUMBER(MATCH(-Tableau6[[#This Row],[MONTANT HT]],Tableau6[MONTANT HT],0)),"AVOIR TOTAL","AVOIR PARTIEL"),IF(AND(ISNUMBER(MATCH(-Tableau6[[#This Row],[MONTANT HT]],Tableau6[MONTANT HT],0)),(Tableau6[[#This Row],[ACOMPTE SUR TTC]]+Tableau6[[#This Row],[MONTANT PAYE]])=0),"FACTURE ANNULEE",IF(Tableau6[[#This Row],[ACOMPTE SUR TTC]]+Tableau6[[#This Row],[MONTANT PAYE]]=0,"ECHUE NON REGLEE",IF(Tableau6[[#This Row],[ACOMPTE SUR TTC]]+Tableau6[[#This Row],[MONTANT PAYE]]=Tableau6[[#This Row],[NET A PAYER]],"PAYE",IF(Tableau6[[#This Row],[ACOMPTE SUR TTC]]+Tableau6[[#This Row],[MONTANT PAYE]]<Tableau6[[#This Row],[NET A PAYER]],"PAIEMENT PARTIEL","TROP PAYE")))))) -> PAYE | W67: =SUMIF(Tableau3[FACTURE],Tableau6[[#This Row],[NUM DE FACTURE]],Tableau3[MONTANT TTC]) -> 10030000 | Y67: =+Tableau6[[#This Row],[NET A PAYER]]-Tableau6[[#This Row],[MONTANT PAYE]] -> 0
A68: KENAM S | B68: 45701 | C68: 45701 | D68: 280 | E68: PFO CONSTRUCTION | F68: LOCATION DE CAMION | G68: 356R1005 | H68: TVAF | J68: 312500 | K68: =+Tableau6[[#This Row],[MONTANT HT BIEN]]+Tableau6[[#This Row],[MONTANT HT SERVICE]] -> 312500 | L68: 0 | M68: =+IFERROR(IF(Tableau6[[#This Row],[CODE TVA]]="TVAF",Tableau6[[#This Row],[MONTANT HT]]*0.18,0),0) -> 56250 | N68: =Tableau6[[#This Row],[MONTANT HT]]+Tableau6[[#This Row],[TVA]]-Tableau6[[#This Row],[ACOMPTE SUR HT]] -> 368750 | P68: =+ROUND(Tableau6[[#This Row],[MONTANT TTC]]-Tableau6[[#This Row],[ACOMPTE SUR TTC]],0) -> 368750 | Q68: BC101432 | R68: =IFERROR(INDEX(Tableau2[[ID BC UNIQUE]:[MONTANT HT VALIDE]],MATCH(Tableau6[[#This Row],[N° BC]],Tableau2[ID BC UNIQUE],0),6),0) -> 312500 | S68: =IFERROR(INDEX(Tableau2[[DATE]:[DELAIS DE PAIEMENT FACTURES EN JOUR]],MATCH(Tableau6[[#This Row],[N° BC]],Tableau2[ID BC UNIQUE],0),5),0) -> 30 | T68: =IF(ISBLANK(Tableau6[[#This Row],[DATE DE DEPOT]]),"",Tableau6[[#This Row],[DATE DE DEPOT]]+Tableau6[[#This Row],[DELAI]]) -> 45731 | U68: =+IF(AND(W68=0,Tableau6[[#This Row],[DATE LIMITE]]<TODAY()),TODAY()-Tableau6[[#This Row],[DATE LIMITE]],0) -> 0 | V68: =IF(Tableau6[[#This Row],[DATE LIMITE]]>=TODAY(),"NON ECHUE",IF(Tableau6[[#This Row],[MONTANT HT]]<0,IF(ISNUMBER(MATCH(-Tableau6[[#This Row],[MONTANT HT]],Tableau6[MONTANT HT],0)),"AVOIR TOTAL","AVOIR PARTIEL"),IF(AND(ISNUMBER(MATCH(-Tableau6[[#This Row],[MONTANT HT]],Tableau6[MONTANT HT],0)),(Tableau6[[#This Row],[ACOMPTE SUR TTC]]+Tableau6[[#This Row],[MONTANT PAYE]])=0),"FACTURE ANNULEE",IF(Tableau6[[#This Row],[ACOMPTE SUR TTC]]+Tableau6[[#This Row],[MONTANT PAYE]]=0,"ECHUE NON REGLEE",IF(Tableau6[[#This Row],[ACOMPTE SUR TTC]]+Tableau6[[#This Row],[MONTANT PAYE]]=Tableau6[[#This Row],[NET A PAYER]],"PAYE",IF(Tableau6[[#This Row],[ACOMPTE SUR TTC]]+Tableau6[[#This Row],[MONTANT PAYE]]<Tableau6[[#This Row],[NET A PAYER]],"PAIEMENT PARTIEL","TROP PAYE")))))) -> PAYE | W68: =SUMIF(Tableau3[FACTURE],Tableau6[[#This Row],[NUM DE FACTURE]],Tableau3[MONTANT TTC]) -> 368750 | Y68: =+Tableau6[[#This Row],[NET A PAYER]]-Tableau6[[#This Row],[MONTANT PAYE]] -> 0
A69: KENAM S | B69: 45701 | C69: 45701 | D69: 281 | E69: PFO CONSTRUCTION | F69: LOCATION DE CAMION | G69: 332R8002 | H69: TVAF | J69: 2430000 | K69: =+Tableau6[[#This Row],[MONTANT HT BIEN]]+Tableau6[[#This Row],[MONTANT HT SERVICE]] -> 2430000 | L69: 0 | M69: =+IFERROR(IF(Tableau6[[#This Row],[CODE TVA]]="TVAF",Tableau6[[#This Row],[MONTANT HT]]*0.18,0),0) -> 437400 | N69: =Tableau6[[#This Row],[MONTANT HT]]+Tableau6[[#This Row],[TVA]]-Tableau6[[#This Row],[ACOMPTE SUR HT]] -> 2867400 | P69: =+ROUND(Tableau6[[#This Row],[MONTANT TTC]]-Tableau6[[#This Row],[ACOMPTE SUR TTC]],0) -> 2867400 | Q69: BC101373 | R69: =IFERROR(INDEX(Tableau2[[ID BC UNIQUE]:[MONTANT HT VALIDE]],MATCH(Tableau6[[#This Row],[N° BC]],Tableau2[ID BC UNIQUE],0),6),0) -> 2430000 | S69: =IFERROR(INDEX(Tableau2[[DATE]:[DELAIS DE PAIEMENT FACTURES EN JOUR]],MATCH(Tableau6[[#This Row],[N° BC]],Tableau2[ID BC UNIQUE],0),5),0) -> 30 | T69: =IF(ISBLANK(Tableau6[[#This Row],[DATE DE DEPOT]]),"",Tableau6[[#This Row],[DATE DE DEPOT]]+Tableau6[[#This Row],[DELAI]]) -> 45731 | U69: =+IF(AND(W69=0,Tableau6[[#This Row],[DATE LIMITE]]<TODAY()),TODAY()-Tableau6[[#This Row],[DATE LIMITE]],0) -> 0 | V69: =IF(Tableau6[[#This Row],[DATE LIMITE]]>=TODAY(),"NON ECHUE",IF(Tableau6[[#This Row],[MONTANT HT]]<0,IF(ISNUMBER(MATCH(-Tableau6[[#This Row],[MONTANT HT]],Tableau6[MONTANT HT],0)),"AVOIR TOTAL","AVOIR PARTIEL"),IF(AND(ISNUMBER(MATCH(-Tableau6[[#This Row],[MONTANT HT]],Tableau6[MONTANT HT],0)),(Tableau6[[#This Row],[ACOMPTE SUR TTC]]+Tableau6[[#This Row],[MONTANT PAYE]])=0),"FACTURE ANNULEE",IF(Tableau6[[#This Row],[ACOMPTE SUR TTC]]+Tableau6[[#This Row],[MONTANT PAYE]]=0,"ECHUE NON REGLEE",IF(Tableau6[[#This Row],[ACOMPTE SUR TTC]]+Tableau6[[#This Row],[MONTANT PAYE]]=Tableau6[[#This Row],[NET A PAYER]],"PAYE",IF(Tableau6[[#This Row],[ACOMPTE SUR TTC]]+Tableau6[[#This Row],[MONTANT PAYE]]<Tableau6[[#This Row],[NET A PAYER]],"PAIEMENT PARTIEL","TROP PAYE")))))) -> PAYE | W69: =SUMIF(Tableau3[FACTURE],Tableau6[[#This Row],[NUM DE FACTURE]],Tableau3[MONTANT TTC]) -> 2867400 | Y69: =+Tableau6[[#This Row],[NET A PAYER]]-Tableau6[[#This Row],[MONTANT PAYE]] -> 0
A70: KENAM S | B70: 45701 | C70: 45701 | D70: 282 | E70: PFO CONSTRUCTION | F70: LOCATION DE CAMION | G70: 255R8002 | H70: TVAF | J70: 3960000 | K70: =+Tableau6[[#This Row],[MONTANT HT BIEN]]+Tableau6[[#This Row],[MONTANT HT SERVICE]] -> 3960000 | L70: 0 | M70: =+IFERROR(IF(Tableau6[[#This Row],[CODE TVA]]="TVAF",Tableau6[[#This Row],[MONTANT HT]]*0.18,0),0) -> 712800 | N70: =Tableau6[[#This Row],[MONTANT HT]]+Tableau6[[#This Row],[TVA]]-Tableau6[[#This Row],[ACOMPTE SUR HT]] -> 4672800 | P70: =+ROUND(Tableau6[[#This Row],[MONTANT TTC]]-Tableau6[[#This Row],[ACOMPTE SUR TTC]],0) -> 4672800 | Q70: BC101383 | R70: =IFERROR(INDEX(Tableau2[[ID BC UNIQUE]:[MONTANT HT VALIDE]],MATCH(Tableau6[[#This Row],[N° BC]],Tableau2[ID BC UNIQUE],0),6),0) -> 3960000 | S70: =IFERROR(INDEX(Tableau2[[DATE]:[DELAIS DE PAIEMENT FACTURES EN JOUR]],MATCH(Tableau6[[#This Row],[N° BC]],Tableau2[ID BC UNIQUE],0),5),0) -> 30 | T70: =IF(ISBLANK(Tableau6[[#This Row],[DATE DE DEPOT]]),"",Tableau6[[#This Row],[DATE DE DEPOT]]+Tableau6[[#This Row],[DELAI]]) -> 45731 | U70: =+IF(AND(W70=0,Tableau6[[#This Row],[DATE LIMITE]]<TODAY()),TODAY()-Tableau6[[#This Row],[DATE LIMITE]],0) -> 0 | V70: =IF(Tableau6[[#This Row],[DATE LIMITE]]>=TODAY(),"NON ECHUE",IF(Tableau6[[#This Row],[MONTANT HT]]<0,IF(ISNUMBER(MATCH(-Tableau6[[#This Row],[MONTANT HT]],Tableau6[MONTANT HT],0)),"AVOIR TOTAL","AVOIR PARTIEL"),IF(AND(ISNUMBER(MATCH(-Tableau6[[#This Row],[MONTANT HT]],Tableau6[MONTANT HT],0)),(Tableau6[[#This Row],[ACOMPTE SUR TTC]]+Tableau6[[#This Row],[MONTANT PAYE]])=0),"FACTURE ANNULEE",IF(Tableau6[[#This Row],[ACOMPTE SUR TTC]]+Tableau6[[#This Row],[MONTANT PAYE]]=0,"ECHUE NON REGLEE",IF(Tableau6[[#This Row],[ACOMPTE SUR TTC]]+Tableau6[[#This Row],[MONTANT PAYE]]=Tableau6[[#This Row],[NET A PAYER]],"PAYE",IF(Tableau6[[#This Row],[ACOMPTE SUR TTC]]+Tableau6[[#This Row],[MONTANT PAYE]]<Tableau6[[#This Row],[NET A PAYER]],"PAIEMENT PARTIEL","TROP PAYE")))))) -> PAYE | W70: =SUMIF(Tableau3[FACTURE],Tableau6[[#This Row],[NUM DE FACTURE]],Tableau3[MONTANT TTC]) -> 4672800 | X70: 45579 | Y70: =+Tableau6[[#This Row],[NET A PAYER]]-Tableau6[[#This Row],[MONTANT PAYE]] -> 0
A71: KENAM S | B71: 45705 | C71: 45705 | D71: 274 | E71: PFO CONSTRUCTION | F71: LOCATION DE CAMION | G71: 654R7007 | H71: TVANF | J71: 980000 | K71: =+Tableau6[[#This Row],[MONTANT HT BIEN]]+Tableau6[[#This Row],[MONTANT HT SERVICE]] -> 980000 | L71: 0 | M71: =+IFERROR(IF(Tableau6[[#This Row],[CODE TVA]]="TVAF",Tableau6[[#This Row],[MONTANT HT]]*0.18,0),0) -> 0 | N71: =Tableau6[[#This Row],[MONTANT HT]]+Tableau6[[#This Row],[TVA]]-Tableau6[[#This Row],[ACOMPTE SUR HT]] -> 980000 | P71: =+ROUND(Tableau6[[#This Row],[MONTANT TTC]]-Tableau6[[#This Row],[ACOMPTE SUR TTC]],0) -> 980000 | Q71: BC101559 | R71: =IFERROR(INDEX(Tableau2[[ID BC UNIQUE]:[MONTANT HT VALIDE]],MATCH(Tableau6[[#This Row],[N° BC]],Tableau2[ID BC UNIQUE],0),6),0) -> 980000 | S71: =IFERROR(INDEX(Tableau2[[DATE]:[DELAIS DE PAIEMENT FACTURES EN JOUR]],MATCH(Tableau6[[#This Row],[N° BC]],Tableau2[ID BC UNIQUE],0),5),0) -> 30 | T71: =IF(ISBLANK(Tableau6[[#This Row],[DATE DE DEPOT]]),"",Tableau6[[#This Row],[DATE DE DEPOT]]+Tableau6[[#This Row],[DELAI]]) -> 45735 | U71: =+IF(AND(W71=0,Tableau6[[#This Row],[DATE LIMITE]]<TODAY()),TODAY()-Tableau6[[#This Row],[DATE LIMITE]],0) -> 0 | V71: =IF(Tableau6[[#This Row],[DATE LIMITE]]>=TODAY(),"NON ECHUE",IF(Tableau6[[#This Row],[MONTANT HT]]<0,IF(ISNUMBER(MATCH(-Tableau6[[#This Row],[MONTANT HT]],Tableau6[MONTANT HT],0)),"AVOIR TOTAL","AVOIR PARTIEL"),IF(AND(ISNUMBER(MATCH(-Tableau6[[#This Row],[MONTANT HT]],Tableau6[MONTANT HT],0)),(Tableau6[[#This Row],[ACOMPTE SUR TTC]]+Tableau6[[#This Row],[MONTANT PAYE]])=0),"FACTURE ANNULEE",IF(Tableau6[[#This Row],[ACOMPTE SUR TTC]]+Tableau6[[#This Row],[MONTANT PAYE]]=0,"ECHUE NON REGLEE",IF(Tableau6[[#This Row],[ACOMPTE SUR TTC]]+Tableau6[[#This Row],[MONTANT PAYE]]=Tableau6[[#This Row],[NET A PAYER]],"PAYE",IF(Tableau6[[#This Row],[ACOMPTE SUR TTC]]+Tableau6[[#This Row],[MONTANT PAYE]]<Tableau6[[#This Row],[NET A PAYER]],"PAIEMENT PARTIEL","TROP PAYE")))))) -> PAYE | W71: =SUMIF(Tableau3[FACTURE],Tableau6[[#This Row],[NUM DE FACTURE]],Tableau3[MONTANT TTC]) -> 980000 | X71: 45548 | Y71: =+Tableau6[[#This Row],[NET A PAYER]]-Tableau6[[#This Row],[MONTANT PAYE]] -> 0
A72: KENAM S | B72: 45705 | C72: 45705 | D72: 292 | E72: PFO CONSTRUCTION | F72: LOCATION DE CAMION | G72: 305R8002 | H72: TVAF | J72: 27468694 | K72: =+Tableau6[[#This Row],[MONTANT HT BIEN]]+Tableau6[[#This Row],[MONTANT HT SERVICE]] -> 27468694 | L72: 0 | M72: =+IFERROR(IF(Tableau6[[#This Row],[CODE TVA]]="TVAF",Tableau6[[#This Row],[MONTANT HT]]*0.18,0),0) -> 4944364.9 | N72: =Tableau6[[#This Row],[MONTANT HT]]+Tableau6[[#This Row],[TVA]]-Tableau6[[#This Row],[ACOMPTE SUR HT]] -> 32413059 | P72: =+ROUND(Tableau6[[#This Row],[MONTANT TTC]]-Tableau6[[#This Row],[ACOMPTE SUR TTC]],0) -> 32413059 | Q72: BC101548 | R72: =IFERROR(INDEX(Tableau2[[ID BC UNIQUE]:[MONTANT HT VALIDE]],MATCH(Tableau6[[#This Row],[N° BC]],Tableau2[ID BC UNIQUE],0),6),0) -> 27468694 | S72: =IFERROR(INDEX(Tableau2[[DATE]:[DELAIS DE PAIEMENT FACTURES EN JOUR]],MATCH(Tableau6[[#This Row],[N° BC]],Tableau2[ID BC UNIQUE],0),5),0) -> 30 | T72: =IF(ISBLANK(Tableau6[[#This Row],[DATE DE DEPOT]]),"",Tableau6[[#This Row],[DATE DE DEPOT]]+Tableau6[[#This Row],[DELAI]]) -> 45735 | U72: =+IF(AND(W72=0,Tableau6[[#This Row],[DATE LIMITE]]<TODAY()),TODAY()-Tableau6[[#This Row],[DATE LIMITE]],0) -> 0 | V72: =IF(Tableau6[[#This Row],[DATE LIMITE]]>=TODAY(),"NON ECHUE",IF(Tableau6[[#This Row],[MONTANT HT]]<0,IF(ISNUMBER(MATCH(-Tableau6[[#This Row],[MONTANT HT]],Tableau6[MONTANT HT],0)),"AVOIR TOTAL","AVOIR PARTIEL"),IF(AND(ISNUMBER(MATCH(-Tableau6[[#This Row],[MONTANT HT]],Tableau6[MONTANT HT],0)),(Tableau6[[#This Row],[ACOMPTE SUR TTC]]+Tableau6[[#This Row],[MONTANT PAYE]])=0),"FACTURE ANNULEE",IF(Tableau6[[#This Row],[ACOMPTE SUR TTC]]+Tableau6[[#This Row],[MONTANT PAYE]]=0,"ECHUE NON REGLEE",IF(Tableau6[[#This Row],[ACOMPTE SUR TTC]]+Tableau6[[#This Row],[MONTANT PAYE]]=Tableau6[[#This Row],[NET A PAYER]],"PAYE",IF(Tableau6[[#This Row],[ACOMPTE SUR TTC]]+Tableau6[[#This Row],[MONTANT PAYE]]<Tableau6[[#This Row],[NET A PAYER]],"PAIEMENT PARTIEL","TROP PAYE")))))) -> PAYE | W72: =SUMIF(Tableau3[FACTURE],Tableau6[[#This Row],[NUM DE FACTURE]],Tableau3[MONTANT TTC]) -> 32413059 | Y72: =+Tableau6[[#This Row],[NET A PAYER]]-Tableau6[[#This Row],[MONTANT PAYE]] -> 0
A73: KENAM S | B73: 45706 | C73: 45706 | D73: 291 | E73: PFO CONSTRUCTION | F73: LOCATION DE CAMION | G73: 305R9012 | H73: TVAF | J73: 340000 | K73: =+Tableau6[[#This Row],[MONTANT HT BIEN]]+Tableau6[[#This Row],[MONTANT HT SERVICE]] -> 340000 | L73: 0 | M73: =+IFERROR(IF(Tableau6[[#This Row],[CODE TVA]]="TVAF",Tableau6[[#This Row],[MONTANT HT]]*0.18,0),0) -> 61200 | N73: =Tableau6[[#This Row],[MONTANT HT]]+Tableau6[[#This Row],[TVA]]-Tableau6[[#This Row],[ACOMPTE SUR HT]] -> 401200 | P73: =+ROUND(Tableau6[[#This Row],[MONTANT TTC]]-Tableau6[[#This Row],[ACOMPTE SUR TTC]],0) -> 401200 | Q73: BC101516 | R73: =IFERROR(INDEX(Tableau2[[ID BC UNIQUE]:[MONTANT HT VALIDE]],MATCH(Tableau6[[#This Row],[N° BC]],Tableau2[ID BC UNIQUE],0),6),0) -> 340000 | S73: =IFERROR(INDEX(Tableau2[[DATE]:[DELAIS DE PAIEMENT FACTURES EN JOUR]],MATCH(Tableau6[[#This Row],[N° BC]],Tableau2[ID BC UNIQUE],0),5),0) -> 30 | T73: =IF(ISBLANK(Tableau6[[#This Row],[DATE DE DEPOT]]),"",Tableau6[[#This Row],[DATE DE DEPOT]]+Tableau6[[#This Row],[DELAI]]) -> 45736 | U73: =+IF(AND(W73=0,Tableau6[[#This Row],[DATE LIMITE]]<TODAY()),TODAY()-Tableau6[[#This Row],[DATE LIMITE]],0) -> 0 | V73: =IF(Tableau6[[#This Row],[DATE LIMITE]]>=TODAY(),"NON ECHUE",IF(Tableau6[[#This Row],[MONTANT HT]]<0,IF(ISNUMBER(MATCH(-Tableau6[[#This Row],[MONTANT HT]],Tableau6[MONTANT HT],0)),"AVOIR TOTAL","AVOIR PARTIEL"),IF(AND(ISNUMBER(MATCH(-Tableau6[[#This Row],[MONTANT HT]],Tableau6[MONTANT HT],0)),(Tableau6[[#This Row],[ACOMPTE SUR TTC]]+Tableau6[[#This Row],[MONTANT PAYE]])=0),"FACTURE ANNULEE",IF(Tableau6[[#This Row],[ACOMPTE SUR TTC]]+Tableau6[[#This Row],[MONTANT PAYE]]=0,"ECHUE NON REGLEE",IF(Tableau6[[#This Row],[ACOMPTE SUR TTC]]+Tableau6[[#This Row],[MONTANT PAYE]]=Tableau6[[#This Row],[NET A PAYER]],"PAYE",IF(Tableau6[[#This Row],[ACOMPTE SUR TTC]]+Tableau6[[#This Row],[MONTANT PAYE]]<Tableau6[[#This Row],[NET A PAYER]],"PAIEMENT PARTIEL","TROP PAYE")))))) -> PAYE | W73: =SUMIF(Tableau3[FACTURE],Tableau6[[#This Row],[NUM DE FACTURE]],Tableau3[MONTANT TTC]) -> 401200 | Y73: =+Tableau6[[#This Row],[NET A PAYER]]-Tableau6[[#This Row],[MONTANT PAYE]] -> 0
A74: KENAM S | B74: 45713 | C74: 45713 | D74: 290 | E74: KOIRA BTP | F74: VENTE DE MATERIEL | G74: 211R2009 | H74: TVAF | I74: 21000000 | K74: =+Tableau6[[#This Row],[MONTANT HT BIEN]]+Tableau6[[#This Row],[MONTANT HT SERVICE]] -> 21000000 | L74: 0 | M74: =+IFERROR(IF(Tableau6[[#This Row],[CODE TVA]]="TVAF",Tableau6[[#This Row],[MONTANT HT]]*0.18,0),0) -> 3780000 | N74: =Tableau6[[#This Row],[MONTANT HT]]+Tableau6[[#This Row],[TVA]]-Tableau6[[#This Row],[ACOMPTE SUR HT]] -> 24780000 | P74: =+ROUND(Tableau6[[#This Row],[MONTANT TTC]]-Tableau6[[#This Row],[ACOMPTE SUR TTC]],0) -> 24780000 | R74: =IFERROR(INDEX(Tableau2[[ID BC UNIQUE]:[MONTANT HT VALIDE]],MATCH(Tableau6[[#This Row],[N° BC]],Tableau2[ID BC UNIQUE],0),6),0) -> 0 | S74: =IFERROR(INDEX(Tableau2[[DATE]:[DELAIS DE PAIEMENT FACTURES EN JOUR]],MATCH(Tableau6[[#This Row],[N° BC]],Tableau2[ID BC UNIQUE],0),5),0) -> 0 | T74: =IF(ISBLANK(Tableau6[[#This Row],[DATE DE DEPOT]]),"",Tableau6[[#This Row],[DATE DE DEPOT]]+Tableau6[[#This Row],[DELAI]]) -> 45713 | U74: =+IF(AND(W74=0,Tableau6[[#This Row],[DATE LIMITE]]<TODAY()),TODAY()-Tableau6[[#This Row],[DATE LIMITE]],0) -> 0 | V74: =IF(Tableau6[[#This Row],[DATE LIMITE]]>=TODAY(),"NON ECHUE",IF(Tableau6[[#This Row],[MONTANT HT]]<0,IF(ISNUMBER(MATCH(-Tableau6[[#This Row],[MONTANT HT]],Tableau6[MONTANT HT],0)),"AVOIR TOTAL","AVOIR PARTIEL"),IF(AND(ISNUMBER(MATCH(-Tableau6[[#This Row],[MONTANT HT]],Tableau6[MONTANT HT],0)),(Tableau6[[#This Row],[ACOMPTE SUR TTC]]+Tableau6[[#This Row],[MONTANT PAYE]])=0),"FACTURE ANNULEE",IF(Tableau6[[#This Row],[ACOMPTE SUR TTC]]+Tableau6[[#This Row],[MONTANT PAYE]]=0,"ECHUE NON REGLEE",IF(Tableau6[[#This Row],[ACOMPTE SUR TTC]]+Tableau6[[#This Row],[MONTANT PAYE]]=Tableau6[[#This Row],[NET A PAYER]],"PAYE",IF(Tableau6[[#This Row],[ACOMPTE SUR TTC]]+Tableau6[[#This Row],[MONTANT PAYE]]<Tableau6[[#This Row],[NET A PAYER]],"PAIEMENT PARTIEL","TROP PAYE")))))) -> PAYE | W74: =SUMIF(Tableau3[FACTURE],Tableau6[[#This Row],[NUM DE FACTURE]],Tableau3[MONTANT TTC]) -> 24780000 | X74: 45585 | Y74: =+Tableau6[[#This Row],[NET A PAYER]]-Tableau6[[#This Row],[MONTANT PAYE]] -> 0
A75: KENAM S | B75: 45716 | C75: 45716 | D75: 293 | E75: PFO CONSTRUCTION | F75: LOCATION DE CAMION | G75: 257B0003 | H75: TVAF | J75: 4200000 | K75: =+Tableau6[[#This Row],[MONTANT HT BIEN]]+Tableau6[[#This Row],[MONTANT HT SERVICE]] -> 4200000 | L75: 0 | M75: =+IFERROR(IF(Tableau6[[#This Row],[CODE TVA]]="TVAF",Tableau6[[#This Row],[MONTANT HT]]*0.18,0),0) -> 756000 | N75: =Tableau6[[#This Row],[MONTANT HT]]+Tableau6[[#This Row],[TVA]]-Tableau6[[#This Row],[ACOMPTE SUR HT]] -> 4956000 | P75: =+ROUND(Tableau6[[#This Row],[MONTANT TTC]]-Tableau6[[#This Row],[ACOMPTE SUR TTC]],0) -> 4956000 | Q75: BC201244 | R75: =IFERROR(INDEX(Tableau2[[ID BC UNIQUE]:[MONTANT HT VALIDE]],MATCH(Tableau6[[#This Row],[N° BC]],Tableau2[ID BC UNIQUE],0),6),0) -> 4200000 | S75: =IFERROR(INDEX(Tableau2[[DATE]:[DELAIS DE PAIEMENT FACTURES EN JOUR]],MATCH(Tableau6[[#This Row],[N° BC]],Tableau2[ID BC UNIQUE],0),5),0) -> 30 | T75: =IF(ISBLANK(Tableau6[[#This Row],[DATE DE DEPOT]]),"",Tableau6[[#This Row],[DATE DE DEPOT]]+Tableau6[[#This Row],[DELAI]]) -> 45746 | U75: =+IF(AND(W75=0,Tableau6[[#This Row],[DATE LIMITE]]<TODAY()),TODAY()-Tableau6[[#This Row],[DATE LIMITE]],0) -> 0 | V75: =IF(Tableau6[[#This Row],[DATE LIMITE]]>=TODAY(),"NON ECHUE",IF(Tableau6[[#This Row],[MONTANT HT]]<0,IF(ISNUMBER(MATCH(-Tableau6[[#This Row],[MONTANT HT]],Tableau6[MONTANT HT],0)),"AVOIR TOTAL","AVOIR PARTIEL"),IF(AND(ISNUMBER(MATCH(-Tableau6[[#This Row],[MONTANT HT]],Tableau6[MONTANT HT],0)),(Tableau6[[#This Row],[ACOMPTE SUR TTC]]+Tableau6[[#This Row],[MONTANT PAYE]])=0),"FACTURE ANNULEE",IF(Tableau6[[#This Row],[ACOMPTE SUR TTC]]+Tableau6[[#This Row],[MONTANT PAYE]]=0,"ECHUE NON REGLEE",IF(Tableau6[[#This Row],[ACOMPTE SUR TTC]]+Tableau6[[#This Row],[MONTANT PAYE]]=Tableau6[[#This Row],[NET A PAYER]],"PAYE",IF(Tableau6[[#This Row],[ACOMPTE SUR TTC]]+Tableau6[[#This Row],[MONTANT PAYE]]<Tableau6[[#This Row],[NET A PAYER]],"PAIEMENT PARTIEL","TROP PAYE")))))) -> PAYE | W75: =SUMIF(Tableau3[FACTURE],Tableau6[[#This Row],[NUM DE FACTURE]],Tableau3[MONTANT TTC]) -> 4956000 | Y75: =+Tableau6[[#This Row],[NET A PAYER]]-Tableau6[[#This Row],[MONTANT PAYE]] -> 0
A76: KENAM S | B76: 45716 | C76: 45716 | D76: 294 | E76: PFO CONSTRUCTION | F76: LOCATION DE CAMION | G76: 257B0003 | H76: TVAF | J76: 3500000 | K76: =+Tableau6[[#This Row],[MONTANT HT BIEN]]+Tableau6[[#This Row],[MONTANT HT SERVICE]] -> 3500000 | L76: 0 | M76: =+IFERROR(IF(Tableau6[[#This Row],[CODE TVA]]="TVAF",Tableau6[[#This Row],[MONTANT HT]]*0.18,0),0) -> 630000 | N76: =Tableau6[[#This Row],[MONTANT HT]]+Tableau6[[#This Row],[TVA]]-Tableau6[[#This Row],[ACOMPTE SUR HT]] -> 4130000 | P76: =+ROUND(Tableau6[[#This Row],[MONTANT TTC]]-Tableau6[[#This Row],[ACOMPTE SUR TTC]],0) -> 4130000 | Q76: BC201245 | R76: =IFERROR(INDEX(Tableau2[[ID BC UNIQUE]:[MONTANT HT VALIDE]],MATCH(Tableau6[[#This Row],[N° BC]],Tableau2[ID BC UNIQUE],0),6),0) -> 3500000 | S76: =IFERROR(INDEX(Tableau2[[DATE]:[DELAIS DE PAIEMENT FACTURES EN JOUR]],MATCH(Tableau6[[#This Row],[N° BC]],Tableau2[ID BC UNIQUE],0),5),0) -> 30 | T76: =IF(ISBLANK(Tableau6[[#This Row],[DATE DE DEPOT]]),"",Tableau6[[#This Row],[DATE DE DEPOT]]+Tableau6[[#This Row],[DELAI]]) -> 45746 | U76: =+IF(AND(W76=0,Tableau6[[#This Row],[DATE LIMITE]]<TODAY()),TODAY()-Tableau6[[#This Row],[DATE LIMITE]],0) -> 0 | V76: =IF(Tableau6[[#This Row],[DATE LIMITE]]>=TODAY(),"NON ECHUE",IF(Tableau6[[#This Row],[MONTANT HT]]<0,IF(ISNUMBER(MATCH(-Tableau6[[#This Row],[MONTANT HT]],Tableau6[MONTANT HT],0)),"AVOIR TOTAL","AVOIR PARTIEL"),IF(AND(ISNUMBER(MATCH(-Tableau6[[#This Row],[MONTANT HT]],Tableau6[MONTANT HT],0)),(Tableau6[[#This Row],[ACOMPTE SUR TTC]]+Tableau6[[#This Row],[MONTANT PAYE]])=0),"FACTURE ANNULEE",IF(Tableau6[[#This Row],[ACOMPTE SUR TTC]]+Tableau6[[#This Row],[MONTANT PAYE]]=0,"ECHUE NON REGLEE",IF(Tableau6[[#This Row],[ACOMPTE SUR TTC]]+Tableau6[[#This Row],[MONTANT PAYE]]=Tableau6[[#This Row],[NET A PAYER]],"PAYE",IF(Tableau6[[#This Row],[ACOMPTE SUR TTC]]+Tableau6[[#This Row],[MONTANT PAYE]]<Tableau6[[#This Row],[NET A PAYER]],"PAIEMENT PARTIEL","TROP PAYE")))))) -> PAYE | W76: =SUMIF(Tableau3[FACTURE],Tableau6[[#This Row],[NUM DE FACTURE]],Tableau3[MONTANT TTC]) -> 4130000 | Y76: =+Tableau6[[#This Row],[NET A PAYER]]-Tableau6[[#This Row],[MONTANT PAYE]] -> 0
A77: KENAM S | B77: 45716 | C77: 45716 | D77: 295 | E77: PFO CONSTRUCTION | F77: LOCATION DE CAMION | G77: 257B0003 | H77: TVAF | J77: 2160000 | K77: =+Tableau6[[#This Row],[MONTANT HT BIEN]]+Tableau6[[#This Row],[MONTANT HT SERVICE]] -> 2160000 | L77: 0 | M77: =+IFERROR(IF(Tableau6[[#This Row],[CODE TVA]]="TVAF",Tableau6[[#This Row],[MONTANT HT]]*0.18,0),0) -> 388800 | N77: =Tableau6[[#This Row],[MONTANT HT]]+Tableau6[[#This Row],[TVA]]-Tableau6[[#This Row],[ACOMPTE SUR HT]] -> 2548800 | P77: =+ROUND(Tableau6[[#This Row],[MONTANT TTC]]-Tableau6[[#This Row],[ACOMPTE SUR TTC]],0) -> 2548800 | Q77: BC201246 | R77: =IFERROR(INDEX(Tableau2[[ID BC UNIQUE]:[MONTANT HT VALIDE]],MATCH(Tableau6[[#This Row],[N° BC]],Tableau2[ID BC UNIQUE],0),6),0) -> 2160000 | S77: =IFERROR(INDEX(Tableau2[[DATE]:[DELAIS DE PAIEMENT FACTURES EN JOUR]],MATCH(Tableau6[[#This Row],[N° BC]],Tableau2[ID BC UNIQUE],0),5),0) -> 30 | T77: =IF(ISBLANK(Tableau6[[#This Row],[DATE DE DEPOT]]),"",Tableau6[[#This Row],[DATE DE DEPOT]]+Tableau6[[#This Row],[DELAI]]) -> 45746 | U77: =+IF(AND(W77=0,Tableau6[[#This Row],[DATE LIMITE]]<TODAY()),TODAY()-Tableau6[[#This Row],[DATE LIMITE]],0) -> 0 | V77: =IF(Tableau6[[#This Row],[DATE LIMITE]]>=TODAY(),"NON ECHUE",IF(Tableau6[[#This Row],[MONTANT HT]]<0,IF(ISNUMBER(MATCH(-Tableau6[[#This Row],[MONTANT HT]],Tableau6[MONTANT HT],0)),"AVOIR TOTAL","AVOIR PARTIEL"),IF(AND(ISNUMBER(MATCH(-Tableau6[[#This Row],[MONTANT HT]],Tableau6[MONTANT HT],0)),(Tableau6[[#This Row],[ACOMPTE SUR TTC]]+Tableau6[[#This Row],[MONTANT PAYE]])=0),"FACTURE ANNULEE",IF(Tableau6[[#This Row],[ACOMPTE SUR TTC]]+Tableau6[[#This Row],[MONTANT PAYE]]=0,"ECHUE NON REGLEE",IF(Tableau6[[#This Row],[ACOMPTE SUR TTC]]+Tableau6[[#This Row],[MONTANT PAYE]]=Tableau6[[#This Row],[NET A PAYER]],"PAYE",IF(Tableau6[[#This Row],[ACOMPTE SUR TTC]]+Tableau6[[#This Row],[MONTANT PAYE]]<Tableau6[[#This Row],[NET A PAYER]],"PAIEMENT PARTIEL","TROP PAYE")))))) -> PAYE | W77: =SUMIF(Tableau3[FACTURE],Tableau6[[#This Row],[NUM DE FACTURE]],Tableau3[MONTANT TTC]) -> 2548800 | Y77: =+Tableau6[[#This Row],[NET A PAYER]]-Tableau6[[#This Row],[MONTANT PAYE]] -> 0
A78: KENAM S | B78: 45716 | C78: 45716 | D78: 296 | E78: PFO CONSTRUCTION | F78: LOCATION DE CAMION | G78: 257B0003 | H78: TVAF | J78: 2520000 | K78: =+Tableau6[[#This Row],[MONTANT HT BIEN]]+Tableau6[[#This Row],[MONTANT HT SERVICE]] -> 2520000 | L78: 0 | M78: =+IFERROR(IF(Tableau6[[#This Row],[CODE TVA]]="TVAF",Tableau6[[#This Row],[MONTANT HT]]*0.18,0),0) -> 453600 | N78: =Tableau6[[#This Row],[MONTANT HT]]+Tableau6[[#This Row],[TVA]]-Tableau6[[#This Row],[ACOMPTE SUR HT]] -> 2973600 | P78: =+ROUND(Tableau6[[#This Row],[MONTANT TTC]]-Tableau6[[#This Row],[ACOMPTE SUR TTC]],0) -> 2973600 | Q78: BC201247 | R78: =IFERROR(INDEX(Tableau2[[ID BC UNIQUE]:[MONTANT HT VALIDE]],MATCH(Tableau6[[#This Row],[N° BC]],Tableau2[ID BC UNIQUE],0),6),0) -> 2520000 | S78: =IFERROR(INDEX(Tableau2[[DATE]:[DELAIS DE PAIEMENT FACTURES EN JOUR]],MATCH(Tableau6[[#This Row],[N° BC]],Tableau2[ID BC UNIQUE],0),5),0) -> 30 | T78: =IF(ISBLANK(Tableau6[[#This Row],[DATE DE DEPOT]]),"",Tableau6[[#This Row],[DATE DE DEPOT]]+Tableau6[[#This Row],[DELAI]]) -> 45746 | U78: =+IF(AND(W78=0,Tableau6[[#This Row],[DATE LIMITE]]<TODAY()),TODAY()-Tableau6[[#This Row],[DATE LIMITE]],0) -> 0 | V78: =IF(Tableau6[[#This Row],[DATE LIMITE]]>=TODAY(),"NON ECHUE",IF(Tableau6[[#This Row],[MONTANT HT]]<0,IF(ISNUMBER(MATCH(-Tableau6[[#This Row],[MONTANT HT]],Tableau6[MONTANT HT],0)),"AVOIR TOTAL","AVOIR PARTIEL"),IF(AND(ISNUMBER(MATCH(-Tableau6[[#This Row],[MONTANT HT]],Tableau6[MONTANT HT],0)),(Tableau6[[#This Row],[ACOMPTE SUR TTC]]+Tableau6[[#This Row],[MONTANT PAYE]])=0),"FACTURE ANNULEE",IF(Tableau6[[#This Row],[ACOMPTE SUR TTC]]+Tableau6[[#This Row],[MONTANT PAYE]]=0,"ECHUE NON REGLEE",IF(Tableau6[[#This Row],[ACOMPTE SUR TTC]]+Tableau6[[#This Row],[MONTANT PAYE]]=Tableau6[[#This Row],[NET A PAYER]],"PAYE",IF(Tableau6[[#This Row],[ACOMPTE SUR TTC]]+Tableau6[[#This Row],[MONTANT PAYE]]<Tableau6[[#This Row],[NET A PAYER]],"PAIEMENT PARTIEL","TROP PAYE")))))) -> PAYE | W78: =SUMIF(Tableau3[FACTURE],Tableau6[[#This Row],[NUM DE FACTURE]],Tableau3[MONTANT TTC]) -> 2973600 | Y78: =+Tableau6[[#This Row],[NET A PAYER]]-Tableau6[[#This Row],[MONTANT PAYE]] -> 0
A79: KENAM S | B79: 45716 | C79: 45716 | D79: 297 | E79: PFO CONSTRUCTION | F79: LOCATION DE CAMION | G79: 257B0003 | H79: TVAF | J79: 540000 | K79: =+Tableau6[[#This Row],[MONTANT HT BIEN]]+Tableau6[[#This Row],[MONTANT HT SERVICE]] -> 540000 | L79: 0 | M79: =+IFERROR(IF(Tableau6[[#This Row],[CODE TVA]]="TVAF",Tableau6[[#This Row],[MONTANT HT]]*0.18,0),0) -> 97200 | N79: =Tableau6[[#This Row],[MONTANT HT]]+Tableau6[[#This Row],[TVA]]-Tableau6[[#This Row],[ACOMPTE SUR HT]] -> 637200 | P79: =+ROUND(Tableau6[[#This Row],[MONTANT TTC]]-Tableau6[[#This Row],[ACOMPTE SUR TTC]],0) -> 637200 | Q79: BC201248 | R79: =IFERROR(INDEX(Tableau2[[ID BC UNIQUE]:[MONTANT HT VALIDE]],MATCH(Tableau6[[#This Row],[N° BC]],Tableau2[ID BC UNIQUE],0),6),0) -> 540000 | S79: =IFERROR(INDEX(Tableau2[[DATE]:[DELAIS DE PAIEMENT FACTURES EN JOUR]],MATCH(Tableau6[[#This Row],[N° BC]],Tableau2[ID BC UNIQUE],0),5),0) -> 30 | T79: =IF(ISBLANK(Tableau6[[#This Row],[DATE DE DEPOT]]),"",Tableau6[[#This Row],[DATE DE DEPOT]]+Tableau6[[#This Row],[DELAI]]) -> 45746 | U79: =+IF(AND(W79=0,Tableau6[[#This Row],[DATE LIMITE]]<TODAY()),TODAY()-Tableau6[[#This Row],[DATE LIMITE]],0) -> 0 | V79: =IF(Tableau6[[#This Row],[DATE LIMITE]]>=TODAY(),"NON ECHUE",IF(Tableau6[[#This Row],[MONTANT HT]]<0,IF(ISNUMBER(MATCH(-Tableau6[[#This Row],[MONTANT HT]],Tableau6[MONTANT HT],0)),"AVOIR TOTAL","AVOIR PARTIEL"),IF(AND(ISNUMBER(MATCH(-Tableau6[[#This Row],[MONTANT HT]],Tableau6[MONTANT HT],0)),(Tableau6[[#This Row],[ACOMPTE SUR TTC]]+Tableau6[[#This Row],[MONTANT PAYE]])=0),"FACTURE ANNULEE",IF(Tableau6[[#This Row],[ACOMPTE SUR TTC]]+Tableau6[[#This Row],[MONTANT PAYE]]=0,"ECHUE NON REGLEE",IF(Tableau6[[#This Row],[ACOMPTE SUR TTC]]+Tableau6[[#This Row],[MONTANT PAYE]]=Tableau6[[#This Row],[NET A PAYER]],"PAYE",IF(Tableau6[[#This Row],[ACOMPTE SUR TTC]]+Tableau6[[#This Row],[MONTANT PAYE]]<Tableau6[[#This Row],[NET A PAYER]],"PAIEMENT PARTIEL","TROP PAYE")))))) -> PAYE | W79: =SUMIF(Tableau3[FACTURE],Tableau6[[#This Row],[NUM DE FACTURE]],Tableau3[MONTANT TTC]) -> 637200 | Y79: =+Tableau6[[#This Row],[NET A PAYER]]-Tableau6[[#This Row],[MONTANT PAYE]] -> 0
A80: KENAM S | B80: 45716 | C80: 45716 | D80: 298 | E80: PFO CONSTRUCTION | F80: LOCATION DE CAMION | G80: 257B0109 | H80: TVAF | J80: 3600000 | K80: =+Tableau6[[#This Row],[MONTANT HT BIEN]]+Tableau6[[#This Row],[MONTANT HT SERVICE]] -> 3600000 | L80: 0 | M80: =+IFERROR(IF(Tableau6[[#This Row],[CODE TVA]]="TVAF",Tableau6[[#This Row],[MONTANT HT]]*0.18,0),0) -> 648000 | N80: =Tableau6[[#This Row],[MONTANT HT]]+Tableau6[[#This Row],[TVA]]-Tableau6[[#This Row],[ACOMPTE SUR HT]] -> 4248000 | P80: =+ROUND(Tableau6[[#This Row],[MONTANT TTC]]-Tableau6[[#This Row],[ACOMPTE SUR TTC]],0) -> 4248000 | Q80: BC201250 | R80: =IFERROR(INDEX(Tableau2[[ID BC UNIQUE]:[MONTANT HT VALIDE]],MATCH(Tableau6[[#This Row],[N° BC]],Tableau2[ID BC UNIQUE],0),6),0) -> 3600000 | S80: =IFERROR(INDEX(Tableau2[[DATE]:[DELAIS DE PAIEMENT FACTURES EN JOUR]],MATCH(Tableau6[[#This Row],[N° BC]],Tableau2[ID BC UNIQUE],0),5),0) -> 30 | T80: =IF(ISBLANK(Tableau6[[#This Row],[DATE DE DEPOT]]),"",Tableau6[[#This Row],[DATE DE DEPOT]]+Tableau6[[#This Row],[DELAI]]) -> 45746 | U80: =+IF(AND(W80=0,Tableau6[[#This Row],[DATE LIMITE]]<TODAY()),TODAY()-Tableau6[[#This Row],[DATE LIMITE]],0) -> 0 | V80: =IF(Tableau6[[#This Row],[DATE LIMITE]]>=TODAY(),"NON ECHUE",IF(Tableau6[[#This Row],[MONTANT HT]]<0,IF(ISNUMBER(MATCH(-Tableau6[[#This Row],[MONTANT HT]],Tableau6[MONTANT HT],0)),"AVOIR TOTAL","AVOIR PARTIEL"),IF(AND(ISNUMBER(MATCH(-Tableau6[[#This Row],[MONTANT HT]],Tableau6[MONTANT HT],0)),(Tableau6[[#This Row],[ACOMPTE SUR TTC]]+Tableau6[[#This Row],[MONTANT PAYE]])=0),"FACTURE ANNULEE",IF(Tableau6[[#This Row],[ACOMPTE SUR TTC]]+Tableau6[[#This Row],[MONTANT PAYE]]=0,"ECHUE NON REGLEE",IF(Tableau6[[#This Row],[ACOMPTE SUR TTC]]+Tableau6[[#This Row],[MONTANT PAYE]]=Tableau6[[#This Row],[NET A PAYER]],"PAYE",IF(Tableau6[[#This Row],[ACOMPTE SUR TTC]]+Tableau6[[#This Row],[MONTANT PAYE]]<Tableau6[[#This Row],[NET A PAYER]],"PAIEMENT PARTIEL","TROP PAYE")))))) -> PAYE | W80: =SUMIF(Tableau3[FACTURE],Tableau6[[#This Row],[NUM DE FACTURE]],Tableau3[MONTANT TTC]) -> 4248000 | Y80: =+Tableau6[[#This Row],[NET A PAYER]]-Tableau6[[#This Row],[MONTANT PAYE]] -> 0
A81: KENAM S | B81: 45716 | C81: 45716 | D81: 299 | E81: PFO CONSTRUCTION | F81: LOCATION DE CAMION | G81: 257B0200 | H81: TVAF | J81: 1400000 | K81: =+Tableau6[[#This Row],[MONTANT HT BIEN]]+Tableau6[[#This Row],[MONTANT HT SERVICE]] -> 1400000 | L81: 0 | M81: =+IFERROR(IF(Tableau6[[#This Row],[CODE TVA]]="TVAF",Tableau6[[#This Row],[MONTANT HT]]*0.18,0),0) -> 252000 | N81: =Tableau6[[#This Row],[MONTANT HT]]+Tableau6[[#This Row],[TVA]]-Tableau6[[#This Row],[ACOMPTE SUR HT]] -> 1652000 | P81: =+ROUND(Tableau6[[#This Row],[MONTANT TTC]]-Tableau6[[#This Row],[ACOMPTE SUR TTC]],0) -> 1652000 | Q81: BC201251 | R81: =IFERROR(INDEX(Tableau2[[ID BC UNIQUE]:[MONTANT HT VALIDE]],MATCH(Tableau6[[#This Row],[N° BC]],Tableau2[ID BC UNIQUE],0),6),0) -> 1400000 | S81: =IFERROR(INDEX(Tableau2[[DATE]:[DELAIS DE PAIEMENT FACTURES EN JOUR]],MATCH(Tableau6[[#This Row],[N° BC]],Tableau2[ID BC UNIQUE],0),5),0) -> 30 | T81: =IF(ISBLANK(Tableau6[[#This Row],[DATE DE DEPOT]]),"",Tableau6[[#This Row],[DATE DE DEPOT]]+Tableau6[[#This Row],[DELAI]]) -> 45746 | U81: =+IF(AND(W81=0,Tableau6[[#This Row],[DATE LIMITE]]<TODAY()),TODAY()-Tableau6[[#This Row],[DATE LIMITE]],0) -> 0 | V81: =IF(Tableau6[[#This Row],[DATE LIMITE]]>=TODAY(),"NON ECHUE",IF(Tableau6[[#This Row],[MONTANT HT]]<0,IF(ISNUMBER(MATCH(-Tableau6[[#This Row],[MONTANT HT]],Tableau6[MONTANT HT],0)),"AVOIR TOTAL","AVOIR PARTIEL"),IF(AND(ISNUMBER(MATCH(-Tableau6[[#This Row],[MONTANT HT]],Tableau6[MONTANT HT],0)),(Tableau6[[#This Row],[ACOMPTE SUR TTC]]+Tableau6[[#This Row],[MONTANT PAYE]])=0),"FACTURE ANNULEE",IF(Tableau6[[#This Row],[ACOMPTE SUR TTC]]+Tableau6[[#This Row],[MONTANT PAYE]]=0,"ECHUE NON REGLEE",IF(Tableau6[[#This Row],[ACOMPTE SUR TTC]]+Tableau6[[#This Row],[MONTANT PAYE]]=Tableau6[[#This Row],[NET A PAYER]],"PAYE",IF(Tableau6[[#This Row],[ACOMPTE SUR TTC]]+Tableau6[[#This Row],[MONTANT PAYE]]<Tableau6[[#This Row],[NET A PAYER]],"PAIEMENT PARTIEL","TROP PAYE")))))) -> PAYE | W81: =SUMIF(Tableau3[FACTURE],Tableau6[[#This Row],[NUM DE FACTURE]],Tableau3[MONTANT TTC]) -> 1652000 | Y81: =+Tableau6[[#This Row],[NET A PAYER]]-Tableau6[[#This Row],[MONTANT PAYE]] -> 0
A82: KENAM S | B82: 45716 | C82: 45716 | D82: 302 | E82: PFO CONSTRUCTION | F82: LOCATION DE CAMION | G82: 257B0200 | H82: TVAF | J82: 600000 | K82: =+Tableau6[[#This Row],[MONTANT HT BIEN]]+Tableau6[[#This Row],[MONTANT HT SERVICE]] -> 600000 | L82: 0 | M82: =+IFERROR(IF(Tableau6[[#This Row],[CODE TVA]]="TVAF",Tableau6[[#This Row],[MONTANT HT]]*0.18,0),0) -> 108000 | N82: =Tableau6[[#This Row],[MONTANT HT]]+Tableau6[[#This Row],[TVA]]-Tableau6[[#This Row],[ACOMPTE SUR HT]] -> 708000 | P82: =+ROUND(Tableau6[[#This Row],[MONTANT TTC]]-Tableau6[[#This Row],[ACOMPTE SUR TTC]],0) -> 708000 | Q82: BC201253 | R82: =IFERROR(INDEX(Tableau2[[ID BC UNIQUE]:[MONTANT HT VALIDE]],MATCH(Tableau6[[#This Row],[N° BC]],Tableau2[ID BC UNIQUE],0),6),0) -> 600000 | S82: =IFERROR(INDEX(Tableau2[[DATE]:[DELAIS DE PAIEMENT FACTURES EN JOUR]],MATCH(Tableau6[[#This Row],[N° BC]],Tableau2[ID BC UNIQUE],0),5),0) -> 30 | T82: =IF(ISBLANK(Tableau6[[#This Row],[DATE DE DEPOT]]),"",Tableau6[[#This Row],[DATE DE DEPOT]]+Tableau6[[#This Row],[DELAI]]) -> 45746 | U82: =+IF(AND(W82=0,Tableau6[[#This Row],[DATE LIMITE]]<TODAY()),TODAY()-Tableau6[[#This Row],[DATE LIMITE]],0) -> 0 | V82: =IF(Tableau6[[#This Row],[DATE LIMITE]]>=TODAY(),"NON ECHUE",IF(Tableau6[[#This Row],[MONTANT HT]]<0,IF(ISNUMBER(MATCH(-Tableau6[[#This Row],[MONTANT HT]],Tableau6[MONTANT HT],0)),"AVOIR TOTAL","AVOIR PARTIEL"),IF(AND(ISNUMBER(MATCH(-Tableau6[[#This Row],[MONTANT HT]],Tableau6[MONTANT HT],0)),(Tableau6[[#This Row],[ACOMPTE SUR TTC]]+Tableau6[[#This Row],[MONTANT PAYE]])=0),"FACTURE ANNULEE",IF(Tableau6[[#This Row],[ACOMPTE SUR TTC]]+Tableau6[[#This Row],[MONTANT PAYE]]=0,"ECHUE NON REGLEE",IF(Tableau6[[#This Row],[ACOMPTE SUR TTC]]+Tableau6[[#This Row],[MONTANT PAYE]]=Tableau6[[#This Row],[NET A PAYER]],"PAYE",IF(Tableau6[[#This Row],[ACOMPTE SUR TTC]]+Tableau6[[#This Row],[MONTANT PAYE]]<Tableau6[[#This Row],[NET A PAYER]],"PAIEMENT PARTIEL","TROP PAYE")))))) -> PAYE | W82: =SUMIF(Tableau3[FACTURE],Tableau6[[#This Row],[NUM DE FACTURE]],Tableau3[MONTANT TTC]) -> 708000 | Y82: =+Tableau6[[#This Row],[NET A PAYER]]-Tableau6[[#This Row],[MONTANT PAYE]] -> 0
A83: KENAM S | B83: 45716 | C83: 45716 | D83: 303 | E83: PFO CONSTRUCTION | F83: LOCATION DE CAMION | G83: 257B0200 | H83: TVAF | J83: 600000 | K83: =+Tableau6[[#This Row],[MONTANT HT BIEN]]+Tableau6[[#This Row],[MONTANT HT SERVICE]] -> 600000 | L83: 0 | M83: =+IFERROR(IF(Tableau6[[#This Row],[CODE TVA]]="TVAF",Tableau6[[#This Row],[MONTANT HT]]*0.18,0),0) -> 108000 | N83: =Tableau6[[#This Row],[MONTANT HT]]+Tableau6[[#This Row],[TVA]]-Tableau6[[#This Row],[ACOMPTE SUR HT]] -> 708000 | P83: =+ROUND(Tableau6[[#This Row],[MONTANT TTC]]-Tableau6[[#This Row],[ACOMPTE SUR TTC]],0) -> 708000 | Q83: BC201254 | R83: =IFERROR(INDEX(Tableau2[[ID BC UNIQUE]:[MONTANT HT VALIDE]],MATCH(Tableau6[[#This Row],[N° BC]],Tableau2[ID BC UNIQUE],0),6),0) -> 600000 | S83: =IFERROR(INDEX(Tableau2[[DATE]:[DELAIS DE PAIEMENT FACTURES EN JOUR]],MATCH(Tableau6[[#This Row],[N° BC]],Tableau2[ID BC UNIQUE],0),5),0) -> 30 | T83: =IF(ISBLANK(Tableau6[[#This Row],[DATE DE DEPOT]]),"",Tableau6[[#This Row],[DATE DE DEPOT]]+Tableau6[[#This Row],[DELAI]]) -> 45746 | U83: =+IF(AND(W83=0,Tableau6[[#This Row],[DATE LIMITE]]<TODAY()),TODAY()-Tableau6[[#This Row],[DATE LIMITE]],0) -> 0 | V83: =IF(Tableau6[[#This Row],[DATE LIMITE]]>=TODAY(),"NON ECHUE",IF(Tableau6[[#This Row],[MONTANT HT]]<0,IF(ISNUMBER(MATCH(-Tableau6[[#This Row],[MONTANT HT]],Tableau6[MONTANT HT],0)),"AVOIR TOTAL","AVOIR PARTIEL"),IF(AND(ISNUMBER(MATCH(-Tableau6[[#This Row],[MONTANT HT]],Tableau6[MONTANT HT],0)),(Tableau6[[#This Row],[ACOMPTE SUR TTC]]+Tableau6[[#This Row],[MONTANT PAYE]])=0),"FACTURE ANNULEE",IF(Tableau6[[#This Row],[ACOMPTE SUR TTC]]+Tableau6[[#This Row],[MONTANT PAYE]]=0,"ECHUE NON REGLEE",IF(Tableau6[[#This Row],[ACOMPTE SUR TTC]]+Tableau6[[#This Row],[MONTANT PAYE]]=Tableau6[[#This Row],[NET A PAYER]],"PAYE",IF(Tableau6[[#This Row],[ACOMPTE SUR TTC]]+Tableau6[[#This Row],[MONTANT PAYE]]<Tableau6[[#This Row],[NET A PAYER]],"PAIEMENT PARTIEL","TROP PAYE")))))) -> PAYE | W83: =SUMIF(Tableau3[FACTURE],Tableau6[[#This Row],[NUM DE FACTURE]],Tableau3[MONTANT TTC]) -> 708000 | Y83: =+Tableau6[[#This Row],[NET A PAYER]]-Tableau6[[#This Row],[MONTANT PAYE]] -> 0
A84: KENAM S | B84: 45716 | C84: 45716 | D84: 304 | E84: PFO CONSTRUCTION | F84: LOCATION DE CAMION | G84: 257B0109 | H84: TVAF | J84: 180000 | K84: =+Tableau6[[#This Row],[MONTANT HT BIEN]]+Tableau6[[#This Row],[MONTANT HT SERVICE]] -> 180000 | L84: 0 | M84: =+IFERROR(IF(Tableau6[[#This Row],[CODE TVA]]="TVAF",Tableau6[[#This Row],[MONTANT HT]]*0.18,0),0) -> 32400 | N84: =Tableau6[[#This Row],[MONTANT HT]]+Tableau6[[#This Row],[TVA]]-Tableau6[[#This Row],[ACOMPTE SUR HT]] -> 212400 | P84: =+ROUND(Tableau6[[#This Row],[MONTANT TTC]]-Tableau6[[#This Row],[ACOMPTE SUR TTC]],0) -> 212400 | Q84: BC201255 | R84: =IFERROR(INDEX(Tableau2[[ID BC UNIQUE]:[MONTANT HT VALIDE]],MATCH(Tableau6[[#This Row],[N° BC]],Tableau2[ID BC UNIQUE],0),6),0) -> 180000 | S84: =IFERROR(INDEX(Tableau2[[DATE]:[DELAIS DE PAIEMENT FACTURES EN JOUR]],MATCH(Tableau6[[#This Row],[N° BC]],Tableau2[ID BC UNIQUE],0),5),0) -> 30 | T84: =IF(ISBLANK(Tableau6[[#This Row],[DATE DE DEPOT]]),"",Tableau6[[#This Row],[DATE DE DEPOT]]+Tableau6[[#This Row],[DELAI]]) -> 45746 | U84: =+IF(AND(W84=0,Tableau6[[#This Row],[DATE LIMITE]]<TODAY()),TODAY()-Tableau6[[#This Row],[DATE LIMITE]],0) -> 0 | V84: =IF(Tableau6[[#This Row],[DATE LIMITE]]>=TODAY(),"NON ECHUE",IF(Tableau6[[#This Row],[MONTANT HT]]<0,IF(ISNUMBER(MATCH(-Tableau6[[#This Row],[MONTANT HT]],Tableau6[MONTANT HT],0)),"AVOIR TOTAL","AVOIR PARTIEL"),IF(AND(ISNUMBER(MATCH(-Tableau6[[#This Row],[MONTANT HT]],Tableau6[MONTANT HT],0)),(Tableau6[[#This Row],[ACOMPTE SUR TTC]]+Tableau6[[#This Row],[MONTANT PAYE]])=0),"FACTURE ANNULEE",IF(Tableau6[[#This Row],[ACOMPTE SUR TTC]]+Tableau6[[#This Row],[MONTANT PAYE]]=0,"ECHUE NON REGLEE",IF(Tableau6[[#This Row],[ACOMPTE SUR TTC]]+Tableau6[[#This Row],[MONTANT PAYE]]=Tableau6[[#This Row],[NET A PAYER]],"PAYE",IF(Tableau6[[#This Row],[ACOMPTE SUR TTC]]+Tableau6[[#This Row],[MONTANT PAYE]]<Tableau6[[#This Row],[NET A PAYER]],"PAIEMENT PARTIEL","TROP PAYE")))))) -> PAYE | W84: =SUMIF(Tableau3[FACTURE],Tableau6[[#This Row],[NUM DE FACTURE]],Tableau3[MONTANT TTC]) -> 212400 | Y84: =+Tableau6[[#This Row],[NET A PAYER]]-Tableau6[[#This Row],[MONTANT PAYE]] -> 0
A85: KENAM S | B85: 45716 | C85: 45716 | D85: 305 | E85: PFO CONSTRUCTION | F85: LOCATION DE CAMION | G85: 257B0003 | H85: TVAF | J85: 3960000 | K85: =+Tableau6[[#This Row],[MONTANT HT BIEN]]+Tableau6[[#This Row],[MONTANT HT SERVICE]] -> 3960000 | L85: 0 | M85: =+IFERROR(IF(Tableau6[[#This Row],[CODE TVA]]="TVAF",Tableau6[[#This Row],[MONTANT HT]]*0.18,0),0) -> 712800 | N85: =Tableau6[[#This Row],[MONTANT HT]]+Tableau6[[#This Row],[TVA]]-Tableau6[[#This Row],[ACOMPTE SUR HT]] -> 4672800 | P85: =+ROUND(Tableau6[[#This Row],[MONTANT TTC]]-Tableau6[[#This Row],[ACOMPTE SUR TTC]],0) -> 4672800 | Q85: BC201256 | R85: =IFERROR(INDEX(Tableau2[[ID BC UNIQUE]:[MONTANT HT VALIDE]],MATCH(Tableau6[[#This Row],[N° BC]],Tableau2[ID BC UNIQUE],0),6),0) -> 3960000 | S85: =IFERROR(INDEX(Tableau2[[DATE]:[DELAIS DE PAIEMENT FACTURES EN JOUR]],MATCH(Tableau6[[#This Row],[N° BC]],Tableau2[ID BC UNIQUE],0),5),0) -> 30 | T85: =IF(ISBLANK(Tableau6[[#This Row],[DATE DE DEPOT]]),"",Tableau6[[#This Row],[DATE DE DEPOT]]+Tableau6[[#This Row],[DELAI]]) -> 45746 | U85: =+IF(AND(W85=0,Tableau6[[#This Row],[DATE LIMITE]]<TODAY()),TODAY()-Tableau6[[#This Row],[DATE LIMITE]],0) -> 0 | V85: =IF(Tableau6[[#This Row],[DATE LIMITE]]>=TODAY(),"NON ECHUE",IF(Tableau6[[#This Row],[MONTANT HT]]<0,IF(ISNUMBER(MATCH(-Tableau6[[#This Row],[MONTANT HT]],Tableau6[MONTANT HT],0)),"AVOIR TOTAL","AVOIR PARTIEL"),IF(AND(ISNUMBER(MATCH(-Tableau6[[#This Row],[MONTANT HT]],Tableau6[MONTANT HT],0)),(Tableau6[[#This Row],[ACOMPTE SUR TTC]]+Tableau6[[#This Row],[MONTANT PAYE]])=0),"FACTURE ANNULEE",IF(Tableau6[[#This Row],[ACOMPTE SUR TTC]]+Tableau6[[#This Row],[MONTANT PAYE]]=0,"ECHUE NON REGLEE",IF(Tableau6[[#This Row],[ACOMPTE SUR TTC]]+Tableau6[[#This Row],[MONTANT PAYE]]=Tableau6[[#This Row],[NET A PAYER]],"PAYE",IF(Tableau6[[#This Row],[ACOMPTE SUR TTC]]+Tableau6[[#This Row],[MONTANT PAYE]]<Tableau6[[#This Row],[NET A PAYER]],"PAIEMENT PARTIEL","TROP PAYE")))))) -> PAYE | W85: =SUMIF(Tableau3[FACTURE],Tableau6[[#This Row],[NUM DE FACTURE]],Tableau3[MONTANT TTC]) -> 4672800 | Y85: =+Tableau6[[#This Row],[NET A PAYER]]-Tableau6[[#This Row],[MONTANT PAYE]] -> 0
A86: KENAM S | B86: 45716 | C86: 45716 | D86: 307 | E86: PFO CONSTRUCTION | F86: LOCATION DE CAMION | G86: 257B0801 | H86: TVAF | J86: 1350000 | K86: =+Tableau6[[#This Row],[MONTANT HT BIEN]]+Tableau6[[#This Row],[MONTANT HT SERVICE]] -> 1350000 | L86: 0 | M86: =+IFERROR(IF(Tableau6[[#This Row],[CODE TVA]]="TVAF",Tableau6[[#This Row],[MONTANT HT]]*0.18,0),0) -> 243000 | N86: =Tableau6[[#This Row],[MONTANT HT]]+Tableau6[[#This Row],[TVA]]-Tableau6[[#This Row],[ACOMPTE SUR HT]] -> 1593000 | P86: =+ROUND(Tableau6[[#This Row],[MONTANT TTC]]-Tableau6[[#This Row],[ACOMPTE SUR TTC]],0) -> 1593000 | Q86: BC201259 | R86: =IFERROR(INDEX(Tableau2[[ID BC UNIQUE]:[MONTANT HT VALIDE]],MATCH(Tableau6[[#This Row],[N° BC]],Tableau2[ID BC UNIQUE],0),6),0) -> 1350000 | S86: =IFERROR(INDEX(Tableau2[[DATE]:[DELAIS DE PAIEMENT FACTURES EN JOUR]],MATCH(Tableau6[[#This Row],[N° BC]],Tableau2[ID BC UNIQUE],0),5),0) -> 30 | T86: =IF(ISBLANK(Tableau6[[#This Row],[DATE DE DEPOT]]),"",Tableau6[[#This Row],[DATE DE DEPOT]]+Tableau6[[#This Row],[DELAI]]) -> 45746 | U86: =+IF(AND(W86=0,Tableau6[[#This Row],[DATE LIMITE]]<TODAY()),TODAY()-Tableau6[[#This Row],[DATE LIMITE]],0) -> 0 | V86: =IF(Tableau6[[#This Row],[DATE LIMITE]]>=TODAY(),"NON ECHUE",IF(Tableau6[[#This Row],[MONTANT HT]]<0,IF(ISNUMBER(MATCH(-Tableau6[[#This Row],[MONTANT HT]],Tableau6[MONTANT HT],0)),"AVOIR TOTAL","AVOIR PARTIEL"),IF(AND(ISNUMBER(MATCH(-Tableau6[[#This Row],[MONTANT HT]],Tableau6[MONTANT HT],0)),(Tableau6[[#This Row],[ACOMPTE SUR TTC]]+Tableau6[[#This Row],[MONTANT PAYE]])=0),"FACTURE ANNULEE",IF(Tableau6[[#This Row],[ACOMPTE SUR TTC]]+Tableau6[[#This Row],[MONTANT PAYE]]=0,"ECHUE NON REGLEE",IF(Tableau6[[#This Row],[ACOMPTE SUR TTC]]+Tableau6[[#This Row],[MONTANT PAYE]]=Tableau6[[#This Row],[NET A PAYER]],"PAYE",IF(Tableau6[[#This Row],[ACOMPTE SUR TTC]]+Tableau6[[#This Row],[MONTANT PAYE]]<Tableau6[[#This Row],[NET A PAYER]],"PAIEMENT PARTIEL","TROP PAYE")))))) -> PAYE | W86: =SUMIF(Tableau3[FACTURE],Tableau6[[#This Row],[NUM DE FACTURE]],Tableau3[MONTANT TTC]) -> 1593000 | Y86: =+Tableau6[[#This Row],[NET A PAYER]]-Tableau6[[#This Row],[MONTANT PAYE]] -> 0
... A88: KENAM S | B88: 45716 | C88: 45716 | D88: 309 | E88: PFO CONSTRUCTION | F88: LOCATION DE CAMION | G88: 257B0203 | H88: TVAF | J88: 180000 | K88: =+Tableau6[[#This Row],[MONTANT HT BIEN]]+Tableau6[[#This Row],[MONTANT HT SERVICE]] -> 180000 | L88: 0 | M88: =+IFERROR(IF(Tableau6[[#This Row],[CODE TVA]]="TVAF",Tableau6[[#This Row],[MONTANT HT]]*0.18,0),0) -> 32400 | N88: =Tableau6[[#This Row],[MONTANT HT]]+Tableau6[[#This Row],[TVA]]-Tableau6[[#This Row],[ACOMPTE SUR HT]] -> 212400 | P88: =+ROUND(Tableau6[[#This Row],[MONTANT TTC]]-Tableau6[[#This Row],[ACOMPTE SUR TTC]],0) -> 212400 | Q88: BC201261 | R88: =IFERROR(INDEX(Tableau2[[ID BC UNIQUE]:[MONTANT HT VALIDE]],MATCH(Tableau6[[#This Row],[N° BC]],Tableau2[ID BC UNIQUE],0),6),0) -> 180000 | S88: =IFERROR(INDEX(Tableau2[[DATE]:[DELAIS DE PAIEMENT FACTURES EN JOUR]],MATCH(Tableau6[[#This Row],[N° BC]],Tableau2[ID BC UNIQUE],0),5),0) -> 30 | T88: =IF(ISBLANK(Tableau6[[#This Row],[DATE DE DEPOT]]),"",Tableau6[[#This Row],[DATE DE DEPOT]]+Tableau6[[#This Row],[DELAI]]) -> 45746 | U88: =+IF(AND(W88=0,Tableau6[[#This Row],[DATE LIMITE]]<TODAY()),TODAY()-Tableau6[[#This Row],[DATE LIMITE]],0) -> 0 | V88: =IF(Tableau6[[#This Row],[DATE LIMITE]]>=TODAY(),"NON ECHUE",IF(Tableau6[[#This Row],[MONTANT HT]]<0,IF(ISNUMBER(MATCH(-Tableau6[[#This Row],[MONTANT HT]],Tableau6[MONTANT HT],0)),"AVOIR TOTAL","AVOIR PARTIEL"),IF(AND(ISNUMBER(MATCH(-Tableau6[[#This Row],[MONTANT HT]],Tableau6[MONTANT HT],0)),(Tableau6[[#This Row],[ACOMPTE SUR TTC]]+Tableau6[[#This Row],[MONTANT PAYE]])=0),"FACTURE ANNULEE",IF(Tableau6[[#This Row],[ACOMPTE SUR TTC]]+Tableau6[[#This Row],[MONTANT PAYE]]=0,"ECHUE NON REGLEE",IF(Tableau6[[#This Row],[ACOMPTE SUR TTC]]+Tableau6[[#This Row],[MONTANT PAYE]]=Tableau6[[#This Row],[NET A PAYER]],"PAYE",IF(Tableau6[[#This Row],[ACOMPTE SUR TTC]]+Tableau6[[#This Row],[MONTANT PAYE]]<Tableau6[[#This Row],[NET A PAYER]],"PAIEMENT PARTIEL","TROP PAYE")))))) -> PAYE | W88: =SUMIF(Tableau3[FACTURE],Tableau6[[#This Row],[NUM DE FACTURE]],Tableau3[MONTANT TTC]) -> 212400 | Y88: =+Tableau6[[#This Row],[NET A PAYER]]-Tableau6[[#This Row],[MONTANT PAYE]] -> 0
A89: KENAM S | B89: 45716 | C89: 45716 | D89: 310 | E89: PFO CONSTRUCTION | F89: LOCATION DE CAMION | G89: 257B0209 | H89: TVAF | J89: 3800000 | K89: =+Tableau6[[#This Row],[MONTANT HT BIEN]]+Tableau6[[#This Row],[MONTANT HT SERVICE]] -> 3800000 | L89: 0 | M89: =+IFERROR(IF(Tableau6[[#This Row],[CODE TVA]]="TVAF",Tableau6[[#This Row],[MONTANT HT]]*0.18,0),0) -> 684000 | N89: =Tableau6[[#This Row],[MONTANT HT]]+Tableau6[[#This Row],[TVA]]-Tableau6[[#This Row],[ACOMPTE SUR HT]] -> 4484000 | O89: 177500 | P89: =+ROUND(Tableau6[[#This Row],[MONTANT TTC]]-Tableau6[[#This Row],[ACOMPTE SUR TTC]],0) -> 4306500 | Q89: BC201263 | R89: =IFERROR(INDEX(Tableau2[[ID BC UNIQUE]:[MONTANT HT VALIDE]],MATCH(Tableau6[[#This Row],[N° BC]],Tableau2[ID BC UNIQUE],0),6),0) -> 3800000 | S89: =IFERROR(INDEX(Tableau2[[DATE]:[DELAIS DE PAIEMENT FACTURES EN JOUR]],MATCH(Tableau6[[#This Row],[N° BC]],Tableau2[ID BC UNIQUE],0),5),0) -> 30 | T89: =IF(ISBLANK(Tableau6[[#This Row],[DATE DE DEPOT]]),"",Tableau6[[#This Row],[DATE DE DEPOT]]+Tableau6[[#This Row],[DELAI]]) -> 45746 | U89: =+IF(AND(W89=0,Tableau6[[#This Row],[DATE LIMITE]]<TODAY()),TODAY()-Tableau6[[#This Row],[DATE LIMITE]],0) -> 0 | V89: =IF(Tableau6[[#This Row],[DATE LIMITE]]>=TODAY(),"NON ECHUE",IF(Tableau6[[#This Row],[MONTANT HT]]<0,IF(ISNUMBER(MATCH(-Tableau6[[#This Row],[MONTANT HT]],Tableau6[MONTANT HT],0)),"AVOIR TOTAL","AVOIR PARTIEL"),IF(AND(ISNUMBER(MATCH(-Tableau6[[#This Row],[MONTANT HT]],Tableau6[MONTANT HT],0)),(Tableau6[[#This Row],[ACOMPTE SUR TTC]]+Tableau6[[#This Row],[MONTANT PAYE]])=0),"FACTURE ANNULEE",IF(Tableau6[[#This Row],[ACOMPTE SUR TTC]]+Tableau6[[#This Row],[MONTANT PAYE]]=0,"ECHUE NON REGLEE",IF(Tableau6[[#This Row],[ACOMPTE SUR TTC]]+Tableau6[[#This Row],[MONTANT PAYE]]=Tableau6[[#This Row],[NET A PAYER]],"PAYE",IF(Tableau6[[#This Row],[ACOMPTE SUR TTC]]+Tableau6[[#This Row],[MONTANT PAYE]]<Tableau6[[#This Row],[NET A PAYER]],"PAIEMENT PARTIEL","TROP PAYE")))))) -> TROP PAYE | W89: =SUMIF(Tableau3[FACTURE],Tableau6[[#This Row],[NUM DE FACTURE]],Tableau3[MONTANT TTC]) -> 4306500 | Y89: =+Tableau6[[#This Row],[NET A PAYER]]-Tableau6[[#This Row],[MONTANT PAYE]] -> 0
A90: KENAM S | B90: 45716 | C90: 45716 | D90: 312 | E90: PFO CONSTRUCTION | F90: LOCATION DE CAMION | G90: 257B0003 | H90: TVAF | J90: 3780000 | K90: =+Tableau6[[#This Row],[MONTANT HT BIEN]]+Tableau6[[#This Row],[MONTANT HT SERVICE]] -> 3780000 | L90: 0 | M90: =+IFERROR(IF(Tableau6[[#This Row],[CODE TVA]]="TVAF",Tableau6[[#This Row],[MONTANT HT]]*0.18,0),0) -> 680400 | N90: =Tableau6[[#This Row],[MONTANT HT]]+Tableau6[[#This Row],[TVA]]-Tableau6[[#This Row],[ACOMPTE SUR HT]] -> 4460400 | P90: =+ROUND(Tableau6[[#This Row],[MONTANT TTC]]-Tableau6[[#This Row],[ACOMPTE SUR TTC]],0) -> 4460400 | Q90: BC201257 | R90: =IFERROR(INDEX(Tableau2[[ID BC UNIQUE]:[MONTANT HT VALIDE]],MATCH(Tableau6[[#This Row],[N° BC]],Tableau2[ID BC UNIQUE],0),6),0) -> 3780000 | S90: =IFERROR(INDEX(Tableau2[[DATE]:[DELAIS DE PAIEMENT FACTURES EN JOUR]],MATCH(Tableau6[[#This Row],[N° BC]],Tableau2[ID BC UNIQUE],0),5),0) -> 30 | T90: =IF(ISBLANK(Tableau6[[#This Row],[DATE DE DEPOT]]),"",Tableau6[[#This Row],[DATE DE DEPOT]]+Tableau6[[#This Row],[DELAI]]) -> 45746 | U90: =+IF(AND(W90=0,Tableau6[[#This Row],[DATE LIMITE]]<TODAY()),TODAY()-Tableau6[[#This Row],[DATE LIMITE]],0) -> 0 | V90: =IF(Tableau6[[#This Row],[DATE LIMITE]]>=TODAY(),"NON ECHUE",IF(Tableau6[[#This Row],[MONTANT HT]]<0,IF(ISNUMBER(MATCH(-Tableau6[[#This Row],[MONTANT HT]],Tableau6[MONTANT HT],0)),"AVOIR TOTAL","AVOIR PARTIEL"),IF(AND(ISNUMBER(MATCH(-Tableau6[[#This Row],[MONTANT HT]],Tableau6[MONTANT HT],0)),(Tableau6[[#This Row],[ACOMPTE SUR TTC]]+Tableau6[[#This Row],[MONTANT PAYE]])=0),"FACTURE ANNULEE",IF(Tableau6[[#This Row],[ACOMPTE SUR TTC]]+Tableau6[[#This Row],[MONTANT PAYE]]=0,"ECHUE NON REGLEE",IF(Tableau6[[#This Row],[ACOMPTE SUR TTC]]+Tableau6[[#This Row],[MONTANT PAYE]]=Tableau6[[#This Row],[NET A PAYER]],"PAYE",IF(Tableau6[[#This Row],[ACOMPTE SUR TTC]]+Tableau6[[#This Row],[MONTANT PAYE]]<Tableau6[[#This Row],[NET A PAYER]],"PAIEMENT PARTIEL","TROP PAYE")))))) -> PAYE | W90: =SUMIF(Tableau3[FACTURE],Tableau6[[#This Row],[NUM DE FACTURE]],Tableau3[MONTANT TTC]) -> 4460400 | Y90: =+Tableau6[[#This Row],[NET A PAYER]]-Tableau6[[#This Row],[MONTANT PAYE]] -> 0
A91: KENAM S | B91: 45716 | C91: 45716 | D91: 313 | E91: PFO CONSTRUCTION | F91: LOCATION DE CAMION | G91: 257B0003 | H91: TVAF | J91: 3500000 | K91: =+Tableau6[[#This Row],[MONTANT HT BIEN]]+Tableau6[[#This Row],[MONTANT HT SERVICE]] -> 3500000 | L91: 0 | M91: =+IFERROR(IF(Tableau6[[#This Row],[CODE TVA]]="TVAF",Tableau6[[#This Row],[MONTANT HT]]*0.18,0),0) -> 630000 | N91: =Tableau6[[#This Row],[MONTANT HT]]+Tableau6[[#This Row],[TVA]]-Tableau6[[#This Row],[ACOMPTE SUR HT]] -> 4130000 | P91: =+ROUND(Tableau6[[#This Row],[MONTANT TTC]]-Tableau6[[#This Row],[ACOMPTE SUR TTC]],0) -> 4130000 | Q91: BC201264 | R91: =IFERROR(INDEX(Tableau2[[ID BC UNIQUE]:[MONTANT HT VALIDE]],MATCH(Tableau6[[#This Row],[N° BC]],Tableau2[ID BC UNIQUE],0),6),0) -> 3500000 | S91: =IFERROR(INDEX(Tableau2[[DATE]:[DELAIS DE PAIEMENT FACTURES EN JOUR]],MATCH(Tableau6[[#This Row],[N° BC]],Tableau2[ID BC UNIQUE],0),5),0) -> 30 | T91: =IF(ISBLANK(Tableau6[[#This Row],[DATE DE DEPOT]]),"",Tableau6[[#This Row],[DATE DE DEPOT]]+Tableau6[[#This Row],[DELAI]]) -> 45746 | U91: =+IF(AND(W91=0,Tableau6[[#This Row],[DATE LIMITE]]<TODAY()),TODAY()-Tableau6[[#This Row],[DATE LIMITE]],0) -> 0 | V91: =IF(Tableau6[[#This Row],[DATE LIMITE]]>=TODAY(),"NON ECHUE",IF(Tableau6[[#This Row],[MONTANT HT]]<0,IF(ISNUMBER(MATCH(-Tableau6[[#This Row],[MONTANT HT]],Tableau6[MONTANT HT],0)),"AVOIR TOTAL","AVOIR PARTIEL"),IF(AND(ISNUMBER(MATCH(-Tableau6[[#This Row],[MONTANT HT]],Tableau6[MONTANT HT],0)),(Tableau6[[#This Row],[ACOMPTE SUR TTC]]+Tableau6[[#This Row],[MONTANT PAYE]])=0),"FACTURE ANNULEE",IF(Tableau6[[#This Row],[ACOMPTE SUR TTC]]+Tableau6[[#This Row],[MONTANT PAYE]]=0,"ECHUE NON REGLEE",IF(Tableau6[[#This Row],[ACOMPTE SUR TTC]]+Tableau6[[#This Row],[MONTANT PAYE]]=Tableau6[[#This Row],[NET A PAYER]],"PAYE",IF(Tableau6[[#This Row],[ACOMPTE SUR TTC]]+Tableau6[[#This Row],[MONTANT PAYE]]<Tableau6[[#This Row],[NET A PAYER]],"PAIEMENT PARTIEL","TROP PAYE")))))) -> PAYE | W91: =SUMIF(Tableau3[FACTURE],Tableau6[[#This Row],[NUM DE FACTURE]],Tableau3[MONTANT TTC]) -> 4130000 | Y91: =+Tableau6[[#This Row],[NET A PAYER]]-Tableau6[[#This Row],[MONTANT PAYE]] -> 0
A92: KENAM S | B92: 45720 | C92: 45720 | D92: 314 | E92: PFO CONSTRUCTION | F92: LOCATION DE CAMION | G92: 257B0005 | H92: TVAF | J92: 5000000 | K92: =+Tableau6[[#This Row],[MONTANT HT BIEN]]+Tableau6[[#This Row],[MONTANT HT SERVICE]] -> 5000000 | L92: 0 | M92: =+IFERROR(IF(Tableau6[[#This Row],[CODE TVA]]="TVAF",Tableau6[[#This Row],[MONTANT HT]]*0.18,0),0) -> 900000 | N92: =Tableau6[[#This Row],[MONTANT HT]]+Tableau6[[#This Row],[TVA]]-Tableau6[[#This Row],[ACOMPTE SUR HT]] -> 5900000 | P92: =+ROUND(Tableau6[[#This Row],[MONTANT TTC]]-Tableau6[[#This Row],[ACOMPTE SUR TTC]],0) -> 5900000 | Q92: BC201332 | R92: =IFERROR(INDEX(Tableau2[[ID BC UNIQUE]:[MONTANT HT VALIDE]],MATCH(Tableau6[[#This Row],[N° BC]],Tableau2[ID BC UNIQUE],0),6),0) -> 5000000 | S92: =IFERROR(INDEX(Tableau2[[DATE]:[DELAIS DE PAIEMENT FACTURES EN JOUR]],MATCH(Tableau6[[#This Row],[N° BC]],Tableau2[ID BC UNIQUE],0),5),0) -> 30 | T92: =IF(ISBLANK(Tableau6[[#This Row],[DATE DE DEPOT]]),"",Tableau6[[#This Row],[DATE DE DEPOT]]+Tableau6[[#This Row],[DELAI]]) -> 45750 | U92: =+IF(AND(W92=0,Tableau6[[#This Row],[DATE LIMITE]]<TODAY()),TODAY()-Tableau6[[#This Row],[DATE LIMITE]],0) -> 0 | V92: =IF(Tableau6[[#This Row],[DATE LIMITE]]>=TODAY(),"NON ECHUE",IF(Tableau6[[#This Row],[MONTANT HT]]<0,IF(ISNUMBER(MATCH(-Tableau6[[#This Row],[MONTANT HT]],Tableau6[MONTANT HT],0)),"AVOIR TOTAL","AVOIR PARTIEL"),IF(AND(ISNUMBER(MATCH(-Tableau6[[#This Row],[MONTANT HT]],Tableau6[MONTANT HT],0)),(Tableau6[[#This Row],[ACOMPTE SUR TTC]]+Tableau6[[#This Row],[MONTANT PAYE]])=0),"FACTURE ANNULEE",IF(Tableau6[[#This Row],[ACOMPTE SUR TTC]]+Tableau6[[#This Row],[MONTANT PAYE]]=0,"ECHUE NON REGLEE",IF(Tableau6[[#This Row],[ACOMPTE SUR TTC]]+Tableau6[[#This Row],[MONTANT PAYE]]=Tableau6[[#This Row],[NET A PAYER]],"PAYE",IF(Tableau6[[#This Row],[ACOMPTE SUR TTC]]+Tableau6[[#This Row],[MONTANT PAYE]]<Tableau6[[#This Row],[NET A PAYER]],"PAIEMENT PARTIEL","TROP PAYE")))))) -> PAYE | W92: =SUMIF(Tableau3[FACTURE],Tableau6[[#This Row],[NUM DE FACTURE]],Tableau3[MONTANT TTC]) -> 5900000 | Y92: =+Tableau6[[#This Row],[NET A PAYER]]-Tableau6[[#This Row],[MONTANT PAYE]] -> 0
A93: KENAM S | B93: 45720 | C93: 45720 | D93: 315 | E93: PFO CONSTRUCTION | F93: LOCATION DE CAMION | G93: 257B0207 | H93: TVAF | J93: 4680000 | K93: =+Tableau6[[#This Row],[MONTANT HT BIEN]]+Tableau6[[#This Row],[MONTANT HT SERVICE]] -> 4680000 | L93: 0 | M93: =+IFERROR(IF(Tableau6[[#This Row],[CODE TVA]]="TVAF",Tableau6[[#This Row],[MONTANT HT]]*0.18,0),0) -> 842400 | N93: =Tableau6[[#This Row],[MONTANT HT]]+Tableau6[[#This Row],[TVA]]-Tableau6[[#This Row],[ACOMPTE SUR HT]] -> 5522400 | P93: =+ROUND(Tableau6[[#This Row],[MONTANT TTC]]-Tableau6[[#This Row],[ACOMPTE SUR TTC]],0) -> 5522400 | Q93: BC201326 | R93: =IFERROR(INDEX(Tableau2[[ID BC UNIQUE]:[MONTANT HT VALIDE]],MATCH(Tableau6[[#This Row],[N° BC]],Tableau2[ID BC UNIQUE],0),6),0) -> 4680000 | S93: =IFERROR(INDEX(Tableau2[[DATE]:[DELAIS DE PAIEMENT FACTURES EN JOUR]],MATCH(Tableau6[[#This Row],[N° BC]],Tableau2[ID BC UNIQUE],0),5),0) -> 30 | T93: =IF(ISBLANK(Tableau6[[#This Row],[DATE DE DEPOT]]),"",Tableau6[[#This Row],[DATE DE DEPOT]]+Tableau6[[#This Row],[DELAI]]) -> 45750 | U93: =+IF(AND(W93=0,Tableau6[[#This Row],[DATE LIMITE]]<TODAY()),TODAY()-Tableau6[[#This Row],[DATE LIMITE]],0) -> 0 | V93: =IF(Tableau6[[#This Row],[DATE LIMITE]]>=TODAY(),"NON ECHUE",IF(Tableau6[[#This Row],[MONTANT HT]]<0,IF(ISNUMBER(MATCH(-Tableau6[[#This Row],[MONTANT HT]],Tableau6[MONTANT HT],0)),"AVOIR TOTAL","AVOIR PARTIEL"),IF(AND(ISNUMBER(MATCH(-Tableau6[[#This Row],[MONTANT HT]],Tableau6[MONTANT HT],0)),(Tableau6[[#This Row],[ACOMPTE SUR TTC]]+Tableau6[[#This Row],[MONTANT PAYE]])=0),"FACTURE ANNULEE",IF(Tableau6[[#This Row],[ACOMPTE SUR TTC]]+Tableau6[[#This Row],[MONTANT PAYE]]=0,"ECHUE NON REGLEE",IF(Tableau6[[#This Row],[ACOMPTE SUR TTC]]+Tableau6[[#This Row],[MONTANT PAYE]]=Tableau6[[#This Row],[NET A PAYER]],"PAYE",IF(Tableau6[[#This Row],[ACOMPTE SUR TTC]]+Tableau6[[#This Row],[MONTANT PAYE]]<Tableau6[[#This Row],[NET A PAYER]],"PAIEMENT PARTIEL","TROP PAYE")))))) -> PAYE | W93: =SUMIF(Tableau3[FACTURE],Tableau6[[#This Row],[NUM DE FACTURE]],Tableau3[MONTANT TTC]) -> 5522400 | Y93: =+Tableau6[[#This Row],[NET A PAYER]]-Tableau6[[#This Row],[MONTANT PAYE]] -> 0
A94: KENAM S | B94: 45720 | C94: 45720 | D94: 316 | E94: PFO CONSTRUCTION | F94: LOCATION DE CAMION | G94: 257B0003 | H94: TVAF | J94: 4800000 | K94: =+Tableau6[[#This Row],[MONTANT HT BIEN]]+Tableau6[[#This Row],[MONTANT HT SERVICE]] -> 4800000 | L94: 0 | M94: =+IFERROR(IF(Tableau6[[#This Row],[CODE TVA]]="TVAF",Tableau6[[#This Row],[MONTANT HT]]*0.18,0),0) -> 864000 | N94: =Tableau6[[#This Row],[MONTANT HT]]+Tableau6[[#This Row],[TVA]]-Tableau6[[#This Row],[ACOMPTE SUR HT]] -> 5664000 | P94: =+ROUND(Tableau6[[#This Row],[MONTANT TTC]]-Tableau6[[#This Row],[ACOMPTE SUR TTC]],0) -> 5664000 | Q94: BC201325 | R94: =IFERROR(INDEX(Tableau2[[ID BC UNIQUE]:[MONTANT HT VALIDE]],MATCH(Tableau6[[#This Row],[N° BC]],Tableau2[ID BC UNIQUE],0),6),0) -> 4800000 | S94: =IFERROR(INDEX(Tableau2[[DATE]:[DELAIS DE PAIEMENT FACTURES EN JOUR]],MATCH(Tableau6[[#This Row],[N° BC]],Tableau2[ID BC UNIQUE],0),5),0) -> 30 | T94: =IF(ISBLANK(Tableau6[[#This Row],[DATE DE DEPOT]]),"",Tableau6[[#This Row],[DATE DE DEPOT]]+Tableau6[[#This Row],[DELAI]]) -> 45750 | U94: =+IF(AND(W94=0,Tableau6[[#This Row],[DATE LIMITE]]<TODAY()),TODAY()-Tableau6[[#This Row],[DATE LIMITE]],0) -> 0 | V94: =IF(Tableau6[[#This Row],[DATE LIMITE]]>=TODAY(),"NON ECHUE",IF(Tableau6[[#This Row],[MONTANT HT]]<0,IF(ISNUMBER(MATCH(-Tableau6[[#This Row],[MONTANT HT]],Tableau6[MONTANT HT],0)),"AVOIR TOTAL","AVOIR PARTIEL"),IF(AND(ISNUMBER(MATCH(-Tableau6[[#This Row],[MONTANT HT]],Tableau6[MONTANT HT],0)),(Tableau6[[#This Row],[ACOMPTE SUR TTC]]+Tableau6[[#This Row],[MONTANT PAYE]])=0),"FACTURE ANNULEE",IF(Tableau6[[#This Row],[ACOMPTE SUR TTC]]+Tableau6[[#This Row],[MONTANT PAYE]]=0,"ECHUE NON REGLEE",IF(Tableau6[[#This Row],[ACOMPTE SUR TTC]]+Tableau6[[#This Row],[MONTANT PAYE]]=Tableau6[[#This Row],[NET A PAYER]],"PAYE",IF(Tableau6[[#This Row],[ACOMPTE SUR TTC]]+Tableau6[[#This Row],[MONTANT PAYE]]<Tableau6[[#This Row],[NET A PAYER]],"PAIEMENT PARTIEL","TROP PAYE")))))) -> PAYE | W94: =SUMIF(Tableau3[FACTURE],Tableau6[[#This Row],[NUM DE FACTURE]],Tableau3[MONTANT TTC]) -> 5664000 | Y94: =+Tableau6[[#This Row],[NET A PAYER]]-Tableau6[[#This Row],[MONTANT PAYE]] -> 0
A95: KENAM S | B95: 45720 | C95: 45720 | D95: 317 | E95: PFO CONSTRUCTION | F95: LOCATION DE CAMION | G95: 257B0403 | H95: TVAF | J95: 6000000 | K95: =+Tableau6[[#This Row],[MONTANT HT BIEN]]+Tableau6[[#This Row],[MONTANT HT SERVICE]] -> 6000000 | L95: 0 | M95: =+IFERROR(IF(Tableau6[[#This Row],[CODE TVA]]="TVAF",Tableau6[[#This Row],[MONTANT HT]]*0.18,0),0) -> 1080000 | N95: =Tableau6[[#This Row],[MONTANT HT]]+Tableau6[[#This Row],[TVA]]-Tableau6[[#This Row],[ACOMPTE SUR HT]] -> 7080000 | P95: =+ROUND(Tableau6[[#This Row],[MONTANT TTC]]-Tableau6[[#This Row],[ACOMPTE SUR TTC]],0) -> 7080000 | Q95: BC201328 | R95: =IFERROR(INDEX(Tableau2[[ID BC UNIQUE]:[MONTANT HT VALIDE]],MATCH(Tableau6[[#This Row],[N° BC]],Tableau2[ID BC UNIQUE],0),6),0) -> 6000000 | S95: =IFERROR(INDEX(Tableau2[[DATE]:[DELAIS DE PAIEMENT FACTURES EN JOUR]],MATCH(Tableau6[[#This Row],[N° BC]],Tableau2[ID BC UNIQUE],0),5),0) -> 30 | T95: =IF(ISBLANK(Tableau6[[#This Row],[DATE DE DEPOT]]),"",Tableau6[[#This Row],[DATE DE DEPOT]]+Tableau6[[#This Row],[DELAI]]) -> 45750 | U95: =+IF(AND(W95=0,Tableau6[[#This Row],[DATE LIMITE]]<TODAY()),TODAY()-Tableau6[[#This Row],[DATE LIMITE]],0) -> 0 | V95: =IF(Tableau6[[#This Row],[DATE LIMITE]]>=TODAY(),"NON ECHUE",IF(Tableau6[[#This Row],[MONTANT HT]]<0,IF(ISNUMBER(MATCH(-Tableau6[[#This Row],[MONTANT HT]],Tableau6[MONTANT HT],0)),"AVOIR TOTAL","AVOIR PARTIEL"),IF(AND(ISNUMBER(MATCH(-Tableau6[[#This Row],[MONTANT HT]],Tableau6[MONTANT HT],0)),(Tableau6[[#This Row],[ACOMPTE SUR TTC]]+Tableau6[[#This Row],[MONTANT PAYE]])=0),"FACTURE ANNULEE",IF(Tableau6[[#This Row],[ACOMPTE SUR TTC]]+Tableau6[[#This Row],[MONTANT PAYE]]=0,"ECHUE NON REGLEE",IF(Tableau6[[#This Row],[ACOMPTE SUR TTC]]+Tableau6[[#This Row],[MONTANT PAYE]]=Tableau6[[#This Row],[NET A PAYER]],"PAYE",IF(Tableau6[[#This Row],[ACOMPTE SUR TTC]]+Tableau6[[#This Row],[MONTANT PAYE]]<Tableau6[[#This Row],[NET A PAYER]],"PAIEMENT PARTIEL","TROP PAYE")))))) -> PAYE | W95: =SUMIF(Tableau3[FACTURE],Tableau6[[#This Row],[NUM DE FACTURE]],Tableau3[MONTANT TTC]) -> 7080000 | Y95: =+Tableau6[[#This Row],[NET A PAYER]]-Tableau6[[#This Row],[MONTANT PAYE]] -> 0
A96: KENAM S | B96: 45720 | C96: 45720 | D96: 318 | E96: PFO CONSTRUCTION | F96: LOCATION DE CAMION | G96: 257B0403 | H96: TVAF | J96: 4320000 | K96: =+Tableau6[[#This Row],[MONTANT HT BIEN]]+Tableau6[[#This Row],[MONTANT HT SERVICE]] -> 4320000 | L96: 0 | M96: =+IFERROR(IF(Tableau6[[#This Row],[CODE TVA]]="TVAF",Tableau6[[#This Row],[MONTANT HT]]*0.18,0),0) -> 777600 | N96: =Tableau6[[#This Row],[MONTANT HT]]+Tableau6[[#This Row],[TVA]]-Tableau6[[#This Row],[ACOMPTE SUR HT]] -> 5097600 | P96: =+ROUND(Tableau6[[#This Row],[MONTANT TTC]]-Tableau6[[#This Row],[ACOMPTE SUR TTC]],0) -> 5097600 | Q96: BC201330 | R96: =IFERROR(INDEX(Tableau2[[ID BC UNIQUE]:[MONTANT HT VALIDE]],MATCH(Tableau6[[#This Row],[N° BC]],Tableau2[ID BC UNIQUE],0),6),0) -> 4320000 | S96: =IFERROR(INDEX(Tableau2[[DATE]:[DELAIS DE PAIEMENT FACTURES EN JOUR]],MATCH(Tableau6[[#This Row],[N° BC]],Tableau2[ID BC UNIQUE],0),5),0) -> 30 | T96: =IF(ISBLANK(Tableau6[[#This Row],[DATE DE DEPOT]]),"",Tableau6[[#This Row],[DATE DE DEPOT]]+Tableau6[[#This Row],[DELAI]]) -> 45750 | U96: =+IF(AND(W96=0,Tableau6[[#This Row],[DATE LIMITE]]<TODAY()),TODAY()-Tableau6[[#This Row],[DATE LIMITE]],0) -> 0 | V96: =IF(Tableau6[[#This Row],[DATE LIMITE]]>=TODAY(),"NON ECHUE",IF(Tableau6[[#This Row],[MONTANT HT]]<0,IF(ISNUMBER(MATCH(-Tableau6[[#This Row],[MONTANT HT]],Tableau6[MONTANT HT],0)),"AVOIR TOTAL","AVOIR PARTIEL"),IF(AND(ISNUMBER(MATCH(-Tableau6[[#This Row],[MONTANT HT]],Tableau6[MONTANT HT],0)),(Tableau6[[#This Row],[ACOMPTE SUR TTC]]+Tableau6[[#This Row],[MONTANT PAYE]])=0),"FACTURE ANNULEE",IF(Tableau6[[#This Row],[ACOMPTE SUR TTC]]+Tableau6[[#This Row],[MONTANT PAYE]]=0,"ECHUE NON REGLEE",IF(Tableau6[[#This Row],[ACOMPTE SUR TTC]]+Tableau6[[#This Row],[MONTANT PAYE]]=Tableau6[[#This Row],[NET A PAYER]],"PAYE",IF(Tableau6[[#This Row],[ACOMPTE SUR TTC]]+Tableau6[[#This Row],[MONTANT PAYE]]<Tableau6[[#This Row],[NET A PAYER]],"PAIEMENT PARTIEL","TROP PAYE")))))) -> PAYE | W96: =SUMIF(Tableau3[FACTURE],Tableau6[[#This Row],[NUM DE FACTURE]],Tableau3[MONTANT TTC]) -> 5097600 | Y96: =+Tableau6[[#This Row],[NET A PAYER]]-Tableau6[[#This Row],[MONTANT PAYE]] -> 0
A97: KENAM S | B97: 45720 | C97: 45720 | D97: 319 | E97: PFO CONSTRUCTION | F97: LOCATION DE CAMION | G97: 257B0005 | H97: TVAF | J97: 5000000 | K97: =+Tableau6[[#This Row],[MONTANT HT BIEN]]+Tableau6[[#This Row],[MONTANT HT SERVICE]] -> 5000000 | L97: 0 | M97: =+IFERROR(IF(Tableau6[[#This Row],[CODE TVA]]="TVAF",Tableau6[[#This Row],[MONTANT HT]]*0.18,0),0) -> 900000 | N97: =Tableau6[[#This Row],[MONTANT HT]]+Tableau6[[#This Row],[TVA]]-Tableau6[[#This Row],[ACOMPTE SUR HT]] -> 5900000 | P97: =+ROUND(Tableau6[[#This Row],[MONTANT TTC]]-Tableau6[[#This Row],[ACOMPTE SUR TTC]],0) -> 5900000 | Q97: BC201331 | R97: =IFERROR(INDEX(Tableau2[[ID BC UNIQUE]:[MONTANT HT VALIDE]],MATCH(Tableau6[[#This Row],[N° BC]],Tableau2[ID BC UNIQUE],0),6),0) -> 5000000 | S97: =IFERROR(INDEX(Tableau2[[DATE]:[DELAIS DE PAIEMENT FACTURES EN JOUR]],MATCH(Tableau6[[#This Row],[N° BC]],Tableau2[ID BC UNIQUE],0),5),0) -> 30 | T97: =IF(ISBLANK(Tableau6[[#This Row],[DATE DE DEPOT]]),"",Tableau6[[#This Row],[DATE DE DEPOT]]+Tableau6[[#This Row],[DELAI]]) -> 45750 | U97: =+IF(AND(W97=0,Tableau6[[#This Row],[DATE LIMITE]]<TODAY()),TODAY()-Tableau6[[#This Row],[DATE LIMITE]],0) -> 0 | V97: =IF(Tableau6[[#This Row],[DATE LIMITE]]>=TODAY(),"NON ECHUE",IF(Tableau6[[#This Row],[MONTANT HT]]<0,IF(ISNUMBER(MATCH(-Tableau6[[#This Row],[MONTANT HT]],Tableau6[MONTANT HT],0)),"AVOIR TOTAL","AVOIR PARTIEL"),IF(AND(ISNUMBER(MATCH(-Tableau6[[#This Row],[MONTANT HT]],Tableau6[MONTANT HT],0)),(Tableau6[[#This Row],[ACOMPTE SUR TTC]]+Tableau6[[#This Row],[MONTANT PAYE]])=0),"FACTURE ANNULEE",IF(Tableau6[[#This Row],[ACOMPTE SUR TTC]]+Tableau6[[#This Row],[MONTANT PAYE]]=0,"ECHUE NON REGLEE",IF(Tableau6[[#This Row],[ACOMPTE SUR TTC]]+Tableau6[[#This Row],[MONTANT PAYE]]=Tableau6[[#This Row],[NET A PAYER]],"PAYE",IF(Tableau6[[#This Row],[ACOMPTE SUR TTC]]+Tableau6[[#This Row],[MONTANT PAYE]]<Tableau6[[#This Row],[NET A PAYER]],"PAIEMENT PARTIEL","TROP PAYE")))))) -> PAYE | W97: =SUMIF(Tableau3[FACTURE],Tableau6[[#This Row],[NUM DE FACTURE]],Tableau3[MONTANT TTC]) -> 5900000 | Y97: =+Tableau6[[#This Row],[NET A PAYER]]-Tableau6[[#This Row],[MONTANT PAYE]] -> 0
A98: KENAM S | B98: 45720 | C98: 45720 | D98: 320 | E98: PFO CONSTRUCTION | F98: LOCATION DE CAMION | G98: 257B0403 | H98: TVAF | J98: 6392000 | K98: =+Tableau6[[#This Row],[MONTANT HT BIEN]]+Tableau6[[#This Row],[MONTANT HT SERVICE]] -> 6392000 | L98: 0 | M98: =+IFERROR(IF(Tableau6[[#This Row],[CODE TVA]]="TVAF",Tableau6[[#This Row],[MONTANT HT]]*0.18,0),0) -> 1150560 | N98: =Tableau6[[#This Row],[MONTANT HT]]+Tableau6[[#This Row],[TVA]]-Tableau6[[#This Row],[ACOMPTE SUR HT]] -> 7542560 | P98: =+ROUND(Tableau6[[#This Row],[MONTANT TTC]]-Tableau6[[#This Row],[ACOMPTE SUR TTC]],0) -> 7542560 | Q98: BC201329 | R98: =IFERROR(INDEX(Tableau2[[ID BC UNIQUE]:[MONTANT HT VALIDE]],MATCH(Tableau6[[#This Row],[N° BC]],Tableau2[ID BC UNIQUE],0),6),0) -> 6392000 | S98: =IFERROR(INDEX(Tableau2[[DATE]:[DELAIS DE PAIEMENT FACTURES EN JOUR]],MATCH(Tableau6[[#This Row],[N° BC]],Tableau2[ID BC UNIQUE],0),5),0) -> 30 | T98: =IF(ISBLANK(Tableau6[[#This Row],[DATE DE DEPOT]]),"",Tableau6[[#This Row],[DATE DE DEPOT]]+Tableau6[[#This Row],[DELAI]]) -> 45750 | U98: =+IF(AND(W98=0,Tableau6[[#This Row],[DATE LIMITE]]<TODAY()),TODAY()-Tableau6[[#This Row],[DATE LIMITE]],0) -> 0 | V98: =IF(Tableau6[[#This Row],[DATE LIMITE]]>=TODAY(),"NON ECHUE",IF(Tableau6[[#This Row],[MONTANT HT]]<0,IF(ISNUMBER(MATCH(-Tableau6[[#This Row],[MONTANT HT]],Tableau6[MONTANT HT],0)),"AVOIR TOTAL","AVOIR PARTIEL"),IF(AND(ISNUMBER(MATCH(-Tableau6[[#This Row],[MONTANT HT]],Tableau6[MONTANT HT],0)),(Tableau6[[#This Row],[ACOMPTE SUR TTC]]+Tableau6[[#This Row],[MONTANT PAYE]])=0),"FACTURE ANNULEE",IF(Tableau6[[#This Row],[ACOMPTE SUR TTC]]+Tableau6[[#This Row],[MONTANT PAYE]]=0,"ECHUE NON REGLEE",IF(Tableau6[[#This Row],[ACOMPTE SUR TTC]]+Tableau6[[#This Row],[MONTANT PAYE]]=Tableau6[[#This Row],[NET A PAYER]],"PAYE",IF(Tableau6[[#This Row],[ACOMPTE SUR TTC]]+Tableau6[[#This Row],[MONTANT PAYE]]<Tableau6[[#This Row],[NET A PAYER]],"PAIEMENT PARTIEL","TROP PAYE")))))) -> PAYE | W98: =SUMIF(Tableau3[FACTURE],Tableau6[[#This Row],[NUM DE FACTURE]],Tableau3[MONTANT TTC]) -> 7542560 | Y98: =+Tableau6[[#This Row],[NET A PAYER]]-Tableau6[[#This Row],[MONTANT PAYE]] -> 0
A99: KENAM S | B99: 45720 | C99: 45720 | D99: 321 | E99: PFO CONSTRUCTION | F99: LOCATION DE CAMION | G99: 257B0109 | H99: TVAF | J99: 4290000 | K99: =+Tableau6[[#This Row],[MONTANT HT BIEN]]+Tableau6[[#This Row],[MONTANT HT SERVICE]] -> 4290000 | L99: 0 | M99: =+IFERROR(IF(Tableau6[[#This Row],[CODE TVA]]="TVAF",Tableau6[[#This Row],[MONTANT HT]]*0.18,0),0) -> 772200 | N99: =Tableau6[[#This Row],[MONTANT HT]]+Tableau6[[#This Row],[TVA]]-Tableau6[[#This Row],[ACOMPTE SUR HT]] -> 5062200 | P99: =+ROUND(Tableau6[[#This Row],[MONTANT TTC]]-Tableau6[[#This Row],[ACOMPTE SUR TTC]],0) -> 5062200 | Q99: BC201324 | R99: =IFERROR(INDEX(Tableau2[[ID BC UNIQUE]:[MONTANT HT VALIDE]],MATCH(Tableau6[[#This Row],[N° BC]],Tableau2[ID BC UNIQUE],0),6),0) -> 4290000 | S99: =IFERROR(INDEX(Tableau2[[DATE]:[DELAIS DE PAIEMENT FACTURES EN JOUR]],MATCH(Tableau6[[#This Row],[N° BC]],Tableau2[ID BC UNIQUE],0),5),0) -> 30 | T99: =IF(ISBLANK(Tableau6[[#This Row],[DATE DE DEPOT]]),"",Tableau6[[#This Row],[DATE DE DEPOT]]+Tableau6[[#This Row],[DELAI]]) -> 45750 | U99: =+IF(AND(W99=0,Tableau6[[#This Row],[DATE LIMITE]]<TODAY()),TODAY()-Tableau6[[#This Row],[DATE LIMITE]],0) -> 0 | V99: =IF(Tableau6[[#This Row],[DATE LIMITE]]>=TODAY(),"NON ECHUE",IF(Tableau6[[#This Row],[MONTANT HT]]<0,IF(ISNUMBER(MATCH(-Tableau6[[#This Row],[MONTANT HT]],Tableau6[MONTANT HT],0)),"AVOIR TOTAL","AVOIR PARTIEL"),IF(AND(ISNUMBER(MATCH(-Tableau6[[#This Row],[MONTANT HT]],Tableau6[MONTANT HT],0)),(Tableau6[[#This Row],[ACOMPTE SUR TTC]]+Tableau6[[#This Row],[MONTANT PAYE]])=0),"FACTURE ANNULEE",IF(Tableau6[[#This Row],[ACOMPTE SUR TTC]]+Tableau6[[#This Row],[MONTANT PAYE]]=0,"ECHUE NON REGLEE",IF(Tableau6[[#This Row],[ACOMPTE SUR TTC]]+Tableau6[[#This Row],[MONTANT PAYE]]=Tableau6[[#This Row],[NET A PAYER]],"PAYE",IF(Tableau6[[#This Row],[ACOMPTE SUR TTC]]+Tableau6[[#This Row],[MONTANT PAYE]]<Tableau6[[#This Row],[NET A PAYER]],"PAIEMENT PARTIEL","TROP PAYE")))))) -> PAYE | W99: =SUMIF(Tableau3[FACTURE],Tableau6[[#This Row],[NUM DE FACTURE]],Tableau3[MONTANT TTC]) -> 5062200 | Y99: =+Tableau6[[#This Row],[NET A PAYER]]-Tableau6[[#This Row],[MONTANT PAYE]] -> 0
A100: KENAM S | B100: 45722 | C100: 45722 | D100: 322 | E100: KOIRA BTP | F100: LOCATION DE CAMION | G100: 211R3002 | H100: TVAF | J100: 640000 | K100: =+Tableau6[[#This Row],[MONTANT HT BIEN]]+Tableau6[[#This Row],[MONTANT HT SERVICE]] -> 640000 | L100: 0 | M100: =+IFERROR(IF(Tableau6[[#This Row],[CODE TVA]]="TVAF",Tableau6[[#This Row],[MONTANT HT]]*0.18,0),0) -> 115200 | N100: =Tableau6[[#This Row],[MONTANT HT]]+Tableau6[[#This Row],[TVA]]-Tableau6[[#This Row],[ACOMPTE SUR HT]] -> 755200 | P100: =+ROUND(Tableau6[[#This Row],[MONTANT TTC]]-Tableau6[[#This Row],[ACOMPTE SUR TTC]],0) -> 755200 | Q100: BC250206 | R100: =IFERROR(INDEX(Tableau2[[ID BC UNIQUE]:[MONTANT HT VALIDE]],MATCH(Tableau6[[#This Row],[N° BC]],Tableau2[ID BC UNIQUE],0),6),0) -> 8188088 | S100: =IFERROR(INDEX(Tableau2[[DATE]:[DELAIS DE PAIEMENT FACTURES EN JOUR]],MATCH(Tableau6[[#This Row],[N° BC]],Tableau2[ID BC UNIQUE],0),5),0) -> 30 | T100: =IF(ISBLANK(Tableau6[[#This Row],[DATE DE DEPOT]]),"",Tableau6[[#This Row],[DATE DE DEPOT]]+Tableau6[[#This Row],[DELAI]]) -> 45752 | U100: =+IF(AND(W100=0,Tableau6[[#This Row],[DATE LIMITE]]<TODAY()),TODAY()-Tableau6[[#This Row],[DATE LIMITE]],0) -> 0 | V100: =IF(Tableau6[[#This Row],[DATE LIMITE]]>=TODAY(),"NON ECHUE",IF(Tableau6[[#This Row],[MONTANT HT]]<0,IF(ISNUMBER(MATCH(-Tableau6[[#This Row],[MONTANT HT]],Tableau6[MONTANT HT],0)),"AVOIR TOTAL","AVOIR PARTIEL"),IF(AND(ISNUMBER(MATCH(-Tableau6[[#This Row],[MONTANT HT]],Tableau6[MONTANT HT],0)),(Tableau6[[#This Row],[ACOMPTE SUR TTC]]+Tableau6[[#This Row],[MONTANT PAYE]])=0),"FACTURE ANNULEE",IF(Tableau6[[#This Row],[ACOMPTE SUR TTC]]+Tableau6[[#This Row],[MONTANT PAYE]]=0,"ECHUE NON REGLEE",IF(Tableau6[[#This Row],[ACOMPTE SUR TTC]]+Tableau6[[#This Row],[MONTANT PAYE]]=Tableau6[[#This Row],[NET A PAYER]],"PAYE",IF(Tableau6[[#This Row],[ACOMPTE SUR TTC]]+Tableau6[[#This Row],[MONTANT PAYE]]<Tableau6[[#This Row],[NET A PAYER]],"PAIEMENT PARTIEL","TROP PAYE")))))) -> PAYE | W100: =SUMIF(Tableau3[FACTURE],Tableau6[[#This Row],[NUM DE FACTURE]],Tableau3[MONTANT TTC]) -> 755200 | Y100: =+Tableau6[[#This Row],[NET A PAYER]]-Tableau6[[#This Row],[MONTANT PAYE]] -> 0
A101: KENAM S | B101: 45722 | C101: 45722 | D101: 323 | E101: KOIRA BTP | F101: LOCATION DE CAMION | G101: 211R3002 | H101: TVAF | J101: =384620-1 -> 384619 | K101: =+Tableau6[[#This Row],[MONTANT HT BIEN]]+Tableau6[[#This Row],[MONTANT HT SERVICE]] -> 384619 | L101: 0 | M101: =+IFERROR(IF(Tableau6[[#This Row],[CODE TVA]]="TVAF",Tableau6[[#This Row],[MONTANT HT]]*0.18,0),0) -> 69231.42 | N101: =Tableau6[[#This Row],[MONTANT HT]]+Tableau6[[#This Row],[TVA]]-Tableau6[[#This Row],[ACOMPTE SUR HT]] -> 453850.42 | P101: =+ROUND(Tableau6[[#This Row],[MONTANT TTC]]-Tableau6[[#This Row],[ACOMPTE SUR TTC]],0) -> 453850 | Q101: BC250206 | R101: =IFERROR(INDEX(Tableau2[[ID BC UNIQUE]:[MONTANT HT VALIDE]],MATCH(Tableau6[[#This Row],[N° BC]],Tableau2[ID BC UNIQUE],0),6),0) -> 8188088 | S101: =IFERROR(INDEX(Tableau2[[DATE]:[DELAIS DE PAIEMENT FACTURES EN JOUR]],MATCH(Tableau6[[#This Row],[N° BC]],Tableau2[ID BC UNIQUE],0),5),0) -> 30 | T101: =IF(ISBLANK(Tableau6[[#This Row],[DATE DE DEPOT]]),"",Tableau6[[#This Row],[DATE DE DEPOT]]+Tableau6[[#This Row],[DELAI]]) -> 45752 | U101: =+IF(AND(W101=0,Tableau6[[#This Row],[DATE LIMITE]]<TODAY()),TODAY()-Tableau6[[#This Row],[DATE LIMITE]],0) -> 0 | V101: =IF(Tableau6[[#This Row],[DATE LIMITE]]>=TODAY(),"NON ECHUE",IF(Tableau6[[#This Row],[MONTANT HT]]<0,IF(ISNUMBER(MATCH(-Tableau6[[#This Row],[MONTANT HT]],Tableau6[MONTANT HT],0)),"AVOIR TOTAL","AVOIR PARTIEL"),IF(AND(ISNUMBER(MATCH(-Tableau6[[#This Row],[MONTANT HT]],Tableau6[MONTANT HT],0)),(Tableau6[[#This Row],[ACOMPTE SUR TTC]]+Tableau6[[#This Row],[MONTANT PAYE]])=0),"FACTURE ANNULEE",IF(Tableau6[[#This Row],[ACOMPTE SUR TTC]]+Tableau6[[#This Row],[MONTANT PAYE]]=0,"ECHUE NON REGLEE",IF(Tableau6[[#This Row],[ACOMPTE SUR TTC]]+Tableau6[[#This Row],[MONTANT PAYE]]=Tableau6[[#This Row],[NET A PAYER]],"PAYE",IF(Tableau6[[#This Row],[ACOMPTE SUR TTC]]+Tableau6[[#This Row],[MONTANT PAYE]]<Tableau6[[#This Row],[NET A PAYER]],"PAIEMENT PARTIEL","TROP PAYE")))))) -> TROP PAYE | W101: =SUMIF(Tableau3[FACTURE],Tableau6[[#This Row],[NUM DE FACTURE]],Tableau3[MONTANT TTC]) -> 453851 | Y101: =+Tableau6[[#This Row],[NET A PAYER]]-Tableau6[[#This Row],[MONTANT PAYE]] -> -1
A102: KENAM S | B102: 45722 | C102: 45722 | D102: 324 | E102: KOIRA BTP | F102: LOCATION DE CAMION | G102: 211R3002 | H102: TVAF | J102: =384620-1 -> 384619 | K102: =+Tableau6[[#This Row],[MONTANT HT BIEN]]+Tableau6[[#This Row],[MONTANT HT SERVICE]] -> 384619 | L102: 0 | M102: =+IFERROR(IF(Tableau6[[#This Row],[CODE TVA]]="TVAF",Tableau6[[#This Row],[MONTANT HT]]*0.18,0),0) -> 69231.42 | N102: =Tableau6[[#This Row],[MONTANT HT]]+Tableau6[[#This Row],[TVA]]-Tableau6[[#This Row],[ACOMPTE SUR HT]] -> 453850.42 | P102: =+ROUND(Tableau6[[#This Row],[MONTANT TTC]]-Tableau6[[#This Row],[ACOMPTE SUR TTC]],0) -> 453850 | Q102: BC250206 | R102: =IFERROR(INDEX(Tableau2[[ID BC UNIQUE]:[MONTANT HT VALIDE]],MATCH(Tableau6[[#This Row],[N° BC]],Tableau2[ID BC UNIQUE],0),6),0) -> 8188088 | S102: =IFERROR(INDEX(Tableau2[[DATE]:[DELAIS DE PAIEMENT FACTURES EN JOUR]],MATCH(Tableau6[[#This Row],[N° BC]],Tableau2[ID BC UNIQUE],0),5),0) -> 30 | T102: =IF(ISBLANK(Tableau6[[#This Row],[DATE DE DEPOT]]),"",Tableau6[[#This Row],[DATE DE DEPOT]]+Tableau6[[#This Row],[DELAI]]) -> 45752 | U102: =+IF(AND(W102=0,Tableau6[[#This Row],[DATE LIMITE]]<TODAY()),TODAY()-Tableau6[[#This Row],[DATE LIMITE]],0) -> 0 | V102: =IF(Tableau6[[#This Row],[DATE LIMITE]]>=TODAY(),"NON ECHUE",IF(Tableau6[[#This Row],[MONTANT HT]]<0,IF(ISNUMBER(MATCH(-Tableau6[[#This Row],[MONTANT HT]],Tableau6[MONTANT HT],0)),"AVOIR TOTAL","AVOIR PARTIEL"),IF(AND(ISNUMBER(MATCH(-Tableau6[[#This Row],[MONTANT HT]],Tableau6[MONTANT HT],0)),(Tableau6[[#This Row],[ACOMPTE SUR TTC]]+Tableau6[[#This Row],[MONTANT PAYE]])=0),"FACTURE ANNULEE",IF(Tableau6[[#This Row],[ACOMPTE SUR TTC]]+Tableau6[[#This Row],[MONTANT PAYE]]=0,"ECHUE NON REGLEE",IF(Tableau6[[#This Row],[ACOMPTE SUR TTC]]+Tableau6[[#This Row],[MONTANT PAYE]]=Tableau6[[#This Row],[NET A PAYER]],"PAYE",IF(Tableau6[[#This Row],[ACOMPTE SUR TTC]]+Tableau6[[#This Row],[MONTANT PAYE]]<Tableau6[[#This Row],[NET A PAYER]],"PAIEMENT PARTIEL","TROP PAYE")))))) -> TROP PAYE | W102: =SUMIF(Tableau3[FACTURE],Tableau6[[#This Row],[NUM DE FACTURE]],Tableau3[MONTANT TTC]) -> 453851 | Y102: =+Tableau6[[#This Row],[NET A PAYER]]-Tableau6[[#This Row],[MONTANT PAYE]] -> -1
A103: KENAM S | B103: 45722 | C103: 45722 | D103: 325 | E103: KOIRA BTP | F103: LOCATION DE CAMION | G103: 211R3002 | H103: TVAF | J103: 2805000 | K103: =+Tableau6[[#This Row],[MONTANT HT BIEN]]+Tableau6[[#This Row],[MONTANT HT SERVICE]] -> 2805000 | L103: 0 | M103: =+IFERROR(IF(Tableau6[[#This Row],[CODE TVA]]="TVAF",Tableau6[[#This Row],[MONTANT HT]]*0.18,0),0) -> 504900 | N103: =Tableau6[[#This Row],[MONTANT HT]]+Tableau6[[#This Row],[TVA]]-Tableau6[[#This Row],[ACOMPTE SUR HT]] -> 3309900 | P103: =+ROUND(Tableau6[[#This Row],[MONTANT TTC]]-Tableau6[[#This Row],[ACOMPTE SUR TTC]],0) -> 3309900 | Q103: BC250206 | R103: =IFERROR(INDEX(Tableau2[[ID BC UNIQUE]:[MONTANT HT VALIDE]],MATCH(Tableau6[[#This Row],[N° BC]],Tableau2[ID BC UNIQUE],0),6),0) -> 8188088 | S103: =IFERROR(INDEX(Tableau2[[DATE]:[DELAIS DE PAIEMENT FACTURES EN JOUR]],MATCH(Tableau6[[#This Row],[N° BC]],Tableau2[ID BC UNIQUE],0),5),0) -> 30 | T103: =IF(ISBLANK(Tableau6[[#This Row],[DATE DE DEPOT]]),"",Tableau6[[#This Row],[DATE DE DEPOT]]+Tableau6[[#This Row],[DELAI]]) -> 45752 | U103: =+IF(AND(W103=0,Tableau6[[#This Row],[DATE LIMITE]]<TODAY()),TODAY()-Tableau6[[#This Row],[DATE LIMITE]],0) -> 0 | V103: =IF(Tableau6[[#This Row],[DATE LIMITE]]>=TODAY(),"NON ECHUE",IF(Tableau6[[#This Row],[MONTANT HT]]<0,IF(ISNUMBER(MATCH(-Tableau6[[#This Row],[MONTANT HT]],Tableau6[MONTANT HT],0)),"AVOIR TOTAL","AVOIR PARTIEL"),IF(AND(ISNUMBER(MATCH(-Tableau6[[#This Row],[MONTANT HT]],Tableau6[MONTANT HT],0)),(Tableau6[[#This Row],[ACOMPTE SUR TTC]]+Tableau6[[#This Row],[MONTANT PAYE]])=0),"FACTURE ANNULEE",IF(Tableau6[[#This Row],[ACOMPTE SUR TTC]]+Tableau6[[#This Row],[MONTANT PAYE]]=0,"ECHUE NON REGLEE",IF(Tableau6[[#This Row],[ACOMPTE SUR TTC]]+Tableau6[[#This Row],[MONTANT PAYE]]=Tableau6[[#This Row],[NET A PAYER]],"PAYE",IF(Tableau6[[#This Row],[ACOMPTE SUR TTC]]+Tableau6[[#This Row],[MONTANT PAYE]]<Tableau6[[#This Row],[NET A PAYER]],"PAIEMENT PARTIEL","TROP PAYE")))))) -> PAYE | W103: =SUMIF(Tableau3[FACTURE],Tableau6[[#This Row],[NUM DE FACTURE]],Tableau3[MONTANT TTC]) -> 3309900 | Y103: =+Tableau6[[#This Row],[NET A PAYER]]-Tableau6[[#This Row],[MONTANT PAYE]] -> 0
A104: KENAM S | B104: 45722 | C104: 45722 | D104: 326 | E104: KOIRA BTP | F104: LOCATION DE CAMION | G104: 211R3002 | H104: TVAF | J104: =403848-1 -> 403847 | K104: =+Tableau6[[#This Row],[MONTANT HT BIEN]]+Tableau6[[#This Row],[MONTANT HT SERVICE]] -> 403847 | L104: 0 | M104: =+IFERROR(IF(Tableau6[[#This Row],[CODE TVA]]="TVAF",Tableau6[[#This Row],[MONTANT HT]]*0.18,0),0) -> 72692.46 | N104: =Tableau6[[#This Row],[MONTANT HT]]+Tableau6[[#This Row],[TVA]]-Tableau6[[#This Row],[ACOMPTE SUR HT]] -> 476539.46 | P104: =+ROUND(Tableau6[[#This Row],[MONTANT TTC]]-Tableau6[[#This Row],[ACOMPTE SUR TTC]],0) -> 476539 | Q104: BC250206 | R104: =IFERROR(INDEX(Tableau2[[ID BC UNIQUE]:[MONTANT HT VALIDE]],MATCH(Tableau6[[#This Row],[N° BC]],Tableau2[ID BC UNIQUE],0),6),0) -> 8188088 | S104: =IFERROR(INDEX(Tableau2[[DATE]:[DELAIS DE PAIEMENT FACTURES EN JOUR]],MATCH(Tableau6[[#This Row],[N° BC]],Tableau2[ID BC UNIQUE],0),5),0) -> 30 | T104: =IF(ISBLANK(Tableau6[[#This Row],[DATE DE DEPOT]]),"",Tableau6[[#This Row],[DATE DE DEPOT]]+Tableau6[[#This Row],[DELAI]]) -> 45752 | U104: =+IF(AND(W104=0,Tableau6[[#This Row],[DATE LIMITE]]<TODAY()),TODAY()-Tableau6[[#This Row],[DATE LIMITE]],0) -> 0 | V104: =IF(Tableau6[[#This Row],[DATE LIMITE]]>=TODAY(),"NON ECHUE",IF(Tableau6[[#This Row],[MONTANT HT]]<0,IF(ISNUMBER(MATCH(-Tableau6[[#This Row],[MONTANT HT]],Tableau6[MONTANT HT],0)),"AVOIR TOTAL","AVOIR PARTIEL"),IF(AND(ISNUMBER(MATCH(-Tableau6[[#This Row],[MONTANT HT]],Tableau6[MONTANT HT],0)),(Tableau6[[#This Row],[ACOMPTE SUR TTC]]+Tableau6[[#This Row],[MONTANT PAYE]])=0),"FACTURE ANNULEE",IF(Tableau6[[#This Row],[ACOMPTE SUR TTC]]+Tableau6[[#This Row],[MONTANT PAYE]]=0,"ECHUE NON REGLEE",IF(Tableau6[[#This Row],[ACOMPTE SUR TTC]]+Tableau6[[#This Row],[MONTANT PAYE]]=Tableau6[[#This Row],[NET A PAYER]],"PAYE",IF(Tableau6[[#This Row],[ACOMPTE SUR TTC]]+Tableau6[[#This Row],[MONTANT PAYE]]<Tableau6[[#This Row],[NET A PAYER]],"PAIEMENT PARTIEL","TROP PAYE")))))) -> TROP PAYE | W104: =SUMIF(Tableau3[FACTURE],Tableau6[[#This Row],[NUM DE FACTURE]],Tableau3[MONTANT TTC]) -> 476540 | Y104: =+Tableau6[[#This Row],[NET A PAYER]]-Tableau6[[#This Row],[MONTANT PAYE]] -> -1
A105: KENAM S | B105: 45722 | C105: 45722 | D105: 327 | E105: KOIRA BTP | F105: LOCATION DE CAMION | G105: 211R3002 | H105: TVAF | J105: 3570000 | K105: =+Tableau6[[#This Row],[MONTANT HT BIEN]]+Tableau6[[#This Row],[MONTANT HT SERVICE]] -> 3570000 | L105: 0 | M105: =+IFERROR(IF(Tableau6[[#This Row],[CODE TVA]]="TVAF",Tableau6[[#This Row],[MONTANT HT]]*0.18,0),0) -> 642600 | N105: =Tableau6[[#This Row],[MONTANT HT]]+Tableau6[[#This Row],[TVA]]-Tableau6[[#This Row],[ACOMPTE SUR HT]] -> 4212600 | P105: =+ROUND(Tableau6[[#This Row],[MONTANT TTC]]-Tableau6[[#This Row],[ACOMPTE SUR TTC]],0) -> 4212600 | Q105: BC250206 | R105: =IFERROR(INDEX(Tableau2[[ID BC UNIQUE]:[MONTANT HT VALIDE]],MATCH(Tableau6[[#This Row],[N° BC]],Tableau2[ID BC UNIQUE],0),6),0) -> 8188088 | S105: =IFERROR(INDEX(Tableau2[[DATE]:[DELAIS DE PAIEMENT FACTURES EN JOUR]],MATCH(Tableau6[[#This Row],[N° BC]],Tableau2[ID BC UNIQUE],0),5),0) -> 30 | T105: =IF(ISBLANK(Tableau6[[#This Row],[DATE DE DEPOT]]),"",Tableau6[[#This Row],[DATE DE DEPOT]]+Tableau6[[#This Row],[DELAI]]) -> 45752 | U105: =+IF(AND(W105=0,Tableau6[[#This Row],[DATE LIMITE]]<TODAY()),TODAY()-Tableau6[[#This Row],[DATE LIMITE]],0) -> 0 | V105: =IF(Tableau6[[#This Row],[DATE LIMITE]]>=TODAY(),"NON ECHUE",IF(Tableau6[[#This Row],[MONTANT HT]]<0,IF(ISNUMBER(MATCH(-Tableau6[[#This Row],[MONTANT HT]],Tableau6[MONTANT HT],0)),"AVOIR TOTAL","AVOIR PARTIEL"),IF(AND(ISNUMBER(MATCH(-Tableau6[[#This Row],[MONTANT HT]],Tableau6[MONTANT HT],0)),(Tableau6[[#This Row],[ACOMPTE SUR TTC]]+Tableau6[[#This Row],[MONTANT PAYE]])=0),"FACTURE ANNULEE",IF(Tableau6[[#This Row],[ACOMPTE SUR TTC]]+Tableau6[[#This Row],[MONTANT PAYE]]=0,"ECHUE NON REGLEE",IF(Tableau6[[#This Row],[ACOMPTE SUR TTC]]+Tableau6[[#This Row],[MONTANT PAYE]]=Tableau6[[#This Row],[NET A PAYER]],"PAYE",IF(Tableau6[[#This Row],[ACOMPTE SUR TTC]]+Tableau6[[#This Row],[MONTANT PAYE]]<Tableau6[[#This Row],[NET A PAYER]],"PAIEMENT PARTIEL","TROP PAYE")))))) -> PAYE | W105: =SUMIF(Tableau3[FACTURE],Tableau6[[#This Row],[NUM DE FACTURE]],Tableau3[MONTANT TTC]) -> 4212600 | Y105: =+Tableau6[[#This Row],[NET A PAYER]]-Tableau6[[#This Row],[MONTANT PAYE]] -> 0
A106: KENAM S | B106: 45723 | C106: 45723 | D106: 329 | E106: PFO CONSTRUCTION | F106: LOCATION DE CAMION | G106: 257B0403 | H106: TVAF | J106: 6000000 | K106: =+Tableau6[[#This Row],[MONTANT HT BIEN]]+Tableau6[[#This Row],[MONTANT HT SERVICE]] -> 6000000 | L106: 0 | M106: =+IFERROR(IF(Tableau6[[#This Row],[CODE TVA]]="TVAF",Tableau6[[#This Row],[MONTANT HT]]*0.18,0),0) -> 1080000 | N106: =Tableau6[[#This Row],[MONTANT HT]]+Tableau6[[#This Row],[TVA]]-Tableau6[[#This Row],[ACOMPTE SUR HT]] -> 7080000 | P106: =+ROUND(Tableau6[[#This Row],[MONTANT TTC]]-Tableau6[[#This Row],[ACOMPTE SUR TTC]],0) -> 7080000 | Q106: BC201395 | R106: =IFERROR(INDEX(Tableau2[[ID BC UNIQUE]:[MONTANT HT VALIDE]],MATCH(Tableau6[[#This Row],[N° BC]],Tableau2[ID BC UNIQUE],0),6),0) -> 6000000 | S106: =IFERROR(INDEX(Tableau2[[DATE]:[DELAIS DE PAIEMENT FACTURES EN JOUR]],MATCH(Tableau6[[#This Row],[N° BC]],Tableau2[ID BC UNIQUE],0),5),0) -> 30 | T106: =IF(ISBLANK(Tableau6[[#This Row],[DATE DE DEPOT]]),"",Tableau6[[#This Row],[DATE DE DEPOT]]+Tableau6[[#This Row],[DELAI]]) -> 45753 | U106: =+IF(AND(W106=0,Tableau6[[#This Row],[DATE LIMITE]]<TODAY()),TODAY()-Tableau6[[#This Row],[DATE LIMITE]],0) -> 0 | V106: =IF(Tableau6[[#This Row],[DATE LIMITE]]>=TODAY(),"NON ECHUE",IF(Tableau6[[#This Row],[MONTANT HT]]<0,IF(ISNUMBER(MATCH(-Tableau6[[#This Row],[MONTANT HT]],Tableau6[MONTANT HT],0)),"AVOIR TOTAL","AVOIR PARTIEL"),IF(AND(ISNUMBER(MATCH(-Tableau6[[#This Row],[MONTANT HT]],Tableau6[MONTANT HT],0)),(Tableau6[[#This Row],[ACOMPTE SUR TTC]]+Tableau6[[#This Row],[MONTANT PAYE]])=0),"FACTURE ANNULEE",IF(Tableau6[[#This Row],[ACOMPTE SUR TTC]]+Tableau6[[#This Row],[MONTANT PAYE]]=0,"ECHUE NON REGLEE",IF(Tableau6[[#This Row],[ACOMPTE SUR TTC]]+Tableau6[[#This Row],[MONTANT PAYE]]=Tableau6[[#This Row],[NET A PAYER]],"PAYE",IF(Tableau6[[#This Row],[ACOMPTE SUR TTC]]+Tableau6[[#This Row],[MONTANT PAYE]]<Tableau6[[#This Row],[NET A PAYER]],"PAIEMENT PARTIEL","TROP PAYE")))))) -> PAYE | W106: =SUMIF(Tableau3[FACTURE],Tableau6[[#This Row],[NUM DE FACTURE]],Tableau3[MONTANT TTC]) -> 7080000 | Y106: =+Tableau6[[#This Row],[NET A PAYER]]-Tableau6[[#This Row],[MONTANT PAYE]] -> 0
A107: KENAM S | B107: 45723 | C107: 45723 | D107: 330 | E107: PFO CONSTRUCTION | F107: LOCATION DE CAMION | G107: 257B0109 | H107: TVAF | J107: 6600000 | K107: =+Tableau6[[#This Row],[MONTANT HT BIEN]]+Tableau6[[#This Row],[MONTANT HT SERVICE]] -> 6600000 | L107: 0 | M107: =+IFERROR(IF(Tableau6[[#This Row],[CODE TVA]]="TVAF",Tableau6[[#This Row],[MONTANT HT]]*0.18,0),0) -> 1188000 | N107: =Tableau6[[#This Row],[MONTANT HT]]+Tableau6[[#This Row],[TVA]]-Tableau6[[#This Row],[ACOMPTE SUR HT]] -> 7788000 | P107: =+ROUND(Tableau6[[#This Row],[MONTANT TTC]]-Tableau6[[#This Row],[ACOMPTE SUR TTC]],0) -> 7788000 | Q107: BC201401 | R107: =IFERROR(INDEX(Tableau2[[ID BC UNIQUE]:[MONTANT HT VALIDE]],MATCH(Tableau6[[#This Row],[N° BC]],Tableau2[ID BC UNIQUE],0),6),0) -> 6600000 | S107: =IFERROR(INDEX(Tableau2[[DATE]:[DELAIS DE PAIEMENT FACTURES EN JOUR]],MATCH(Tableau6[[#This Row],[N° BC]],Tableau2[ID BC UNIQUE],0),5),0) -> 30 | T107: =IF(ISBLANK(Tableau6[[#This Row],[DATE DE DEPOT]]),"",Tableau6[[#This Row],[DATE DE DEPOT]]+Tableau6[[#This Row],[DELAI]]) -> 45753 | U107: =+IF(AND(W107=0,Tableau6[[#This Row],[DATE LIMITE]]<TODAY()),TODAY()-Tableau6[[#This Row],[DATE LIMITE]],0) -> 0 | V107: =IF(Tableau6[[#This Row],[DATE LIMITE]]>=TODAY(),"NON ECHUE",IF(Tableau6[[#This Row],[MONTANT HT]]<0,IF(ISNUMBER(MATCH(-Tableau6[[#This Row],[MONTANT HT]],Tableau6[MONTANT HT],0)),"AVOIR TOTAL","AVOIR PARTIEL"),IF(AND(ISNUMBER(MATCH(-Tableau6[[#This Row],[MONTANT HT]],Tableau6[MONTANT HT],0)),(Tableau6[[#This Row],[ACOMPTE SUR TTC]]+Tableau6[[#This Row],[MONTANT PAYE]])=0),"FACTURE ANNULEE",IF(Tableau6[[#This Row],[ACOMPTE SUR TTC]]+Tableau6[[#This Row],[MONTANT PAYE]]=0,"ECHUE NON REGLEE",IF(Tableau6[[#This Row],[ACOMPTE SUR TTC]]+Tableau6[[#This Row],[MONTANT PAYE]]=Tableau6[[#This Row],[NET A PAYER]],"PAYE",IF(Tableau6[[#This Row],[ACOMPTE SUR TTC]]+Tableau6[[#This Row],[MONTANT PAYE]]<Tableau6[[#This Row],[NET A PAYER]],"PAIEMENT PARTIEL","TROP PAYE")))))) -> PAYE | W107: =SUMIF(Tableau3[FACTURE],Tableau6[[#This Row],[NUM DE FACTURE]],Tableau3[MONTANT TTC]) -> 7788000 | Y107: =+Tableau6[[#This Row],[NET A PAYER]]-Tableau6[[#This Row],[MONTANT PAYE]] -> 0
A108: KENAM S | B108: 45723 | C108: 45723 | D108: 331 | E108: PFO CONSTRUCTION | F108: LOCATION DE CAMION | G108: 257B0003 | H108: TVAF | J108: 5000000 | K108: =+Tableau6[[#This Row],[MONTANT HT BIEN]]+Tableau6[[#This Row],[MONTANT HT SERVICE]] -> 5000000 | L108: 0 | M108: =+IFERROR(IF(Tableau6[[#This Row],[CODE TVA]]="TVAF",Tableau6[[#This Row],[MONTANT HT]]*0.18,0),0) -> 900000 | N108: =Tableau6[[#This Row],[MONTANT HT]]+Tableau6[[#This Row],[TVA]]-Tableau6[[#This Row],[ACOMPTE SUR HT]] -> 5900000 | P108: =+ROUND(Tableau6[[#This Row],[MONTANT TTC]]-Tableau6[[#This Row],[ACOMPTE SUR TTC]],0) -> 5900000 | Q108: BC201397 | R108: =IFERROR(INDEX(Tableau2[[ID BC UNIQUE]:[MONTANT HT VALIDE]],MATCH(Tableau6[[#This Row],[N° BC]],Tableau2[ID BC UNIQUE],0),6),0) -> 5000000 | S108: =IFERROR(INDEX(Tableau2[[DATE]:[DELAIS DE PAIEMENT FACTURES EN JOUR]],MATCH(Tableau6[[#This Row],[N° BC]],Tableau2[ID BC UNIQUE],0),5),0) -> 30 | T108: =IF(ISBLANK(Tableau6[[#This Row],[DATE DE DEPOT]]),"",Tableau6[[#This Row],[DATE DE DEPOT]]+Tableau6[[#This Row],[DELAI]]) -> 45753 | U108: =+IF(AND(W108=0,Tableau6[[#This Row],[DATE LIMITE]]<TODAY()),TODAY()-Tableau6[[#This Row],[DATE LIMITE]],0) -> 0 | V108: =IF(Tableau6[[#This Row],[DATE LIMITE]]>=TODAY(),"NON ECHUE",IF(Tableau6[[#This Row],[MONTANT HT]]<0,IF(ISNUMBER(MATCH(-Tableau6[[#This Row],[MONTANT HT]],Tableau6[MONTANT HT],0)),"AVOIR TOTAL","AVOIR PARTIEL"),IF(AND(ISNUMBER(MATCH(-Tableau6[[#This Row],[MONTANT HT]],Tableau6[MONTANT HT],0)),(Tableau6[[#This Row],[ACOMPTE SUR TTC]]+Tableau6[[#This Row],[MONTANT PAYE]])=0),"FACTURE ANNULEE",IF(Tableau6[[#This Row],[ACOMPTE SUR TTC]]+Tableau6[[#This Row],[MONTANT PAYE]]=0,"ECHUE NON REGLEE",IF(Tableau6[[#This Row],[ACOMPTE SUR TTC]]+Tableau6[[#This Row],[MONTANT PAYE]]=Tableau6[[#This Row],[NET A PAYER]],"PAYE",IF(Tableau6[[#This Row],[ACOMPTE SUR TTC]]+Tableau6[[#This Row],[MONTANT PAYE]]<Tableau6[[#This Row],[NET A PAYER]],"PAIEMENT PARTIEL","TROP PAYE")))))) -> PAYE | W108: =SUMIF(Tableau3[FACTURE],Tableau6[[#This Row],[NUM DE FACTURE]],Tableau3[MONTANT TTC]) -> 5900000 | Y108: =+Tableau6[[#This Row],[NET A PAYER]]-Tableau6[[#This Row],[MONTANT PAYE]] -> 0
A109: KENAM S | B109: 45723 | C109: 45723 | D109: 332 | E109: PFO CONSTRUCTION | F109: LOCATION DE CAMION | G109: 257B0209 | H109: TVAF | J109: 8000000 | K109: =+Tableau6[[#This Row],[MONTANT HT BIEN]]+Tableau6[[#This Row],[MONTANT HT SERVICE]] -> 8000000 | L109: 0 | M109: =+IFERROR(IF(Tableau6[[#This Row],[CODE TVA]]="TVAF",Tableau6[[#This Row],[MONTANT HT]]*0.18,0),0) -> 1440000 | N109: =Tableau6[[#This Row],[MONTANT HT]]+Tableau6[[#This Row],[TVA]]-Tableau6[[#This Row],[ACOMPTE SUR HT]] -> 9440000 | P109: =+ROUND(Tableau6[[#This Row],[MONTANT TTC]]-Tableau6[[#This Row],[ACOMPTE SUR TTC]],0) -> 9440000 | Q109: BC201398 | R109: =IFERROR(INDEX(Tableau2[[ID BC UNIQUE]:[MONTANT HT VALIDE]],MATCH(Tableau6[[#This Row],[N° BC]],Tableau2[ID BC UNIQUE],0),6),0) -> 8000000 | S109: =IFERROR(INDEX(Tableau2[[DATE]:[DELAIS DE PAIEMENT FACTURES EN JOUR]],MATCH(Tableau6[[#This Row],[N° BC]],Tableau2[ID BC UNIQUE],0),5),0) -> 30 | T109: =IF(ISBLANK(Tableau6[[#This Row],[DATE DE DEPOT]]),"",Tableau6[[#This Row],[DATE DE DEPOT]]+Tableau6[[#This Row],[DELAI]]) -> 45753 | U109: =+IF(AND(W109=0,Tableau6[[#This Row],[DATE LIMITE]]<TODAY()),TODAY()-Tableau6[[#This Row],[DATE LIMITE]],0) -> 0 | V109: =IF(Tableau6[[#This Row],[DATE LIMITE]]>=TODAY(),"NON ECHUE",IF(Tableau6[[#This Row],[MONTANT HT]]<0,IF(ISNUMBER(MATCH(-Tableau6[[#This Row],[MONTANT HT]],Tableau6[MONTANT HT],0)),"AVOIR TOTAL","AVOIR PARTIEL"),IF(AND(ISNUMBER(MATCH(-Tableau6[[#This Row],[MONTANT HT]],Tableau6[MONTANT HT],0)),(Tableau6[[#This Row],[ACOMPTE SUR TTC]]+Tableau6[[#This Row],[MONTANT PAYE]])=0),"FACTURE ANNULEE",IF(Tableau6[[#This Row],[ACOMPTE SUR TTC]]+Tableau6[[#This Row],[MONTANT PAYE]]=0,"ECHUE NON REGLEE",IF(Tableau6[[#This Row],[ACOMPTE SUR TTC]]+Tableau6[[#This Row],[MONTANT PAYE]]=Tableau6[[#This Row],[NET A PAYER]],"PAYE",IF(Tableau6[[#This Row],[ACOMPTE SUR TTC]]+Tableau6[[#This Row],[MONTANT PAYE]]<Tableau6[[#This Row],[NET A PAYER]],"PAIEMENT PARTIEL","TROP PAYE")))))) -> PAYE | W109: =SUMIF(Tableau3[FACTURE],Tableau6[[#This Row],[NUM DE FACTURE]],Tableau3[MONTANT TTC]) -> 9440000 | Y109: =+Tableau6[[#This Row],[NET A PAYER]]-Tableau6[[#This Row],[MONTANT PAYE]] -> 0
A110: KENAM S | B110: 45723 | C110: 45723 | D110: 333 | E110: PFO CONSTRUCTION | F110: LOCATION DE CAMION | G110: 257B0207 | H110: TVAF | J110: 4680000 | K110: =+Tableau6[[#This Row],[MONTANT HT BIEN]]+Tableau6[[#This Row],[MONTANT HT SERVICE]] -> 4680000 | L110: 0 | M110: =+IFERROR(IF(Tableau6[[#This Row],[CODE TVA]]="TVAF",Tableau6[[#This Row],[MONTANT HT]]*0.18,0),0) -> 842400 | N110: =Tableau6[[#This Row],[MONTANT HT]]+Tableau6[[#This Row],[TVA]]-Tableau6[[#This Row],[ACOMPTE SUR HT]] -> 5522400 | P110: =+ROUND(Tableau6[[#This Row],[MONTANT TTC]]-Tableau6[[#This Row],[ACOMPTE SUR TTC]],0) -> 5522400 | Q110: BC201396 | R110: =IFERROR(INDEX(Tableau2[[ID BC UNIQUE]:[MONTANT HT VALIDE]],MATCH(Tableau6[[#This Row],[N° BC]],Tableau2[ID BC UNIQUE],0),6),0) -> 4680000 | S110: =IFERROR(INDEX(Tableau2[[DATE]:[DELAIS DE PAIEMENT FACTURES EN JOUR]],MATCH(Tableau6[[#This Row],[N° BC]],Tableau2[ID BC UNIQUE],0),5),0) -> 30 | T110: =IF(ISBLANK(Tableau6[[#This Row],[DATE DE DEPOT]]),"",Tableau6[[#This Row],[DATE DE DEPOT]]+Tableau6[[#This Row],[DELAI]]) -> 45753 | U110: =+IF(AND(W110=0,Tableau6[[#This Row],[DATE LIMITE]]<TODAY()),TODAY()-Tableau6[[#This Row],[DATE LIMITE]],0) -> 0 | V110: =IF(Tableau6[[#This Row],[DATE LIMITE]]>=TODAY(),"NON ECHUE",IF(Tableau6[[#This Row],[MONTANT HT]]<0,IF(ISNUMBER(MATCH(-Tableau6[[#This Row],[MONTANT HT]],Tableau6[MONTANT HT],0)),"AVOIR TOTAL","AVOIR PARTIEL"),IF(AND(ISNUMBER(MATCH(-Tableau6[[#This Row],[MONTANT HT]],Tableau6[MONTANT HT],0)),(Tableau6[[#This Row],[ACOMPTE SUR TTC]]+Tableau6[[#This Row],[MONTANT PAYE]])=0),"FACTURE ANNULEE",IF(Tableau6[[#This Row],[ACOMPTE SUR TTC]]+Tableau6[[#This Row],[MONTANT PAYE]]=0,"ECHUE NON REGLEE",IF(Tableau6[[#This Row],[ACOMPTE SUR TTC]]+Tableau6[[#This Row],[MONTANT PAYE]]=Tableau6[[#This Row],[NET A PAYER]],"PAYE",IF(Tableau6[[#This Row],[ACOMPTE SUR TTC]]+Tableau6[[#This Row],[MONTANT PAYE]]<Tableau6[[#This Row],[NET A PAYER]],"PAIEMENT PARTIEL","TROP PAYE")))))) -> PAYE | W110: =SUMIF(Tableau3[FACTURE],Tableau6[[#This Row],[NUM DE FACTURE]],Tableau3[MONTANT TTC]) -> 5522400 | Y110: =+Tableau6[[#This Row],[NET A PAYER]]-Tableau6[[#This Row],[MONTANT PAYE]] -> 0
A111: KENAM S | B111: 45723 | C111: 45723 | D111: 334 | E111: PFO CONSTRUCTION | F111: LOCATION DE CAMION | G111: 257B0109 | H111: TVAF | J111: 7680000 | K111: =+Tableau6[[#This Row],[MONTANT HT BIEN]]+Tableau6[[#This Row],[MONTANT HT SERVICE]] -> 7680000 | L111: 0 | M111: =+IFERROR(IF(Tableau6[[#This Row],[CODE TVA]]="TVAF",Tableau6[[#This Row],[MONTANT HT]]*0.18,0),0) -> 1382400 | N111: =Tableau6[[#This Row],[MONTANT HT]]+Tableau6[[#This Row],[TVA]]-Tableau6[[#This Row],[ACOMPTE SUR HT]] -> 9062400 | P111: =+ROUND(Tableau6[[#This Row],[MONTANT TTC]]-Tableau6[[#This Row],[ACOMPTE SUR TTC]],0) -> 9062400 | Q111: BC201394 | R111: =IFERROR(INDEX(Tableau2[[ID BC UNIQUE]:[MONTANT HT VALIDE]],MATCH(Tableau6[[#This Row],[N° BC]],Tableau2[ID BC UNIQUE],0),6),0) -> 7680000 | S111: =IFERROR(INDEX(Tableau2[[DATE]:[DELAIS DE PAIEMENT FACTURES EN JOUR]],MATCH(Tableau6[[#This Row],[N° BC]],Tableau2[ID BC UNIQUE],0),5),0) -> 30 | T111: =IF(ISBLANK(Tableau6[[#This Row],[DATE DE DEPOT]]),"",Tableau6[[#This Row],[DATE DE DEPOT]]+Tableau6[[#This Row],[DELAI]]) -> 45753 | U111: =+IF(AND(W111=0,Tableau6[[#This Row],[DATE LIMITE]]<TODAY()),TODAY()-Tableau6[[#This Row],[DATE LIMITE]],0) -> 0 | V111: =IF(Tableau6[[#This Row],[DATE LIMITE]]>=TODAY(),"NON ECHUE",IF(Tableau6[[#This Row],[MONTANT HT]]<0,IF(ISNUMBER(MATCH(-Tableau6[[#This Row],[MONTANT HT]],Tableau6[MONTANT HT],0)),"AVOIR TOTAL","AVOIR PARTIEL"),IF(AND(ISNUMBER(MATCH(-Tableau6[[#This Row],[MONTANT HT]],Tableau6[MONTANT HT],0)),(Tableau6[[#This Row],[ACOMPTE SUR TTC]]+Tableau6[[#This Row],[MONTANT PAYE]])=0),"FACTURE ANNULEE",IF(Tableau6[[#This Row],[ACOMPTE SUR TTC]]+Tableau6[[#This Row],[MONTANT PAYE]]=0,"ECHUE NON REGLEE",IF(Tableau6[[#This Row],[ACOMPTE SUR TTC]]+Tableau6[[#This Row],[MONTANT PAYE]]=Tableau6[[#This Row],[NET A PAYER]],"PAYE",IF(Tableau6[[#This Row],[ACOMPTE SUR TTC]]+Tableau6[[#This Row],[MONTANT PAYE]]<Tableau6[[#This Row],[NET A PAYER]],"PAIEMENT PARTIEL","TROP PAYE")))))) -> PAYE | W111: =SUMIF(Tableau3[FACTURE],Tableau6[[#This Row],[NUM DE FACTURE]],Tableau3[MONTANT TTC]) -> 9062400 | Y111: =+Tableau6[[#This Row],[NET A PAYER]]-Tableau6[[#This Row],[MONTANT PAYE]] -> 0
A112: KENAM S | B112: 45723 | C112: 45723 | D112: 335 | E112: PFO CONSTRUCTION | F112: LOCATION DE CAMION | G112: 257B0109 | H112: TVAF | J112: 4400000 | K112: =+Tableau6[[#This Row],[MONTANT HT BIEN]]+Tableau6[[#This Row],[MONTANT HT SERVICE]] -> 4400000 | L112: 0 | M112: =+IFERROR(IF(Tableau6[[#This Row],[CODE TVA]]="TVAF",Tableau6[[#This Row],[MONTANT HT]]*0.18,0),0) -> 792000 | N112: =Tableau6[[#This Row],[MONTANT HT]]+Tableau6[[#This Row],[TVA]]-Tableau6[[#This Row],[ACOMPTE SUR HT]] -> 5192000 | P112: =+ROUND(Tableau6[[#This Row],[MONTANT TTC]]-Tableau6[[#This Row],[ACOMPTE SUR TTC]],0) -> 5192000 | Q112: BC201399 | R112: =IFERROR(INDEX(Tableau2[[ID BC UNIQUE]:[MONTANT HT VALIDE]],MATCH(Tableau6[[#This Row],[N° BC]],Tableau2[ID BC UNIQUE],0),6),0) -> 4400000 | S112: =IFERROR(INDEX(Tableau2[[DATE]:[DELAIS DE PAIEMENT FACTURES EN JOUR]],MATCH(Tableau6[[#This Row],[N° BC]],Tableau2[ID BC UNIQUE],0),5),0) -> 30 | T112: =IF(ISBLANK(Tableau6[[#This Row],[DATE DE DEPOT]]),"",Tableau6[[#This Row],[DATE DE DEPOT]]+Tableau6[[#This Row],[DELAI]]) -> 45753 | U112: =+IF(AND(W112=0,Tableau6[[#This Row],[DATE LIMITE]]<TODAY()),TODAY()-Tableau6[[#This Row],[DATE LIMITE]],0) -> 0 | V112: =IF(Tableau6[[#This Row],[DATE LIMITE]]>=TODAY(),"NON ECHUE",IF(Tableau6[[#This Row],[MONTANT HT]]<0,IF(ISNUMBER(MATCH(-Tableau6[[#This Row],[MONTANT HT]],Tableau6[MONTANT HT],0)),"AVOIR TOTAL","AVOIR PARTIEL"),IF(AND(ISNUMBER(MATCH(-Tableau6[[#This Row],[MONTANT HT]],Tableau6[MONTANT HT],0)),(Tableau6[[#This Row],[ACOMPTE SUR TTC]]+Tableau6[[#This Row],[MONTANT PAYE]])=0),"FACTURE ANNULEE",IF(Tableau6[[#This Row],[ACOMPTE SUR TTC]]+Tableau6[[#This Row],[MONTANT PAYE]]=0,"ECHUE NON REGLEE",IF(Tableau6[[#This Row],[ACOMPTE SUR TTC]]+Tableau6[[#This Row],[MONTANT PAYE]]=Tableau6[[#This Row],[NET A PAYER]],"PAYE",IF(Tableau6[[#This Row],[ACOMPTE SUR TTC]]+Tableau6[[#This Row],[MONTANT PAYE]]<Tableau6[[#This Row],[NET A PAYER]],"PAIEMENT PARTIEL","TROP PAYE")))))) -> PAYE | W112: =SUMIF(Tableau3[FACTURE],Tableau6[[#This Row],[NUM DE FACTURE]],Tableau3[MONTANT TTC]) -> 5192000 | Y112: =+Tableau6[[#This Row],[NET A PAYER]]-Tableau6[[#This Row],[MONTANT PAYE]] -> 0
A113: KENAM S | B113: 45723 | C113: 45723 | D113: 336 | E113: PFO CONSTRUCTION | F113: LOCATION DE CAMION | G113: 257B0109 | H113: TVAF | J113: 7360000 | K113: =+Tableau6[[#This Row],[MONTANT HT BIEN]]+Tableau6[[#This Row],[MONTANT HT SERVICE]] -> 7360000 | L113: 0 | M113: =+IFERROR(IF(Tableau6[[#This Row],[CODE TVA]]="TVAF",Tableau6[[#This Row],[MONTANT HT]]*0.18,0),0) -> 1324800 | N113: =Tableau6[[#This Row],[MONTANT HT]]+Tableau6[[#This Row],[TVA]]-Tableau6[[#This Row],[ACOMPTE SUR HT]] -> 8684800 | P113: =+ROUND(Tableau6[[#This Row],[MONTANT TTC]]-Tableau6[[#This Row],[ACOMPTE SUR TTC]],0) -> 8684800 | Q113: BC201400 | R113: =IFERROR(INDEX(Tableau2[[ID BC UNIQUE]:[MONTANT HT VALIDE]],MATCH(Tableau6[[#This Row],[N° BC]],Tableau2[ID BC UNIQUE],0),6),0) -> 7360000 | S113: =IFERROR(INDEX(Tableau2[[DATE]:[DELAIS DE PAIEMENT FACTURES EN JOUR]],MATCH(Tableau6[[#This Row],[N° BC]],Tableau2[ID BC UNIQUE],0),5),0) -> 30 | T113: =IF(ISBLANK(Tableau6[[#This Row],[DATE DE DEPOT]]),"",Tableau6[[#This Row],[DATE DE DEPOT]]+Tableau6[[#This Row],[DELAI]]) -> 45753 | U113: =+IF(AND(W113=0,Tableau6[[#This Row],[DATE LIMITE]]<TODAY()),TODAY()-Tableau6[[#This Row],[DATE LIMITE]],0) -> 0 | V113: =IF(Tableau6[[#This Row],[DATE LIMITE]]>=TODAY(),"NON ECHUE",IF(Tableau6[[#This Row],[MONTANT HT]]<0,IF(ISNUMBER(MATCH(-Tableau6[[#This Row],[MONTANT HT]],Tableau6[MONTANT HT],0)),"AVOIR TOTAL","AVOIR PARTIEL"),IF(AND(ISNUMBER(MATCH(-Tableau6[[#This Row],[MONTANT HT]],Tableau6[MONTANT HT],0)),(Tableau6[[#This Row],[ACOMPTE SUR TTC]]+Tableau6[[#This Row],[MONTANT PAYE]])=0),"FACTURE ANNULEE",IF(Tableau6[[#This Row],[ACOMPTE SUR TTC]]+Tableau6[[#This Row],[MONTANT PAYE]]=0,"ECHUE NON REGLEE",IF(Tableau6[[#This Row],[ACOMPTE SUR TTC]]+Tableau6[[#This Row],[MONTANT PAYE]]=Tableau6[[#This Row],[NET A PAYER]],"PAYE",IF(Tableau6[[#This Row],[ACOMPTE SUR TTC]]+Tableau6[[#This Row],[MONTANT PAYE]]<Tableau6[[#This Row],[NET A PAYER]],"PAIEMENT PARTIEL","TROP PAYE")))))) -> PAYE | W113: =SUMIF(Tableau3[FACTURE],Tableau6[[#This Row],[NUM DE FACTURE]],Tableau3[MONTANT TTC]) -> 8684800 | Y113: =+Tableau6[[#This Row],[NET A PAYER]]-Tableau6[[#This Row],[MONTANT PAYE]] -> 0
