Workbook
Name \0: #REF!
Name \1: #REF!
Name \a: #REF!
Name \b: #REF!
Name \C: #REF!
Name \D: #REF!
Name \e: #REF!
Name \f: #REF!
Name \h: #REF!
Name \i: #REF!
Name \j: #REF!
Name \l: #REF!
Name \m: #REF!
Name \n: #REF!
Name \o: #REF!
Name \p: #REF!
Name \s: #REF!
Name \t: #REF!
Name \u: #REF!
Name \z: #REF!
Name ______________tap2: #REF!
Name _____________tap2: #REF!
Name ____________tap2: #REF!
Name ___________tap2: #REF!
Name __________tap2: #REF!
Name _________tap2: #REF!
Name ________tap2: #REF!
Name _______tap2: #REF!
Name ______tap2: #REF!
Name _____tap2: #REF!
Name ____tap2: #REF!
Name ___tap2: #REF!
Name __bed53: #REF!
Name __cav1: #REF!
Name __COM2: #REF!
Name __DJI2: #REF!
Name __EAO2: #REF!
Name __EAR2: #REF!
Name __ETH2: #REF!
Name __KE2: #REF!
Name __L: #REF!
Name __MAU2: #REF!
Name __MD2: #REF!
Name __MS2: #REF!
Name __RE2: #REF!
Name __SEY2: #REF!
Name __SM2: #REF!
Name __SOM2: #REF!
Name __tap2: #REF!
Name __tot1: #REF!
Name __tot2: #REF!
Name __TZ2: #REF!
Name __UG2: #REF!
Name _0_09_84: #REF!
Name _1: #REF!
Name _10003: #REF!
Name _10004: #REF!
Name _10006: #REF!
Name _10012: #REF!
Name _10015: #REF!

Sheet FACTURES FOURNISSEURS
J1: TOTAL | K1: =+SUBTOTAL(9,Tableau330[MONTANT HT BIENS]) -> 46204913 | L1: =+SUBTOTAL(9,Tableau330[[MONTANT HT SERVICES ]]) -> 23488773 | M1: =+SUBTOTAL(9,Tableau330[MONTANT HT]) -> 3.9791433e+08 | N1: =+SUBTOTAL(9,Tableau330[TVA]) -> 46846525 | O1: =+SUBTOTAL(9,Tableau330[MONTANT TTC]) -> 4.4476086e+08 | P1: =+SUBTOTAL(9,Tableau330[[TIMBRE ]]) -> 11999 | Q1: =+SUBTOTAL(9,Tableau330[AUTRES TAXES]) -> 37258 | R1: =+SUBTOTAL(9,Tableau330[MONTANT TTC]) -> 4.4476086e+08 | S1: =+SUBTOTAL(9,Tableau330[MONTANT PAYE]) -> 4.2783171e+08 | T1: =+SUBTOTAL(9,Tableau330[SOLDE]) -> 16978410
A2: DATE | B2: PERIODE | C2: TYPE F/ | D2: N° F/ | E2: FOURNISSEURS | F2: NCC | G2: REGIME | H2: DESIGNATION | I2: CODE TVA | J2: PRORATA D | K2: MONTANT HT BIENS | L2: MONTANT HT SERVICES | M2: MONTANT HT | N2: TVA | O2: MONTANT TTC | P2: TIMBRE | Q2: AUTRES TAXES | R2: NET A PAYER | S2: MONTANT PAYE | T2: SOLDE | U2: DELAI_PAIEMENT | V2: DATE ECHEANCE | W2: NATURE COMPTABLE | X2: PAYE | Y2: MODE | Z2: REFERENCE REGLEMENT | AA2: OBSERVATIONS
A3: 45609 | B3: =IF(ISBLANK(Tableau330[[#This Row],[DATE ]]),"",UPPER(PROPER(TEXT(Tableau330[[#This Row],[DATE ]],"mmmm yyyy")))) -> NOVEMBRE 2024 | C3: FN | D3: 013657 | E3: INDUSTRAP | F3: 9000831 C | H3: ACHAT DE COLORANT 200 ML | I3: TVA | J3: 1 | M3: 931016 | N3: =+IF(Tableau330[[#This Row],[CODE TVA]]="",0,ROUND(Tableau330[[#This Row],[MONTANT HT]]*0.18*Tableau330[[#This Row],[PRORATA D]],1)) -> 167582.9 | O3: =+IFERROR(Tableau330[[#This Row],[MONTANT HT]]+Tableau330[[#This Row],[TVA]],0) -> 1098598.9 | R3: =+Tableau330[[#This Row],[MONTANT TTC]]+Tableau330[[#This Row],[TIMBRE ]]+Tableau330[[#This Row],[AUTRES TAXES]] -> 1098598.9 | S3: 1098598.9 | T3: =+ROUND(Tableau330[[#This Row],[NET A PAYER]],0)-Tableau330[[#This Row],[MONTANT PAYE]] -> 0.12 | V3: =+Tableau330[[#This Row],[DELAI_PAIEMENT]]+Tableau330[[#This Row],[DATE ]] -> 45609
A4: 45619 | B4: =IF(ISBLANK(Tableau330[[#This Row],[DATE ]]),"",UPPER(PROPER(TEXT(Tableau330[[#This Row],[DATE ]],"mmmm yyyy")))) -> NOVEMBRE 2024 | C4: FN | D4: 022884 | E4: SPRIINT TECH | F4: 1106600 L | H4: E/G AV AERO ECO 450MM | I4: TVA | J4: 1 | M4: 10928 | N4: =+IF(Tableau330[[#This Row],[CODE TVA]]="",0,ROUND(Tableau330[[#This Row],[MONTANT HT]]*0.18*Tableau330[[#This Row],[PRORATA D]],1)) -> 1967 | O4: =+IFERROR(Tableau330[[#This Row],[MONTANT HT]]+Tableau330[[#This Row],[TVA]],0) -> 12895 | R4: =+Tableau330[[#This Row],[MONTANT TTC]]+Tableau330[[#This Row],[TIMBRE ]]+Tableau330[[#This Row],[AUTRES TAXES]] -> 12895 | S4: 12895 | T4: =+ROUND(Tableau330[[#This Row],[NET A PAYER]],0)-Tableau330[[#This Row],[MONTANT PAYE]] -> 0 | V4: =+Tableau330[[#This Row],[DELAI_PAIEMENT]]+Tableau330[[#This Row],[DATE ]] -> 45619
A5: 45623 | B5: =IF(ISBLANK(Tableau330[[#This Row],[DATE ]]),"",UPPER(PROPER(TEXT(Tableau330[[#This Row],[DATE ]],"mmmm yyyy")))) -> NOVEMBRE 2024 | C5: NON-FN | D5: 8584501 | E5: ETS KIRAKOYA TIDIANE | F5: 1217411 Q | H5: ACHAT PNEU 13R225, 315/80R225 | M5: 525000 | N5: =+IF(Tableau330[[#This Row],[CODE TVA]]="",0,ROUND(Tableau330[[#This Row],[MONTANT HT]]*0.18*Tableau330[[#This Row],[PRORATA D]],1)) -> 0 | O5: =+IFERROR(Tableau330[[#This Row],[MONTANT HT]]+Tableau330[[#This Row],[TVA]],0) -> 525000 | R5: =+Tableau330[[#This Row],[MONTANT TTC]]+Tableau330[[#This Row],[TIMBRE ]]+Tableau330[[#This Row],[AUTRES TAXES]] -> 525000 | S5: 525000 | T5: =+ROUND(Tableau330[[#This Row],[NET A PAYER]],0)-Tableau330[[#This Row],[MONTANT PAYE]] -> 0 | V5: =+Tableau330[[#This Row],[DELAI_PAIEMENT]]+Tableau330[[#This Row],[DATE ]] -> 45623
A6: 45626 | B6: =IF(ISBLANK(Tableau330[[#This Row],[DATE ]]),"",UPPER(PROPER(TEXT(Tableau330[[#This Row],[DATE ]],"mmmm yyyy")))) -> NOVEMBRE 2024 | C6: FN | D6: 0006110 | E6: PACSI | F6: 1303973 A | G6: RNI | H6: ACHAT CORDEAU, BATTERIE, MOTEUR, DISQUE, CARREAUX-EX_2024 | I6: TVA | J6: 1 | M6: 120512 | N6: =+IF(Tableau330[[#This Row],[CODE TVA]]="",0,ROUND(Tableau330[[#This Row],[MONTANT HT]]*0.18*Tableau330[[#This Row],[PRORATA D]],1)) -> 21692.2 | O6: =+IFERROR(Tableau330[[#This Row],[MONTANT HT]]+Tableau330[[#This Row],[TVA]],0) -> 142204.2 | Q6: 7110 | R6: =+Tableau330[[#This Row],[MONTANT TTC]]+Tableau330[[#This Row],[TIMBRE ]]+Tableau330[[#This Row],[AUTRES TAXES]] -> 149314.2 | T6: =+ROUND(Tableau330[[#This Row],[NET A PAYER]],0)-Tableau330[[#This Row],[MONTANT PAYE]] -> 149314 | V6: =+Tableau330[[#This Row],[DELAI_PAIEMENT]]+Tableau330[[#This Row],[DATE ]] -> 45626 | X6: OUI_T | Y6: ESPECES
A7: 45645 | B7: =IF(ISBLANK(Tableau330[[#This Row],[DATE ]]),"",UPPER(PROPER(TEXT(Tableau330[[#This Row],[DATE ]],"mmmm yyyy")))) -> DÉCEMBRE 2024 | C7: FN | D7: 007009 | E7: RIMCO-SETACI | F7: 9809714 J | G7: RNI | H7: SINOTRUK BENNE 8*4 HOWO_782 & 783 | I7: TVA | J7: 1 | M7: 88135593 | N7: =+IF(Tableau330[[#This Row],[CODE TVA]]="",0,ROUND(Tableau330[[#This Row],[MONTANT HT]]*0.18*Tableau330[[#This Row],[PRORATA D]],1)) -> 15864407 | O7: =+IFERROR(Tableau330[[#This Row],[MONTANT HT]]+Tableau330[[#This Row],[TVA]],0) -> 1.04e+08 | R7: =+Tableau330[[#This Row],[MONTANT TTC]]+Tableau330[[#This Row],[TIMBRE ]]+Tableau330[[#This Row],[AUTRES TAXES]] -> 1.04e+08 | S7: 1.04e+08 | T7: =+ROUND(Tableau330[[#This Row],[NET A PAYER]],0)-Tableau330[[#This Row],[MONTANT PAYE]] -> 0.26000001 | V7: =+Tableau330[[#This Row],[DELAI_PAIEMENT]]+Tableau330[[#This Row],[DATE ]] -> 45645
A8: 45660 | B8: =IF(ISBLANK(Tableau330[[#This Row],[DATE ]]),"",UPPER(PROPER(TEXT(Tableau330[[#This Row],[DATE ]],"mmmm yyyy")))) -> JANVIER 2025 | C8: FN | D8: 0009609 | E8: AL FAYSAL SARL | F8: 1648055 N | G8: RNI | H8: TILAPIA | M8: 14000 | N8: =+IF(Tableau330[[#This Row],[CODE TVA]]="",0,ROUND(Tableau330[[#This Row],[MONTANT HT]]*0.18*Tableau330[[#This Row],[PRORATA D]],1)) -> 0 | O8: =+IFERROR(Tableau330[[#This Row],[MONTANT HT]]+Tableau330[[#This Row],[TVA]],0) -> 14000 | R8: =+Tableau330[[#This Row],[MONTANT TTC]]+Tableau330[[#This Row],[TIMBRE ]]+Tableau330[[#This Row],[AUTRES TAXES]] -> 14000 | S8: 14000 | T8: =+ROUND(Tableau330[[#This Row],[NET A PAYER]],0)-Tableau330[[#This Row],[MONTANT PAYE]] -> 0 | V8: =+Tableau330[[#This Row],[DELAI_PAIEMENT]]+Tableau330[[#This Row],[DATE ]] -> 45660
A9: 45660 | B9: =IF(ISBLANK(Tableau330[[#This Row],[DATE ]]),"",UPPER(PROPER(TEXT(Tableau330[[#This Row],[DATE ]],"mmmm yyyy")))) -> JANVIER 2025 | C9: FN | D9: 007123 | E9: PROSUMA | F9: 5011806 N | H9: RIZ | I9: TVA | M9: 34000 | N9: =+IF(Tableau330[[#This Row],[CODE TVA]]="",0,ROUND(Tableau330[[#This Row],[MONTANT HT]]*0.18*Tableau330[[#This Row],[PRORATA D]],1)) -> 0 | O9: =+IFERROR(Tableau330[[#This Row],[MONTANT HT]]+Tableau330[[#This Row],[TVA]],0) -> 34000 | R9: =+Tableau330[[#This Row],[MONTANT TTC]]+Tableau330[[#This Row],[TIMBRE ]]+Tableau330[[#This Row],[AUTRES TAXES]] -> 34000 | S9: 34000 | T9: =+ROUND(Tableau330[[#This Row],[NET A PAYER]],0)-Tableau330[[#This Row],[MONTANT PAYE]] -> 0 | V9: =+Tableau330[[#This Row],[DELAI_PAIEMENT]]+Tableau330[[#This Row],[DATE ]] -> 45660
A10: 45661 | B10: =IF(ISBLANK(Tableau330[[#This Row],[DATE ]]),"",UPPER(PROPER(TEXT(Tableau330[[#This Row],[DATE ]],"mmmm yyyy")))) -> JANVIER 2025 | C10: NON-FN | D10: 0078861 | E10: SOUADIK SBM | F10: 2300142 N | H10: ACHAT CARBURANT | M10: 498000 | N10: =+IF(Tableau330[[#This Row],[CODE TVA]]="",0,ROUND(Tableau330[[#This Row],[MONTANT HT]]*0.18*Tableau330[[#This Row],[PRORATA D]],1)) -> 0 | O10: =+IFERROR(Tableau330[[#This Row],[MONTANT HT]]+Tableau330[[#This Row],[TVA]],0) -> 498000 | R10: =+Tableau330[[#This Row],[MONTANT TTC]]+Tableau330[[#This Row],[TIMBRE ]]+Tableau330[[#This Row],[AUTRES TAXES]] -> 498000 | S10: 498000 | T10: =+ROUND(Tableau330[[#This Row],[NET A PAYER]],0)-Tableau330[[#This Row],[MONTANT PAYE]] -> 0 | V10: =+Tableau330[[#This Row],[DELAI_PAIEMENT]]+Tableau330[[#This Row],[DATE ]] -> 45661
A11: 45661 | B11: =IF(ISBLANK(Tableau330[[#This Row],[DATE ]]),"",UPPER(PROPER(TEXT(Tableau330[[#This Row],[DATE ]],"mmmm yyyy")))) -> JANVIER 2025 | C11: FN | D11: 022678 | E11: PROSUMA | F11: 5011806 N | H11: ACHAT SUCRE, EAU, DESO, ASSIETTES | I11: TVA | J11: 1 | M11: 10974 | N11: =+IF(Tableau330[[#This Row],[CODE TVA]]="",0,ROUND(Tableau330[[#This Row],[MONTANT HT]]*0.18*Tableau330[[#This Row],[PRORATA D]],1)) -> 1975.3 | O11: =+IFERROR(Tableau330[[#This Row],[MONTANT HT]]+Tableau330[[#This Row],[TVA]],0) -> 12949.3 | R11: =+Tableau330[[#This Row],[MONTANT TTC]]+Tableau330[[#This Row],[TIMBRE ]]+Tableau330[[#This Row],[AUTRES TAXES]] -> 12949.3 | S11: 12949 | T11: =+ROUND(Tableau330[[#This Row],[NET A PAYER]],0)-Tableau330[[#This Row],[MONTANT PAYE]] -> 0 | V11: =+Tableau330[[#This Row],[DELAI_PAIEMENT]]+Tableau330[[#This Row],[DATE ]] -> 45661
A12: 45663 | B12: =IF(ISBLANK(Tableau330[[#This Row],[DATE ]]),"",UPPER(PROPER(TEXT(Tableau330[[#This Row],[DATE ]],"mmmm yyyy")))) -> JANVIER 2025 | C12: FN | D12: 016310 | E12: INDUSTRAP | F12: 9000831 C | H12: CIMENT CAROCOL BLANC 25 KG | I12: TVA | J12: 1 | M12: 201271 | N12: =+IF(Tableau330[[#This Row],[CODE TVA]]="",0,ROUND(Tableau330[[#This Row],[MONTANT HT]]*0.18*Tableau330[[#This Row],[PRORATA D]],1)) -> 36228.8 | O12: =+IFERROR(Tableau330[[#This Row],[MONTANT HT]]+Tableau330[[#This Row],[TVA]],0) -> 237499.8 | R12: =+Tableau330[[#This Row],[MONTANT TTC]]+Tableau330[[#This Row],[TIMBRE ]]+Tableau330[[#This Row],[AUTRES TAXES]] -> 237499.8 | S12: 237499.78 | T12: =+ROUND(Tableau330[[#This Row],[NET A PAYER]],0)-Tableau330[[#This Row],[MONTANT PAYE]] -> 0.22 | V12: =+Tableau330[[#This Row],[DELAI_PAIEMENT]]+Tableau330[[#This Row],[DATE ]] -> 45663
A13: 45663 | B13: =IF(ISBLANK(Tableau330[[#This Row],[DATE ]]),"",UPPER(PROPER(TEXT(Tableau330[[#This Row],[DATE ]],"mmmm yyyy")))) -> JANVIER 2025 | C13: FN | D13: 016311 | E13: INDUSTRAP | F13: 9000831 C | H13: TRAPEAU INT 30 KG | I13: TVA | J13: 1 | M13: 550847.5 | N13: =+IF(Tableau330[[#This Row],[CODE TVA]]="",0,ROUND(Tableau330[[#This Row],[MONTANT HT]]*0.18*Tableau330[[#This Row],[PRORATA D]],1)) -> 99152.6 | O13: =+IFERROR(Tableau330[[#This Row],[MONTANT HT]]+Tableau330[[#This Row],[TVA]],0) -> 650000.1 | R13: =+Tableau330[[#This Row],[MONTANT TTC]]+Tableau330[[#This Row],[TIMBRE ]]+Tableau330[[#This Row],[AUTRES TAXES]] -> 650000.1 | S13: 650000 | T13: =+ROUND(Tableau330[[#This Row],[NET A PAYER]],0)-Tableau330[[#This Row],[MONTANT PAYE]] -> 0 | V13: =+Tableau330[[#This Row],[DELAI_PAIEMENT]]+Tableau330[[#This Row],[DATE ]] -> 45663
A14: 45664 | B14: =IF(ISBLANK(Tableau330[[#This Row],[DATE ]]),"",UPPER(PROPER(TEXT(Tableau330[[#This Row],[DATE ]],"mmmm yyyy")))) -> JANVIER 2025 | C14: FN | D14: 0003828 | E14: CHINA MART | F14: 2215123 N | H14: CYLINDRE, SAC CADEAU, ENVELOPPE | M14: 8360 | N14: =+IF(Tableau330[[#This Row],[CODE TVA]]="",0,ROUND(Tableau330[[#This Row],[MONTANT HT]]*0.18*Tableau330[[#This Row],[PRORATA D]],1)) -> 0 | O14: =+IFERROR(Tableau330[[#This Row],[MONTANT HT]]+Tableau330[[#This Row],[TVA]],0) -> 8360 | R14: =+Tableau330[[#This Row],[MONTANT TTC]]+Tableau330[[#This Row],[TIMBRE ]]+Tableau330[[#This Row],[AUTRES TAXES]] -> 8360 | S14: 8360 | T14: =+ROUND(Tableau330[[#This Row],[NET A PAYER]],0)-Tableau330[[#This Row],[MONTANT PAYE]] -> 0 | V14: =+Tableau330[[#This Row],[DELAI_PAIEMENT]]+Tableau330[[#This Row],[DATE ]] -> 45664
A15: 45665 | B15: =IF(ISBLANK(Tableau330[[#This Row],[DATE ]]),"",UPPER(PROPER(TEXT(Tableau330[[#This Row],[DATE ]],"mmmm yyyy")))) -> JANVIER 2025 | C15: NON-FN | D15: 25YPVFC50005 | E15: RIMCO-SETACI | F15: 9809714 J | G15: RNI | H15: 02 KIA K2700DC 4*4 | I15: TVA | J15: 1 | M15: 28305085 | N15: =+IF(Tableau330[[#This Row],[CODE TVA]]="",0,ROUND(Tableau330[[#This Row],[MONTANT HT]]*0.18*Tableau330[[#This Row],[PRORATA D]],1)) -> 5094915.3 | O15: =+IFERROR(Tableau330[[#This Row],[MONTANT HT]]+Tableau330[[#This Row],[TVA]],0) -> 33400000 | R15: =+Tableau330[[#This Row],[MONTANT TTC]]+Tableau330[[#This Row],[TIMBRE ]]+Tableau330[[#This Row],[AUTRES TAXES]] -> 33400000 | S15: 33400000 | T15: =+ROUND(Tableau330[[#This Row],[NET A PAYER]],0)-Tableau330[[#This Row],[MONTANT PAYE]] -> 0 | V15: =+Tableau330[[#This Row],[DELAI_PAIEMENT]]+Tableau330[[#This Row],[DATE ]] -> 45665 | AA15: DUPLICATA F/ EGAREE
A16: 45668 | B16: =IF(ISBLANK(Tableau330[[#This Row],[DATE ]]),"",UPPER(PROPER(TEXT(Tableau330[[#This Row],[DATE ]],"mmmm yyyy")))) -> JANVIER 2025 | C16: NON-FN | D16: 872824 | E16: 4LIFE IMPRIM | H16: AUTOCOLLANT, CALENDRIER, BLOC NOTE | M16: 1300000 | N16: =+IF(Tableau330[[#This Row],[CODE TVA]]="",0,ROUND(Tableau330[[#This Row],[MONTANT HT]]*0.18*Tableau330[[#This Row],[PRORATA D]],1)) -> 0 | O16: =+IFERROR(Tableau330[[#This Row],[MONTANT HT]]+Tableau330[[#This Row],[TVA]],0) -> 1300000 | R16: =+Tableau330[[#This Row],[MONTANT TTC]]+Tableau330[[#This Row],[TIMBRE ]]+Tableau330[[#This Row],[AUTRES TAXES]] -> 1300000 | S16: 1300000 | T16: =+ROUND(Tableau330[[#This Row],[NET A PAYER]],0)-Tableau330[[#This Row],[MONTANT PAYE]] -> 0 | V16: =+Tableau330[[#This Row],[DELAI_PAIEMENT]]+Tableau330[[#This Row],[DATE ]] -> 45668
A17: 45668 | B17: =IF(ISBLANK(Tableau330[[#This Row],[DATE ]]),"",UPPER(PROPER(TEXT(Tableau330[[#This Row],[DATE ]],"mmmm yyyy")))) -> JANVIER 2025 | C17: NON-FN | D17: 184337 | E17: BARRY OUSMANE | H17: COMPTEUR D'HEURE POUR CAMION | M17: 75000 | N17: =+IF(Tableau330[[#This Row],[CODE TVA]]="",0,ROUND(Tableau330[[#This Row],[MONTANT HT]]*0.18*Tableau330[[#This Row],[PRORATA D]],1)) -> 0 | O17: =+IFERROR(Tableau330[[#This Row],[MONTANT HT]]+Tableau330[[#This Row],[TVA]],0) -> 75000 | R17: =+Tableau330[[#This Row],[MONTANT TTC]]+Tableau330[[#This Row],[TIMBRE ]]+Tableau330[[#This Row],[AUTRES TAXES]] -> 75000 | S17: 75000 | T17: =+ROUND(Tableau330[[#This Row],[NET A PAYER]],0)-Tableau330[[#This Row],[MONTANT PAYE]] -> 0 | V17: =+Tableau330[[#This Row],[DELAI_PAIEMENT]]+Tableau330[[#This Row],[DATE ]] -> 45668
A18: 45671 | B18: =IF(ISBLANK(Tableau330[[#This Row],[DATE ]]),"",UPPER(PROPER(TEXT(Tableau330[[#This Row],[DATE ]],"mmmm yyyy")))) -> JANVIER 2025 | C18: NON-FN | D18: 125 | E18: COMPAGNIE IVOIRIENNE D'ELECTRICITE | F18: 9004996 S | G18: RNI | H18: CONSOMMATION D'ELECTRICITE DU 04/11/24 AU 04/01/25 | I18: TVA | J18: 1 | M18: 90600 | N18: =+IF(Tableau330[[#This Row],[CODE TVA]]="",0,ROUND(Tableau330[[#This Row],[MONTANT HT]]*0.18*Tableau330[[#This Row],[PRORATA D]],1)) -> 16308 | O18: =+IFERROR(Tableau330[[#This Row],[MONTANT HT]]+Tableau330[[#This Row],[TVA]],0) -> 106908 | P18: 500 | Q18: =1095+2260+2000 -> 5355 | R18: =+Tableau330[[#This Row],[MONTANT TTC]]+Tableau330[[#This Row],[TIMBRE ]]+Tableau330[[#This Row],[AUTRES TAXES]] -> 112763 | S18: 112763 | T18: =+ROUND(Tableau330[[#This Row],[NET A PAYER]],0)-Tableau330[[#This Row],[MONTANT PAYE]] -> 0 | V18: =+Tableau330[[#This Row],[DELAI_PAIEMENT]]+Tableau330[[#This Row],[DATE ]] -> 45671
A19: 45672 | B19: =IF(ISBLANK(Tableau330[[#This Row],[DATE ]]),"",UPPER(PROPER(TEXT(Tableau330[[#This Row],[DATE ]],"mmmm yyyy")))) -> JANVIER 2025 | C19: NON-FN | D19: 0673507 | E19: 4LIFE IMPRIM | H19: AUTOCLLANT, CALENDRIER BLOCS NOTES AGENDA | M19: 627500 | N19: =+IF(Tableau330[[#This Row],[CODE TVA]]="",0,ROUND(Tableau330[[#This Row],[MONTANT HT]]*0.18*Tableau330[[#This Row],[PRORATA D]],1)) -> 0 | O19: =+IFERROR(Tableau330[[#This Row],[MONTANT HT]]+Tableau330[[#This Row],[TVA]],0) -> 627500 | R19: =+Tableau330[[#This Row],[MONTANT TTC]]+Tableau330[[#This Row],[TIMBRE ]]+Tableau330[[#This Row],[AUTRES TAXES]] -> 627500 | S19: 627500 | T19: =+ROUND(Tableau330[[#This Row],[NET A PAYER]],0)-Tableau330[[#This Row],[MONTANT PAYE]] -> 0 | V19: =+Tableau330[[#This Row],[DELAI_PAIEMENT]]+Tableau330[[#This Row],[DATE ]] -> 45672
A20: 45673 | B20: =IF(ISBLANK(Tableau330[[#This Row],[DATE ]]),"",UPPER(PROPER(TEXT(Tableau330[[#This Row],[DATE ]],"mmmm yyyy")))) -> JANVIER 2025 | C20: FN | D20: 022691 | E20: PROSUMA | F20: 5011806 N | H20: PAPIER RAME, NETTOYANT SPRAY | I20: TVA | J20: 1 | M20: 8898 | N20: =+IF(Tableau330[[#This Row],[CODE TVA]]="",0,ROUND(Tableau330[[#This Row],[MONTANT HT]]*0.18*Tableau330[[#This Row],[PRORATA D]],1)) -> 1601.6 | O20: =+IFERROR(Tableau330[[#This Row],[MONTANT HT]]+Tableau330[[#This Row],[TVA]],0) -> 10499.6 | R20: =+Tableau330[[#This Row],[MONTANT TTC]]+Tableau330[[#This Row],[TIMBRE ]]+Tableau330[[#This Row],[AUTRES TAXES]] -> 10499.6 | S20: 10499.64 | T20: =+ROUND(Tableau330[[#This Row],[NET A PAYER]],0)-Tableau330[[#This Row],[MONTANT PAYE]] -> 0.36 | V20: =+Tableau330[[#This Row],[DELAI_PAIEMENT]]+Tableau330[[#This Row],[DATE ]] -> 45673
A21: 45677 | B21: =IF(ISBLANK(Tableau330[[#This Row],[DATE ]]),"",UPPER(PROPER(TEXT(Tableau330[[#This Row],[DATE ]],"mmmm yyyy")))) -> JANVIER 2025 | C21: FN | D21: 029790 | E21: SPRIINT TECH | F21: 1106600 L | G21: RNI | H21: BATTERIE 12 VT | I21: TVA | J21: 1 | M21: 347034 | N21: =+IF(Tableau330[[#This Row],[CODE TVA]]="",0,ROUND(Tableau330[[#This Row],[MONTANT HT]]*0.18*Tableau330[[#This Row],[PRORATA D]],1)) -> 62466.1 | O21: =+IFERROR(Tableau330[[#This Row],[MONTANT HT]]+Tableau330[[#This Row],[TVA]],0) -> 409500.1 | P21: 500 | Q21: 20475 | R21: =+Tableau330[[#This Row],[MONTANT TTC]]+Tableau330[[#This Row],[TIMBRE ]]+Tableau330[[#This Row],[AUTRES TAXES]] -> 430475.1 | S21: 430475 | T21: =+ROUND(Tableau330[[#This Row],[NET A PAYER]],0)-Tableau330[[#This Row],[MONTANT PAYE]] -> 0 | V21: =+Tableau330[[#This Row],[DELAI_PAIEMENT]]+Tableau330[[#This Row],[DATE ]] -> 45677
A22: 45678 | B22: =IF(ISBLANK(Tableau330[[#This Row],[DATE ]]),"",UPPER(PROPER(TEXT(Tableau330[[#This Row],[DATE ]],"mmmm yyyy")))) -> JANVIER 2025 | C22: FN | D22: 007704 | E22: RIMCO-SETACI | F22: 9809714 J | G22: RNI | H22: SINOTRUK BENNE 8*4 HOWO_784 | I22: TVA | J22: 1 | M22: 45338983 | N22: =+IF(Tableau330[[#This Row],[CODE TVA]]="",0,ROUND(Tableau330[[#This Row],[MONTANT HT]]*0.18*Tableau330[[#This Row],[PRORATA D]],1)) -> 8161016.9 | O22: =+IFERROR(Tableau330[[#This Row],[MONTANT HT]]+Tableau330[[#This Row],[TVA]],0) -> 53500000 | R22: =+Tableau330[[#This Row],[MONTANT TTC]]+Tableau330[[#This Row],[TIMBRE ]]+Tableau330[[#This Row],[AUTRES TAXES]] -> 53500000 | S22: 53500000 | T22: =+ROUND(Tableau330[[#This Row],[NET A PAYER]],0)-Tableau330[[#This Row],[MONTANT PAYE]] -> 0.060000002 | V22: =+Tableau330[[#This Row],[DELAI_PAIEMENT]]+Tableau330[[#This Row],[DATE ]] -> 45678
A23: 45678 | B23: =IF(ISBLANK(Tableau330[[#This Row],[DATE ]]),"",UPPER(PROPER(TEXT(Tableau330[[#This Row],[DATE ]],"mmmm yyyy")))) -> JANVIER 2025 | C23: FN | D23: 039129 | E23: BECROU SERVICES ET COMMUNICATION SARL | F23: 1801689 A | H23: CACHET 11 | M23: 20000 | N23: =+IF(Tableau330[[#This Row],[CODE TVA]]="",0,ROUND(Tableau330[[#This Row],[MONTANT HT]]*0.18*Tableau330[[#This Row],[PRORATA D]],1)) -> 0 | O23: =+IFERROR(Tableau330[[#This Row],[MONTANT HT]]+Tableau330[[#This Row],[TVA]],0) -> 20000 | R23: =+Tableau330[[#This Row],[MONTANT TTC]]+Tableau330[[#This Row],[TIMBRE ]]+Tableau330[[#This Row],[AUTRES TAXES]] -> 20000 | S23: 20000 | T23: =+ROUND(Tableau330[[#This Row],[NET A PAYER]],0)-Tableau330[[#This Row],[MONTANT PAYE]] -> 0 | V23: =+Tableau330[[#This Row],[DELAI_PAIEMENT]]+Tableau330[[#This Row],[DATE ]] -> 45678
A24: 45679 | B24: =IF(ISBLANK(Tableau330[[#This Row],[DATE ]]),"",UPPER(PROPER(TEXT(Tableau330[[#This Row],[DATE ]],"mmmm yyyy")))) -> JANVIER 2025 | C24: FN | D24: 173920 | E24: BUSINESS SERVICES INFORMATIQUES | F24: 1801689 A | H24: REPARATION D'IMPRIMANTE CANON | J24: 1 | M24: 15000 | N24: =+IF(Tableau330[[#This Row],[CODE TVA]]="",0,ROUND(Tableau330[[#This Row],[MONTANT HT]]*0.18*Tableau330[[#This Row],[PRORATA D]],1)) -> 0 | O24: =+IFERROR(Tableau330[[#This Row],[MONTANT HT]]+Tableau330[[#This Row],[TVA]],0) -> 15000 | R24: =+Tableau330[[#This Row],[MONTANT TTC]]+Tableau330[[#This Row],[TIMBRE ]]+Tableau330[[#This Row],[AUTRES TAXES]] -> 15000 | S24: 15000 | T24: =+ROUND(Tableau330[[#This Row],[NET A PAYER]],0)-Tableau330[[#This Row],[MONTANT PAYE]] -> 0 | V24: =+Tableau330[[#This Row],[DELAI_PAIEMENT]]+Tableau330[[#This Row],[DATE ]] -> 45679
A25: 45679 | B25: =IF(ISBLANK(Tableau330[[#This Row],[DATE ]]),"",UPPER(PROPER(TEXT(Tableau330[[#This Row],[DATE ]],"mmmm yyyy")))) -> JANVIER 2025 | C25: FN | D25: 029953 | E25: SPRIINT TECH | F25: 1106600 L | G25: RNI | H25: BATTERIE 12 VT | I25: TVA | J25: 1 | M25: 173517 | N25: =+IF(Tableau330[[#This Row],[CODE TVA]]="",0,ROUND(Tableau330[[#This Row],[MONTANT HT]]*0.18*Tableau330[[#This Row],[PRORATA D]],1)) -> 31233.1 | O25: =+IFERROR(Tableau330[[#This Row],[MONTANT HT]]+Tableau330[[#This Row],[TVA]],0) -> 204750.1 | Q25: 10238 | R25: =+Tableau330[[#This Row],[MONTANT TTC]]+Tableau330[[#This Row],[TIMBRE ]]+Tableau330[[#This Row],[AUTRES TAXES]] -> 214988.1 | S25: 214988 | T25: =+ROUND(Tableau330[[#This Row],[NET A PAYER]],0)-Tableau330[[#This Row],[MONTANT PAYE]] -> 0 | V25: =+Tableau330[[#This Row],[DELAI_PAIEMENT]]+Tableau330[[#This Row],[DATE ]] -> 45679
A26: 45679 | B26: =IF(ISBLANK(Tableau330[[#This Row],[DATE ]]),"",UPPER(PROPER(TEXT(Tableau330[[#This Row],[DATE ]],"mmmm yyyy")))) -> JANVIER 2025 | C26: NON-FN | D26: 2501/22/29 | E26: ISIS | H26: LOCATIONS BUREAU 02/25, 03/25 | M26: 600000 | N26: =+IF(Tableau330[[#This Row],[CODE TVA]]="",0,ROUND(Tableau330[[#This Row],[MONTANT HT]]*0.18*Tableau330[[#This Row],[PRORATA D]],1)) -> 0 | O26: =+IFERROR(Tableau330[[#This Row],[MONTANT HT]]+Tableau330[[#This Row],[TVA]],0) -> 600000 | R26: =+Tableau330[[#This Row],[MONTANT TTC]]+Tableau330[[#This Row],[TIMBRE ]]+Tableau330[[#This Row],[AUTRES TAXES]] -> 600000 | S26: 600000 | T26: =+ROUND(Tableau330[[#This Row],[NET A PAYER]],0)-Tableau330[[#This Row],[MONTANT PAYE]] -> 0 | V26: =+Tableau330[[#This Row],[DELAI_PAIEMENT]]+Tableau330[[#This Row],[DATE ]] -> 45679
A27: 45682 | B27: =IF(ISBLANK(Tableau330[[#This Row],[DATE ]]),"",UPPER(PROPER(TEXT(Tableau330[[#This Row],[DATE ]],"mmmm yyyy")))) -> JANVIER 2025 | C27: NON-FN | D27: 16653 | E27: SAWADOGO | H27: CABLE MOTOR | M27: 4000 | N27: =+IF(Tableau330[[#This Row],[CODE TVA]]="",0,ROUND(Tableau330[[#This Row],[MONTANT HT]]*0.18*Tableau330[[#This Row],[PRORATA D]],1)) -> 0 | O27: =+IFERROR(Tableau330[[#This Row],[MONTANT HT]]+Tableau330[[#This Row],[TVA]],0) -> 4000 | R27: =+Tableau330[[#This Row],[MONTANT TTC]]+Tableau330[[#This Row],[TIMBRE ]]+Tableau330[[#This Row],[AUTRES TAXES]] -> 4000 | S27: 4000 | T27: =+ROUND(Tableau330[[#This Row],[NET A PAYER]],0)-Tableau330[[#This Row],[MONTANT PAYE]] -> 0 | V27: =+Tableau330[[#This Row],[DELAI_PAIEMENT]]+Tableau330[[#This Row],[DATE ]] -> 45682
A28: 45685 | B28: =IF(ISBLANK(Tableau330[[#This Row],[DATE ]]),"",UPPER(PROPER(TEXT(Tableau330[[#This Row],[DATE ]],"mmmm yyyy")))) -> JANVIER 2025 | C28: FN | D28: 000359 | E28: MIRAN SARL | F28: 2300760 Z | G28: TEE | H28: BRIQUE CREUX 15*20*40 | M28: 300000 | N28: =+IF(Tableau330[[#This Row],[CODE TVA]]="",0,ROUND(Tableau330[[#This Row],[MONTANT HT]]*0.18*Tableau330[[#This Row],[PRORATA D]],1)) -> 0 | O28: =+IFERROR(Tableau330[[#This Row],[MONTANT HT]]+Tableau330[[#This Row],[TVA]],0) -> 300000 | R28: =+Tableau330[[#This Row],[MONTANT TTC]]+Tableau330[[#This Row],[TIMBRE ]]+Tableau330[[#This Row],[AUTRES TAXES]] -> 300000 | S28: 300000 | T28: =+ROUND(Tableau330[[#This Row],[NET A PAYER]],0)-Tableau330[[#This Row],[MONTANT PAYE]] -> 0 | V28: =+Tableau330[[#This Row],[DELAI_PAIEMENT]]+Tableau330[[#This Row],[DATE ]] -> 45685
A29: 45686 | B29: =IF(ISBLANK(Tableau330[[#This Row],[DATE ]]),"",UPPER(PROPER(TEXT(Tableau330[[#This Row],[DATE ]],"mmmm yyyy")))) -> JANVIER 2025 | C29: FN | D29: 035379 | E29: SPRIINT TECH | F29: 1106600 L | G29: RNI | H29: BATTERIE 12 VT | I29: TVA | J29: 1 | M29: -520551 | N29: =+IF(Tableau330[[#This Row],[CODE TVA]]="",0,ROUND(Tableau330[[#This Row],[MONTANT HT]]*0.18*Tableau330[[#This Row],[PRORATA D]],1)) -> -93699.2 | O29: =+IFERROR(Tableau330[[#This Row],[MONTANT HT]]+Tableau330[[#This Row],[TVA]],0) -> -614250.2 | Q29: -30713 | R29: =+Tableau330[[#This Row],[MONTANT TTC]]+Tableau330[[#This Row],[TIMBRE ]]+Tableau330[[#This Row],[AUTRES TAXES]] -> -644963.2 | S29: -644963.18 | T29: =+ROUND(Tableau330[[#This Row],[NET A PAYER]],0)-Tableau330[[#This Row],[MONTANT PAYE]] -> 0.18 | V29: =+Tableau330[[#This Row],[DELAI_PAIEMENT]]+Tableau330[[#This Row],[DATE ]] -> 45686
A30: 45686 | B30: =IF(ISBLANK(Tableau330[[#This Row],[DATE ]]),"",UPPER(PROPER(TEXT(Tableau330[[#This Row],[DATE ]],"mmmm yyyy")))) -> JANVIER 2025 | C30: FN | D30: 035381 | E30: SPRIINT TECH | F30: 1106600 L | G30: RNI | H30: BATTERIE 12 VT | I30: TVA | J30: 1 | M30: 521187 | N30: =+IF(Tableau330[[#This Row],[CODE TVA]]="",0,ROUND(Tableau330[[#This Row],[MONTANT HT]]*0.18*Tableau330[[#This Row],[PRORATA D]],1)) -> 93813.7 | O30: =+IFERROR(Tableau330[[#This Row],[MONTANT HT]]+Tableau330[[#This Row],[TVA]],0) -> 615000.7 | R30: =+Tableau330[[#This Row],[MONTANT TTC]]+Tableau330[[#This Row],[TIMBRE ]]+Tableau330[[#This Row],[AUTRES TAXES]] -> 615000.7 | S30: 615000.66 | T30: =+ROUND(Tableau330[[#This Row],[NET A PAYER]],0)-Tableau330[[#This Row],[MONTANT PAYE]] -> 0.34 | V30: =+Tableau330[[#This Row],[DELAI_PAIEMENT]]+Tableau330[[#This Row],[DATE ]] -> 45686
A31: 45686 | B31: =IF(ISBLANK(Tableau330[[#This Row],[DATE ]]),"",UPPER(PROPER(TEXT(Tableau330[[#This Row],[DATE ]],"mmmm yyyy")))) -> JANVIER 2025 | C31: FN | D31: 035382 | E31: SPRIINT TECH | H31: BATTERIE 12 VT | I31: TVA | J31: 1 | M31: 173729 | N31: =+IF(Tableau330[[#This Row],[CODE TVA]]="",0,ROUND(Tableau330[[#This Row],[MONTANT HT]]*0.18*Tableau330[[#This Row],[PRORATA D]],1)) -> 31271.2 | O31: =+IFERROR(Tableau330[[#This Row],[MONTANT HT]]+Tableau330[[#This Row],[TVA]],0) -> 205000.2 | R31: =+Tableau330[[#This Row],[MONTANT TTC]]+Tableau330[[#This Row],[TIMBRE ]]+Tableau330[[#This Row],[AUTRES TAXES]] -> 205000.2 | S31: 205000 | T31: =+ROUND(Tableau330[[#This Row],[NET A PAYER]],0)-Tableau330[[#This Row],[MONTANT PAYE]] -> 0 | V31: =+Tableau330[[#This Row],[DELAI_PAIEMENT]]+Tableau330[[#This Row],[DATE ]] -> 45686
A32: 45687 | B32: =IF(ISBLANK(Tableau330[[#This Row],[DATE ]]),"",UPPER(PROPER(TEXT(Tableau330[[#This Row],[DATE ]],"mmmm yyyy")))) -> JANVIER 2025 | C32: FN | D32: 035474 | E32: SPRIINT TECH | F32: 1106600 L | G32: RNI | H32: BATTERIE 12 VT | I32: TVA | J32: 1 | M32: 347034 | N32: =+IF(Tableau330[[#This Row],[CODE TVA]]="",0,ROUND(Tableau330[[#This Row],[MONTANT HT]]*0.18*Tableau330[[#This Row],[PRORATA D]],1)) -> 62466.1 | O32: =+IFERROR(Tableau330[[#This Row],[MONTANT HT]]+Tableau330[[#This Row],[TVA]],0) -> 409500.1 | P32: 500 | R32: =+Tableau330[[#This Row],[MONTANT TTC]]+Tableau330[[#This Row],[TIMBRE ]]+Tableau330[[#This Row],[AUTRES TAXES]] -> 410000.1 | S32: 410000 | T32: =+ROUND(Tableau330[[#This Row],[NET A PAYER]],0)-Tableau330[[#This Row],[MONTANT PAYE]] -> 0 | V32: =+Tableau330[[#This Row],[DELAI_PAIEMENT]]+Tableau330[[#This Row],[DATE ]] -> 45687
A33: 45688 | B33: =IF(ISBLANK(Tableau330[[#This Row],[DATE ]]),"",UPPER(PROPER(TEXT(Tableau330[[#This Row],[DATE ]],"mmmm yyyy")))) -> JANVIER 2025 | C33: FN | D33: 0017863 | E33: GUEPARD CIMENT | F33: 1700515 H | G33: RNI | H33: CIMENT GUEPARD CPJ 42,5 N | I33: TVA | J33: 1 | M33: 1322024 | N33: =+IF(Tableau330[[#This Row],[CODE TVA]]="",0,ROUND(Tableau330[[#This Row],[MONTANT HT]]*0.18*Tableau330[[#This Row],[PRORATA D]],1)) -> 237964.3 | O33: =+IFERROR(Tableau330[[#This Row],[MONTANT HT]]+Tableau330[[#This Row],[TVA]],0) -> 1559988.3 | R33: =+Tableau330[[#This Row],[MONTANT TTC]]+Tableau330[[#This Row],[TIMBRE ]]+Tableau330[[#This Row],[AUTRES TAXES]] -> 1559988.3 | S33: 1559988 | T33: =+ROUND(Tableau330[[#This Row],[NET A PAYER]],0)-Tableau330[[#This Row],[MONTANT PAYE]] -> 0 | V33: =+Tableau330[[#This Row],[DELAI_PAIEMENT]]+Tableau330[[#This Row],[DATE ]] -> 45688
A34: 45691 | B34: =IF(ISBLANK(Tableau330[[#This Row],[DATE ]]),"",UPPER(PROPER(TEXT(Tableau330[[#This Row],[DATE ]],"mmmm yyyy")))) -> FÉVRIER 2025 | C34: FN | D34: 00051 | E34: ANOH TECHNOLOGIES | F34: 2243084 G | G34: TEE | H34: 04 TELEPHONE SANS FILS VTECH | M34: 150000 | N34: =+IF(Tableau330[[#This Row],[CODE TVA]]="",0,ROUND(Tableau330[[#This Row],[MONTANT HT]]*0.18*Tableau330[[#This Row],[PRORATA D]],1)) -> 0 | O34: =+IFERROR(Tableau330[[#This Row],[MONTANT HT]]+Tableau330[[#This Row],[TVA]],0) -> 150000 | R34: =+Tableau330[[#This Row],[MONTANT TTC]]+Tableau330[[#This Row],[TIMBRE ]]+Tableau330[[#This Row],[AUTRES TAXES]] -> 150000 | S34: 150000 | T34: =+ROUND(Tableau330[[#This Row],[NET A PAYER]],0)-Tableau330[[#This Row],[MONTANT PAYE]] -> 0 | V34: =+Tableau330[[#This Row],[DELAI_PAIEMENT]]+Tableau330[[#This Row],[DATE ]] -> 45691
A35: 45691 | B35: =IF(ISBLANK(Tableau330[[#This Row],[DATE ]]),"",UPPER(PROPER(TEXT(Tableau330[[#This Row],[DATE ]],"mmmm yyyy")))) -> FÉVRIER 2025 | C35: FN | D35: 022727 | E35: PROSUMA | F35: 5011806 N | H35: PAPIER RAME, SUCRE MORCEAUX, LIPTON | I35: TVA | J35: 0.6637547 | M35: =9703+587 -> 10290 | N35: =+IF(Tableau330[[#This Row],[CODE TVA]]="",0,ROUND(Tableau330[[#This Row],[MONTANT HT]]*0.18*Tableau330[[#This Row],[PRORATA D]],1)) -> 1229.4 | O35: =+IFERROR(Tableau330[[#This Row],[MONTANT HT]]+Tableau330[[#This Row],[TVA]],0) -> 11519.4 | R35: =+Tableau330[[#This Row],[MONTANT TTC]]+Tableau330[[#This Row],[TIMBRE ]]+Tableau330[[#This Row],[AUTRES TAXES]] -> 11519.4 | S35: 11519 | T35: =+ROUND(Tableau330[[#This Row],[NET A PAYER]],0)-Tableau330[[#This Row],[MONTANT PAYE]] -> 0 | V35: =+Tableau330[[#This Row],[DELAI_PAIEMENT]]+Tableau330[[#This Row],[DATE ]] -> 45691
A36: 45691 | B36: =IF(ISBLANK(Tableau330[[#This Row],[DATE ]]),"",UPPER(PROPER(TEXT(Tableau330[[#This Row],[DATE ]],"mmmm yyyy")))) -> FÉVRIER 2025 | C36: FN | D36: 022769 | E36: PROSUMA | F36: 5011806 N | H36: EAU MINERALE | M36: 2500 | N36: =+IF(Tableau330[[#This Row],[CODE TVA]]="",0,ROUND(Tableau330[[#This Row],[MONTANT HT]]*0.18*Tableau330[[#This Row],[PRORATA D]],1)) -> 0 | O36: =+IFERROR(Tableau330[[#This Row],[MONTANT HT]]+Tableau330[[#This Row],[TVA]],0) -> 2500 | R36: =+Tableau330[[#This Row],[MONTANT TTC]]+Tableau330[[#This Row],[TIMBRE ]]+Tableau330[[#This Row],[AUTRES TAXES]] -> 2500 | S36: 2500 | T36: =+ROUND(Tableau330[[#This Row],[NET A PAYER]],0)-Tableau330[[#This Row],[MONTANT PAYE]] -> 0 | V36: =+Tableau330[[#This Row],[DELAI_PAIEMENT]]+Tableau330[[#This Row],[DATE ]] -> 45691
A37: 45694 | B37: =IF(ISBLANK(Tableau330[[#This Row],[DATE ]]),"",UPPER(PROPER(TEXT(Tableau330[[#This Row],[DATE ]],"mmmm yyyy")))) -> FÉVRIER 2025 | C37: FN | D37: 00406803 | E37: ESPERANCE TRANSPORT SUPER | F37: 2043577 U | H37: CLE CONTACTE POUR NIVELLEUSE | M37: 10000 | N37: =+IF(Tableau330[[#This Row],[CODE TVA]]="",0,ROUND(Tableau330[[#This Row],[MONTANT HT]]*0.18*Tableau330[[#This Row],[PRORATA D]],1)) -> 0 | O37: =+IFERROR(Tableau330[[#This Row],[MONTANT HT]]+Tableau330[[#This Row],[TVA]],0) -> 10000 | R37: =+Tableau330[[#This Row],[MONTANT TTC]]+Tableau330[[#This Row],[TIMBRE ]]+Tableau330[[#This Row],[AUTRES TAXES]] -> 10000 | S37: 10000 | T37: =+ROUND(Tableau330[[#This Row],[NET A PAYER]],0)-Tableau330[[#This Row],[MONTANT PAYE]] -> 0 | V37: =+Tableau330[[#This Row],[DELAI_PAIEMENT]]+Tableau330[[#This Row],[DATE ]] -> 45694
A38: 45695 | B38: =IF(ISBLANK(Tableau330[[#This Row],[DATE ]]),"",UPPER(PROPER(TEXT(Tableau330[[#This Row],[DATE ]],"mmmm yyyy")))) -> FÉVRIER 2025 | C38: FN | D38: 00406801 | E38: ESPERANCE TRANSPORT SUPER | F38: 2043577 U | H38: LOYER ET CAUTION MAISON CHAUFFEUR A KOUTO | M38: 50000 | N38: =+IF(Tableau330[[#This Row],[CODE TVA]]="",0,ROUND(Tableau330[[#This Row],[MONTANT HT]]*0.18*Tableau330[[#This Row],[PRORATA D]],1)) -> 0 | O38: =+IFERROR(Tableau330[[#This Row],[MONTANT HT]]+Tableau330[[#This Row],[TVA]],0) -> 50000 | R38: =+Tableau330[[#This Row],[MONTANT TTC]]+Tableau330[[#This Row],[TIMBRE ]]+Tableau330[[#This Row],[AUTRES TAXES]] -> 50000 | S38: 50000 | T38: =+ROUND(Tableau330[[#This Row],[NET A PAYER]],0)-Tableau330[[#This Row],[MONTANT PAYE]] -> 0 | V38: =+Tableau330[[#This Row],[DELAI_PAIEMENT]]+Tableau330[[#This Row],[DATE ]] -> 45695
A39: 45696 | B39: =IF(ISBLANK(Tableau330[[#This Row],[DATE ]]),"",UPPER(PROPER(TEXT(Tableau330[[#This Row],[DATE ]],"mmmm yyyy")))) -> FÉVRIER 2025 | C39: FN | D39: 022916 | E39: PROSUMA | F39: 5011806 N | H39: DIVERS ARTICLES | I39: TVA | J39: 1 | M39: 68008 | N39: =+IF(Tableau330[[#This Row],[CODE TVA]]="",0,ROUND(Tableau330[[#This Row],[MONTANT HT]]*0.18*Tableau330[[#This Row],[PRORATA D]],1)) -> 12241.4 | O39: =+IFERROR(Tableau330[[#This Row],[MONTANT HT]]+Tableau330[[#This Row],[TVA]],0) -> 80249.4 | P39: 100 | R39: =+Tableau330[[#This Row],[MONTANT TTC]]+Tableau330[[#This Row],[TIMBRE ]]+Tableau330[[#This Row],[AUTRES TAXES]] -> 80349.4 | S39: 80349 | T39: =+ROUND(Tableau330[[#This Row],[NET A PAYER]],0)-Tableau330[[#This Row],[MONTANT PAYE]] -> 0 | V39: =+Tableau330[[#This Row],[DELAI_PAIEMENT]]+Tableau330[[#This Row],[DATE ]] -> 45696
A40: 45697 | B40: =IF(ISBLANK(Tableau330[[#This Row],[DATE ]]),"",UPPER(PROPER(TEXT(Tableau330[[#This Row],[DATE ]],"mmmm yyyy")))) -> FÉVRIER 2025 | C40: FN | D40: 0356788 | E40: AUTO ROY | F40: 0814617 Y | G40: RME | H40: PNEU 385/65 R22,5 | M40: 300000 | N40: =+IF(Tableau330[[#This Row],[CODE TVA]]="",0,ROUND(Tableau330[[#This Row],[MONTANT HT]]*0.18*Tableau330[[#This Row],[PRORATA D]],1)) -> 0 | O40: =+IFERROR(Tableau330[[#This Row],[MONTANT HT]]+Tableau330[[#This Row],[TVA]],0) -> 300000 | R40: =+Tableau330[[#This Row],[MONTANT TTC]]+Tableau330[[#This Row],[TIMBRE ]]+Tableau330[[#This Row],[AUTRES TAXES]] -> 300000 | S40: 300000 | T40: =+ROUND(Tableau330[[#This Row],[NET A PAYER]],0)-Tableau330[[#This Row],[MONTANT PAYE]] -> 0 | V40: =+Tableau330[[#This Row],[DELAI_PAIEMENT]]+Tableau330[[#This Row],[DATE ]] -> 45697
A41: 45697 | B41: =IF(ISBLANK(Tableau330[[#This Row],[DATE ]]),"",UPPER(PROPER(TEXT(Tableau330[[#This Row],[DATE ]],"mmmm yyyy")))) -> FÉVRIER 2025 | C41: FN | D41: 009718 | E41: AL FAYSAL SARL | F41: 1648055 N | G41: RNI | H41: CARPE | M41: 19000 | N41: =+IF(Tableau330[[#This Row],[CODE TVA]]="",0,ROUND(Tableau330[[#This Row],[MONTANT HT]]*0.18*Tableau330[[#This Row],[PRORATA D]],1)) -> 0 | O41: =+IFERROR(Tableau330[[#This Row],[MONTANT HT]]+Tableau330[[#This Row],[TVA]],0) -> 19000 | R41: =+Tableau330[[#This Row],[MONTANT TTC]]+Tableau330[[#This Row],[TIMBRE ]]+Tableau330[[#This Row],[AUTRES TAXES]] -> 19000 | S41: 19000 | T41: =+ROUND(Tableau330[[#This Row],[NET A PAYER]],0)-Tableau330[[#This Row],[MONTANT PAYE]] -> 0 | V41: =+Tableau330[[#This Row],[DELAI_PAIEMENT]]+Tableau330[[#This Row],[DATE ]] -> 45697
A42: 45699 | B42: =IF(ISBLANK(Tableau330[[#This Row],[DATE ]]),"",UPPER(PROPER(TEXT(Tableau330[[#This Row],[DATE ]],"mmmm yyyy")))) -> FÉVRIER 2025 | C42: FN | D42: 018764 | E42: PETRO IVOIRE SA | F42: 9402809 K | G42: RNI | H42: HUILE MOTEUR SAE 50 FUT | M42: 455000 | N42: =+IF(Tableau330[[#This Row],[CODE TVA]]="",0,ROUND(Tableau330[[#This Row],[MONTANT HT]]*0.18*Tableau330[[#This Row],[PRORATA D]],1)) -> 0 | O42: =+IFERROR(Tableau330[[#This Row],[MONTANT HT]]+Tableau330[[#This Row],[TVA]],0) -> 455000 | R42: =+Tableau330[[#This Row],[MONTANT TTC]]+Tableau330[[#This Row],[TIMBRE ]]+Tableau330[[#This Row],[AUTRES TAXES]] -> 455000 | S42: 455000 | T42: =+ROUND(Tableau330[[#This Row],[NET A PAYER]],0)-Tableau330[[#This Row],[MONTANT PAYE]] -> 0 | V42: =+Tableau330[[#This Row],[DELAI_PAIEMENT]]+Tableau330[[#This Row],[DATE ]] -> 45699
A43: 45700 | B43: =IF(ISBLANK(Tableau330[[#This Row],[DATE ]]),"",UPPER(PROPER(TEXT(Tableau330[[#This Row],[DATE ]],"mmmm yyyy")))) -> FÉVRIER 2025 | C43: NON-FN | D43: 0673505 | E43: 4LIFE IMPRIM | H43: AUTOCLLANTS | M43: 300000 | N43: =+IF(Tableau330[[#This Row],[CODE TVA]]="",0,ROUND(Tableau330[[#This Row],[MONTANT HT]]*0.18*Tableau330[[#This Row],[PRORATA D]],1)) -> 0 | O43: =+IFERROR(Tableau330[[#This Row],[MONTANT HT]]+Tableau330[[#This Row],[TVA]],0) -> 300000 | R43: =+Tableau330[[#This Row],[MONTANT TTC]]+Tableau330[[#This Row],[TIMBRE ]]+Tableau330[[#This Row],[AUTRES TAXES]] -> 300000 | S43: 300000 | T43: =+ROUND(Tableau330[[#This Row],[NET A PAYER]],0)-Tableau330[[#This Row],[MONTANT PAYE]] -> 0 | V43: =+Tableau330[[#This Row],[DELAI_PAIEMENT]]+Tableau330[[#This Row],[DATE ]] -> 45700
A44: 45701 | B44: =IF(ISBLANK(Tableau330[[#This Row],[DATE ]]),"",UPPER(PROPER(TEXT(Tableau330[[#This Row],[DATE ]],"mmmm yyyy")))) -> FÉVRIER 2025 | C44: FN | D44: 036300 | E44: SPRIINT TECH | F44: 1106600 L | G44: RNI | H44: BATTERIE 12 VT | I44: TVA | J44: 1 | M44: 236864 | N44: =+IF(Tableau330[[#This Row],[CODE TVA]]="",0,ROUND(Tableau330[[#This Row],[MONTANT HT]]*0.18*Tableau330[[#This Row],[PRORATA D]],1)) -> 42635.5 | O44: =+IFERROR(Tableau330[[#This Row],[MONTANT HT]]+Tableau330[[#This Row],[TVA]],0) -> 279499.5 | P44: 500 | R44: =+Tableau330[[#This Row],[MONTANT TTC]]+Tableau330[[#This Row],[TIMBRE ]]+Tableau330[[#This Row],[AUTRES TAXES]] -> 279999.5 | S44: 279999.52 | T44: =+ROUND(Tableau330[[#This Row],[NET A PAYER]],0)-Tableau330[[#This Row],[MONTANT PAYE]] -> 0.48 | V44: =+Tableau330[[#This Row],[DELAI_PAIEMENT]]+Tableau330[[#This Row],[DATE ]] -> 45701
A45: 45705 | B45: =IF(ISBLANK(Tableau330[[#This Row],[DATE ]]),"",UPPER(PROPER(TEXT(Tableau330[[#This Row],[DATE ]],"mmmm yyyy")))) -> FÉVRIER 2025 | C45: FN | D45: 036518 | E45: SPRIINT TECH | F45: 1106600 L | G45: RNI | H45: BATTERIE 12 VT | I45: TVA | J45: 1 | M45: 173305 | N45: =+IF(Tableau330[[#This Row],[CODE TVA]]="",0,ROUND(Tableau330[[#This Row],[MONTANT HT]]*0.18*Tableau330[[#This Row],[PRORATA D]],1)) -> 31194.9 | O45: =+IFERROR(Tableau330[[#This Row],[MONTANT HT]]+Tableau330[[#This Row],[TVA]],0) -> 204499.9 | P45: 500 | R45: =+Tableau330[[#This Row],[MONTANT TTC]]+Tableau330[[#This Row],[TIMBRE ]]+Tableau330[[#This Row],[AUTRES TAXES]] -> 204999.9 | S45: 204999.9 | T45: =+ROUND(Tableau330[[#This Row],[NET A PAYER]],0)-Tableau330[[#This Row],[MONTANT PAYE]] -> 0.1 | V45: =+Tableau330[[#This Row],[DELAI_PAIEMENT]]+Tableau330[[#This Row],[DATE ]] -> 45705
A46: 45706 | B46: =IF(ISBLANK(Tableau330[[#This Row],[DATE ]]),"",UPPER(PROPER(TEXT(Tableau330[[#This Row],[DATE ]],"mmmm yyyy")))) -> FÉVRIER 2025 | C46: FN | D46: 015795 | E46: NESPRESSO | F46: 5011806 N | H46: CAFE NESPRESSO | I46: TVA | M46: 16600 | N46: =+IF(Tableau330[[#This Row],[CODE TVA]]="",0,ROUND(Tableau330[[#This Row],[MONTANT HT]]*0.18*Tableau330[[#This Row],[PRORATA D]],1)) -> 0 | O46: =+IFERROR(Tableau330[[#This Row],[MONTANT HT]]+Tableau330[[#This Row],[TVA]],0) -> 16600 | R46: =+Tableau330[[#This Row],[MONTANT TTC]]+Tableau330[[#This Row],[TIMBRE ]]+Tableau330[[#This Row],[AUTRES TAXES]] -> 16600 | S46: 16600 | T46: =+ROUND(Tableau330[[#This Row],[NET A PAYER]],0)-Tableau330[[#This Row],[MONTANT PAYE]] -> 0 | V46: =+Tableau330[[#This Row],[DELAI_PAIEMENT]]+Tableau330[[#This Row],[DATE ]] -> 45706
A47: 45706 | B47: =IF(ISBLANK(Tableau330[[#This Row],[DATE ]]),"",UPPER(PROPER(TEXT(Tableau330[[#This Row],[DATE ]],"mmmm yyyy")))) -> FÉVRIER 2025 | C47: FN | D47: 022832 | E47: PROSUMA | F47: 5011806 N | H47: EAU MINERALE | I47: TVA | M47: 18250 | N47: =+IF(Tableau330[[#This Row],[CODE TVA]]="",0,ROUND(Tableau330[[#This Row],[MONTANT HT]]*0.18*Tableau330[[#This Row],[PRORATA D]],1)) -> 0 | O47: =+IFERROR(Tableau330[[#This Row],[MONTANT HT]]+Tableau330[[#This Row],[TVA]],0) -> 18250 | R47: =+Tableau330[[#This Row],[MONTANT TTC]]+Tableau330[[#This Row],[TIMBRE ]]+Tableau330[[#This Row],[AUTRES TAXES]] -> 18250 | S47: 18250 | T47: =+ROUND(Tableau330[[#This Row],[NET A PAYER]],0)-Tableau330[[#This Row],[MONTANT PAYE]] -> 0 | V47: =+Tableau330[[#This Row],[DELAI_PAIEMENT]]+Tableau330[[#This Row],[DATE ]] -> 45706
A48: 45706 | B48: =IF(ISBLANK(Tableau330[[#This Row],[DATE ]]),"",UPPER(PROPER(TEXT(Tableau330[[#This Row],[DATE ]],"mmmm yyyy")))) -> FÉVRIER 2025 | C48: FN | D48: 023255 | E48: PROSUMA | F48: 5011806 N | G48: RNI | H48: DIVERS ARTICLES | I48: TVA | J48: 0.8706 | M48: =7407+1100 -> 8507 | N48: =+IF(Tableau330[[#This Row],[CODE TVA]]="",0,ROUND(Tableau330[[#This Row],[MONTANT HT]]*0.18*Tableau330[[#This Row],[PRORATA D]],1)) -> 1333.1 | O48: =+IFERROR(Tableau330[[#This Row],[MONTANT HT]]+Tableau330[[#This Row],[TVA]],0) -> 9840.1 | P48: 100 | R48: =+Tableau330[[#This Row],[MONTANT TTC]]+Tableau330[[#This Row],[TIMBRE ]]+Tableau330[[#This Row],[AUTRES TAXES]] -> 9940.1 | S48: 9940 | T48: =+ROUND(Tableau330[[#This Row],[NET A PAYER]],0)-Tableau330[[#This Row],[MONTANT PAYE]] -> 0 | V48: =+Tableau330[[#This Row],[DELAI_PAIEMENT]]+Tableau330[[#This Row],[DATE ]] -> 45706
A49: 45709 | B49: =IF(ISBLANK(Tableau330[[#This Row],[DATE ]]),"",UPPER(PROPER(TEXT(Tableau330[[#This Row],[DATE ]],"mmmm yyyy")))) -> FÉVRIER 2025 | C49: FN | D49: 022836 | E49: PROSUMA | F49: 5011806 N | H49: DESINFECTANT, DESODORISANT, PELLE | I49: TVA | J49: 1 | M49: -4576.27 | N49: =+IF(Tableau330[[#This Row],[CODE TVA]]="",0,ROUND(Tableau330[[#This Row],[MONTANT HT]]*0.18*Tableau330[[#This Row],[PRORATA D]],1)) -> -823.7 | O49: =+IFERROR(Tableau330[[#This Row],[MONTANT HT]]+Tableau330[[#This Row],[TVA]],0) -> -5399.97 | R49: =+Tableau330[[#This Row],[MONTANT TTC]]+Tableau330[[#This Row],[TIMBRE ]]+Tableau330[[#This Row],[AUTRES TAXES]] -> -5399.97 | S49: -5400 | T49: =+ROUND(Tableau330[[#This Row],[NET A PAYER]],0)-Tableau330[[#This Row],[MONTANT PAYE]] -> 0 | V49: =+Tableau330[[#This Row],[DELAI_PAIEMENT]]+Tableau330[[#This Row],[DATE ]] -> 45709
A50: 45712 | B50: =IF(ISBLANK(Tableau330[[#This Row],[DATE ]]),"",UPPER(PROPER(TEXT(Tableau330[[#This Row],[DATE ]],"mmmm yyyy")))) -> FÉVRIER 2025 | C50: NON-FN | D50: 0000894 | E50: SBEM-CI | F50: 2237119 Y | G50: RSI | H50: 06 BOMBONNES D'EAU | M50: 15000 | N50: =+IF(Tableau330[[#This Row],[CODE TVA]]="",0,ROUND(Tableau330[[#This Row],[MONTANT HT]]*0.18*Tableau330[[#This Row],[PRORATA D]],1)) -> 0 | O50: =+IFERROR(Tableau330[[#This Row],[MONTANT HT]]+Tableau330[[#This Row],[TVA]],0) -> 15000 | R50: =+Tableau330[[#This Row],[MONTANT TTC]]+Tableau330[[#This Row],[TIMBRE ]]+Tableau330[[#This Row],[AUTRES TAXES]] -> 15000 | S50: 15000 | T50: =+ROUND(Tableau330[[#This Row],[NET A PAYER]],0)-Tableau330[[#This Row],[MONTANT PAYE]] -> 0 | V50: =+Tableau330[[#This Row],[DELAI_PAIEMENT]]+Tableau330[[#This Row],[DATE ]] -> 45712
A51: 45716 | B51: =IF(ISBLANK(Tableau330[[#This Row],[DATE ]]),"",UPPER(PROPER(TEXT(Tableau330[[#This Row],[DATE ]],"mmmm yyyy")))) -> FÉVRIER 2025 | C51: NON-FN | D51: 09 | E51: G.M.S | H51: FRAIS DE GARDIENNAGE | M51: 100000 | N51: =+IF(Tableau330[[#This Row],[CODE TVA]]="",0,ROUND(Tableau330[[#This Row],[MONTANT HT]]*0.18*Tableau330[[#This Row],[PRORATA D]],1)) -> 0 | O51: =+IFERROR(Tableau330[[#This Row],[MONTANT HT]]+Tableau330[[#This Row],[TVA]],0) -> 100000 | R51: =+Tableau330[[#This Row],[MONTANT TTC]]+Tableau330[[#This Row],[TIMBRE ]]+Tableau330[[#This Row],[AUTRES TAXES]] -> 100000 | S51: 100000 | T51: =+ROUND(Tableau330[[#This Row],[NET A PAYER]],0)-Tableau330[[#This Row],[MONTANT PAYE]] -> 0 | V51: =+Tableau330[[#This Row],[DELAI_PAIEMENT]]+Tableau330[[#This Row],[DATE ]] -> 45716
A52: 45717 | B52: =IF(ISBLANK(Tableau330[[#This Row],[DATE ]]),"",UPPER(PROPER(TEXT(Tableau330[[#This Row],[DATE ]],"mmmm yyyy")))) -> MARS 2025 | C52: NON-FN | D52: Q12542025032023 | E52: ISIS | F52: 1434717 L | H52: LOCATION BUREAU 03/25 | M52: 300000 | N52: =+IF(Tableau330[[#This Row],[CODE TVA]]="",0,ROUND(Tableau330[[#This Row],[MONTANT HT]]*0.18*Tableau330[[#This Row],[PRORATA D]],1)) -> 0 | O52: =+IFERROR(Tableau330[[#This Row],[MONTANT HT]]+Tableau330[[#This Row],[TVA]],0) -> 300000 | R52: =+Tableau330[[#This Row],[MONTANT TTC]]+Tableau330[[#This Row],[TIMBRE ]]+Tableau330[[#This Row],[AUTRES TAXES]] -> 300000 | S52: 300000 | T52: =+ROUND(Tableau330[[#This Row],[NET A PAYER]],0)-Tableau330[[#This Row],[MONTANT PAYE]] -> 0 | V52: =+Tableau330[[#This Row],[DELAI_PAIEMENT]]+Tableau330[[#This Row],[DATE ]] -> 45717
A53: 45719 | B53: =IF(ISBLANK(Tableau330[[#This Row],[DATE ]]),"",UPPER(PROPER(TEXT(Tableau330[[#This Row],[DATE ]],"mmmm yyyy")))) -> MARS 2025 | C53: NON-FN | D53: 0673504 | E53: 4LIFE IMPRIM | H53: T SHIRTS DE QUALITE MOYENNE | M53: 200000 | N53: =+IF(Tableau330[[#This Row],[CODE TVA]]="",0,ROUND(Tableau330[[#This Row],[MONTANT HT]]*0.18*Tableau330[[#This Row],[PRORATA D]],1)) -> 0 | O53: =+IFERROR(Tableau330[[#This Row],[MONTANT HT]]+Tableau330[[#This Row],[TVA]],0) -> 200000 | R53: =+Tableau330[[#This Row],[MONTANT TTC]]+Tableau330[[#This Row],[TIMBRE ]]+Tableau330[[#This Row],[AUTRES TAXES]] -> 200000 | S53: 200000 | T53: =+ROUND(Tableau330[[#This Row],[NET A PAYER]],0)-Tableau330[[#This Row],[MONTANT PAYE]] -> 0 | V53: =+Tableau330[[#This Row],[DELAI_PAIEMENT]]+Tableau330[[#This Row],[DATE ]] -> 45719
A54: 45720 | B54: =IF(ISBLANK(Tableau330[[#This Row],[DATE ]]),"",UPPER(PROPER(TEXT(Tableau330[[#This Row],[DATE ]],"mmmm yyyy")))) -> MARS 2025 | C54: FN | D54: 005487 | E54: ICOGE | F54: 0041924 Y | G54: RNI | H54: ARTICLES DIVERS | I54: TVA | J54: 1 | M54: 14195 | N54: =+IF(Tableau330[[#This Row],[CODE TVA]]="",0,ROUND(Tableau330[[#This Row],[MONTANT HT]]*0.18*Tableau330[[#This Row],[PRORATA D]],1)) -> 2555.1 | O54: =+IFERROR(Tableau330[[#This Row],[MONTANT HT]]+Tableau330[[#This Row],[TVA]],0) -> 16750.1 | R54: =+Tableau330[[#This Row],[MONTANT TTC]]+Tableau330[[#This Row],[TIMBRE ]]+Tableau330[[#This Row],[AUTRES TAXES]] -> 16750.1 | S54: 16750 | T54: =+ROUND(Tableau330[[#This Row],[NET A PAYER]],0)-Tableau330[[#This Row],[MONTANT PAYE]] -> 0 | V54: =+Tableau330[[#This Row],[DELAI_PAIEMENT]]+Tableau330[[#This Row],[DATE ]] -> 45720
A55: 45720 | B55: =IF(ISBLANK(Tableau330[[#This Row],[DATE ]]),"",UPPER(PROPER(TEXT(Tableau330[[#This Row],[DATE ]],"mmmm yyyy")))) -> MARS 2025 | C55: FN | D55: 016708 | E55: SOCOPRIX | F55: 0648485 P | H55: SENTEUR, SAC RIZ, EAU | M55: 605175 | N55: =+IF(Tableau330[[#This Row],[CODE TVA]]="",0,ROUND(Tableau330[[#This Row],[MONTANT HT]]*0.18*Tableau330[[#This Row],[PRORATA D]],1)) -> 0 | O55: =+IFERROR(Tableau330[[#This Row],[MONTANT HT]]+Tableau330[[#This Row],[TVA]],0) -> 605175 | R55: =+Tableau330[[#This Row],[MONTANT TTC]]+Tableau330[[#This Row],[TIMBRE ]]+Tableau330[[#This Row],[AUTRES TAXES]] -> 605175 | S55: 605175 | T55: =+ROUND(Tableau330[[#This Row],[NET A PAYER]],0)-Tableau330[[#This Row],[MONTANT PAYE]] -> 0 | V55: =+Tableau330[[#This Row],[DELAI_PAIEMENT]]+Tableau330[[#This Row],[DATE ]] -> 45720
A56: 45720 | B56: =IF(ISBLANK(Tableau330[[#This Row],[DATE ]]),"",UPPER(PROPER(TEXT(Tableau330[[#This Row],[DATE ]],"mmmm yyyy")))) -> MARS 2025 | C56: FN | D56: 0312 | E56: SBEM-CI | F56: 2237119 Y | G56: RME | H56: RECHARGE BONBONNE | M56: 30000 | N56: =+IF(Tableau330[[#This Row],[CODE TVA]]="",0,ROUND(Tableau330[[#This Row],[MONTANT HT]]*0.18*Tableau330[[#This Row],[PRORATA D]],1)) -> 0 | O56: =+IFERROR(Tableau330[[#This Row],[MONTANT HT]]+Tableau330[[#This Row],[TVA]],0) -> 30000 | R56: =+Tableau330[[#This Row],[MONTANT TTC]]+Tableau330[[#This Row],[TIMBRE ]]+Tableau330[[#This Row],[AUTRES TAXES]] -> 30000 | S56: 30000 | T56: =+ROUND(Tableau330[[#This Row],[NET A PAYER]],0)-Tableau330[[#This Row],[MONTANT PAYE]] -> 0 | V56: =+Tableau330[[#This Row],[DELAI_PAIEMENT]]+Tableau330[[#This Row],[DATE ]] -> 45720
A57: 45721 | B57: =IF(ISBLANK(Tableau330[[#This Row],[DATE ]]),"",UPPER(PROPER(TEXT(Tableau330[[#This Row],[DATE ]],"mmmm yyyy")))) -> MARS 2025 | C57: FN | D57: 022872 | E57: PROSUMA | F57: 5011806 N | G57: RNI | H57: PAPIER RAME | I57: TVA | J57: 1 | M57: 3220.34 | N57: =+IF(Tableau330[[#This Row],[CODE TVA]]="",0,ROUND(Tableau330[[#This Row],[MONTANT HT]]*0.18*Tableau330[[#This Row],[PRORATA D]],1)) -> 579.7 | O57: =+IFERROR(Tableau330[[#This Row],[MONTANT HT]]+Tableau330[[#This Row],[TVA]],0) -> 3800.04 | R57: =+Tableau330[[#This Row],[MONTANT TTC]]+Tableau330[[#This Row],[TIMBRE ]]+Tableau330[[#This Row],[AUTRES TAXES]] -> 3800.04 | S57: 3800 | T57: =+ROUND(Tableau330[[#This Row],[NET A PAYER]],0)-Tableau330[[#This Row],[MONTANT PAYE]] -> 0 | V57: =+Tableau330[[#This Row],[DELAI_PAIEMENT]]+Tableau330[[#This Row],[DATE ]] -> 45721
A58: 45721 | B58: =IF(ISBLANK(Tableau330[[#This Row],[DATE ]]),"",UPPER(PROPER(TEXT(Tableau330[[#This Row],[DATE ]],"mmmm yyyy")))) -> MARS 2025 | C58: FN | D58: 173930 | E58: BSITECH | F58: 2141642 C | H58: ENCRE LIQUIDE NOIR | M58: 15000 | N58: =+IF(Tableau330[[#This Row],[CODE TVA]]="",0,ROUND(Tableau330[[#This Row],[MONTANT HT]]*0.18*Tableau330[[#This Row],[PRORATA D]],1)) -> 0 | O58: =+IFERROR(Tableau330[[#This Row],[MONTANT HT]]+Tableau330[[#This Row],[TVA]],0) -> 15000 | R58: =+Tableau330[[#This Row],[MONTANT TTC]]+Tableau330[[#This Row],[TIMBRE ]]+Tableau330[[#This Row],[AUTRES TAXES]] -> 15000 | S58: 15000 | T58: =+ROUND(Tableau330[[#This Row],[NET A PAYER]],0)-Tableau330[[#This Row],[MONTANT PAYE]] -> 0 | V58: =+Tableau330[[#This Row],[DELAI_PAIEMENT]]+Tableau330[[#This Row],[DATE ]] -> 45721
A59: 45721 | B59: =IF(ISBLANK(Tableau330[[#This Row],[DATE ]]),"",UPPER(PROPER(TEXT(Tableau330[[#This Row],[DATE ]],"mmmm yyyy")))) -> MARS 2025 | C59: FN | D59: 003278 | E59: TIMA | F59: 1304631 C | H59: RIZ | M59: 2255000 | N59: =+IF(Tableau330[[#This Row],[CODE TVA]]="",0,ROUND(Tableau330[[#This Row],[MONTANT HT]]*0.18*Tableau330[[#This Row],[PRORATA D]],1)) -> 0 | O59: =+IFERROR(Tableau330[[#This Row],[MONTANT HT]]+Tableau330[[#This Row],[TVA]],0) -> 2255000 | R59: =+Tableau330[[#This Row],[MONTANT TTC]]+Tableau330[[#This Row],[TIMBRE ]]+Tableau330[[#This Row],[AUTRES TAXES]] -> 2255000 | S59: 2255000 | T59: =+ROUND(Tableau330[[#This Row],[NET A PAYER]],0)-Tableau330[[#This Row],[MONTANT PAYE]] -> 0 | V59: =+Tableau330[[#This Row],[DELAI_PAIEMENT]]+Tableau330[[#This Row],[DATE ]] -> 45721
A60: 45721 | B60: =IF(ISBLANK(Tableau330[[#This Row],[DATE ]]),"",UPPER(PROPER(TEXT(Tableau330[[#This Row],[DATE ]],"mmmm yyyy")))) -> MARS 2025 | C60: FN | D60: 007234 | E60: PROSUMA | F60: 5011806 N | H60: SUCRE MORCEAUX | M60: 121875 | N60: =+IF(Tableau330[[#This Row],[CODE TVA]]="",0,ROUND(Tableau330[[#This Row],[MONTANT HT]]*0.18*Tableau330[[#This Row],[PRORATA D]],1)) -> 0 | O60: =+IFERROR(Tableau330[[#This Row],[MONTANT HT]]+Tableau330[[#This Row],[TVA]],0) -> 121875 | R60: =+Tableau330[[#This Row],[MONTANT TTC]]+Tableau330[[#This Row],[TIMBRE ]]+Tableau330[[#This Row],[AUTRES TAXES]] -> 121875 | S60: 121875 | T60: =+ROUND(Tableau330[[#This Row],[NET A PAYER]],0)-Tableau330[[#This Row],[MONTANT PAYE]] -> 0 | V60: =+Tableau330[[#This Row],[DELAI_PAIEMENT]]+Tableau330[[#This Row],[DATE ]] -> 45721
A61: 45721 | B61: =IF(ISBLANK(Tableau330[[#This Row],[DATE ]]),"",UPPER(PROPER(TEXT(Tableau330[[#This Row],[DATE ]],"mmmm yyyy")))) -> MARS 2025 | C61: FN | D61: 000296 | E61: GLOBAL BULDING & SERVICES | F61: 2404349 A | H61: METRE DE FIL, PAQUETS DE VIS, BARRES DE GOULOTTE | I61: TVA | J61: 1 | M61: =132020+4421 -> 136441 | N61: =+IF(Tableau330[[#This Row],[CODE TVA]]="",0,ROUND(Tableau330[[#This Row],[MONTANT HT]]*0.18*Tableau330[[#This Row],[PRORATA D]],1)) -> 24559.4 | O61: =+IFERROR(Tableau330[[#This Row],[MONTANT HT]]+Tableau330[[#This Row],[TVA]],0) -> 161000.4 | R61: =+Tableau330[[#This Row],[MONTANT TTC]]+Tableau330[[#This Row],[TIMBRE ]]+Tableau330[[#This Row],[AUTRES TAXES]] -> 161000.4 | S61: 161000 | T61: =+ROUND(Tableau330[[#This Row],[NET A PAYER]],0)-Tableau330[[#This Row],[MONTANT PAYE]] -> 0 | V61: =+Tableau330[[#This Row],[DELAI_PAIEMENT]]+Tableau330[[#This Row],[DATE ]] -> 45721
A62: 45721 | B62: =IF(ISBLANK(Tableau330[[#This Row],[DATE ]]),"",UPPER(PROPER(TEXT(Tableau330[[#This Row],[DATE ]],"mmmm yyyy")))) -> MARS 2025 | C62: RECU | D62: TT25085 | E62: PROSUMA | H62: SUCRE BLANC | M62: 121875 | N62: =+IF(Tableau330[[#This Row],[CODE TVA]]="",0,ROUND(Tableau330[[#This Row],[MONTANT HT]]*0.18*Tableau330[[#This Row],[PRORATA D]],1)) -> 0 | O62: =+IFERROR(Tableau330[[#This Row],[MONTANT HT]]+Tableau330[[#This Row],[TVA]],0) -> 121875 | R62: =+Tableau330[[#This Row],[MONTANT TTC]]+Tableau330[[#This Row],[TIMBRE ]]+Tableau330[[#This Row],[AUTRES TAXES]] -> 121875 | S62: 121875 | T62: =+ROUND(Tableau330[[#This Row],[NET A PAYER]],0)-Tableau330[[#This Row],[MONTANT PAYE]] -> 0 | V62: =+Tableau330[[#This Row],[DELAI_PAIEMENT]]+Tableau330[[#This Row],[DATE ]] -> 45721
A63: 45723 | B63: =IF(ISBLANK(Tableau330[[#This Row],[DATE ]]),"",UPPER(PROPER(TEXT(Tableau330[[#This Row],[DATE ]],"mmmm yyyy")))) -> MARS 2025 | C63: NON-FN | D63: 127 | E63: COMPAGNIE IVOIRIENNE D'ELECTRICITE | F63: 9004996 S | G63: RNI | H63: CONSOMMATION D'ELECTRICITE DU 04/01/25 AU 04/03/25 | I63: TVA | J63: 1 | M63: 104025 | N63: =+IF(Tableau330[[#This Row],[CODE TVA]]="",0,ROUND(Tableau330[[#This Row],[MONTANT HT]]*0.18*Tableau330[[#This Row],[PRORATA D]],1)) -> 18724.5 | O63: =+IFERROR(Tableau330[[#This Row],[MONTANT HT]]+Tableau330[[#This Row],[TVA]],0) -> 122749.5 | R63: =+Tableau330[[#This Row],[MONTANT TTC]]+Tableau330[[#This Row],[TIMBRE ]]+Tableau330[[#This Row],[AUTRES TAXES]] -> 122749.5 | S63: 122749.5 | T63: =+ROUND(Tableau330[[#This Row],[NET A PAYER]],0)-Tableau330[[#This Row],[MONTANT PAYE]] -> 0.5 | V63: =+Tableau330[[#This Row],[DELAI_PAIEMENT]]+Tableau330[[#This Row],[DATE ]] -> 45723
A64: 45726 | B64: =IF(ISBLANK(Tableau330[[#This Row],[DATE ]]),"",UPPER(PROPER(TEXT(Tableau330[[#This Row],[DATE ]],"mmmm yyyy")))) -> MARS 2025 | C64: FN | D64: 0120402 | E64: PETRO IVOIRE SA | F64: 9402809 K | H64: HUILE MOTEUR SAE 50 FUT | M64: 455000 | N64: =+IF(Tableau330[[#This Row],[CODE TVA]]="",0,ROUND(Tableau330[[#This Row],[MONTANT HT]]*0.18*Tableau330[[#This Row],[PRORATA D]],1)) -> 0 | O64: =+IFERROR(Tableau330[[#This Row],[MONTANT HT]]+Tableau330[[#This Row],[TVA]],0) -> 455000 | R64: =+Tableau330[[#This Row],[MONTANT TTC]]+Tableau330[[#This Row],[TIMBRE ]]+Tableau330[[#This Row],[AUTRES TAXES]] -> 455000 | S64: 455000 | T64: =+ROUND(Tableau330[[#This Row],[NET A PAYER]],0)-Tableau330[[#This Row],[MONTANT PAYE]] -> 0 | V64: =+Tableau330[[#This Row],[DELAI_PAIEMENT]]+Tableau330[[#This Row],[DATE ]] -> 45726
A65: 45733 | B65: =IF(ISBLANK(Tableau330[[#This Row],[DATE ]]),"",UPPER(PROPER(TEXT(Tableau330[[#This Row],[DATE ]],"mmmm yyyy")))) -> MARS 2025 | C65: FN | D65: 004112 | E65: BUREAU VERITAS | F65: 0024089 W | H65: FRAIS DE VERIFICATION REGLEMENTAIRE DES ENGINS DE LEVAGE | I65: TVA | J65: 1 | M65: 675000 | N65: =+IF(Tableau330[[#This Row],[CODE TVA]]="",0,ROUND(Tableau330[[#This Row],[MONTANT HT]]*0.18*Tableau330[[#This Row],[PRORATA D]],1)) -> 121500 | O65: =+IFERROR(Tableau330[[#This Row],[MONTANT HT]]+Tableau330[[#This Row],[TVA]],0) -> 796500 | R65: =+Tableau330[[#This Row],[MONTANT TTC]]+Tableau330[[#This Row],[TIMBRE ]]+Tableau330[[#This Row],[AUTRES TAXES]] -> 796500 | S65: 796500 | T65: =+ROUND(Tableau330[[#This Row],[NET A PAYER]],0)-Tableau330[[#This Row],[MONTANT PAYE]] -> 0 | V65: =+Tableau330[[#This Row],[DELAI_PAIEMENT]]+Tableau330[[#This Row],[DATE ]] -> 45733
A66: 45737 | B66: =IF(ISBLANK(Tableau330[[#This Row],[DATE ]]),"",UPPER(PROPER(TEXT(Tableau330[[#This Row],[DATE ]],"mmmm yyyy")))) -> MARS 2025 | C66: NON-FN | D66: EFN250321 | E66: ETUDE ME COULIBALY EDITH-SYLVIANE-NOTAIRE | F66: 1003850 A | H66: DROITS D'ETAT, DEBOURS ET EMOLUMENTS | M66: 31873000 | N66: =+IF(Tableau330[[#This Row],[CODE TVA]]="",0,ROUND(Tableau330[[#This Row],[MONTANT HT]]*0.18*Tableau330[[#This Row],[PRORATA D]],1)) -> 0 | O66: =+IFERROR(Tableau330[[#This Row],[MONTANT HT]]+Tableau330[[#This Row],[TVA]],0) -> 31873000 | R66: =+Tableau330[[#This Row],[MONTANT TTC]]+Tableau330[[#This Row],[TIMBRE ]]+Tableau330[[#This Row],[AUTRES TAXES]] -> 31873000 | S66: 31873000 | T66: =+ROUND(Tableau330[[#This Row],[NET A PAYER]],0)-Tableau330[[#This Row],[MONTANT PAYE]] -> 0 | V66: =+Tableau330[[#This Row],[DELAI_PAIEMENT]]+Tableau330[[#This Row],[DATE ]] -> 45737 | X66: NON
A67: 45741 | B67: =IF(ISBLANK(Tableau330[[#This Row],[DATE ]]),"",UPPER(PROPER(TEXT(Tableau330[[#This Row],[DATE ]],"mmmm yyyy")))) -> MARS 2025 | C67: FN | D67: 001024 | E67: HONDA | F67: 0100719 X | G67: RNI | H67: VEHICULE FOTON-345 | I67: TVA | J67: 1 | M67: 10466102 | N67: =+IF(Tableau330[[#This Row],[CODE TVA]]="",0,ROUND(Tableau330[[#This Row],[MONTANT HT]]*0.18*Tableau330[[#This Row],[PRORATA D]],1)) -> 1883898.4 | O67: =+IFERROR(Tableau330[[#This Row],[MONTANT HT]]+Tableau330[[#This Row],[TVA]],0) -> 12350000 | R67: =+Tableau330[[#This Row],[MONTANT TTC]]+Tableau330[[#This Row],[TIMBRE ]]+Tableau330[[#This Row],[AUTRES TAXES]] -> 12350000 | S67: 12350000 | T67: =+ROUND(Tableau330[[#This Row],[NET A PAYER]],0)-Tableau330[[#This Row],[MONTANT PAYE]] -> 0 | V67: =+Tableau330[[#This Row],[DELAI_PAIEMENT]]+Tableau330[[#This Row],[DATE ]] -> 45741 | AA67: IMMOBILISATION
A68: 45745 | B68: =IF(ISBLANK(Tableau330[[#This Row],[DATE ]]),"",UPPER(PROPER(TEXT(Tableau330[[#This Row],[DATE ]],"mmmm yyyy")))) -> MARS 2025 | C68: NON-FN | D68: 09 | E68: G.M.S | H68: FRAIS DE GARDIENNAGE | M68: 100000 | N68: =+IF(Tableau330[[#This Row],[CODE TVA]]="",0,ROUND(Tableau330[[#This Row],[MONTANT HT]]*0.18*Tableau330[[#This Row],[PRORATA D]],1)) -> 0 | O68: =+IFERROR(Tableau330[[#This Row],[MONTANT HT]]+Tableau330[[#This Row],[TVA]],0) -> 100000 | R68: =+Tableau330[[#This Row],[MONTANT TTC]]+Tableau330[[#This Row],[TIMBRE ]]+Tableau330[[#This Row],[AUTRES TAXES]] -> 100000 | S68: 100000 | T68: =+ROUND(Tableau330[[#This Row],[NET A PAYER]],0)-Tableau330[[#This Row],[MONTANT PAYE]] -> 0 | V68: =+Tableau330[[#This Row],[DELAI_PAIEMENT]]+Tableau330[[#This Row],[DATE ]] -> 45745
A69: 45745 | B69: =IF(ISBLANK(Tableau330[[#This Row],[DATE ]]),"",UPPER(PROPER(TEXT(Tableau330[[#This Row],[DATE ]],"mmmm yyyy")))) -> MARS 2025 | C69: FN | D69: 000549 | E69: TATA | F69: 1218049 R | G69: RNI | H69: TRAVELLER T2 BUS-425 | I69: TVA | J69: 1 | M69: 26271186 | N69: =+IF(Tableau330[[#This Row],[CODE TVA]]="",0,ROUND(Tableau330[[#This Row],[MONTANT HT]]*0.18*Tableau330[[#This Row],[PRORATA D]],1)) -> 4728813.6 | O69: =+IFERROR(Tableau330[[#This Row],[MONTANT HT]]+Tableau330[[#This Row],[TVA]],0) -> 31000000 | R69: =+Tableau330[[#This Row],[MONTANT TTC]]+Tableau330[[#This Row],[TIMBRE ]]+Tableau330[[#This Row],[AUTRES TAXES]] -> 31000000 | S69: 31000000 | T69: =+ROUND(Tableau330[[#This Row],[NET A PAYER]],0)-Tableau330[[#This Row],[MONTANT PAYE]] -> 0.00079999864 | V69: =+Tableau330[[#This Row],[DELAI_PAIEMENT]]+Tableau330[[#This Row],[DATE ]] -> 45745 | AA69: IMMOBILISATION
A70: 45745 | B70: =IF(ISBLANK(Tableau330[[#This Row],[DATE ]]),"",UPPER(PROPER(TEXT(Tableau330[[#This Row],[DATE ]],"mmmm yyyy")))) -> MARS 2025 | C70: FN | D70: 000558 | E70: TATA | F70: 1218049 R | G70: RNI | H70: TRAVELLER T2 BUS-411 | I70: TVA | J70: 1 | M70: 26271186 | N70: =+IF(Tableau330[[#This Row],[CODE TVA]]="",0,ROUND(Tableau330[[#This Row],[MONTANT HT]]*0.18*Tableau330[[#This Row],[PRORATA D]],1)) -> 4728813.6 | O70: =+IFERROR(Tableau330[[#This Row],[MONTANT HT]]+Tableau330[[#This Row],[TVA]],0) -> 31000000 | R70: =+Tableau330[[#This Row],[MONTANT TTC]]+Tableau330[[#This Row],[TIMBRE ]]+Tableau330[[#This Row],[AUTRES TAXES]] -> 31000000 | S70: 31000000 | T70: =+ROUND(Tableau330[[#This Row],[NET A PAYER]],0)-Tableau330[[#This Row],[MONTANT PAYE]] -> 0.00079999864 | V70: =+Tableau330[[#This Row],[DELAI_PAIEMENT]]+Tableau330[[#This Row],[DATE ]] -> 45745 | AA70: IMMOBILISATION
A71: 45745 | B71: =IF(ISBLANK(Tableau330[[#This Row],[DATE ]]),"",UPPER(PROPER(TEXT(Tableau330[[#This Row],[DATE ]],"mmmm yyyy")))) -> MARS 2025 | C71: FN | D71: 000548 | E71: TATA | F71: 1218049 R | G71: RNI | H71: XENON 2,2L 4*4-179 | I71: TVA | J71: 1 | M71: 13135593 | N71: =+IF(Tableau330[[#This Row],[CODE TVA]]="",0,ROUND(Tableau330[[#This Row],[MONTANT HT]]*0.18*Tableau330[[#This Row],[PRORATA D]],1)) -> 2364406.8 | O71: =+IFERROR(Tableau330[[#This Row],[MONTANT HT]]+Tableau330[[#This Row],[TVA]],0) -> 15500000 | R71: =+Tableau330[[#This Row],[MONTANT TTC]]+Tableau330[[#This Row],[TIMBRE ]]+Tableau330[[#This Row],[AUTRES TAXES]] -> 15500000 | S71: 15500000 | T71: =+ROUND(Tableau330[[#This Row],[NET A PAYER]],0)-Tableau330[[#This Row],[MONTANT PAYE]] -> 0.00039999932 | V71: =+Tableau330[[#This Row],[DELAI_PAIEMENT]]+Tableau330[[#This Row],[DATE ]] -> 45745 | AA71: IMMOBILISATION
A72: 45747 | B72: =IF(ISBLANK(Tableau330[[#This Row],[DATE ]]),"",UPPER(PROPER(TEXT(Tableau330[[#This Row],[DATE ]],"mmmm yyyy")))) -> MARS 2025 | C72: FN | D72: 000901 | E72: GUEPARD CIMENT | F72: 1700515 H | H72: CIMENT GUEPARD CPJ 42,5 N | I72: TVA | J72: 1 | M72: 1983051 | N72: =+IF(Tableau330[[#This Row],[CODE TVA]]="",0,ROUND(Tableau330[[#This Row],[MONTANT HT]]*0.18*Tableau330[[#This Row],[PRORATA D]],1)) -> 356949.2 | O72: =+IFERROR(Tableau330[[#This Row],[MONTANT HT]]+Tableau330[[#This Row],[TVA]],0) -> 2340000.2 | R72: =+Tableau330[[#This Row],[MONTANT TTC]]+Tableau330[[#This Row],[TIMBRE ]]+Tableau330[[#This Row],[AUTRES TAXES]] -> 2340000.2 | S72: 2340000 | T72: =+ROUND(Tableau330[[#This Row],[NET A PAYER]],0)-Tableau330[[#This Row],[MONTANT PAYE]] -> 0 | V72: =+Tableau330[[#This Row],[DELAI_PAIEMENT]]+Tableau330[[#This Row],[DATE ]] -> 45747
A73: 45749 | B73: =IF(ISBLANK(Tableau330[[#This Row],[DATE ]]),"",UPPER(PROPER(TEXT(Tableau330[[#This Row],[DATE ]],"mmmm yyyy")))) -> AVRIL 2025 | C73: NON-FN | D73: 0673510 | E73: 4LIFE IMPRIM | H73: CARNET A5 + IMPRESSION COULEUR | M73: 260000 | N73: =+IF(Tableau330[[#This Row],[CODE TVA]]="",0,ROUND(Tableau330[[#This Row],[MONTANT HT]]*0.18*Tableau330[[#This Row],[PRORATA D]],1)) -> 0 | O73: =+IFERROR(Tableau330[[#This Row],[MONTANT HT]]+Tableau330[[#This Row],[TVA]],0) -> 260000 | R73: =+Tableau330[[#This Row],[MONTANT TTC]]+Tableau330[[#This Row],[TIMBRE ]]+Tableau330[[#This Row],[AUTRES TAXES]] -> 260000 | S73: 260000 | T73: =+ROUND(Tableau330[[#This Row],[NET A PAYER]],0)-Tableau330[[#This Row],[MONTANT PAYE]] -> 0 | V73: =+Tableau330[[#This Row],[DELAI_PAIEMENT]]+Tableau330[[#This Row],[DATE ]] -> 45749
A74: 45750 | B74: =IF(ISBLANK(Tableau330[[#This Row],[DATE ]]),"",UPPER(PROPER(TEXT(Tableau330[[#This Row],[DATE ]],"mmmm yyyy")))) -> AVRIL 2025 | C74: NON-FN | D74: 2504/03/39 | E74: ISIS | F74: 1434717 L | H74: LOCATION BUREAU 04/25 | M74: 300000 | N74: =+IF(Tableau330[[#This Row],[CODE TVA]]="",0,ROUND(Tableau330[[#This Row],[MONTANT HT]]*0.18*Tableau330[[#This Row],[PRORATA D]],1)) -> 0 | O74: =+IFERROR(Tableau330[[#This Row],[MONTANT HT]]+Tableau330[[#This Row],[TVA]],0) -> 300000 | R74: =+Tableau330[[#This Row],[MONTANT TTC]]+Tableau330[[#This Row],[TIMBRE ]]+Tableau330[[#This Row],[AUTRES TAXES]] -> 300000 | S74: 300000 | T74: =+ROUND(Tableau330[[#This Row],[NET A PAYER]],0)-Tableau330[[#This Row],[MONTANT PAYE]] -> 0 | V74: =+Tableau330[[#This Row],[DELAI_PAIEMENT]]+Tableau330[[#This Row],[DATE ]] -> 45750
A75: 45754 | B75: =IF(ISBLANK(Tableau330[[#This Row],[DATE ]]),"",UPPER(PROPER(TEXT(Tableau330[[#This Row],[DATE ]],"mmmm yyyy")))) -> AVRIL 2025 | C75: FN | D75: 007294 | E75: PROSUMA | F75: 5011806 N | H75: RIZ, HUILE | I75: TVA | J75: 0.229 | M75: 66127 | N75: =+IF(Tableau330[[#This Row],[CODE TVA]]="",0,ROUND(Tableau330[[#This Row],[MONTANT HT]]*0.18*Tableau330[[#This Row],[PRORATA D]],1)) -> 2725.8 | O75: =+IFERROR(Tableau330[[#This Row],[MONTANT HT]]+Tableau330[[#This Row],[TVA]],0) -> 68852.8 | R75: =+Tableau330[[#This Row],[MONTANT TTC]]+Tableau330[[#This Row],[TIMBRE ]]+Tableau330[[#This Row],[AUTRES TAXES]] -> 68852.8 | S75: 68852.755 | T75: =+ROUND(Tableau330[[#This Row],[NET A PAYER]],0)-Tableau330[[#This Row],[MONTANT PAYE]] -> 0.24506 | V75: =+Tableau330[[#This Row],[DELAI_PAIEMENT]]+Tableau330[[#This Row],[DATE ]] -> 45754
A76: 45754 | B76: =IF(ISBLANK(Tableau330[[#This Row],[DATE ]]),"",UPPER(PROPER(TEXT(Tableau330[[#This Row],[DATE ]],"mmmm yyyy")))) -> AVRIL 2025 | C76: FN | D76: 023000 | E76: PROSUMA | F76: 5011806 N | H76: JAVEL, LAVE-VITRE, SAVON LIQUIDE, EAU | I76: TVA | J76: 0.371 | M76: =9427.97+1069 -> 10496.97 | N76: =+IF(Tableau330[[#This Row],[CODE TVA]]="",0,ROUND(Tableau330[[#This Row],[MONTANT HT]]*0.18*Tableau330[[#This Row],[PRORATA D]],1)) -> 701 | O76: =+IFERROR(Tableau330[[#This Row],[MONTANT HT]]+Tableau330[[#This Row],[TVA]],0) -> 11197.97 | R76: =+Tableau330[[#This Row],[MONTANT TTC]]+Tableau330[[#This Row],[TIMBRE ]]+Tableau330[[#This Row],[AUTRES TAXES]] -> 11197.97 | S76: 11197.958 | T76: =+ROUND(Tableau330[[#This Row],[NET A PAYER]],0)-Tableau330[[#This Row],[MONTANT PAYE]] -> 0.0423434 | V76: =+Tableau330[[#This Row],[DELAI_PAIEMENT]]+Tableau330[[#This Row],[DATE ]] -> 45754
A77: 45754 | B77: =IF(ISBLANK(Tableau330[[#This Row],[DATE ]]),"",UPPER(PROPER(TEXT(Tableau330[[#This Row],[DATE ]],"mmmm yyyy")))) -> AVRIL 2025 | C77: FN | D77: 023000 | E77: PROSUMA | F77: 5011806 N | H77: SAC POUBELLE, SUCRE MORCEAUX | I77: TVA | J77: 0.57 | M77: =1949+137 -> 2086 | N77: =+IF(Tableau330[[#This Row],[CODE TVA]]="",0,ROUND(Tableau330[[#This Row],[MONTANT HT]]*0.18*Tableau330[[#This Row],[PRORATA D]],1)) -> 214 | O77: =+IFERROR(Tableau330[[#This Row],[MONTANT HT]]+Tableau330[[#This Row],[TVA]],0) -> 2300 | R77: =+Tableau330[[#This Row],[MONTANT TTC]]+Tableau330[[#This Row],[TIMBRE ]]+Tableau330[[#This Row],[AUTRES TAXES]] -> 2300 | S77: 2300 | T77: =+ROUND(Tableau330[[#This Row],[NET A PAYER]],0)-Tableau330[[#This Row],[MONTANT PAYE]] -> 0 | V77: =+Tableau330[[#This Row],[DELAI_PAIEMENT]]+Tableau330[[#This Row],[DATE ]] -> 45754
A78: 45755 | B78: =IF(ISBLANK(Tableau330[[#This Row],[DATE ]]),"",UPPER(PROPER(TEXT(Tableau330[[#This Row],[DATE ]],"mmmm yyyy")))) -> AVRIL 2025 | C78: FN | D78: 006015 | E78: ICOGE | F78: 0041924 Y | G78: RNI | H78: RAME DOUBLE A | I78: TVA | J78: 1 | M78: 15255 | N78: =+IF(Tableau330[[#This Row],[CODE TVA]]="",0,ROUND(Tableau330[[#This Row],[MONTANT HT]]*0.18*Tableau330[[#This Row],[PRORATA D]],1)) -> 2745.9 | O78: =+IFERROR(Tableau330[[#This Row],[MONTANT HT]]+Tableau330[[#This Row],[TVA]],0) -> 18000.9 | R78: =+Tableau330[[#This Row],[MONTANT TTC]]+Tableau330[[#This Row],[TIMBRE ]]+Tableau330[[#This Row],[AUTRES TAXES]] -> 18000.9 | S78: 18000.9 | T78: =+ROUND(Tableau330[[#This Row],[NET A PAYER]],0)-Tableau330[[#This Row],[MONTANT PAYE]] -> 0.1 | V78: =+Tableau330[[#This Row],[DELAI_PAIEMENT]]+Tableau330[[#This Row],[DATE ]] -> 45755
A79: 45757 | B79: =IF(ISBLANK(Tableau330[[#This Row],[DATE ]]),"",UPPER(PROPER(TEXT(Tableau330[[#This Row],[DATE ]],"mmmm yyyy")))) -> AVRIL 2025 | C79: NON-FN | D79: 0000051 | E79: KS QUICALLERIE | F79: 2164691 V | H79: MARTEAU MASSE, CLE CRENAUX, CUTTER | M79: 47000 | N79: =+IF(Tableau330[[#This Row],[CODE TVA]]="",0,ROUND(Tableau330[[#This Row],[MONTANT HT]]*0.18*Tableau330[[#This Row],[PRORATA D]],1)) -> 0 | O79: =+IFERROR(Tableau330[[#This Row],[MONTANT HT]]+Tableau330[[#This Row],[TVA]],0) -> 47000 | R79: =+Tableau330[[#This Row],[MONTANT TTC]]+Tableau330[[#This Row],[TIMBRE ]]+Tableau330[[#This Row],[AUTRES TAXES]] -> 47000 | S79: 47000 | T79: =+ROUND(Tableau330[[#This Row],[NET A PAYER]],0)-Tableau330[[#This Row],[MONTANT PAYE]] -> 0 | V79: =+Tableau330[[#This Row],[DELAI_PAIEMENT]]+Tableau330[[#This Row],[DATE ]] -> 45757
A80: 45757 | B80: =IF(ISBLANK(Tableau330[[#This Row],[DATE ]]),"",UPPER(PROPER(TEXT(Tableau330[[#This Row],[DATE ]],"mmmm yyyy")))) -> AVRIL 2025 | C80: FN | D80: 0091 | E80: CHINA MART | F80: 2215123 N | G80: RME | H80: BOL, CARNET, CAHIER | M80: 12010 | N80: =+IF(Tableau330[[#This Row],[CODE TVA]]="",0,ROUND(Tableau330[[#This Row],[MONTANT HT]]*0.18*Tableau330[[#This Row],[PRORATA D]],1)) -> 0 | O80: =+IFERROR(Tableau330[[#This Row],[MONTANT HT]]+Tableau330[[#This Row],[TVA]],0) -> 12010 | R80: =+Tableau330[[#This Row],[MONTANT TTC]]+Tableau330[[#This Row],[TIMBRE ]]+Tableau330[[#This Row],[AUTRES TAXES]] -> 12010 | S80: 12010 | T80: =+ROUND(Tableau330[[#This Row],[NET A PAYER]],0)-Tableau330[[#This Row],[MONTANT PAYE]] -> 0 | V80: =+Tableau330[[#This Row],[DELAI_PAIEMENT]]+Tableau330[[#This Row],[DATE ]] -> 45757
A81: 45758 | B81: =IF(ISBLANK(Tableau330[[#This Row],[DATE ]]),"",UPPER(PROPER(TEXT(Tableau330[[#This Row],[DATE ]],"mmmm yyyy")))) -> AVRIL 2025 | C81: FN | D81: 0444872 | E81: ETABLISSEMENT OSMEN ET FRERES | F81: 1822609 A | G81: TEE | H81: LAME RESSORT | M81: 230000 | N81: =+IF(Tableau330[[#This Row],[CODE TVA]]="",0,ROUND(Tableau330[[#This Row],[MONTANT HT]]*0.18*Tableau330[[#This Row],[PRORATA D]],1)) -> 0 | O81: =+IFERROR(Tableau330[[#This Row],[MONTANT HT]]+Tableau330[[#This Row],[TVA]],0) -> 230000 | R81: =+Tableau330[[#This Row],[MONTANT TTC]]+Tableau330[[#This Row],[TIMBRE ]]+Tableau330[[#This Row],[AUTRES TAXES]] -> 230000 | S81: 230000 | T81: =+ROUND(Tableau330[[#This Row],[NET A PAYER]],0)-Tableau330[[#This Row],[MONTANT PAYE]] -> 0 | V81: =+Tableau330[[#This Row],[DELAI_PAIEMENT]]+Tableau330[[#This Row],[DATE ]] -> 45758
A82: 45758 | B82: =IF(ISBLANK(Tableau330[[#This Row],[DATE ]]),"",UPPER(PROPER(TEXT(Tableau330[[#This Row],[DATE ]],"mmmm yyyy")))) -> AVRIL 2025 | C82: FN | D82: 0419576 | E82: AUTO ROY | F82: 0814617 Y | G82: RME | H82: PNEU 315-80-225 | M82: 920000 | N82: =+IF(Tableau330[[#This Row],[CODE TVA]]="",0,ROUND(Tableau330[[#This Row],[MONTANT HT]]*0.18*Tableau330[[#This Row],[PRORATA D]],1)) -> 0 | O82: =+IFERROR(Tableau330[[#This Row],[MONTANT HT]]+Tableau330[[#This Row],[TVA]],0) -> 920000 | R82: =+Tableau330[[#This Row],[MONTANT TTC]]+Tableau330[[#This Row],[TIMBRE ]]+Tableau330[[#This Row],[AUTRES TAXES]] -> 920000 | S82: 920000 | T82: =+ROUND(Tableau330[[#This Row],[NET A PAYER]],0)-Tableau330[[#This Row],[MONTANT PAYE]] -> 0 | V82: =+Tableau330[[#This Row],[DELAI_PAIEMENT]]+Tableau330[[#This Row],[DATE ]] -> 45758
A83: 45762 | B83: =IF(ISBLANK(Tableau330[[#This Row],[DATE ]]),"",UPPER(PROPER(TEXT(Tableau330[[#This Row],[DATE ]],"mmmm yyyy")))) -> AVRIL 2025 | C83: FN | D83: 0090979 | E83: AUTO ROY | F83: 0814617 Y | H83: PNEU 900*20 | M83: 295000 | N83: =+IF(Tableau330[[#This Row],[CODE TVA]]="",0,ROUND(Tableau330[[#This Row],[MONTANT HT]]*0.18*Tableau330[[#This Row],[PRORATA D]],1)) -> 0 | O83: =+IFERROR(Tableau330[[#This Row],[MONTANT HT]]+Tableau330[[#This Row],[TVA]],0) -> 295000 | R83: =+Tableau330[[#This Row],[MONTANT TTC]]+Tableau330[[#This Row],[TIMBRE ]]+Tableau330[[#This Row],[AUTRES TAXES]] -> 295000 | S83: 295000 | T83: =+ROUND(Tableau330[[#This Row],[NET A PAYER]],0)-Tableau330[[#This Row],[MONTANT PAYE]] -> 0 | V83: =+Tableau330[[#This Row],[DELAI_PAIEMENT]]+Tableau330[[#This Row],[DATE ]] -> 45762
A84: 45768 | B84: =IF(ISBLANK(Tableau330[[#This Row],[DATE ]]),"",UPPER(PROPER(TEXT(Tableau330[[#This Row],[DATE ]],"mmmm yyyy")))) -> AVRIL 2025 | C84: NON-FN | D84: 0673511 | E84: 4LIFE IMPRIM | H84: PICK UP, AGENDAS, CARTE DE VISITE | M84: 535000 | N84: =+IF(Tableau330[[#This Row],[CODE TVA]]="",0,ROUND(Tableau330[[#This Row],[MONTANT HT]]*0.18*Tableau330[[#This Row],[PRORATA D]],1)) -> 0 | O84: =+IFERROR(Tableau330[[#This Row],[MONTANT HT]]+Tableau330[[#This Row],[TVA]],0) -> 535000 | R84: =+Tableau330[[#This Row],[MONTANT TTC]]+Tableau330[[#This Row],[TIMBRE ]]+Tableau330[[#This Row],[AUTRES TAXES]] -> 535000 | S84: 535000 | T84: =+ROUND(Tableau330[[#This Row],[NET A PAYER]],0)-Tableau330[[#This Row],[MONTANT PAYE]] -> 0 | V84: =+Tableau330[[#This Row],[DELAI_PAIEMENT]]+Tableau330[[#This Row],[DATE ]] -> 45768
A85: 45770 | B85: =IF(ISBLANK(Tableau330[[#This Row],[DATE ]]),"",UPPER(PROPER(TEXT(Tableau330[[#This Row],[DATE ]],"mmmm yyyy")))) -> AVRIL 2025 | C85: FN | D85: 0207401 | E85: PETRO IVOIRE SA | F85: 9402809 K | H85: HUILE MOTEUR SAE 50 FUT | M85: 455000 | N85: =+IF(Tableau330[[#This Row],[CODE TVA]]="",0,ROUND(Tableau330[[#This Row],[MONTANT HT]]*0.18*Tableau330[[#This Row],[PRORATA D]],1)) -> 0 | O85: =+IFERROR(Tableau330[[#This Row],[MONTANT HT]]+Tableau330[[#This Row],[TVA]],0) -> 455000 | R85: =+Tableau330[[#This Row],[MONTANT TTC]]+Tableau330[[#This Row],[TIMBRE ]]+Tableau330[[#This Row],[AUTRES TAXES]] -> 455000 | S85: 455000 | T85: =+ROUND(Tableau330[[#This Row],[NET A PAYER]],0)-Tableau330[[#This Row],[MONTANT PAYE]] -> 0 | V85: =+Tableau330[[#This Row],[DELAI_PAIEMENT]]+Tableau330[[#This Row],[DATE ]] -> 45770
A86: 45773 | B86: =IF(ISBLANK(Tableau330[[#This Row],[DATE ]]),"",UPPER(PROPER(TEXT(Tableau330[[#This Row],[DATE ]],"mmmm yyyy")))) -> AVRIL 2025 | C86: FN | D86: 023050 | E86: PROSUMA | F86: 5011806 N | H86: EAU MINERALE | M86: 6250 | N86: =+IF(Tableau330[[#This Row],[CODE TVA]]="",0,ROUND(Tableau330[[#This Row],[MONTANT HT]]*0.18*Tableau330[[#This Row],[PRORATA D]],1)) -> 0 | O86: =+IFERROR(Tableau330[[#This Row],[MONTANT HT]]+Tableau330[[#This Row],[TVA]],0) -> 6250 | R86: =+Tableau330[[#This Row],[MONTANT TTC]]+Tableau330[[#This Row],[TIMBRE ]]+Tableau330[[#This Row],[AUTRES TAXES]] -> 6250 | S86: 6250 | T86: =+ROUND(Tableau330[[#This Row],[NET A PAYER]],0)-Tableau330[[#This Row],[MONTANT PAYE]] -> 0 | V86: =+Tableau330[[#This Row],[DELAI_PAIEMENT]]+Tableau330[[#This Row],[DATE ]] -> 45773
A87: 45779 | B87: =IF(ISBLANK(Tableau330[[#This Row],[DATE ]]),"",UPPER(PROPER(TEXT(Tableau330[[#This Row],[DATE ]],"mmmm yyyy")))) -> MAI 2025 | C87: FN | D87: 023061 | E87: PROSUMA | F87: 5011806 N | H87: PAPIER HYGIENE, JAVEL ET SUCRE | J87: 0 | M87: 5975 | N87: =+IF(Tableau330[[#This Row],[CODE TVA]]="",0,ROUND(Tableau330[[#This Row],[MONTANT HT]]*0.18*Tableau330[[#This Row],[PRORATA D]],1)) -> 0 | O87: =+IFERROR(Tableau330[[#This Row],[MONTANT HT]]+Tableau330[[#This Row],[TVA]],0) -> 5975 | R87: =+Tableau330[[#This Row],[MONTANT TTC]]+Tableau330[[#This Row],[TIMBRE ]]+Tableau330[[#This Row],[AUTRES TAXES]] -> 5975 | S87: 5975 | T87: =+ROUND(Tableau330[[#This Row],[NET A PAYER]],0)-Tableau330[[#This Row],[MONTANT PAYE]] -> 0 | V87: =+Tableau330[[#This Row],[DELAI_PAIEMENT]]+Tableau330[[#This Row],[DATE ]] -> 45779
A88: 45780 | B88: =IF(ISBLANK(Tableau330[[#This Row],[DATE ]]),"",UPPER(PROPER(TEXT(Tableau330[[#This Row],[DATE ]],"mmmm yyyy")))) -> MAI 2025 | C88: NON-FN | D88: 01511548 | E88: AUTO ROY | F88: 0814617 Y | G88: RME | H88: PNEUS 315/80 | M88: 480000 | N88: =+IF(Tableau330[[#This Row],[CODE TVA]]="",0,ROUND(Tableau330[[#This Row],[MONTANT HT]]*0.18*Tableau330[[#This Row],[PRORATA D]],1)) -> 0 | O88: =+IFERROR(Tableau330[[#This Row],[MONTANT HT]]+Tableau330[[#This Row],[TVA]],0) -> 480000 | R88: =+Tableau330[[#This Row],[MONTANT TTC]]+Tableau330[[#This Row],[TIMBRE ]]+Tableau330[[#This Row],[AUTRES TAXES]] -> 480000 | S88: 480000 | T88: =+ROUND(Tableau330[[#This Row],[NET A PAYER]],0)-Tableau330[[#This Row],[MONTANT PAYE]] -> 0 | V88: =+Tableau330[[#This Row],[DELAI_PAIEMENT]]+Tableau330[[#This Row],[DATE ]] -> 45780
A89: 45782 | B89: =IF(ISBLANK(Tableau330[[#This Row],[DATE ]]),"",UPPER(PROPER(TEXT(Tableau330[[#This Row],[DATE ]],"mmmm yyyy")))) -> MAI 2025 | C89: NON-FN | D89: 00173936 | E89: BUSINESS SERVICES ET TECHNOLOGIES | F89: 2141642 C | H89: ENCRES DE COULEURS | M89: 63000 | N89: =+IF(Tableau330[[#This Row],[CODE TVA]]="",0,ROUND(Tableau330[[#This Row],[MONTANT HT]]*0.18*Tableau330[[#This Row],[PRORATA D]],1)) -> 0 | O89: =+IFERROR(Tableau330[[#This Row],[MONTANT HT]]+Tableau330[[#This Row],[TVA]],0) -> 63000 | R89: =+Tableau330[[#This Row],[MONTANT TTC]]+Tableau330[[#This Row],[TIMBRE ]]+Tableau330[[#This Row],[AUTRES TAXES]] -> 63000 | S89: 63000 | T89: =+ROUND(Tableau330[[#This Row],[NET A PAYER]],0)-Tableau330[[#This Row],[MONTANT PAYE]] -> 0 | V89: =+Tableau330[[#This Row],[DELAI_PAIEMENT]]+Tableau330[[#This Row],[DATE ]] -> 45782
A90: 45783 | B90: =IF(ISBLANK(Tableau330[[#This Row],[DATE ]]),"",UPPER(PROPER(TEXT(Tableau330[[#This Row],[DATE ]],"mmmm yyyy")))) -> MAI 2025 | C90: FN | D90: 007352 | E90: PROSUMA | F90: 5011806 N | H90: RIZ, HUILE | M90: 68250 | N90: =+IF(Tableau330[[#This Row],[CODE TVA]]="",0,ROUND(Tableau330[[#This Row],[MONTANT HT]]*0.18*Tableau330[[#This Row],[PRORATA D]],1)) -> 0 | O90: =+IFERROR(Tableau330[[#This Row],[MONTANT HT]]+Tableau330[[#This Row],[TVA]],0) -> 68250 | R90: =+Tableau330[[#This Row],[MONTANT TTC]]+Tableau330[[#This Row],[TIMBRE ]]+Tableau330[[#This Row],[AUTRES TAXES]] -> 68250 | S90: 68250 | T90: =+ROUND(Tableau330[[#This Row],[NET A PAYER]],0)-Tableau330[[#This Row],[MONTANT PAYE]] -> 0 | V90: =+Tableau330[[#This Row],[DELAI_PAIEMENT]]+Tableau330[[#This Row],[DATE ]] -> 45783
A91: 45783 | B91: =IF(ISBLANK(Tableau330[[#This Row],[DATE ]]),"",UPPER(PROPER(TEXT(Tableau330[[#This Row],[DATE ]],"mmmm yyyy")))) -> MAI 2025 | C91: FN | D91: 0009950 | E91: AL FAYSAL SARL | F91: 1648055 N | H91: TILAPIA | M91: 26000 | N91: =+IF(Tableau330[[#This Row],[CODE TVA]]="",0,ROUND(Tableau330[[#This Row],[MONTANT HT]]*0.18*Tableau330[[#This Row],[PRORATA D]],1)) -> 0 | O91: =+IFERROR(Tableau330[[#This Row],[MONTANT HT]]+Tableau330[[#This Row],[TVA]],0) -> 26000 | R91: =+Tableau330[[#This Row],[MONTANT TTC]]+Tableau330[[#This Row],[TIMBRE ]]+Tableau330[[#This Row],[AUTRES TAXES]] -> 26000 | S91: 26000 | T91: =+ROUND(Tableau330[[#This Row],[NET A PAYER]],0)-Tableau330[[#This Row],[MONTANT PAYE]] -> 0 | V91: =+Tableau330[[#This Row],[DELAI_PAIEMENT]]+Tableau330[[#This Row],[DATE ]] -> 45783
A92: 45783 | B92: =IF(ISBLANK(Tableau330[[#This Row],[DATE ]]),"",UPPER(PROPER(TEXT(Tableau330[[#This Row],[DATE ]],"mmmm yyyy")))) -> MAI 2025 | C92: FN | D92: 000720 | E92: RIMCO-SETACI | F92: 9809714 J | G92: RNI | H92: MAIN D'ŒUVRE, TAMPON DE LAME RESSORT ARRIERE | I92: TVA | J92: 1 | M92: 440875 | N92: =+IF(Tableau330[[#This Row],[CODE TVA]]="",0,ROUND(Tableau330[[#This Row],[MONTANT HT]]*0.18*Tableau330[[#This Row],[PRORATA D]],1)) -> 79357.5 | O92: =+IFERROR(Tableau330[[#This Row],[MONTANT HT]]+Tableau330[[#This Row],[TVA]],0) -> 520232.5 | R92: =+Tableau330[[#This Row],[MONTANT TTC]]+Tableau330[[#This Row],[TIMBRE ]]+Tableau330[[#This Row],[AUTRES TAXES]] -> 520232.5 | T92: =+ROUND(Tableau330[[#This Row],[NET A PAYER]],0)-Tableau330[[#This Row],[MONTANT PAYE]] -> 520233 | V92: =+Tableau330[[#This Row],[DELAI_PAIEMENT]]+Tableau330[[#This Row],[DATE ]] -> 45783 | X92: NON
A93: 45790 | B93: =IF(ISBLANK(Tableau330[[#This Row],[DATE ]]),"",UPPER(PROPER(TEXT(Tableau330[[#This Row],[DATE ]],"mmmm yyyy")))) -> MAI 2025 | C93: NON-FN | D93: AXA/SP/AC/05/2025 | E93: AXA COTE D'IVOIRE | H93: FRAIS ASSURANCE SANTE YAFOLO | M93: 5037260 | N93: =+IF(Tableau330[[#This Row],[CODE TVA]]="",0,ROUND(Tableau330[[#This Row],[MONTANT HT]]*0.18*Tableau330[[#This Row],[PRORATA D]],1)) -> 0 | O93: =+IFERROR(Tableau330[[#This Row],[MONTANT HT]]+Tableau330[[#This Row],[TVA]],0) -> 5037260 | R93: =+Tableau330[[#This Row],[MONTANT TTC]]+Tableau330[[#This Row],[TIMBRE ]]+Tableau330[[#This Row],[AUTRES TAXES]] -> 5037260 | S93: 5037260 | T93: =+ROUND(Tableau330[[#This Row],[NET A PAYER]],0)-Tableau330[[#This Row],[MONTANT PAYE]] -> 0 | V93: =+Tableau330[[#This Row],[DELAI_PAIEMENT]]+Tableau330[[#This Row],[DATE ]] -> 45790 | X93: NON
A94: 45791 | B94: =IF(ISBLANK(Tableau330[[#This Row],[DATE ]]),"",UPPER(PROPER(TEXT(Tableau330[[#This Row],[DATE ]],"mmmm yyyy")))) -> MAI 2025 | C94: NON-FN | E94: GEOLOSYST | H94: SERVICE GEOLOCALISATION | M94: 1010000 | N94: =+IF(Tableau330[[#This Row],[CODE TVA]]="",0,ROUND(Tableau330[[#This Row],[MONTANT HT]]*0.18*Tableau330[[#This Row],[PRORATA D]],1)) -> 0 | O94: =+IFERROR(Tableau330[[#This Row],[MONTANT HT]]+Tableau330[[#This Row],[TVA]],0) -> 1010000 | R94: =+Tableau330[[#This Row],[MONTANT TTC]]+Tableau330[[#This Row],[TIMBRE ]]+Tableau330[[#This Row],[AUTRES TAXES]] -> 1010000 | S94: 1010000 | T94: =+ROUND(Tableau330[[#This Row],[NET A PAYER]],0)-Tableau330[[#This Row],[MONTANT PAYE]] -> 0 | V94: =+Tableau330[[#This Row],[DELAI_PAIEMENT]]+Tableau330[[#This Row],[DATE ]] -> 45791
A95: 45793 | B95: =IF(ISBLANK(Tableau330[[#This Row],[DATE ]]),"",UPPER(PROPER(TEXT(Tableau330[[#This Row],[DATE ]],"mmmm yyyy")))) -> MAI 2025 | C95: NON-FN | D95: 2025/16/04 | E95: ISIS | F95: 1434717 L | H95: LOCATION BUREAU 05/25 | M95: 300000 | N95: =+IF(Tableau330[[#This Row],[CODE TVA]]="",0,ROUND(Tableau330[[#This Row],[MONTANT HT]]*0.18*Tableau330[[#This Row],[PRORATA D]],1)) -> 0 | O95: =+IFERROR(Tableau330[[#This Row],[MONTANT HT]]+Tableau330[[#This Row],[TVA]],0) -> 300000 | R95: =+Tableau330[[#This Row],[MONTANT TTC]]+Tableau330[[#This Row],[TIMBRE ]]+Tableau330[[#This Row],[AUTRES TAXES]] -> 300000 | S95: 300000 | T95: =+ROUND(Tableau330[[#This Row],[NET A PAYER]],0)-Tableau330[[#This Row],[MONTANT PAYE]] -> 0 | V95: =+Tableau330[[#This Row],[DELAI_PAIEMENT]]+Tableau330[[#This Row],[DATE ]] -> 45793
A96: 45794 | B96: =IF(ISBLANK(Tableau330[[#This Row],[DATE ]]),"",UPPER(PROPER(TEXT(Tableau330[[#This Row],[DATE ]],"mmmm yyyy")))) -> MAI 2025 | C96: NON-FN | D96: 0737540 | E96: GOD IS ONE | H96: FILTRE | M96: 17000 | N96: =+IF(Tableau330[[#This Row],[CODE TVA]]="",0,ROUND(Tableau330[[#This Row],[MONTANT HT]]*0.18*Tableau330[[#This Row],[PRORATA D]],1)) -> 0 | O96: =+IFERROR(Tableau330[[#This Row],[MONTANT HT]]+Tableau330[[#This Row],[TVA]],0) -> 17000 | R96: =+Tableau330[[#This Row],[MONTANT TTC]]+Tableau330[[#This Row],[TIMBRE ]]+Tableau330[[#This Row],[AUTRES TAXES]] -> 17000 | S96: 17000 | T96: =+ROUND(Tableau330[[#This Row],[NET A PAYER]],0)-Tableau330[[#This Row],[MONTANT PAYE]] -> 0 | V96: =+Tableau330[[#This Row],[DELAI_PAIEMENT]]+Tableau330[[#This Row],[DATE ]] -> 45794
A97: 45794 | B97: =IF(ISBLANK(Tableau330[[#This Row],[DATE ]]),"",UPPER(PROPER(TEXT(Tableau330[[#This Row],[DATE ]],"mmmm yyyy")))) -> MAI 2025 | C97: NON-FN | D97: 0673512 | E97: 4LIFE IMPRIM | H97: KAKEMONO, FLYERS A5 | M97: 255000 | N97: =+IF(Tableau330[[#This Row],[CODE TVA]]="",0,ROUND(Tableau330[[#This Row],[MONTANT HT]]*0.18*Tableau330[[#This Row],[PRORATA D]],1)) -> 0 | O97: =+IFERROR(Tableau330[[#This Row],[MONTANT HT]]+Tableau330[[#This Row],[TVA]],0) -> 255000 | R97: =+Tableau330[[#This Row],[MONTANT TTC]]+Tableau330[[#This Row],[TIMBRE ]]+Tableau330[[#This Row],[AUTRES TAXES]] -> 255000 | S97: 255000 | T97: =+ROUND(Tableau330[[#This Row],[NET A PAYER]],0)-Tableau330[[#This Row],[MONTANT PAYE]] -> 0 | V97: =+Tableau330[[#This Row],[DELAI_PAIEMENT]]+Tableau330[[#This Row],[DATE ]] -> 45794
A98: 45798 | B98: =IF(ISBLANK(Tableau330[[#This Row],[DATE ]]),"",UPPER(PROPER(TEXT(Tableau330[[#This Row],[DATE ]],"mmmm yyyy")))) -> MAI 2025 | C98: NON-FN_PF | D98: JPCC/PROF-03/2025 | E98: JEAN-PIERRE CONSULTING CONTINENTAL | F98: 2054674 G | H98: HONORAIRE DE VISA DES ETATS FINANCIERS | M98: 1760000 | N98: =+IF(Tableau330[[#This Row],[CODE TVA]]="",0,ROUND(Tableau330[[#This Row],[MONTANT HT]]*0.18*Tableau330[[#This Row],[PRORATA D]],1)) -> 0 | O98: =+IFERROR(Tableau330[[#This Row],[MONTANT HT]]+Tableau330[[#This Row],[TVA]],0) -> 1760000 | R98: =+Tableau330[[#This Row],[MONTANT TTC]]+Tableau330[[#This Row],[TIMBRE ]]+Tableau330[[#This Row],[AUTRES TAXES]] -> 1760000 | S98: 1760000 | T98: =+ROUND(Tableau330[[#This Row],[NET A PAYER]],0)-Tableau330[[#This Row],[MONTANT PAYE]] -> 0 | V98: =+Tableau330[[#This Row],[DELAI_PAIEMENT]]+Tableau330[[#This Row],[DATE ]] -> 45798
A99: 45798 | B99: =IF(ISBLANK(Tableau330[[#This Row],[DATE ]]),"",UPPER(PROPER(TEXT(Tableau330[[#This Row],[DATE ]],"mmmm yyyy")))) -> MAI 2025 | C99: NON-FN_PF | D99: 03/2025 | E99: JEAN-PIERRE CONSULTING CONTINENTAL | F99: 2054674 G | H99: NOTE HONORAIRE-VISA ETATS FINANCIERS | M99: 1760000 | N99: =+IF(Tableau330[[#This Row],[CODE TVA]]="",0,ROUND(Tableau330[[#This Row],[MONTANT HT]]*0.18*Tableau330[[#This Row],[PRORATA D]],1)) -> 0 | O99: =+IFERROR(Tableau330[[#This Row],[MONTANT HT]]+Tableau330[[#This Row],[TVA]],0) -> 1760000 | R99: =+Tableau330[[#This Row],[MONTANT TTC]]+Tableau330[[#This Row],[TIMBRE ]]+Tableau330[[#This Row],[AUTRES TAXES]] -> 1760000 | S99: 1000000 | T99: =+ROUND(Tableau330[[#This Row],[NET A PAYER]],0)-Tableau330[[#This Row],[MONTANT PAYE]] -> 760000 | V99: =+Tableau330[[#This Row],[DELAI_PAIEMENT]]+Tableau330[[#This Row],[DATE ]] -> 45798 | X99: OUI_P | Y99: CHEQUE | Z99: BDU_0001490
A100: 45799 | B100: =IF(ISBLANK(Tableau330[[#This Row],[DATE ]]),"",UPPER(PROPER(TEXT(Tableau330[[#This Row],[DATE ]],"mmmm yyyy")))) -> MAI 2025 | C100: FN | D100: 006566 | E100: ICOGE | F100: 0041924 Y | H100: DIVERS ARTICLES | I100: TVA | J100: 1 | M100: 30339 | N100: =+IF(Tableau330[[#This Row],[CODE TVA]]="",0,ROUND(Tableau330[[#This Row],[MONTANT HT]]*0.18*Tableau330[[#This Row],[PRORATA D]],1)) -> 5461 | O100: =+IFERROR(Tableau330[[#This Row],[MONTANT HT]]+Tableau330[[#This Row],[TVA]],0) -> 35800 | R100: =+Tableau330[[#This Row],[MONTANT TTC]]+Tableau330[[#This Row],[TIMBRE ]]+Tableau330[[#This Row],[AUTRES TAXES]] -> 35800 | S100: 35800 | T100: =+ROUND(Tableau330[[#This Row],[NET A PAYER]],0)-Tableau330[[#This Row],[MONTANT PAYE]] -> 0 | V100: =+Tableau330[[#This Row],[DELAI_PAIEMENT]]+Tableau330[[#This Row],[DATE ]] -> 45799
...

Sheet SOUS_TRAITANTS
C1: Montant Initial de Contrat | F1: Compte de Résultat | G1: Tableau des Flux de Trésorerie | H1: Bilan - Passif | I1: Engagement Restant (Non Facturé)
A4: N° Contrat | B4: Nom Sous-Traitant | C4: Montant Total Contrat | D4: Date Début | E4: Date Fin | F4: Montant Consommé (période) | G4: Paiements Effectués | H4: Solde Facturé Non Payé | I4: Solde Restant | J4: Observations
A5: ST-001 | B5: Entreprise A | C5: 5000000 | D5: 01/01/2025 | E5: 31/12/2025 | F5: 2000000 | G5: 1000000 | H5: =+F5-G5 -> 1000000 | I5: 4000000 | J5: Facture attendue
A6: ST-002 | B6: Entreprise B | C6: 3000000 | D6: 15/02/2025 | E6: 30/06/2025 | F6: 1500000 | G6: 1000000 | H6: =+F6-G6 -> 500000 | I6: 1500000 | J6: Avancement 50%
A7: ST-003 | B7: Entreprise C | C7: 7000000 | D7: 01/03/2025 | E7: 31/12/2025 | F7: 3000000 | G7: 2500000 | H7: =+F7-G7 -> 500000 | I7: 4500000 | J7: Contrat en cours
B8: TOTAL | C8: =SUM(C5:C7) -> 15000000 | F8: =SUM(F5:F7) -> 6500000 | G8: =SUM(G5:G7) -> 4500000 | H8: =SUM(H5:H7) -> 2000000 | I8: =SUM(I5:I7) -> 10000000

Sheet BASE FRAIS GENERAUX (2)
A2: N° | B2: ENTITE | C2: SOUS ENTITE | D2: FOURNISSEUR | E2: CONTRAT N° | F2: TYPE DE CONTRAT | G2: NATURE DE CONTRAT | H2: BIEN CONCERNE | I2: N° FICHE/DOSSIER | J2: POSTE BUDGETAIRE | K2: MONTANT HT | L2: TAUX TVA | M2: TVA | N2: MONTANT TTC | O2: MONTANT PERIODIQUE | P2: DUREE | Q2: UNITE_DUREE | R2: DATE DE DEBUT | S2: JOUR DE PRELEVEMENT | T2: MOIS COUVERTS PAR VERSEMENT INITIAL | U2: PREMIERE DATE ECHEANCE | V2: PROCHAINE ÉCHÉANCE | W2: PÉRIODICITÉ | X2: DATE DERNIER PAIEMENT | Y2: DATE PROCHAIN PRELEVEMENT | Z2: STATUT (PAYÉ/IMPAYÉ) | AA2: NBRE PRELEVEMENTS REALISES | AB2: NBRE PRELEVEMENTS IMPAYES | AC2: PROCHAINE ECHEANCE | AD2: NBRE DE FACTURES RECUS | AE2: MODE DE PAIEMENT | AF2: RECONDUCTION | AG2: COMMENTAIRE
A3: =+COUNTIF($J$2:J3,"="&Tableau529[[#This Row],[POSTE BUDGETAIRE]]) -> 1 | B3: SIM GROUP | D3: OUMAR | F3: ABONNEMENT | G3: CONTRAT DE BAIL | J3: LOCATION | K3: 700000 | M3: =+Tableau529[[#This Row],[MONTANT HT]]*Tableau529[[#This Row],[TAUX TVA]] -> 0 | N3: =+Tableau529[[#This Row],[MONTANT HT]]+Tableau529[[#This Row],[TVA]] -> 700000 | O3: 700000 | Q3: MOIS | S3: 5 | V3: =IF(Tableau529[[#This Row],[PREMIERE DATE ECHEANCE]]="","",EDATE(Tableau529[[#This Row],[PREMIERE DATE ECHEANCE]],1)+COUNTIFS(Tableau529[[#This Row],[STATUT (PAYÉ/IMPAYÉ)]],"Impayé")*CHOOSE(MATCH(Tableau529[[#This Row],[PÉRIODICITÉ]],{"hebdomadaire";"quinzaine";"mensuelle";"bimestrielle";"trimestrielle";"semestrielle";"annuelle"},0),7,15,30,60,90,180,365)) | W3: MENSUELLE | X3: 45839 | Y3: =IF(Tableau529[[#This Row],[PÉRIODICITÉ]]="mensuelle",DATE(YEAR(Tableau529[[#This Row],[DATE DE DEBUT]])+INT((MONTH(Tableau529[[#This Row],[DATE DE DEBUT]])+Tableau529[[#This Row],[MOIS COUVERTS PAR VERSEMENT INITIAL]]+Tableau529[[#This Row],[NBRE PRELEVEMENTS REALISES]]-Tableau529[[#This Row],[NBRE PRELEVEMENTS IMPAYES]]-1)/12), MOD(MONTH(Tableau529[[#This Row],[DATE DE DEBUT]])+Tableau529[[#This Row],[MOIS COUVERTS PAR VERSEMENT INITIAL]]+Tableau529[[#This Row],[NBRE PRELEVEMENTS REALISES]]-Tableau529[[#This Row],[NBRE PRELEVEMENTS IMPAYES]]-1,12)+1,Tableau529[[#This Row],[JOUR DE PRELEVEMENT]]), IF(Tableau529[[#This Row],[PÉRIODICITÉ]]="bimestrielle",DATE(YEAR(Tableau529[[#This Row],[DATE DE DEBUT]])+INT((MONTH(Tableau529[[#This Row],[DATE DE DEBUT]])+(Tableau529[[#This Row],[MOIS COUVERTS PAR VERSEMENT INITIAL]]+Tableau529[[#This Row],[NBRE PRELEVEMENTS REALISES]]-Tableau529[[#This Row],[NBRE PRELEVEMENTS IMPAYES]])*2-1)/12), MOD(MONTH(Tableau529[[#This Row],[DATE DE DEBUT]])+(Tableau529[[#This Row],[MOIS COUVERTS PAR VERSEMENT INITIAL]]+Tableau529[[#This Row],[NBRE PRELEVEMENTS REALISES]]-Tableau529[[#This Row],[NBRE PRELEVEMENTS IMPAYES]])*2-1,12)+1,Tableau529[[#This Row],[JOUR DE PRELEVEMENT]]), "")) -> #VALUE! | Z3: =IFERROR( IF(Tableau529[[#This Row],[NBRE PRELEVEMENTS IMPAYES]]<=0,"PAYÉ", IF(Tableau529[[#This Row],[NBRE PRELEVEMENTS REALISES]]>0,"EN RETARD","IMPAYÉ")),"") -> EN RETARD | AA3: =IF(OR(Tableau529[[#This Row],[PREMIERE DATE ECHEANCE]]="",Tableau529[[#This Row],[PÉRIODICITÉ]]=""),"", MAX(0, INT((TODAY() - Tableau529[[#This Row],[PREMIERE DATE ECHEANCE]]) / CHOOSE(MATCH(Tableau529[[#This Row],[PÉRIODICITÉ]], {"HEBDOMADAIRE";"QUINZAINE";"MENSUELLE";"BIMESTRIELLE";"TRIMESTRIELLE";"SEMESTRIELLE";"ANNUELLE"}, 0), 7,15,30,60,90,180,365 ) ) -Tableau529[[#This Row],[MOIS COUVERTS PAR VERSEMENT INITIAL]] ) ) | AB3: =IF(OR(Tableau529[[#This Row],[PREMIERE DATE ECHEANCE]]="",Tableau529[[#This Row],[PÉRIODICITÉ]]=""),"", MAX(0, INT((TODAY() - Tableau529[[#This Row],[PREMIERE DATE ECHEANCE]]) / CHOOSE(MATCH(Tableau529[[#This Row],[PÉRIODICITÉ]], {"HEBDOMADAIRE";"QUINZAINE";"MENSUELLE";"BIMESTRIELLE";"TRIMESTRIELLE";"SEMESTRIELLE";"ANNUELLE"}, 0), 7,15,30,60,90,180,365) ) -Tableau529[[#This Row],[MOIS COUVERTS PAR VERSEMENT INITIAL]] -Tableau529[[#This Row],[NBRE PRELEVEMENTS REALISES]] ) ) | AC3: =IF(W3="mensuelle",DATE(YEAR(X3),MONTH(X3)+1,DAY(X3)), IF(W3="hebdomadaire",X3+7, IF(W3="quinzaine",X3+14, IF(W3="trimestrielle",DATE(YEAR(X3),MONTH(X3)+3,DAY(X3)), IF(W3="semestrielle",DATE(YEAR(X3),MONTH(X3)+6,DAY(X3)), IF(W3="annuelle",DATE(YEAR(X3),MONTH(X3)+12,DAY(X3)), "")))))) -> 45870 | AE3: RECURENT
A4: =+COUNTIF($J$2:J4,"="&Tableau529[[#This Row],[POSTE BUDGETAIRE]]) -> 1 | B4: TEXTIPRINT | D4: TIMAOC SDI | E4: CV0023/25 | F4: PAIEMENT ECHELONNE | G4: VENTE AVEC PAIEMENT ECHELONNE | H4: PRESSE NUMERIQUE-KONICA | J4: IMMOBILISATION | K4: 17796610 | L4: 0.18 | M4: =+Tableau529[[#This Row],[MONTANT HT]]*Tableau529[[#This Row],[TAUX TVA]] -> 3203389.8 | N4: =+Tableau529[[#This Row],[MONTANT HT]]+Tableau529[[#This Row],[TVA]] -> 21000000 | O4: 1000000 | P4: 20 | Q4: MOIS | R4: 45581 | S4: 10 | T4: 3 | U4: =IFERROR(EDATE( DATE(YEAR(Tableau529[[#This Row],[DATE DE DEBUT]]), MONTH(Tableau529[[#This Row],[DATE DE DEBUT]]), Tableau529[[#This Row],[JOUR DE PRELEVEMENT]]), Tableau529[[#This Row],[MOIS COUVERTS PAR VERSEMENT INITIAL]] ),"") -> 45667 | V4: =IF(Tableau529[[#This Row],[PREMIERE DATE ECHEANCE]]="","",EDATE(Tableau529[[#This Row],[PREMIERE DATE ECHEANCE]],1)+COUNTIFS(Tableau529[[#This Row],[STATUT (PAYÉ/IMPAYÉ)]],"Impayé")*CHOOSE(MATCH(Tableau529[[#This Row],[PÉRIODICITÉ]],{"hebdomadaire";"quinzaine";"mensuelle";"bimestrielle";"trimestrielle";"semestrielle";"annuelle"},0),7,15,30,60,90,180,365)) -> 45698 | W4: MENSUELLE | X4: 45581 | Y4: =IF(Tableau529[[#This Row],[PÉRIODICITÉ]]="mensuelle",DATE(YEAR(Tableau529[[#This Row],[DATE DE DEBUT]])+INT((MONTH(Tableau529[[#This Row],[DATE DE DEBUT]])+Tableau529[[#This Row],[MOIS COUVERTS PAR VERSEMENT INITIAL]]+Tableau529[[#This Row],[NBRE PRELEVEMENTS REALISES]]-Tableau529[[#This Row],[NBRE PRELEVEMENTS IMPAYES]]-1)/12), MOD(MONTH(Tableau529[[#This Row],[DATE DE DEBUT]])+Tableau529[[#This Row],[MOIS COUVERTS PAR VERSEMENT INITIAL]]+Tableau529[[#This Row],[NBRE PRELEVEMENTS REALISES]]-Tableau529[[#This Row],[NBRE PRELEVEMENTS IMPAYES]]-1,12)+1,Tableau529[[#This Row],[JOUR DE PRELEVEMENT]]), IF(Tableau529[[#This Row],[PÉRIODICITÉ]]="bimestrielle",DATE(YEAR(Tableau529[[#This Row],[DATE DE DEBUT]])+INT((MONTH(Tableau529[[#This Row],[DATE DE DEBUT]])+(Tableau529[[#This Row],[MOIS COUVERTS PAR VERSEMENT INITIAL]]+Tableau529[[#This Row],[NBRE PRELEVEMENTS REALISES]]-Tableau529[[#This Row],[NBRE PRELEVEMENTS IMPAYES]])*2-1)/12), MOD(MONTH(Tableau529[[#This Row],[DATE DE DEBUT]])+(Tableau529[[#This Row],[MOIS COUVERTS PAR VERSEMENT INITIAL]]+Tableau529[[#This Row],[NBRE PRELEVEMENTS REALISES]]-Tableau529[[#This Row],[NBRE PRELEVEMENTS IMPAYES]])*2-1,12)+1,Tableau529[[#This Row],[JOUR DE PRELEVEMENT]]), "")) -> 46001 | Z4: =IFERROR( IF(Tableau529[[#This Row],[NBRE PRELEVEMENTS IMPAYES]]<=0,"PAYÉ", IF(Tableau529[[#This Row],[NBRE PRELEVEMENTS REALISES]]>0,"EN RETARD","IMPAYÉ")),"") -> PAYÉ | AA4: =IF(OR(Tableau529[[#This Row],[PREMIERE DATE ECHEANCE]]="",Tableau529[[#This Row],[PÉRIODICITÉ]]=""),"", MAX(0, INT((TODAY() - Tableau529[[#This Row],[PREMIERE DATE ECHEANCE]]) / CHOOSE(MATCH(Tableau529[[#This Row],[PÉRIODICITÉ]], {"HEBDOMADAIRE";"QUINZAINE";"MENSUELLE";"BIMESTRIELLE";"TRIMESTRIELLE";"SEMESTRIELLE";"ANNUELLE"}, 0), 7,15,30,60,90,180,365 ) ) -Tableau529[[#This Row],[MOIS COUVERTS PAR VERSEMENT INITIAL]] ) ) -> 11 | AB4: =IF(OR(Tableau529[[#This Row],[PREMIERE DATE ECHEANCE]]="",Tableau529[[#This Row],[PÉRIODICITÉ]]=""),"", MAX(0, INT((TODAY() - Tableau529[[#This Row],[PREMIERE DATE ECHEANCE]]) / CHOOSE(MATCH(Tableau529[[#This Row],[PÉRIODICITÉ]], {"HEBDOMADAIRE";"QUINZAINE";"MENSUELLE";"BIMESTRIELLE";"TRIMESTRIELLE";"SEMESTRIELLE";"ANNUELLE"}, 0), 7,15,30,60,90,180,365) ) -Tableau529[[#This Row],[MOIS COUVERTS PAR VERSEMENT INITIAL]] -Tableau529[[#This Row],[NBRE PRELEVEMENTS REALISES]] ) ) -> 0 | AC4: =IF(W4="mensuelle",DATE(YEAR(X4),MONTH(X4)+1,DAY(X4)), IF(W4="hebdomadaire",X4+7, IF(W4="quinzaine",X4+14, IF(W4="trimestrielle",DATE(YEAR(X4),MONTH(X4)+3,DAY(X4)), IF(W4="semestrielle",DATE(YEAR(X4),MONTH(X4)+6,DAY(X4)), IF(W4="annuelle",DATE(YEAR(X4),MONTH(X4)+12,DAY(X4)), "")))))) -> 45612 | AE4: ECHEANCIER | AF4: NON
AA8: =IF(TYPE_DE_CONTRAT="ABONNEMENT",MAX(0,X2-Z2),MAX(0,MIN(DUREE,X2)-Z2)) -> #NAME?

Sheet NOTE
B2: Procédure manuelle pour compléter les informations
B3: 1. Collectez les factures liées :
B4: Demandez aux fournisseurs de fournir les factures pour chaque fiche de dépense validée.
B5: 2. Vérifiez les montants et les conditions :
B6: Assurez-vous que les montants sur la facture correspondent à ceux engagés.
B7: Si une différence est détectée, mettez à jour le montant dans la fiche.
B8: 3. Mettez à jour le tableau :
B9: Ajoutez les informations de la facture (fournisseur, numéro de facture, échéance réelle).
B10: Changez le statut à "Dette fournisseur".
B12: Transition visuelle pour le suivi
B13: Utilisez une mise en forme conditionnelle pour identifier les fiches prêtes à être converties :
B14: Rouge : Engagement sans facture.
... B38: Une facture peut passer successivement par ces statuts :
B40: Étape | C40: Statut à indiquer sur la facture
B41: 1 | C41: En attente de paiement
B42: 2 | C42: Retenue pour paiement suivant (si applicable)
B43: 3 | C43: Payée le [date]
B46: 3. ✍️ Mise à jour des statuts à la main
B48: ✅ Recommandations :
B50: Barrer proprement l'ancien statut à l’encre (ne pas utiliser de correcteur blanc).
B52: Écrire clairement le nouveau statut juste à côté ou en dessous.
B54: Utiliser un stylo bleu ou noir pour la lisibilité.
B56: Ajouter vos initiales et la date de mise à jour, surtout si plusieurs personnes manipulent la facture.
B58: 📌 Exemple sur une facture :
B60: swift
B61: CopierModifier
B62: ~~En attente de paiement~~
B63: Retenue pour paiement fin juillet – MA – 12/07/2025
B65: puis :
... B76: 📁 Classement par statut avec intercalaires ou chemises de couleur :
B78: Couleur / Section | C78: Contenu
B79: 🔵 Bleu : À traiter | C79: Factures "en attente de paiement"
B80: 🟡 Jaune : À programmer | C80: Factures "retenues pour paiement suivant"
B81: 🟢 Vert : Payées | C81: Factures "réglées", avec mention de la date
B83: ✅ Astuces :
B85: Classer par date d’échéance à l’intérieur de chaque section.
B87: Joindre si besoin une fiche de suivi manuelle à chaque facture.

Sheet PLAN COMPTABLE

Sheet EVALUATION DETTES
A1: ENTITÉ | B1: DATE | C1: TYPE D’INFORMATION | D1: MONTANT (FCFA) | E1: DESCRIPTION | F1: DEMANDEUR | G1: DELAI | H1: ÉCHÉANCE | I1: STATUT
A2: ROYAL LT | B2: 45609 | C2: ENGAGEMENT | D2: 218300 | E2: EDITION FACTURES NORMALISEES A4 RECTO SIMPLE | G2: 0 | H2: =+Tableau15[[#This Row],[DATE]]+Tableau15[[#This Row],[DELAI]] -> 45609 | I2: EN ATTENTE DE PAIEMENT
A3: ROYAL LT | B3: 45664 | C3: ENGAGEMENT | D3: 250000 | E3: REPARATION CAMION A BOUAKE-PERIODE DECEMBRE 2024 | G3: 0 | H3: =+Tableau15[[#This Row],[DATE]]+Tableau15[[#This Row],[DELAI]] -> 45664 | I3: EN ATTENTE DE PAIEMENT
A4: SIGIB | B4: 45609 | C4: ENGAGEMENT | D4: 218300 | E4: EDITION FACTURES NORMALISEES A4 RECTO SIMPLE | G4: 0 | H4: =+Tableau15[[#This Row],[DATE]]+Tableau15[[#This Row],[DELAI]] -> 45609 | I4: EN ATTENTE DE PAIEMENT
A5: SIM BETON | B5: 45650 | C5: DETTES FOURNISSEURS | D5: 2550000 | E5: LOYER SITE DE PRODUCTION ABJ-4,5 MOIS_OPTIGESTION | G5: 0 | H5: =+Tableau15[[#This Row],[DATE]]+Tableau15[[#This Row],[DELAI]] -> 45650 | I5: NON REGLE
A6: SIM BETON | B6: 45665 | C6: ENGAGEMENT | D6: 82600 | E6: CARNET BL 3 FEUILLETS | G6: 0 | H6: =+Tableau15[[#This Row],[DATE]]+Tableau15[[#This Row],[DELAI]] -> 45665 | I6: EN ATTENTE DE PAIEMENT
A7: SIM BETON | B7: 45670 | C7: ENGAGEMENT | D7: 111000 | E7: FRAIS DE PRODUCTION SEMAINE DU 14 AU 19/01/2025-SITE BKE | G7: 0 | H7: =+Tableau15[[#This Row],[DATE]]+Tableau15[[#This Row],[DELAI]] -> 45670 | I7: EN ATTENTE DE PAIEMENT
A8: SIM BETON | B8: 45670 | C8: ENGAGEMENT | D8: 221375 | E8: FRAIS DE PRODUCTION SEMAINE DU 14 AU 19/01/2025-SITE ABJ | G8: 0 | H8: =+Tableau15[[#This Row],[DATE]]+Tableau15[[#This Row],[DELAI]] -> 45670 | I8: EN ATTENTE DE PAIEMENT
A9: SIM BETON | B9: 45670 | C9: ENGAGEMENT | D9: 93500 | E9: FRAIS DE PRODUCTION SEMAINE DU 14 AU 19/01/2025-SITE MAN | G9: 0 | H9: =+Tableau15[[#This Row],[DATE]]+Tableau15[[#This Row],[DELAI]] -> 45670 | I9: EN ATTENTE DE PAIEMENT
A10: SIM GROUP | B10: 45653 | C10: DETTES FOURNISSEURS | D10: =100000+473000+123000+42000 -> 738000 | E10: FACTURES GARAGE TS & FILS (04) | G10: 0 | H10: =+Tableau15[[#This Row],[DATE]]+Tableau15[[#This Row],[DELAI]] -> 45653 | I10: EN ATTENTE DE PAIEMENT
A11: SIM GROUP | B11: 45668 | C11: ENGAGEMENT | D11: 450000 | E11: CAUTION AGENT DE SECURITE ET FRAIS CREATION SIM BETON | G11: 0 | H11: =+Tableau15[[#This Row],[DATE]]+Tableau15[[#This Row],[DELAI]] -> 45668 | I11: EN ATTENTE DE PAIEMENT
A12: SINERGIE RESEAU | B12: 45941 | C12: ENGAGEMENT | D12: 200000 | E12: PRESTATION CIC-SAN PEDRO | G12: 0 | H12: =+Tableau15[[#This Row],[DATE]]+Tableau15[[#This Row],[DELAI]] -> 45941 | I12: EN ATTENTE DE PAIEMENT
A13: SINERGIE RESEAU | B13: 45466 | C13: FRAIS PROFESSIONNELS | D13: 43935 | E13: CARBURANT ET ACHAT MECHES-KOUAME SYLVIE | G13: 0 | H13: =+Tableau15[[#This Row],[DATE]]+Tableau15[[#This Row],[DELAI]] -> 45466 | I13: EN ATTENTE DE PAIEMENT
A14: SINERGIE RESEAU | B14: 45482 | C14: FRAIS PROFESSIONNELS | D14: 16500 | E14: CARBURANT ET ACHAT MECHES-KOUAME SYLVIE | G14: 0 | H14: =+Tableau15[[#This Row],[DATE]]+Tableau15[[#This Row],[DELAI]] -> 45482 | I14: EN ATTENTE DE PAIEMENT
A15: SINERGIE RESEAU | B15: 45486 | C15: FRAIS PROFESSIONNELS | D15: 16500 | E15: MO JOURNALIERE POUR PRESTATION-KOUAME SYLVIE | G15: 0 | H15: =+Tableau15[[#This Row],[DATE]]+Tableau15[[#This Row],[DELAI]] -> 45486 | I15: EN ATTENTE DE PAIEMENT
A16: SINERGIE RESEAU | B16: 45487 | C16: FRAIS PROFESSIONNELS | D16: 8080 | E16: FOUILLES ALEX-KOUAME SYLVIE | G16: 0 | H16: =+Tableau15[[#This Row],[DATE]]+Tableau15[[#This Row],[DELAI]] -> 45487 | I16: EN ATTENTE DE PAIEMENT
A17: SINERGIE RESEAU | B17: 45488 | C17: FRAIS PROFESSIONNELS | D17: 33000 | E17: PRESTATION INFRA DU 15/7/24-KOUAME SYLVIE | G17: 0 | H17: =+Tableau15[[#This Row],[DATE]]+Tableau15[[#This Row],[DELAI]] -> 45488 | I17: EN ATTENTE DE PAIEMENT
A18: SINERGIE RESEAU | B18: 45573 | C18: FRAIS PROFESSIONNELS | D18: 3500 | E18: TRANSPORT POUR LE RETRAIT DU BC N° 4 CIC-TIKANA | G18: 0 | H18: =+Tableau15[[#This Row],[DATE]]+Tableau15[[#This Row],[DELAI]] -> 45573 | I18: NON REMBOURSE
A19: SINERGIE RESEAU | B19: 45580 | C19: DETTES SOCIALES | D19: 458927 | E19: COTISATION CNPS 3T 2024 | G19: 0 | H19: =+Tableau15[[#This Row],[DATE]]+Tableau15[[#This Row],[DELAI]] -> 45580 | I19: EN ATTENTE DE PAIEMENT
A20: SINERGIE RESEAU | B20: 45581 | C20: FRAIS PROFESSIONNELS | D20: 40000 | E20: ACHAT OUTIL SLITTER-TIKANA | G20: 0 | H20: =+Tableau15[[#This Row],[DATE]]+Tableau15[[#This Row],[DELAI]] -> 45581 | I20: NON REMBOURSE
A21: SINERGIE RESEAU | B21: 45586 | C21: FRAIS PROFESSIONNELS | D21: 15000 | E21: FRAIS DE DEPLACEMENT YANGO CARGO ALLER-TIKANA | G21: 0 | H21: =+Tableau15[[#This Row],[DATE]]+Tableau15[[#This Row],[DELAI]] -> 45586 | I21: NON REMBOURSE
A22: SINERGIE RESEAU | B22: 45598 | C22: ENGAGEMENT | D22: 52500 | E22: FOUILLES IMPREVU | G22: 0 | H22: =+Tableau15[[#This Row],[DATE]]+Tableau15[[#This Row],[DELAI]] -> 45598 | I22: EN ATTENTE DE PAIEMENT
... A37: SINERGIE RESEAU | B37: 45670 | C37: ENGAGEMENT | D37: 525200 | E37: PRESTATION ELECTRICITE-CIC MAN | G37: 0 | H37: =+Tableau15[[#This Row],[DATE]]+Tableau15[[#This Row],[DELAI]] -> 45670 | I37: EN ATTENTE DE PAIEMENT
H38: =+Tableau15[[#This Row],[DATE]]+Tableau15[[#This Row],[DELAI]] -> 0
H39: =+Tableau15[[#This Row],[DATE]]+Tableau15[[#This Row],[DELAI]] -> 0
H40: =+Tableau15[[#This Row],[DATE]]+Tableau15[[#This Row],[DELAI]] -> 0
H41: =+Tableau15[[#This Row],[DATE]]+Tableau15[[#This Row],[DELAI]] -> 0
H42: =+Tableau15[[#This Row],[DATE]]+Tableau15[[#This Row],[DELAI]] -> 0
H43: =+Tableau15[[#This Row],[DATE]]+Tableau15[[#This Row],[DELAI]] -> 0
A44: Total | D44: =SUBTOTAL(109,Tableau15[MONTANT (FCFA)]) -> 10948542 | I44: =SUBTOTAL(103,Tableau15[STATUT]) -> 36

Sheet ECHEANCIER
A1: ENTITÉ | B1: FOURNISSEUR | C1: CONTACT | D1: TYPE DE DETTES | E1: TYPE DE DÉPENSE | F1: DETAIL DE LA DEPENSE | G1: NUMÉRO DE FACTURE | H1: DATE DE FACTURATION | I1: MONTANT TTC | J1: ÉCHÉANCE | K1: MONTANT ÉCHU | L1: MONTANT NON ÉCHU | M1: STATUT (PAYÉ / EN ATTENTE) | N1: DATE DE PAIEMENT
A2: SINERGIE RESEAU | B2: TRAORE MAMADOU P/C HAMED LOCATION | D2: HORS GROUPE | E2: ACHATS D 'EXPLOITATION | F2: LOCATIONS GRUE | I2: 1000000 | M2: EN ATTENTE
A3: SINERGIE RESEAU | B3: FARAH ET FRERES | D3: HORS GROUPE | E3: ACHATS D 'EXPLOITATION | F3: ACQUISITION DE 3 VEHICULES | I3: 5050000 | M3: EN ATTENTE
A4: SINERGIE RESEAU | B4: SANOGO | C4: 0103404600 | D4: HORS GROUPE | E4: ACHATS D 'EXPLOITATION | F4: GROUPE ELECTROGÈNE-LOCATION DE MARTEAUX PIQUEUR | I4: 350000 | M4: EN ATTENTE
A5: SINERGIE RESEAU | B5: KOUAME SYLVIE | D5: HORS GROUPE | E5: ACHATS D 'EXPLOITATION | F5: MATERIEL INFRA | I5: 1618400 | M5: EN ATTENTE
A6: SINERGIE RESEAU | B6: ENTREPRISE SAVANE | C6: 0700612128 | D6: HORS GROUPE | E6: ACHATS D 'EXPLOITATION | F6: LOCATION DE VEHICULE POUR ACTION INFRA | I6: 610000 | M6: EN ATTENTE
A7: SINERGIE RESEAU | B7: FOUILLES | D7: HORS GROUPE | E7: ACHATS D 'EXPLOITATION | F7: FOUILLES BETON (AVRIL, MAI, JUIN, JUILLET ET AOUT) 2024 | I7: 1014000 | M7: EN ATTENTE
A8: SINERGIE RESEAU | B8: FOUILLES | D8: HORS GROUPE | E8: ACHATS D 'EXPLOITATION | F8: FOUILLES METALLIQUES ( AVRIL, MAI, JUIN ET JUILLET) 2024 | I8: 1215500 | M8: EN ATTENTE
A9: SINERGIE RESEAU | B9: LOCATION ABOBO | D9: HORS GROUPE | E9: ACHATS D 'EXPLOITATION | F9: LOCATION DE BACHÉ | I9: 80000 | M9: EN ATTENTE
A10: SINERGIE RESEAU | B10: TEFR | D10: HORS GROUPE | E10: ACHATS D 'EXPLOITATION | F10: EQUIPE DE TIRAGE ABOBO / INNOV | I10: 147510 | M10: EN ATTENTE
A11: SINERGIE RESEAU | B11: ROYAL LOGISTIQUES | D11: INTRA-GROUPE | E11: ACHATS D 'EXPLOITATION | F11: LOCATIONS GRUE | I11: 10640000 | M11: EN ATTENTE
A12: SINERGIE RESEAU | B12: TEXTIPRINT | D12: INTRA-GROUPE | E12: ACHATS D 'EXPLOITATION | F12: PRÊT A TEXTPRINT | I12: 3136800 | M12: EN ATTENTE
A13: SINERGIE RESEAU | B13: SIGIB | D13: INTRA-GROUPE | E13: ACHATS D 'EXPLOITATION | F13: PRÊT A SIGIB | I13: 500000 | M13: EN ATTENTE
A14: SIGIB | B14: PERSONNEL | D14: INTRA-GROUPE | E14: FRAIS GENERAUX | F14: SALAIRE AOUT A OCTOBRE 2024 | H14: 45505 | I14: 1860000 | J14: 45596 | M14: EN ATTENTE
A15: SIGIB | B15: COULIBALY | D15: HORS GROUPE | E15: ACHATS D 'EXPLOITATION | F15: LOCATION DE LOGICIEL MAI A JUILLET 2024 | H15: 45413 | I15: 100000 | J15: 45504 | M15: EN ATTENTE
A16: SIGIB | B16: N'GORAN ULRICHE | C16: 0757288788 | D16: HORS GROUPE | E16: ACHATS D 'EXPLOITATION | F16: CREATION DE LOGO ET AFFICHE | H16: 45474 | I16: 25000 | J16: 45504 | M16: EN ATTENTE
A17: SIGIB | B17: KOFFI GERARD | C17: 0768054715 | D17: HORS GROUPE | E17: ACHATS D 'EXPLOITATION | F17: FOUILLES | H17: 45474 | I17: 70000 | J17: 45504 | M17: EN ATTENTE
A18: ROYAL LT | B18: KOUYATE | D18: HORS GROUPE | E18: ACHATS D 'EXPLOITATION | F18: MECANIQUE HYDROLIQUE GRUE ET PIECES DETACHEES | H18: 45222 | I18: 560000 | J18: 45222 | M18: EN ATTENTE
A19: ROYAL LT | B19: ADIMI | D19: HORS GROUPE | E19: ACHATS D 'EXPLOITATION | F19: AQUISITION D'UN TRACTEUR ROUTIER COULEUR VERTE | H19: 45199 | I19: 5000000 | J19: 45199 | M19: EN ATTENTE
A20: ROYAL LT | B20: KAMATE | D20: HORS GROUPE | E20: ACHATS D 'EXPLOITATION | F20: MECANIQUE DE CAMION BLEU-DEPANNAGE | H20: 45352 | I20: 90000 | J20: 45352 | M20: EN ATTENTE
A21: ROYAL LT | B21: SALIFOU | D21: HORS GROUPE | E21: ACHATS D 'EXPLOITATION | F21: MECANIQUE DE CAMION VERT-DEPANNAGE | H21: 45364 | I21: 400000 | J21: 45364 | M21: EN ATTENTE
A22: ROYAL LT | B22: SINERGIE RESEAU | D22: INTRA-GROUPE | E22: ACHATS D 'EXPLOITATION | F22: LOCATION ET IMPLANTATION DEC 2023-OCT 2024 | H22: 45200 | I22: 13650000 | J22: 45566 | M22: EN ATTENTE
A23: ROYAL LT | B23: SIM BETON CI | D23: INTRA-GROUPE | E23: ACHATS D 'EXPLOITATION | F23: LOCATION GRUE | H23: 45536 | I23: 6770000 | J23: 45536 | M23: EN ATTENTE
A24: ROYAL LT | B24: SIM BETON BF | D24: INTRA-GROUPE | E24: ACHATS D 'EXPLOITATION | F24: LOCATION GRUE | H24: 45566 | I24: 625000 | J24: 45566 | M24: EN ATTENTE
A25: ROYAL LT | B25: SIGIB | D25: INTRA-GROUPE | E25: ACHATS D 'EXPLOITATION | F25: LOCATION GRUE | H25: 45566 | I25: 150000 | J25: 45566 | M25: EN ATTENTE
A26: TEXTIPRINT | B26: BONAVENTURE | D26: HORS GROUPE | E26: ACHATS D 'EXPLOITATION | F26: DOCUMENT A DOS CARRE PPE 2023 | I26: 270000 | M26: EN ATTENTE
A27: TEXTIPRINT | B27: BONAVENTURE | D27: HORS GROUPE | E27: ACHATS D 'EXPLOITATION | F27: DOCUMENT A DOS CARRE PPE 0CTOBRE 2024 | I27: 145000 | M27: EN ATTENTE
A28: TEXTIPRINT | B28: SIGIB | D28: INTRA-GROUPE | E28: ACHATS D 'EXPLOITATION | F28: DETTE | I28: 1935000 | M28: EN ATTENTE
A29: TEXTIPRINT | B29: ZOUZOUA | D29: HORS GROUPE | E29: ACHATS D 'EXPLOITATION | F29: ACHAT DE BACHE 2022 | I29: 50000 | M29: EN ATTENTE
A30: TEXTIPRINT | B30: M. JD | D30: HORS GROUPE | E30: ACHATS D 'EXPLOITATION | F30: CONFECTION DE 38 TENUES MARS 2024 | I30: 150000 | M30: EN ATTENTE
A31: TEXTIPRINT | B31: GROUP HOREB | D31: HORS GROUPE | E31: ACHATS D 'EXPLOITATION | F31: IMPRESSION SUR 100 CHASUBLES SIKA M | I31: 50000 | M31: EN ATTENTE
A32: TEXTIPRINT | B32: ALYCARTOUCHE | D32: HORS GROUPE | E32: ACHATS D 'EXPLOITATION | F32: ACHAT DE BACHE FEVRIER 2024 | I32: 250000 | M32: EN ATTENTE
A33: TEXTIPRINT | B33: MALICK | D33: HORS GROUPE | E33: ACHATS D 'EXPLOITATION | F33: SOLDE CONFECTION DE SUPPORT METALLIQUE NSIA FEVRIER 2023 | I33: 30000 | M33: EN ATTENTE
A34: TEXTIPRINT | B34: WINNER PROD FIRMIN | D34: HORS GROUPE | E34: ACHATS D 'EXPLOITATION | F34: CONFECTION DE 676 PLAQUES EN PLEXIGLASS | I34: 150000 | M34: EN ATTENTE
A35: TEXTIPRINT | B35: GUIGUI ARMEL NATHAN IMPRIME | D35: HORS GROUPE | E35: ACHATS D 'EXPLOITATION | F35: CONFECTION DE 500 CALENDRIERS A3 PPE OCTOBRE 2024 | I35: 30000 | M35: EN ATTENTE
A36: TEXTIPRINT | B36: KOUAME SALOMON ET YAHIRI EMMANUEL | D36: HORS GROUPE | E36: ACHATS D 'EXPLOITATION | F36: DROITS A REVERSER | I36: 565462 | M36: EN ATTENTE
A37: SIM BETON | B37: SORO NOUHOUOLA ETIENNE | D37: INTRA-GROUPE | E37: ACHATS D 'EXPLOITATION | F37: PRÊT POUR LA PRODUCTION-RAPPORTS MENSUELS SIM BETON | I37: 2968862 | M37: EN ATTENTE
... A39: SIM BETON | B39: SORO NOUHOUOLA ETIENNE | D39: INTRA-GROUPE | E39: ACHATS D 'EXPLOITATION | F39: LOYER DU MAGASIN ANCIEN SITE | I39: 410000 | M39: EN ATTENTE
A40: =+UPPER("Total") -> TOTAL | I40: =SUBTOTAL(109,Tableau1[MONTANT TTC]) -> 61962714 | N40: =SUBTOTAL(103,Tableau1[DATE DE PAIEMENT]) -> 0

Sheet DONNEES
B2: ENTITÉ | D2: TYPE DE DETTE | E2: CAS DE FIGURE | G2: TYPE D’ INFORMATION | I2: CATEGORIE FINANCIERE | K2: ÉTAT DE LA DETTE | M2: STATUT BC | O2: TRANSACTION INTRACOMMERCIALE
B3: SIM GROUP | D3: FOURNISSEUR | E3: Facture fournisseur non encore réglée | G3: Créances Clients | I3: PRÊT BANCAIRE | K3: ÉCHU | M3: COMMANDÉ | O3: INTRA-GROUPE
B4: SINERGIE RESEAU | D4: FISCALE | E4: TVA collectée ou à reverser | G4: Dettes Fournisseurs | I4: LIGNE DE CRÉDIT | K4: À ÉCHOIR | M4: FACTURÉ | O4: HORS-GROUPE
B5: SIM BETON | D5: SOCIALE | E5: Cotisations sociales URSSAF, retraite, etc. | G5: Dettes Fiscales | I5: DÉCOUVERT BANCAIRE | M5: NON FACTURÉ
B6: ROYAL LT | D6: FINANCIÈRE-EMPRUNT | E6: Emprunt bancaire à rembourser | G6: Solde Bancaire
B7: SIGIB | D7: PERSONNEL-REMUNERATION | E7: Salaires ou primes dus | G7: Solde Caisse | K7: TAUX TVA
D8: PERSONNEL-AVANCE/REMB | E8: Avance/remboursement dû à un employé | G8: Créances Clients | K8: 0
D9: PRÊT INTERCO | E9: PRÊT ENTRE ENTITE | G9: Dettes Fournisseurs | K9: 0.09
G10: Dettes Fiscales | I10: POSTE TRESORERIE | K10: 0.18
G11: Solde Bancaire | I11: OBA
D12: TYPE D'ENGAGEMENT | G12: Solde Caisse | I12: BDU
D13: ENGAGEMENT PREVISIONNELLE | G13: Créances Clients | I13: UBA
D14: DETTE REELLE | G14: Dettes Fournisseurs | I14: GTBANK
G15: Dettes Fiscales | I15: COFINA
G16: Solde Bancaire | I16: CAISSE
D17: PERIODICITE | G17: Solde Caisse | I17: WAVE
D18: HEBDOMADAIRE | I18: ORANGE MONNEY
D19: QUINZAINE
D20: MENSUELLE
D21: BIMESTRIELLE
D22: TRIMESTRIELLE
D23: SEMESTRIELLE
D24: ANNUELLE

Sheet BASE DES ENGAGEMENTS
A1: ETAT DE LA DETTE ELARGIE
A3: ENTITE | B3: DATE DE SAISIE | C3: DATE_FICHE | D3: N° FICHE/DOSSIER | E3: N° FACTURE/REF | F3: TYPE D'ENGAGEMENT | G3: TYPE DE DETTE | H3: DEMANDEUR | I3: FOURNISSEUR/ORGANISME/TIERS | J3: TYPE TIERS HORS OU INTRA GROUPE | K3: NATURE | L3: DETAIL | M3: CENTRE IMPUTATION | N3: MONTANT HT | O3: TAUX TVA | P3: MONTANT TVA | Q3: MONTANT TTC | R3: MONTANT PAYÉ (FCFA) | S3: SOLDE RESTANT (FCFA) | T3: LITIGE DÉTECTÉ | U3: DÉTAILS LITIGE | V3: ÉTAT | W3: BON DE COMMANDE N° | X3: CONCORDANCE AVEC BC | Y3: OBSERVATIONS
A4: SIM BETON | C4: 45680 | D4: FD250123-1 | F4: ENGAGEMENT PREVISIONNELLE | H4: KOUAKOU BRICE VENANCE | K4: FRAIS DE MISSION | L4: CARBURANT | M4: USINE ABJ | N4: 15000 | O4: 0 | P4: =+Tableau2229[[#This Row],[MONTANT HT]]*Tableau2229[[#This Row],[TAUX TVA]] -> 0 | Q4: =+Tableau2229[[#This Row],[MONTANT HT]]+Tableau2229[[#This Row],[MONTANT TVA]] -> 15000 | S4: =+Tableau2229[[#This Row],[MONTANT TTC]]-Tableau2229[[#This Row],[MONTANT PAYÉ (FCFA)]] -> 15000
A5: SINERGIE RESEAU | C5: 45681 | D5: FD250124-2 | F5: ENGAGEMENT PREVISIONNELLE | H5: GBANHOUN SANDRINE | K5: ACHAT DE FOURNITURES | L5: ACHAT D AGREGAT | M5: PROJET AGL KM4 | N5: 240000 | O5: 0 | P5: =+Tableau2229[[#This Row],[MONTANT HT]]*Tableau2229[[#This Row],[TAUX TVA]] -> 0 | Q5: =+Tableau2229[[#This Row],[MONTANT HT]]+Tableau2229[[#This Row],[MONTANT TVA]] -> 240000 | S5: =+Tableau2229[[#This Row],[MONTANT TTC]]-Tableau2229[[#This Row],[MONTANT PAYÉ (FCFA)]] -> 240000 | V5: PAYE
A6: SIM BETON | C6: 45682 | D6: FD250125-1 | F6: ENGAGEMENT PREVISIONNELLE | H6: TANON ANDRE | K6: TRANSPORT | L6: TRANSPORT DE CIMENT ABJ BKE ET MAN | M6: USINE BKE-USINE MAN | N6: 1300000 | O6: 0 | P6: =+Tableau2229[[#This Row],[MONTANT HT]]*Tableau2229[[#This Row],[TAUX TVA]] -> 0 | Q6: =+Tableau2229[[#This Row],[MONTANT HT]]+Tableau2229[[#This Row],[MONTANT TVA]] -> 1300000 | S6: =+Tableau2229[[#This Row],[MONTANT TTC]]-Tableau2229[[#This Row],[MONTANT PAYÉ (FCFA)]] -> 1300000
A7: SIM BETON | C7: 45682 | D7: FD250125-2 | F7: ENGAGEMENT PREVISIONNELLE | H7: TANON ANDRE | K7: TRANSPORT | L7: TRANSPORT DE GRAVIER ABJ | M7: USINE ABJ | N7: 270000 | O7: 0 | P7: =+Tableau2229[[#This Row],[MONTANT HT]]*Tableau2229[[#This Row],[TAUX TVA]] -> 0 | Q7: =+Tableau2229[[#This Row],[MONTANT HT]]+Tableau2229[[#This Row],[MONTANT TVA]] -> 270000 | S7: =+Tableau2229[[#This Row],[MONTANT TTC]]-Tableau2229[[#This Row],[MONTANT PAYÉ (FCFA)]] -> 270000
A8: SIM BETON | C8: 45682 | D8: FD250125-3 | F8: ENGAGEMENT PREVISIONNELLE | H8: TANON ANDRE | K8: ACHAT DE FOURNITURES | L8: ACHAT DE 2 VOYAGE SABLE | M8: USINE ABJ | N8: 170000 | O8: 0 | P8: =+Tableau2229[[#This Row],[MONTANT HT]]*Tableau2229[[#This Row],[TAUX TVA]] -> 0 | Q8: =+Tableau2229[[#This Row],[MONTANT HT]]+Tableau2229[[#This Row],[MONTANT TVA]] -> 170000 | S8: =+Tableau2229[[#This Row],[MONTANT TTC]]-Tableau2229[[#This Row],[MONTANT PAYÉ (FCFA)]] -> 170000
A9: SIM BETON | C9: 45682 | D9: FD250125-4 | F9: ENGAGEMENT PREVISIONNELLE | H9: TANON ANDRE | K9: LOCATION | L9: LOCATION DE GRUE | M9: USINE BKE | N9: 150000 | O9: 0 | P9: =+Tableau2229[[#This Row],[MONTANT HT]]*Tableau2229[[#This Row],[TAUX TVA]] -> 0 | Q9: =+Tableau2229[[#This Row],[MONTANT HT]]+Tableau2229[[#This Row],[MONTANT TVA]] -> 150000 | S9: =+Tableau2229[[#This Row],[MONTANT TTC]]-Tableau2229[[#This Row],[MONTANT PAYÉ (FCFA)]] -> 150000
A10: SIM BETON | C10: 45684 | D10: FD250127-1 | F10: ENGAGEMENT PREVISIONNELLE | H10: TANON ANDRE | K10: ACHAT DE PETIT MATERIEL | L10: ACHAT DE PINCEAU NIV MACON | M10: USINE MAN | N10: 8000 | O10: 0 | P10: =+Tableau2229[[#This Row],[MONTANT HT]]*Tableau2229[[#This Row],[TAUX TVA]] -> 0 | Q10: =+Tableau2229[[#This Row],[MONTANT HT]]+Tableau2229[[#This Row],[MONTANT TVA]] -> 8000 | S10: =+Tableau2229[[#This Row],[MONTANT TTC]]-Tableau2229[[#This Row],[MONTANT PAYÉ (FCFA)]] -> 8000
A11: SIM BETON | C11: 45684 | D11: FD250127-2 | F11: ENGAGEMENT PREVISIONNELLE | H11: TANON ANDRE | K11: ACHAT DE FOURNITURES | L11: ACHAT DE BOULON, CLE,… | M11: USINE MAN | N11: 191000 | O11: 0 | P11: =+Tableau2229[[#This Row],[MONTANT HT]]*Tableau2229[[#This Row],[TAUX TVA]] -> 0 | Q11: =+Tableau2229[[#This Row],[MONTANT HT]]+Tableau2229[[#This Row],[MONTANT TVA]] -> 191000 | S11: =+Tableau2229[[#This Row],[MONTANT TTC]]-Tableau2229[[#This Row],[MONTANT PAYÉ (FCFA)]] -> 191000
A12: SIM BETON | C12: 45684 | D12: FD250127-3 | F12: ENGAGEMENT PREVISIONNELLE | H12: SORO ETIENNE | K12: ACHAT DE FOURNITURES | L12: FRAIS DE PRODUCTION DU 27/01/25 AU 01/02/25 | M12: USINE ABJ | N12: 111500 | O12: 0 | P12: =+Tableau2229[[#This Row],[MONTANT HT]]*Tableau2229[[#This Row],[TAUX TVA]] -> 0 | Q12: =+Tableau2229[[#This Row],[MONTANT HT]]+Tableau2229[[#This Row],[MONTANT TVA]] -> 111500 | S12: =+Tableau2229[[#This Row],[MONTANT TTC]]-Tableau2229[[#This Row],[MONTANT PAYÉ (FCFA)]] -> 111500
A13: SIM BETON | C13: 45684 | D13: FD250127-4 | F13: ENGAGEMENT PREVISIONNELLE | H13: SORO ETIENNE | K13: ACHAT DE FOURNITURES | L13: FRAIS DE PRODUCTION DU 27/01/25 AU 01/02/25 | M13: USINE BKE | N13: 147250 | O13: 0 | P13: =+Tableau2229[[#This Row],[MONTANT HT]]*Tableau2229[[#This Row],[TAUX TVA]] -> 0 | Q13: =+Tableau2229[[#This Row],[MONTANT HT]]+Tableau2229[[#This Row],[MONTANT TVA]] -> 147250 | S13: =+Tableau2229[[#This Row],[MONTANT TTC]]-Tableau2229[[#This Row],[MONTANT PAYÉ (FCFA)]] -> 147250
A14: SIM GROUP | C14: 45684 | D14: FD250127-5 | F14: ENGAGEMENT PREVISIONNELLE | H14: KONAN N'DRI | K14: ACHAT DE PETIT MATERIEL | L14: ACHAT D UN TELEPHONE PORTABLE | M14: TRESORERIE | N14: 67000 | O14: 0 | P14: =+Tableau2229[[#This Row],[MONTANT HT]]*Tableau2229[[#This Row],[TAUX TVA]] -> 0 | Q14: =+Tableau2229[[#This Row],[MONTANT HT]]+Tableau2229[[#This Row],[MONTANT TVA]] -> 67000 | S14: =+Tableau2229[[#This Row],[MONTANT TTC]]-Tableau2229[[#This Row],[MONTANT PAYÉ (FCFA)]] -> 67000
A15: SIM BETON | C15: 45684 | D15: FD250127-6 | F15: ENGAGEMENT PREVISIONNELLE | H15: GOSSAN P/C SORO | K15: MAIN ŒUVRE | L15: MO ARMATURIERS EQUIPE SEKOFOLE DU 06/01 -23/01/25 | M15: USINE ABJ | N15: 467500 | O15: 0 | P15: =+Tableau2229[[#This Row],[MONTANT HT]]*Tableau2229[[#This Row],[TAUX TVA]] -> 0 | Q15: =+Tableau2229[[#This Row],[MONTANT HT]]+Tableau2229[[#This Row],[MONTANT TVA]] -> 467500 | S15: =+Tableau2229[[#This Row],[MONTANT TTC]]-Tableau2229[[#This Row],[MONTANT PAYÉ (FCFA)]] -> 467500
A16: SIM BETON | C16: 45684 | D16: FD250127-7 | F16: ENGAGEMENT PREVISIONNELLE | H16: GOSSAN P/C FOFANA | K16: MAIN ŒUVRE | L16: MO ARMATURIERS EQUIPE BEAN DU 08/01 -16/01/25 | M16: USINE BKE | N16: 265000 | O16: 0 | P16: =+Tableau2229[[#This Row],[MONTANT HT]]*Tableau2229[[#This Row],[TAUX TVA]] -> 0 | Q16: =+Tableau2229[[#This Row],[MONTANT HT]]+Tableau2229[[#This Row],[MONTANT TVA]] -> 265000 | S16: =+Tableau2229[[#This Row],[MONTANT TTC]]-Tableau2229[[#This Row],[MONTANT PAYÉ (FCFA)]] -> 265000
A17: SIM BETON | C17: 45684 | D17: FD250127-8 | F17: ENGAGEMENT PREVISIONNELLE | H17: GOSSAN P/C ACHI | K17: MAIN ŒUVRE | L17: MO ARMATURIERS EQUIPE YAO DU 10/01 -23/01/25 | M17: USINE MAN | N17: 274000 | O17: 0 | P17: =+Tableau2229[[#This Row],[MONTANT HT]]*Tableau2229[[#This Row],[TAUX TVA]] -> 0 | Q17: =+Tableau2229[[#This Row],[MONTANT HT]]+Tableau2229[[#This Row],[MONTANT TVA]] -> 274000 | S17: =+Tableau2229[[#This Row],[MONTANT TTC]]-Tableau2229[[#This Row],[MONTANT PAYÉ (FCFA)]] -> 274000
... A27: SIM BETON | C27: 45696 | D27: FD250208-5 | F27: ENGAGEMENT PREVISIONNELLE | H27: KONAN N'DRI | K27: EMPRUNT INTER CO | L27: PRÊT RECU DE TEXTIPRINT | M27: SIM BETON | N27: 500000 | O27: 0 | P27: =+Tableau2229[[#This Row],[MONTANT HT]]*Tableau2229[[#This Row],[TAUX TVA]] -> 0 | Q27: =+Tableau2229[[#This Row],[MONTANT HT]]+Tableau2229[[#This Row],[MONTANT TVA]] -> 500000 | S27: =+Tableau2229[[#This Row],[MONTANT TTC]]-Tableau2229[[#This Row],[MONTANT PAYÉ (FCFA)]] -> 500000
A28: SIM BETON | C28: 45696 | D28: FD250208-6 | F28: ENGAGEMENT PREVISIONNELLE | H28: GOSSAN | K28: EMPRUNT | L28: EMPRUNT AUPRES DE L ADG | N28: 295000 | O28: 0 | P28: =+Tableau2229[[#This Row],[MONTANT HT]]*Tableau2229[[#This Row],[TAUX TVA]] -> 0 | Q28: =+Tableau2229[[#This Row],[MONTANT HT]]+Tableau2229[[#This Row],[MONTANT TVA]] -> 295000 | S28: =+Tableau2229[[#This Row],[MONTANT TTC]]-Tableau2229[[#This Row],[MONTANT PAYÉ (FCFA)]] -> 295000
A29: SIM BETON | C29: 45698 | D29: FD250210-1 | F29: ENGAGEMENT PREVISIONNELLE | H29: YEO NOUGNON | K29: TRANSPORT | L29: TRANSPORT DE GRAVIER | M29: SIM BETON | N29: 180000 | O29: 0 | P29: =+Tableau2229[[#This Row],[MONTANT HT]]*Tableau2229[[#This Row],[TAUX TVA]] -> 0 | Q29: =+Tableau2229[[#This Row],[MONTANT HT]]+Tableau2229[[#This Row],[MONTANT TVA]] -> 180000 | S29: =+Tableau2229[[#This Row],[MONTANT TTC]]-Tableau2229[[#This Row],[MONTANT PAYÉ (FCFA)]] -> 180000
A30: SIM BETON | C30: 45698 | D30: FD250210-2 | F30: ENGAGEMENT PREVISIONNELLE | H30: YEO NOUGNON | K30: ACHAT DE FOURNITURES | L30: FRAIS DE PRODUCTION DU 10/02/2025 AU 15/02/2025 | M30: SIM BETON | N30: 134250 | O30: 0 | P30: =+Tableau2229[[#This Row],[MONTANT HT]]*Tableau2229[[#This Row],[TAUX TVA]] -> 0 | Q30: =+Tableau2229[[#This Row],[MONTANT HT]]+Tableau2229[[#This Row],[MONTANT TVA]] -> 134250 | S30: =+Tableau2229[[#This Row],[MONTANT TTC]]-Tableau2229[[#This Row],[MONTANT PAYÉ (FCFA)]] -> 134250
A31: SIM BETON | C31: 45698 | D31: FD250210-3 | F31: ENGAGEMENT PREVISIONNELLE | H31: YEO NOUGNON | K31: ACHAT DE FOURNITURES | L31: ACHAT DE VOYAGE DE SABLE | M31: SIM BETON | N31: 300000 | O31: 0 | P31: =+Tableau2229[[#This Row],[MONTANT HT]]*Tableau2229[[#This Row],[TAUX TVA]] -> 0 | Q31: =+Tableau2229[[#This Row],[MONTANT HT]]+Tableau2229[[#This Row],[MONTANT TVA]] -> 300000 | S31: =+Tableau2229[[#This Row],[MONTANT TTC]]-Tableau2229[[#This Row],[MONTANT PAYÉ (FCFA)]] -> 300000
A32: SIM BETON | C32: 45698 | D32: FD250210-4 | F32: ENGAGEMENT PREVISIONNELLE | H32: YEO NOUGNON | K32: ACHAT DE FOURNITURES | L32: LOCATION GROUPE ELECTROGENE | M32: SIM BETON | N32: 75000 | O32: 0 | P32: =+Tableau2229[[#This Row],[MONTANT HT]]*Tableau2229[[#This Row],[TAUX TVA]] -> 0 | Q32: =+Tableau2229[[#This Row],[MONTANT HT]]+Tableau2229[[#This Row],[MONTANT TVA]] -> 75000 | S32: =+Tableau2229[[#This Row],[MONTANT TTC]]-Tableau2229[[#This Row],[MONTANT PAYÉ (FCFA)]] -> 75000
A33: SIM BETON | C33: 45698 | D33: FD250210-5 | F33: ENGAGEMENT PREVISIONNELLE | H33: YEO DG | K33: EMPRUNT | L33: EMPRUNT AUPRES DU DG LOCATION ROYAL BEOUIN-BOUAKE | M33: SIM BETON | N33: 250000 | O33: 0 | P33: =+Tableau2229[[#This Row],[MONTANT HT]]*Tableau2229[[#This Row],[TAUX TVA]] -> 0 | Q33: =+Tableau2229[[#This Row],[MONTANT HT]]+Tableau2229[[#This Row],[MONTANT TVA]] -> 250000 | S33: =+Tableau2229[[#This Row],[MONTANT TTC]]-Tableau2229[[#This Row],[MONTANT PAYÉ (FCFA)]] -> 250000
A34: SIM BETON | C34: 45698 | D34: FD250210-6 | F34: ENGAGEMENT PREVISIONNELLE | H34: AHUI SYNTHIA | K34: ACHAT DE FOURNITURES | L34: FRAIS DE CARBURANT POUR ROYAL | M34: SIM BETON | N34: 230000 | O34: 0 | P34: =+Tableau2229[[#This Row],[MONTANT HT]]*Tableau2229[[#This Row],[TAUX TVA]] -> 0 | Q34: =+Tableau2229[[#This Row],[MONTANT HT]]+Tableau2229[[#This Row],[MONTANT TVA]] -> 230000 | S34: =+Tableau2229[[#This Row],[MONTANT TTC]]-Tableau2229[[#This Row],[MONTANT PAYÉ (FCFA)]] -> 230000
A35: SIM BETON | C35: 45698 | D35: FD250210-7 | F35: ENGAGEMENT PREVISIONNELLE | H35: BORIS MADOU | K35: ACHAT DE SERVICE | L35: ACHAT DE MO DES ARMATURES | M35: SIM BETON | N35: 100000 | O35: 0 | P35: =+Tableau2229[[#This Row],[MONTANT HT]]*Tableau2229[[#This Row],[TAUX TVA]] -> 0 | Q35: =+Tableau2229[[#This Row],[MONTANT HT]]+Tableau2229[[#This Row],[MONTANT TVA]] -> 100000 | S35: =+Tableau2229[[#This Row],[MONTANT TTC]]-Tableau2229[[#This Row],[MONTANT PAYÉ (FCFA)]] -> 100000
A36: SIM GROUP | C36: 45698 | D36: FD250210-8 | E36: 120 | F36: DETTE REELLE | G36: FOURNISSEUR | H36: KONAN N'DRI | I36: CIE | J36: HG | K36: AUTRES ENERGIES ELECTRICITE | L36: CONSOMMATION ELECTRICITE 04/10/2024 AU 04/12/2024 | M36: SIM GROUP | N36: 322915 | O36: 0.18 | P36: =+Tableau2229[[#This Row],[MONTANT HT]]*Tableau2229[[#This Row],[TAUX TVA]] -> 58124.7 | Q36: =+Tableau2229[[#This Row],[MONTANT HT]]+Tableau2229[[#This Row],[MONTANT TVA]] -> 381039.7 | S36: =+Tableau2229[[#This Row],[MONTANT TTC]]-Tableau2229[[#This Row],[MONTANT PAYÉ (FCFA)]] -> 381039.7
A37: SIM GROUP | C37: 45698 | D37: FD250210-9 | E37: 0211202401 | F37: DETTE REELLE | G37: FOURNISSEUR | H37: KONAN N'DRI | I37: SODECI | J37: HG | K37: AUTRES ENERGIES EAU | L37: CONSOMMATION EAU DES PERIODES DE SEPT, OCT ET NOV 2024 | M37: SIM GROUP | N37: 17875 | O37: 0.18 | P37: =+Tableau2229[[#This Row],[MONTANT HT]]*Tableau2229[[#This Row],[TAUX TVA]] -> 3217.5 | Q37: =+Tableau2229[[#This Row],[MONTANT HT]]+Tableau2229[[#This Row],[MONTANT TVA]] -> 21092.5 | S37: =+Tableau2229[[#This Row],[MONTANT TTC]]-Tableau2229[[#This Row],[MONTANT PAYÉ (FCFA)]] -> 21092.5
A38: SIM BETON | C38: 45698 | D38: FD250210-10 | F38: ENGAGEMENT PREVISIONNELLE | G38: FOURNISSEUR | H38: KONAN N'DRI | J38: IG | K38: LOCATION | L38: LOCATION DE 02 CAMIONS | M38: SIM GROUP | N38: 350000 | O38: 0 | P38: =+Tableau2229[[#This Row],[MONTANT HT]]*Tableau2229[[#This Row],[TAUX TVA]] -> 0 | Q38: =+Tableau2229[[#This Row],[MONTANT HT]]+Tableau2229[[#This Row],[MONTANT TVA]] -> 350000 | S38: =+Tableau2229[[#This Row],[MONTANT TTC]]-Tableau2229[[#This Row],[MONTANT PAYÉ (FCFA)]] -> 350000
A39: SIM BETON | C39: 45698 | D39: FD250210-11 | F39: ENGAGEMENT PREVISIONNELLE | H39: TANON ANDRE | K39: FOURNITURE DE BUREAU | L39: CARNET DE BL A 3 FEUILLETS | M39: SIM BETON | N39: 82600 | O39: 0 | P39: =+Tableau2229[[#This Row],[MONTANT HT]]*Tableau2229[[#This Row],[TAUX TVA]] -> 0 | Q39: =+Tableau2229[[#This Row],[MONTANT HT]]+Tableau2229[[#This Row],[MONTANT TVA]] -> 82600 | S39: =+Tableau2229[[#This Row],[MONTANT TTC]]-Tableau2229[[#This Row],[MONTANT PAYÉ (FCFA)]] -> 82600
A40: SINERGIE RESEAU | C40: 45575 | D40: FD241010-1 | F40: ENGAGEMENT PREVISIONNELLE | H40: GBANHOUN SANDRINE | J40: IG | K40: ACHAT DE SERVICE | L40: PRESTATION D'IMPLANTATION DE PBA DU 10/10/2024 | M40: CIC SAN PEDRO | N40: 200000 | O40: 0 | P40: =+Tableau2229[[#This Row],[MONTANT HT]]*Tableau2229[[#This Row],[TAUX TVA]] -> 0 | Q40: =+Tableau2229[[#This Row],[MONTANT HT]]+Tableau2229[[#This Row],[MONTANT TVA]] -> 200000 | S40: =+Tableau2229[[#This Row],[MONTANT TTC]]-Tableau2229[[#This Row],[MONTANT PAYÉ (FCFA)]] -> 200000
A41: SINERGIE RESEAU | C41: 45541 | D41: FD240906-1 | E41: 00434636 | F41: ENGAGEMENT PREVISIONNELLE | G41: FOURNISSEUR | H41: TIKANA FATIMA | I41: ENTREPRISE SAVANE | J41: HG | K41: LOCATION | L41: LOCATION D'UN PICK UP-1MOIS-TX ABIDJAN | M41: INFRA | N41: 702000 | O41: 0 | P41: =+Tableau2229[[#This Row],[MONTANT HT]]*Tableau2229[[#This Row],[TAUX TVA]] -> 0 | Q41: =+Tableau2229[[#This Row],[MONTANT HT]]+Tableau2229[[#This Row],[MONTANT TVA]] -> 702000 | S41: =+Tableau2229[[#This Row],[MONTANT TTC]]-Tableau2229[[#This Row],[MONTANT PAYÉ (FCFA)]] -> 702000
A42: SIM BETON | C42: 45618 | D42: FD241122-1 | F42: ENGAGEMENT PREVISIONNELLE | H42: DOSSO MEDJOUA | J42: HG | K42: ACHAT DE SERVICE | L42: FOURNITURES ET CORRECTION DE MOULE | M42: USINE ABJ | N42: 13180000 | O42: 0 | P42: =+Tableau2229[[#This Row],[MONTANT HT]]*Tableau2229[[#This Row],[TAUX TVA]] -> 0 | Q42: =+Tableau2229[[#This Row],[MONTANT HT]]+Tableau2229[[#This Row],[MONTANT TVA]] -> 13180000 | S42: =+Tableau2229[[#This Row],[MONTANT TTC]]-Tableau2229[[#This Row],[MONTANT PAYÉ (FCFA)]] -> 13180000
A43: SINERGIE RESEAU | C43: 45575 | D43: FD241104-1 | F43: ENGAGEMENT PREVISIONNELLE | H43: KOUAME SYLVIE | K43: ACHAT DE SERVICE | L43: ACHAT POUR PRESTATION INFRA FTTH DU 04/11/2024 | M43: CAMUSAT FTTH | N43: 22500 | O43: 0 | P43: =+Tableau2229[[#This Row],[MONTANT HT]]*Tableau2229[[#This Row],[TAUX TVA]] -> 0 | Q43: =+Tableau2229[[#This Row],[MONTANT HT]]+Tableau2229[[#This Row],[MONTANT TVA]] -> 22500 | S43: =+Tableau2229[[#This Row],[MONTANT TTC]]-Tableau2229[[#This Row],[MONTANT PAYÉ (FCFA)]] -> 22500
A44: SINERGIE RESEAU | C44: 45586 | D44: FD241021-1 | F44: ENGAGEMENT PREVISIONNELLE | H44: KOUAME SYLVIE | K44: ACHAT DE SERVICE | L44: TRANSPORT ALLER PAR YANGO CARGO POUR PRESTATION | M44: CAMUSAT FTTH | N44: 15000 | O44: 0 | P44: =+Tableau2229[[#This Row],[MONTANT HT]]*Tableau2229[[#This Row],[TAUX TVA]] -> 0 | Q44: =+Tableau2229[[#This Row],[MONTANT HT]]+Tableau2229[[#This Row],[MONTANT TVA]] -> 15000 | R44: 7000 | S44: =+Tableau2229[[#This Row],[MONTANT TTC]]-Tableau2229[[#This Row],[MONTANT PAYÉ (FCFA)]] -> 8000
A45: SINERGIE RESEAU | C45: 45586 | D45: FD241021-2 | F45: ENGAGEMENT PREVISIONNELLE | H45: TIKANA FATIMA | K45: ACHAT DE SERVICE | L45: ACHAT POUR PRESTATION PM DU 21/10/24 | M45: CIC PM | N45: 128000 | O45: 0 | P45: =+Tableau2229[[#This Row],[MONTANT HT]]*Tableau2229[[#This Row],[TAUX TVA]] -> 0 | Q45: =+Tableau2229[[#This Row],[MONTANT HT]]+Tableau2229[[#This Row],[MONTANT TVA]] -> 128000 | S45: =+Tableau2229[[#This Row],[MONTANT TTC]]-Tableau2229[[#This Row],[MONTANT PAYÉ (FCFA)]] -> 128000
A46: SINERGIE RESEAU | C46: 45596 | D46: FD241031-3 | F46: ENGAGEMENT PREVISIONNELLE | H46: KOFFI LAURA | K46: ACHAT DE SERVICE | L46: ACHAT DE PRESTATION PM DU 31/10/24 | M46: CIC PM | N46: 115000 | O46: 0 | P46: =+Tableau2229[[#This Row],[MONTANT HT]]*Tableau2229[[#This Row],[TAUX TVA]] -> 0 | Q46: =+Tableau2229[[#This Row],[MONTANT HT]]+Tableau2229[[#This Row],[MONTANT TVA]] -> 115000 | S46: =+Tableau2229[[#This Row],[MONTANT TTC]]-Tableau2229[[#This Row],[MONTANT PAYÉ (FCFA)]] -> 115000
A47: SINERGIE RESEAU | C47: 45617 | D47: FD241121-1 | F47: ENGAGEMENT PREVISIONNELLE | H47: KOFFI LAURA | K47: ACHAT DE SERVICE | L47: ACHAT DE PRESTATION PM DU 21/11/24 | M47: CIC PM | N47: 36000 | O47: 0 | P47: =+Tableau2229[[#This Row],[MONTANT HT]]*Tableau2229[[#This Row],[TAUX TVA]] -> 0 | Q47: =+Tableau2229[[#This Row],[MONTANT HT]]+Tableau2229[[#This Row],[MONTANT TVA]] -> 36000 | S47: =+Tableau2229[[#This Row],[MONTANT TTC]]-Tableau2229[[#This Row],[MONTANT PAYÉ (FCFA)]] -> 36000
A48: SIGIB | C48: 45609 | D48: FD241113-1 | F48: ENGAGEMENT PREVISIONNELLE | H48: KONAN N'DRI | K48: FOURNITURE DE BUREAU | L48: ACHAT DE FACTURE NORMALISE | M48: SIGIB | N48: 218300 | O48: 0 | P48: =+Tableau2229[[#This Row],[MONTANT HT]]*Tableau2229[[#This Row],[TAUX TVA]] -> 0 | Q48: =+Tableau2229[[#This Row],[MONTANT HT]]+Tableau2229[[#This Row],[MONTANT TVA]] -> 218300 | S48: =+Tableau2229[[#This Row],[MONTANT TTC]]-Tableau2229[[#This Row],[MONTANT PAYÉ (FCFA)]] -> 218300
A49: SINERGIE RESEAU | C49: 45573 | D49: FD241008-1 | F49: ENGAGEMENT PREVISIONNELLE | H49: KONAN N'DRI | K49: TRANSPORT | L49: TRANSPORT POUR LE RETRAIT DU BC N° 004 CIC | M49: SINERGIE | N49: 3500 | O49: 0 | P49: =+Tableau2229[[#This Row],[MONTANT HT]]*Tableau2229[[#This Row],[TAUX TVA]] -> 0 | Q49: =+Tableau2229[[#This Row],[MONTANT HT]]+Tableau2229[[#This Row],[MONTANT TVA]] -> 3500 | S49: =+Tableau2229[[#This Row],[MONTANT TTC]]-Tableau2229[[#This Row],[MONTANT PAYÉ (FCFA)]] -> 3500
A50: SINERGIE RESEAU | C50: 45595 | D50: FD241030-1 | F50: ENGAGEMENT PREVISIONNELLE | H50: EPONON EMMANUEL | K50: TRANSPORT | L50: TRANSPORT ET SOIN MEDICAUX D UN FOUILLEUR BLESSE | M50: SINERGIE | N50: 8000 | O50: 0 | P50: =+Tableau2229[[#This Row],[MONTANT HT]]*Tableau2229[[#This Row],[TAUX TVA]] -> 0 | Q50: =+Tableau2229[[#This Row],[MONTANT HT]]+Tableau2229[[#This Row],[MONTANT TVA]] -> 8000 | S50: =+Tableau2229[[#This Row],[MONTANT TTC]]-Tableau2229[[#This Row],[MONTANT PAYÉ (FCFA)]] -> 8000
A51: SINERGIE RESEAU | C51: 45595 | D51: FD241030-2 | E51: 001658 | F51: DETTE REELLE | G51: FOURNISSEUR | H51: EPONON EMMANUEL | I51: WATTA CONSTRUCTION SA | K51: MISSION | L51: FRAIS HEBERGEMENT DU 30 AU 31/10/2024 | M51: SIM GROUP | N51: 30000 | O51: 0 | P51: =+Tableau2229[[#This Row],[MONTANT HT]]*Tableau2229[[#This Row],[TAUX TVA]] -> 0 | Q51: =+Tableau2229[[#This Row],[MONTANT HT]]+Tableau2229[[#This Row],[MONTANT TVA]] -> 30000 | S51: =+Tableau2229[[#This Row],[MONTANT TTC]]-Tableau2229[[#This Row],[MONTANT PAYÉ (FCFA)]] -> 30000
A52: SINERGIE RESEAU | C52: 45600 | D52: FD2401104-1 | F52: ENGAGEMENT PREVISIONNELLE | H52: KOFFI LAURA | K52: ACHAT DE SERVICE | L52: ACHAT DE PRESTATION PM DU 04/11/24 | M52: CIC PM | N52: 127000 | O52: 0 | P52: =+Tableau2229[[#This Row],[MONTANT HT]]*Tableau2229[[#This Row],[TAUX TVA]] -> 0 | Q52: =+Tableau2229[[#This Row],[MONTANT HT]]+Tableau2229[[#This Row],[MONTANT TVA]] -> 127000 | S52: =+Tableau2229[[#This Row],[MONTANT TTC]]-Tableau2229[[#This Row],[MONTANT PAYÉ (FCFA)]] -> 127000
A53: ROYAL | C53: 45609 | D53: FD241113-1 | F53: ENGAGEMENT PREVISIONNELLE | H53: KONAN N'DRI | K53: FOURNITURE DE BUREAU | L53: ACHAT DE FACTURE NORMALISE | M53: ROYAL | N53: 218300 | O53: 0 | P53: =+Tableau2229[[#This Row],[MONTANT HT]]*Tableau2229[[#This Row],[TAUX TVA]] -> 0 | Q53: =+Tableau2229[[#This Row],[MONTANT HT]]+Tableau2229[[#This Row],[MONTANT TVA]] -> 218300 | S53: =+Tableau2229[[#This Row],[MONTANT TTC]]-Tableau2229[[#This Row],[MONTANT PAYÉ (FCFA)]] -> 218300
A54: SINERGIE RESEAU | C54: 45580 | D54: FD241015-1 | F54: ENGAGEMENT PREVISIONNELLE | H54: TIKANA FATIMA | K54: CHARGE SOCIALES | L54: COTISATION CNPS T3 2024 | M54: SINERGIE | N54: 458927 | O54: 0 | P54: =+Tableau2229[[#This Row],[MONTANT HT]]*Tableau2229[[#This Row],[TAUX TVA]] -> 0 | Q54: =+Tableau2229[[#This Row],[MONTANT HT]]+Tableau2229[[#This Row],[MONTANT TVA]] -> 458927 | S54: =+Tableau2229[[#This Row],[MONTANT TTC]]-Tableau2229[[#This Row],[MONTANT PAYÉ (FCFA)]] -> 458927
A55: SINERGIE RESEAU | C55: 45598 | D55: FD241102-1 | F55: ENGAGEMENT PREVISIONNELLE | H55: KOFFI LAURA | K55: ACHAT DE SERVICE | L55: ACHAT DE PRESTATION PM DU 02/11/24 | M55: CIC PM | N55: 93500 | O55: 0 | P55: =+Tableau2229[[#This Row],[MONTANT HT]]*Tableau2229[[#This Row],[TAUX TVA]] -> 0 | Q55: =+Tableau2229[[#This Row],[MONTANT HT]]+Tableau2229[[#This Row],[MONTANT TVA]] -> 93500 | R55: 41000 | S55: =+Tableau2229[[#This Row],[MONTANT TTC]]-Tableau2229[[#This Row],[MONTANT PAYÉ (FCFA)]] -> 52500
A56: SINERGIE RESEAU | C56: 45601 | D56: FD241105-1 | F56: ENGAGEMENT PREVISIONNELLE | H56: KOFFI LAURA | K56: ACHAT DE SERVICE | L56: ACHAT DE PRESTATION PM DU 05/11/24 | M56: CIC PM | N56: 242000 | O56: 0 | P56: =+Tableau2229[[#This Row],[MONTANT HT]]*Tableau2229[[#This Row],[TAUX TVA]] -> 0 | Q56: =+Tableau2229[[#This Row],[MONTANT HT]]+Tableau2229[[#This Row],[MONTANT TVA]] -> 242000 | S56: =+Tableau2229[[#This Row],[MONTANT TTC]]-Tableau2229[[#This Row],[MONTANT PAYÉ (FCFA)]] -> 242000
A57: SINERGIE RESEAU | C57: 45601 | D57: FD240713-1 | F57: ENGAGEMENT PREVISIONNELLE | H57: KOUAME SYLVIE | K57: ACHAT DE SERVICE | L57: ACHAT DE PRESTATION PM DU 13/07/24 | M57: CIC PM | N57: 16500 | O57: 0 | P57: =+Tableau2229[[#This Row],[MONTANT HT]]*Tableau2229[[#This Row],[TAUX TVA]] -> 0 | Q57: =+Tableau2229[[#This Row],[MONTANT HT]]+Tableau2229[[#This Row],[MONTANT TVA]] -> 16500 | S57: =+Tableau2229[[#This Row],[MONTANT TTC]]-Tableau2229[[#This Row],[MONTANT PAYÉ (FCFA)]] -> 16500
A58: SINERGIE RESEAU | C58: 45581 | D58: FD241016-1 | F58: ENGAGEMENT PREVISIONNELLE | H58: KOUAME SYLVIE | K58: ACHAT DE SERVICE | L58: LOCATION VEHICULE, ACHAT SLITTER ET COLLE FORTE | M58: CAMUSAT FTTH | N58: 86000 | O58: 0 | P58: =+Tableau2229[[#This Row],[MONTANT HT]]*Tableau2229[[#This Row],[TAUX TVA]] -> 0 | Q58: =+Tableau2229[[#This Row],[MONTANT HT]]+Tableau2229[[#This Row],[MONTANT TVA]] -> 86000 | R58: 40000 | S58: =+Tableau2229[[#This Row],[MONTANT TTC]]-Tableau2229[[#This Row],[MONTANT PAYÉ (FCFA)]] -> 46000
A59: SIM BETON | C59: 45647 | D59: FD241221-1 | F59: ENGAGEMENT PREVISIONNELLE | H59: KOUAKOU BRICE VENANCE | K59: ENTRETIEN ET REPARATION | L59: VIDANGE VEHICULE DU COMMERCIALE | M59: SIM BETON | N59: 28500 | O59: 0 | P59: =+Tableau2229[[#This Row],[MONTANT HT]]*Tableau2229[[#This Row],[TAUX TVA]] -> 0 | Q59: =+Tableau2229[[#This Row],[MONTANT HT]]+Tableau2229[[#This Row],[MONTANT TVA]] -> 28500 | S59: =+Tableau2229[[#This Row],[MONTANT TTC]]-Tableau2229[[#This Row],[MONTANT PAYÉ (FCFA)]] -> 28500
A60: SINERGIE RESEAU | C60: 45487 | D60: FD240714-1 | F60: ENGAGEMENT PREVISIONNELLE | H60: KOUAME SYLVIE | K60: ACHAT DE SERVICE | L60: FOUILLE ALEX ET TX DU 14/07/2024 | M60: CIC PM | N60: 8080 | O60: 0 | P60: =+Tableau2229[[#This Row],[MONTANT HT]]*Tableau2229[[#This Row],[TAUX TVA]] -> 0 | Q60: =+Tableau2229[[#This Row],[MONTANT HT]]+Tableau2229[[#This Row],[MONTANT TVA]] -> 8080 | R60: 8080 | S60: =+Tableau2229[[#This Row],[MONTANT TTC]]-Tableau2229[[#This Row],[MONTANT PAYÉ (FCFA)]] -> 0
A61: SINERGIE RESEAU | C61: 45610 | D61: FD241124-1 | F61: ENGAGEMENT PREVISIONNELLE | H61: KOUAME SYLVIE | K61: TRANSPORT | L61: TRANSPORT POUR VALIDATION D ATTACHEMENT | M61: CAMUSAT FTTH | N61: 7850 | O61: 0 | P61: =+Tableau2229[[#This Row],[MONTANT HT]]*Tableau2229[[#This Row],[TAUX TVA]] -> 0 | Q61: =+Tableau2229[[#This Row],[MONTANT HT]]+Tableau2229[[#This Row],[MONTANT TVA]] -> 7850 | R61: 7850 | S61: =+Tableau2229[[#This Row],[MONTANT TTC]]-Tableau2229[[#This Row],[MONTANT PAYÉ (FCFA)]] -> 0
A62: SINERGIE RESEAU | C62: 45647 | D62: FD241221-1 | F62: ENGAGEMENT PREVISIONNELLE | H62: KOUAME SYLVIE | K62: ACHAT D EQUIPEMENT | L62: ACHAT DE MATERIELS ET OUTILLAGES | M62: INFRA | N62: 3256450 | O62: 0 | P62: =+Tableau2229[[#This Row],[MONTANT HT]]*Tableau2229[[#This Row],[TAUX TVA]] -> 0 | Q62: =+Tableau2229[[#This Row],[MONTANT HT]]+Tableau2229[[#This Row],[MONTANT TVA]] -> 3256450 | R62: 1000000 | S62: =+Tableau2229[[#This Row],[MONTANT TTC]]-Tableau2229[[#This Row],[MONTANT PAYÉ (FCFA)]] -> 2256450
A63: SINERGIE RESEAU | C63: 45604 | D63: FD241108-1 | F63: ENGAGEMENT PREVISIONNELLE | H63: KOUAME SYLVIE | K63: ACHAT DE SERVICE | L63: FRAIS DE RELUIRE | M63: INFRA | N63: 3900 | O63: 0 | P63: =+Tableau2229[[#This Row],[MONTANT HT]]*Tableau2229[[#This Row],[TAUX TVA]] -> 0 | Q63: =+Tableau2229[[#This Row],[MONTANT HT]]+Tableau2229[[#This Row],[MONTANT TVA]] -> 3900 | S63: =+Tableau2229[[#This Row],[MONTANT TTC]]-Tableau2229[[#This Row],[MONTANT PAYÉ (FCFA)]] -> 3900
A64: SINERGIE RESEAU | C64: 45586 | D64: FD241021-1 | F64: ENGAGEMENT PREVISIONNELLE | H64: GBANHOUN SANDRINE | K64: TRANSPORT | L64: TRANSPORT DU TECHNICIEN POUR VISITE A SICMA | M64: INNOV TECH | N64: 5000 | O64: 0 | P64: =+Tableau2229[[#This Row],[MONTANT HT]]*Tableau2229[[#This Row],[TAUX TVA]] -> 0 | Q64: =+Tableau2229[[#This Row],[MONTANT HT]]+Tableau2229[[#This Row],[MONTANT TVA]] -> 5000 | S64: =+Tableau2229[[#This Row],[MONTANT TTC]]-Tableau2229[[#This Row],[MONTANT PAYÉ (FCFA)]] -> 5000
A65: SINERGIE RESEAU | C65: 45482 | D65: FD240709-1 | F65: ENGAGEMENT PREVISIONNELLE | H65: KOUAME SYLVIE | K65: ACHAT DE SERVICE | L65: ACHAT DE PRESTATION PM DU 09/07/24 | M65: CIC PM | N65: 16500 | O65: 0 | P65: =+Tableau2229[[#This Row],[MONTANT HT]]*Tableau2229[[#This Row],[TAUX TVA]] -> 0 | Q65: =+Tableau2229[[#This Row],[MONTANT HT]]+Tableau2229[[#This Row],[MONTANT TVA]] -> 16500 | S65: =+Tableau2229[[#This Row],[MONTANT TTC]]-Tableau2229[[#This Row],[MONTANT PAYÉ (FCFA)]] -> 16500
A66: SINERGIE RESEAU | C66: 45488 | D66: FD240715-1 | F66: ENGAGEMENT PREVISIONNELLE | H66: KOUAME SYLVIE | K66: ACHAT DE SERVICE | L66: ACHAT DE PRESTATION PM DU 09/07/24 | M66: CIC PM | N66: 93500 | O66: 0 | P66: =+Tableau2229[[#This Row],[MONTANT HT]]*Tableau2229[[#This Row],[TAUX TVA]] -> 0 | Q66: =+Tableau2229[[#This Row],[MONTANT HT]]+Tableau2229[[#This Row],[MONTANT TVA]] -> 93500 | S66: =+Tableau2229[[#This Row],[MONTANT TTC]]-Tableau2229[[#This Row],[MONTANT PAYÉ (FCFA)]] -> 93500
A67: SINERGIE RESEAU | C67: 45466 | D67: FD240623-1 | F67: ENGAGEMENT PREVISIONNELLE | H67: KOUAME SYLVIE | K67: ACHAT DE SERVICE | L67: ACHAT DE PRESTATION PM DU 23/06/24 | M67: INFRA | N67: 43935 | O67: 0 | P67: =+Tableau2229[[#This Row],[MONTANT HT]]*Tableau2229[[#This Row],[TAUX TVA]] -> 0 | Q67: =+Tableau2229[[#This Row],[MONTANT HT]]+Tableau2229[[#This Row],[MONTANT TVA]] -> 43935 | S67: =+Tableau2229[[#This Row],[MONTANT TTC]]-Tableau2229[[#This Row],[MONTANT PAYÉ (FCFA)]] -> 43935
A68: SIM GROUP | B68: 45723 | C68: 45699 | D68: FD250211 | F68: ENGAGEMENT PREVISIONNELLE | H68: N'GUESSAN ARMELLE | K68: ACHAT DE SERVICE | L68: FRAIS D'ETABLISSEMENT DE DOCUMENTS ADMINISTRATIF | M68: SIM GROUP | N68: 225000 | O68: 0 | P68: =+Tableau2229[[#This Row],[MONTANT HT]]*Tableau2229[[#This Row],[TAUX TVA]] -> 0 | Q68: =+Tableau2229[[#This Row],[MONTANT HT]]+Tableau2229[[#This Row],[MONTANT TVA]] -> 225000 | S68: =+Tableau2229[[#This Row],[MONTANT TTC]]-Tableau2229[[#This Row],[MONTANT PAYÉ (FCFA)]] -> 225000
A69: SIM BETON | B69: 45723 | C69: 45721 | D69: FD250305 | F69: ENGAGEMENT PREVISIONNELLE | H69: ZAR SANDRINE P/C ZAR SECURITY | K69: ACHAT DE SERVICE | L69: FRAIS DE GARDIENNAGE USINE BKE FEVRIER 2025 | M69: USINE BKE | N69: 300000 | O69: 0 | P69: =+Tableau2229[[#This Row],[MONTANT HT]]*Tableau2229[[#This Row],[TAUX TVA]] -> 0 | Q69: =+Tableau2229[[#This Row],[MONTANT HT]]+Tableau2229[[#This Row],[MONTANT TVA]] -> 300000 | S69: =+Tableau2229[[#This Row],[MONTANT TTC]]-Tableau2229[[#This Row],[MONTANT PAYÉ (FCFA)]] -> 300000
A70: SIM GROUP | B70: 45723 | C70: 45721 | D70: FD250305 | F70: ENGAGEMENT PREVISIONNELLE | H70: ZAR SANDRINE P/C ZAR SECURITY | K70: ACHAT DE SERVICE | L70: FRAIS DE GARDIENNAGE USINE BKE FEVRIER 2025 | M70: SIM GROUP | N70: 300000 | O70: 0 | P70: =+Tableau2229[[#This Row],[MONTANT HT]]*Tableau2229[[#This Row],[TAUX TVA]] -> 0 | Q70: =+Tableau2229[[#This Row],[MONTANT HT]]+Tableau2229[[#This Row],[MONTANT TVA]] -> 300000 | S70: =+Tableau2229[[#This Row],[MONTANT TTC]]-Tableau2229[[#This Row],[MONTANT PAYÉ (FCFA)]] -> 300000
A71: SIM GROUP | B71: 45723 | C71: 45723 | D71: FD250307 | F71: ENGAGEMENT PREVISIONNELLE | H71: EPONON EMMANUEL | K71: ACHAT DE FOURNITURES | L71: PLEIN DE CARBURANT POUR LE VEHICULE KIA SPORTAGE | M71: SIM GROUP | N71: 45000 | O71: 0 | P71: =+Tableau2229[[#This Row],[MONTANT HT]]*Tableau2229[[#This Row],[TAUX TVA]] -> 0 | Q71: =+Tableau2229[[#This Row],[MONTANT HT]]+Tableau2229[[#This Row],[MONTANT TVA]] -> 45000 | S71: =+Tableau2229[[#This Row],[MONTANT TTC]]-Tableau2229[[#This Row],[MONTANT PAYÉ (FCFA)]] -> 45000
A72: SIM GROUP | B72: 45723 | C72: 45721 | D72: FD250305 | F72: ENGAGEMENT PREVISIONNELLE | H72: ZAR SANDRINE P/C DIANE SEKO | K72: ACHAT DE SERVICE | L72: LOYER ECHU MOIS DE FEVRIER 2025 | M72: SIM GROUP | N72: 700000 | O72: 0 | P72: =+Tableau2229[[#This Row],[MONTANT HT]]*Tableau2229[[#This Row],[TAUX TVA]] -> 0 | Q72: =+Tableau2229[[#This Row],[MONTANT HT]]+Tableau2229[[#This Row],[MONTANT TVA]] -> 700000 | S72: =+Tableau2229[[#This Row],[MONTANT TTC]]-Tableau2229[[#This Row],[MONTANT PAYÉ (FCFA)]] -> 700000
A73: SIM GROUP | B73: 45723 | C73: 45715 | D73: FD250227 | F73: ENGAGEMENT PREVISIONNELLE | H73: TANON ANDRE | K73: ACHAT DE FOURNITURES | L73: ACHAT DE GAINES, FIL NYLON, | M73: SIM GROUP | N73: 208506 | O73: 0 | P73: =+Tableau2229[[#This Row],[MONTANT HT]]*Tableau2229[[#This Row],[TAUX TVA]] -> 0 | Q73: =+Tableau2229[[#This Row],[MONTANT HT]]+Tableau2229[[#This Row],[MONTANT TVA]] -> 208506 | S73: =+Tableau2229[[#This Row],[MONTANT TTC]]-Tableau2229[[#This Row],[MONTANT PAYÉ (FCFA)]] -> 208506
A74: SIM BETON | B74: 45723 | C74: 45702 | D74: FD250214 | F74: ENGAGEMENT PREVISIONNELLE | H74: YEO NOUGNON | K74: ACHAT D EQUIPEMENT | L74: ACHAT DE POSTE A SOUDER | M74: USINE BKE | N74: 92070 | O74: 0 | P74: =+Tableau2229[[#This Row],[MONTANT HT]]*Tableau2229[[#This Row],[TAUX TVA]] -> 0 | Q74: =+Tableau2229[[#This Row],[MONTANT HT]]+Tableau2229[[#This Row],[MONTANT TVA]] -> 92070 | S74: =+Tableau2229[[#This Row],[MONTANT TTC]]-Tableau2229[[#This Row],[MONTANT PAYÉ (FCFA)]] -> 92070
A75: SIM BETON | B75: 45723 | C75: 45722 | D75: FD250306 | F75: ENGAGEMENT PREVISIONNELLE | H75: EPONON EMMANUEL | K75: ACHAT DE SERVICE | L75: MO JOURNALIERES 28/02/25 AU 06/03/25 | M75: USINE MAN | N75: 168500 | O75: 0 | P75: =+Tableau2229[[#This Row],[MONTANT HT]]*Tableau2229[[#This Row],[TAUX TVA]] -> 0 | Q75: =+Tableau2229[[#This Row],[MONTANT HT]]+Tableau2229[[#This Row],[MONTANT TVA]] -> 168500 | S75: =+Tableau2229[[#This Row],[MONTANT TTC]]-Tableau2229[[#This Row],[MONTANT PAYÉ (FCFA)]] -> 168500
A76: SIM BETON | B76: 45723 | C76: 45722 | D76: FD250306 | F76: ENGAGEMENT PREVISIONNELLE | H76: EPONON EMMANUEL | K76: ACHAT DE SERVICE | L76: MO FERAILLEURS AU RENDEMENT 28/02/25 AU 06/03/25 | M76: USINE MAN | N76: 24500 | O76: 0 | P76: =+Tableau2229[[#This Row],[MONTANT HT]]*Tableau2229[[#This Row],[TAUX TVA]] -> 0 | Q76: =+Tableau2229[[#This Row],[MONTANT HT]]+Tableau2229[[#This Row],[MONTANT TVA]] -> 24500 | S76: =+Tableau2229[[#This Row],[MONTANT TTC]]-Tableau2229[[#This Row],[MONTANT PAYÉ (FCFA)]] -> 24500
A77: SIM BETON | B77: 45723 | C77: 45722 | D77: FD250306 | F77: ENGAGEMENT PREVISIONNELLE | H77: EPONON EMMANUEL | K77: ACHAT DE SERVICE | L77: MO JOURNALIERES 28/02/25 AU 06/03/25 | M77: USINE ABJ | N77: 178000 | O77: 0 | P77: =+Tableau2229[[#This Row],[MONTANT HT]]*Tableau2229[[#This Row],[TAUX TVA]] -> 0 | Q77: =+Tableau2229[[#This Row],[MONTANT HT]]+Tableau2229[[#This Row],[MONTANT TVA]] -> 178000 | S77: =+Tableau2229[[#This Row],[MONTANT TTC]]-Tableau2229[[#This Row],[MONTANT PAYÉ (FCFA)]] -> 178000
A78: SIM BETON | B78: 45723 | C78: 45714 | D78: FD250226 | F78: ENGAGEMENT PREVISIONNELLE | H78: EPONON EMMANUEL | K78: ACHAT DE SERVICE | L78: MO FERAILLEURS AU RENDEMENT 28/02/25 AU 06/03/25 | M78: USINE ABJ | N78: 94500 | O78: 0 | P78: =+Tableau2229[[#This Row],[MONTANT HT]]*Tableau2229[[#This Row],[TAUX TVA]] -> 0 | Q78: =+Tableau2229[[#This Row],[MONTANT HT]]+Tableau2229[[#This Row],[MONTANT TVA]] -> 94500 | S78: =+Tableau2229[[#This Row],[MONTANT TTC]]-Tableau2229[[#This Row],[MONTANT PAYÉ (FCFA)]] -> 94500
A79: SIM BETON | B79: 45723 | C79: 45710 | D79: FD250222 | F79: ENGAGEMENT PREVISIONNELLE | H79: EPONON EMMANUEL | K79: ACHAT DE SERVICE | L79: MO FERAILLEURS AU RENDEMENT 15/02/25 AU 21/02/25 | M79: USINE ABJ | N79: 150000 | O79: 0 | P79: =+Tableau2229[[#This Row],[MONTANT HT]]*Tableau2229[[#This Row],[TAUX TVA]] -> 0 | Q79: =+Tableau2229[[#This Row],[MONTANT HT]]+Tableau2229[[#This Row],[MONTANT TVA]] -> 150000 | S79: =+Tableau2229[[#This Row],[MONTANT TTC]]-Tableau2229[[#This Row],[MONTANT PAYÉ (FCFA)]] -> 150000
A80: SIM BETON | B80: 45723 | C80: 45709 | D80: FD250221 | F80: ENGAGEMENT PREVISIONNELLE | H80: TANON ANDRE | K80: ACHAT DE FOURNITURES | L80: ACHAT DE CIMENT | M80: USINE BKE | N80: 4119995 | O80: 0 | P80: =+Tableau2229[[#This Row],[MONTANT HT]]*Tableau2229[[#This Row],[TAUX TVA]] -> 0 | Q80: =+Tableau2229[[#This Row],[MONTANT HT]]+Tableau2229[[#This Row],[MONTANT TVA]] -> 4119995 | R80: =3680000+40400+1000 -> 3721400 | S80: =+Tableau2229[[#This Row],[MONTANT TTC]]-Tableau2229[[#This Row],[MONTANT PAYÉ (FCFA)]] -> 398595
A81: SIM BETON | B81: 45723 | C81: 45709 | D81: FD250221 | F81: ENGAGEMENT PREVISIONNELLE | H81: TANON ANDRE | K81: ACHAT DE FOURNITURES | L81: ACHAT AGREGATS | M81: USINE BKE | N81: 1210000 | O81: 0 | P81: =+Tableau2229[[#This Row],[MONTANT HT]]*Tableau2229[[#This Row],[TAUX TVA]] -> 0 | Q81: =+Tableau2229[[#This Row],[MONTANT HT]]+Tableau2229[[#This Row],[MONTANT TVA]] -> 1210000 | S81: =+Tableau2229[[#This Row],[MONTANT TTC]]-Tableau2229[[#This Row],[MONTANT PAYÉ (FCFA)]] -> 1210000
A82: SIM BETON | B82: 45723 | C82: 45709 | D82: FD250221 | F82: ENGAGEMENT PREVISIONNELLE | H82: TANON ANDRE | K82: ACHAT DE FOURNITURES | L82: ACHAT DE CIMENT | M82: USINE MAN | N82: 4119995 | O82: 0 | P82: =+Tableau2229[[#This Row],[MONTANT HT]]*Tableau2229[[#This Row],[TAUX TVA]] -> 0 | Q82: =+Tableau2229[[#This Row],[MONTANT HT]]+Tableau2229[[#This Row],[MONTANT TVA]] -> 4119995 | S82: =+Tableau2229[[#This Row],[MONTANT TTC]]-Tableau2229[[#This Row],[MONTANT PAYÉ (FCFA)]] -> 4119995
A83: SIM BETON | B83: 45723 | C83: 45709 | D83: FD250221 | F83: ENGAGEMENT PREVISIONNELLE | H83: TANON ANDRE | K83: ACHAT DE FOURNITURES | L83: ACHAT AGREGATS | M83: USINE MAN | N83: 1750000 | O83: 0 | P83: =+Tableau2229[[#This Row],[MONTANT HT]]*Tableau2229[[#This Row],[TAUX TVA]] -> 0 | Q83: =+Tableau2229[[#This Row],[MONTANT HT]]+Tableau2229[[#This Row],[MONTANT TVA]] -> 1750000 | S83: =+Tableau2229[[#This Row],[MONTANT TTC]]-Tableau2229[[#This Row],[MONTANT PAYÉ (FCFA)]] -> 1750000
A84: SINERGIE RESEAU | B84: 45723 | C84: 45701 | D84: FD250213 | F84: ENGAGEMENT PREVISIONNELLE | H84: YEO NOUGNON | K84: ACHAT DE PETIT MATERIEL | L84: ACHAT DE PNEU ET EQUILIBRAGE | M84: CIC MAN | N84: 186000 | O84: 0 | P84: =+Tableau2229[[#This Row],[MONTANT HT]]*Tableau2229[[#This Row],[TAUX TVA]] -> 0 | Q84: =+Tableau2229[[#This Row],[MONTANT HT]]+Tableau2229[[#This Row],[MONTANT TVA]] -> 186000 | R84: 90000 | S84: =+Tableau2229[[#This Row],[MONTANT TTC]]-Tableau2229[[#This Row],[MONTANT PAYÉ (FCFA)]] -> 96000
A85: SINERGIE RESEAU | B85: 45723 | C85: 45722 | D85: FD250306 | F85: ENGAGEMENT PREVISIONNELLE | H85: YEO NOUGNON | K85: ACHAT DE PETIT MATERIEL | L85: ACHAT DE PNEU | M85: CIC MAN | N85: 70000 | O85: 0 | P85: =+Tableau2229[[#This Row],[MONTANT HT]]*Tableau2229[[#This Row],[TAUX TVA]] -> 0 | Q85: =+Tableau2229[[#This Row],[MONTANT HT]]+Tableau2229[[#This Row],[MONTANT TVA]] -> 70000 | S85: =+Tableau2229[[#This Row],[MONTANT TTC]]-Tableau2229[[#This Row],[MONTANT PAYÉ (FCFA)]] -> 70000
A86: SINERGIE RESEAU | B86: 45723 | C86: 45721 | D86: FD250305 | F86: ENGAGEMENT PREVISIONNELLE | H86: GBANHOUN SANDRINE | K86: FRAIS DE MISSION | L86: FRAIS DE MISSION A KAADE 01/03/25 AU 09/03/25 | M86: CIC SNT | N86: 181800 | O86: 0 | P86: =+Tableau2229[[#This Row],[MONTANT HT]]*Tableau2229[[#This Row],[TAUX TVA]] -> 0 | Q86: =+Tableau2229[[#This Row],[MONTANT HT]]+Tableau2229[[#This Row],[MONTANT TVA]] -> 181800 | S86: =+Tableau2229[[#This Row],[MONTANT TTC]]-Tableau2229[[#This Row],[MONTANT PAYÉ (FCFA)]] -> 181800
A87: SINERGIE RESEAU | B87: 45723 | C87: 45722 | D87: FD250306 | F87: ENGAGEMENT PREVISIONNELLE | H87: KOFFI LAURA | K87: ACHAT DE SERVICE | L87: ACHAT PRESTATIONS PM DU 06/03/25 | M87: CIC PM | N87: 165000 | O87: 0 | P87: =+Tableau2229[[#This Row],[MONTANT HT]]*Tableau2229[[#This Row],[TAUX TVA]] -> 0 | Q87: =+Tableau2229[[#This Row],[MONTANT HT]]+Tableau2229[[#This Row],[MONTANT TVA]] -> 165000 | R87: 100000 | S87: =+Tableau2229[[#This Row],[MONTANT TTC]]-Tableau2229[[#This Row],[MONTANT PAYÉ (FCFA)]] -> 65000
A88: SINERGIE RESEAU | B88: 45723 | C88: 45723 | D88: FD250307 | F88: ENGAGEMENT PREVISIONNELLE | H88: KOFFI LAURA | K88: ACHAT DE SERVICE | L88: ACHAT PRESTATIONS PM DU 07/03/25 | M88: CIC PM | N88: 164603 | O88: 0 | P88: =+Tableau2229[[#This Row],[MONTANT HT]]*Tableau2229[[#This Row],[TAUX TVA]] -> 0 | Q88: =+Tableau2229[[#This Row],[MONTANT HT]]+Tableau2229[[#This Row],[MONTANT TVA]] -> 164603 | S88: =+Tableau2229[[#This Row],[MONTANT TTC]]-Tableau2229[[#This Row],[MONTANT PAYÉ (FCFA)]] -> 164603
A89: SINERGIE RESEAU | B89: 45723 | C89: 45723 | D89: FD250307 | F89: ENGAGEMENT PREVISIONNELLE | H89: GBANHOUN SANDRINE | K89: ACHAT DE SERVICE | L89: ACHAT PRESTATIONS PBA DU 07/03/25 | M89: CIC KAADE SNT | N89: 79790 | O89: 0 | P89: =+Tableau2229[[#This Row],[MONTANT HT]]*Tableau2229[[#This Row],[TAUX TVA]] -> 0 | Q89: =+Tableau2229[[#This Row],[MONTANT HT]]+Tableau2229[[#This Row],[MONTANT TVA]] -> 79790 | S89: =+Tableau2229[[#This Row],[MONTANT TTC]]-Tableau2229[[#This Row],[MONTANT PAYÉ (FCFA)]] -> 79790
A90: SINERGIE RESEAU | B90: 45723 | C90: 45723 | D90: FD250307 | F90: ENGAGEMENT PREVISIONNELLE | H90: GBANHOUN SANDRINE | K90: ACHAT DE SERVICE | L90: TRANSPORT TOULEUPLEU DU 07/03/25 | M90: CIC TOULEUPLEU | N90: 10000 | O90: 0 | P90: =+Tableau2229[[#This Row],[MONTANT HT]]*Tableau2229[[#This Row],[TAUX TVA]] -> 0 | Q90: =+Tableau2229[[#This Row],[MONTANT HT]]+Tableau2229[[#This Row],[MONTANT TVA]] -> 10000 | S90: =+Tableau2229[[#This Row],[MONTANT TTC]]-Tableau2229[[#This Row],[MONTANT PAYÉ (FCFA)]] -> 10000
A91: SINERGIE RESEAU | B91: 45723 | C91: 45723 | D91: FD250307 | F91: ENGAGEMENT PREVISIONNELLE | H91: GBANHOUN SANDRINE | K91: ACHAT DE SERVICE | L91: ACHAT PRESTATION FOUILLES NON REGLER | M91: CIC M BENGUE | N91: 199475 | O91: 0 | P91: =+Tableau2229[[#This Row],[MONTANT HT]]*Tableau2229[[#This Row],[TAUX TVA]] -> 0 | Q91: =+Tableau2229[[#This Row],[MONTANT HT]]+Tableau2229[[#This Row],[MONTANT TVA]] -> 199475 | S91: =+Tableau2229[[#This Row],[MONTANT TTC]]-Tableau2229[[#This Row],[MONTANT PAYÉ (FCFA)]] -> 199475
A92: SIM BETON | B92: 45723 | C92: 45723 | D92: FD250307 | F92: ENGAGEMENT PREVISIONNELLE | H92: EPONON EMMANUEL | K92: ACHAT DE SERVICE | L92: MO JOURNALIERES 03/03/25 AU 05/03/25 | M92: CIC BKE | N92: 25000 | O92: 0 | P92: =+Tableau2229[[#This Row],[MONTANT HT]]*Tableau2229[[#This Row],[TAUX TVA]] -> 0 | Q92: =+Tableau2229[[#This Row],[MONTANT HT]]+Tableau2229[[#This Row],[MONTANT TVA]] -> 25000 | S92: =+Tableau2229[[#This Row],[MONTANT TTC]]-Tableau2229[[#This Row],[MONTANT PAYÉ (FCFA)]] -> 25000
A93: SIM GROUP | P93: =+Tableau2229[[#This Row],[MONTANT HT]]*Tableau2229[[#This Row],[TAUX TVA]] -> 0 | Q93: =+Tableau2229[[#This Row],[MONTANT HT]]+Tableau2229[[#This Row],[MONTANT TVA]] -> 0 | S93: =+Tableau2229[[#This Row],[MONTANT TTC]]-Tableau2229[[#This Row],[MONTANT PAYÉ (FCFA)]] -> 0

Sheet BASE DE LA DETTE
A1: ETAT DE LA DETTE ELARGIE
A3: ENTITE | B3: DATE DE SAISIE | C3: DATE_FICHE | D3: DATE_FACTURE | E3: N° FICHE/DOSSIER | F3: N° FACTURE/REF | G3: TYPE D'ENGAGEMENT | H3: TYPE DE DETTE | I3: DEMANDEUR | J3: FOURNISSEUR/ORGANISME/TIERS | K3: TYPE TIERS HORS OU INTRA GROUPE | L3: NATURE | M3: DETAIL | N3: CENTRE IMPUTATION | O3: MONTANT HT | P3: TAUX TVA | Q3: MONTANT TVA | R3: MONTANT TTC | S3: DELAIS | T3: DATE ÉCHÉANCE_ ENGAGEMENT | U3: NBRE DE JOURS AVANT ECHEANCE | V3: MONTANT PAYÉ (FCFA) | W3: SOLDE RESTANT (FCFA) | X3: LITIGE DÉTECTÉ | Y3: DÉTAILS LITIGE | Z3: ÉTAT | AA3: BON DE COMMANDE N° | AB3: CONCORDANCE AVEC BC | AC3: OBSERVATIONS
A4: SIM BETON | C4: 45680 | E4: FD250123-1 | G4: ENGAGEMENT PREVISIONNELLE | I4: KOUAKOU BRICE VENANCE | L4: FRAIS DE MISSION | M4: CARBURANT | N4: USINE ABJ | O4: 15000 | P4: 0 | Q4: =+Tableau222[[#This Row],[MONTANT HT]]*Tableau222[[#This Row],[TAUX TVA]] -> 0 | R4: =+Tableau222[[#This Row],[MONTANT HT]]+Tableau222[[#This Row],[MONTANT TVA]] -> 15000 | T4: =+IF(OR(AND(Tableau222[[#This Row],[DATE_FICHE]]<>"",Tableau222[[#This Row],[DATE_FACTURE]]<>""),AND(Tableau222[[#This Row],[DATE_FICHE]]="",Tableau222[[#This Row],[DATE_FACTURE]]<>"")),Tableau222[[#This Row],[DATE_FACTURE]]+Tableau222[[#This Row],[DELAIS]],IF(AND(Tableau222[[#This Row],[DATE_FICHE]]<>"",Tableau222[[#This Row],[DATE_FACTURE]]=""),Tableau222[[#This Row],[DATE_FICHE]]+Tableau222[[#This Row],[DELAIS]])) -> 45680 | W4: =+Tableau222[[#This Row],[MONTANT TTC]]-Tableau222[[#This Row],[MONTANT PAYÉ (FCFA)]] -> 15000
A5: SINERGIE RESEAU | C5: 45681 | E5: FD250124-2 | G5: ENGAGEMENT PREVISIONNELLE | I5: GBANHOUN SANDRINE | L5: ACHAT DE FOURNITURES | M5: ACHAT D AGREGAT | N5: PROJET AGL KM4 | O5: 240000 | P5: 0 | Q5: =+Tableau222[[#This Row],[MONTANT HT]]*Tableau222[[#This Row],[TAUX TVA]] -> 0 | R5: =+Tableau222[[#This Row],[MONTANT HT]]+Tableau222[[#This Row],[MONTANT TVA]] -> 240000 | T5: =+IF(OR(AND(Tableau222[[#This Row],[DATE_FICHE]]<>"",Tableau222[[#This Row],[DATE_FACTURE]]<>""),AND(Tableau222[[#This Row],[DATE_FICHE]]="",Tableau222[[#This Row],[DATE_FACTURE]]<>"")),Tableau222[[#This Row],[DATE_FACTURE]]+Tableau222[[#This Row],[DELAIS]],IF(AND(Tableau222[[#This Row],[DATE_FICHE]]<>"",Tableau222[[#This Row],[DATE_FACTURE]]=""),Tableau222[[#This Row],[DATE_FICHE]]+Tableau222[[#This Row],[DELAIS]])) -> 45681 | W5: =+Tableau222[[#This Row],[MONTANT TTC]]-Tableau222[[#This Row],[MONTANT PAYÉ (FCFA)]] -> 240000 | Z5: PAYE
A6: SIM BETON | C6: 45682 | E6: FD250125-1 | G6: ENGAGEMENT PREVISIONNELLE | I6: TANON ANDRE | L6: TRANSPORT | M6: TRANSPORT DE CIMENT ABJ BKE ET MAN | N6: USINE BKE-USINE MAN | O6: 1300000 | P6: 0 | Q6: =+Tableau222[[#This Row],[MONTANT HT]]*Tableau222[[#This Row],[TAUX TVA]] -> 0 | R6: =+Tableau222[[#This Row],[MONTANT HT]]+Tableau222[[#This Row],[MONTANT TVA]] -> 1300000 | T6: =+IF(OR(AND(Tableau222[[#This Row],[DATE_FICHE]]<>"",Tableau222[[#This Row],[DATE_FACTURE]]<>""),AND(Tableau222[[#This Row],[DATE_FICHE]]="",Tableau222[[#This Row],[DATE_FACTURE]]<>"")),Tableau222[[#This Row],[DATE_FACTURE]]+Tableau222[[#This Row],[DELAIS]],IF(AND(Tableau222[[#This Row],[DATE_FICHE]]<>"",Tableau222[[#This Row],[DATE_FACTURE]]=""),Tableau222[[#This Row],[DATE_FICHE]]+Tableau222[[#This Row],[DELAIS]])) -> 45682 | W6: =+Tableau222[[#This Row],[MONTANT TTC]]-Tableau222[[#This Row],[MONTANT PAYÉ (FCFA)]] -> 1300000
A7: SIM BETON | C7: 45682 | E7: FD250125-2 | G7: ENGAGEMENT PREVISIONNELLE | I7: TANON ANDRE | L7: TRANSPORT | M7: TRANSPORT DE GRAVIER ABJ | N7: USINE ABJ | O7: 270000 | P7: 0 | Q7: =+Tableau222[[#This Row],[MONTANT HT]]*Tableau222[[#This Row],[TAUX TVA]] -> 0 | R7: =+Tableau222[[#This Row],[MONTANT HT]]+Tableau222[[#This Row],[MONTANT TVA]] -> 270000 | T7: =+IF(OR(AND(Tableau222[[#This Row],[DATE_FICHE]]<>"",Tableau222[[#This Row],[DATE_FACTURE]]<>""),AND(Tableau222[[#This Row],[DATE_FICHE]]="",Tableau222[[#This Row],[DATE_FACTURE]]<>"")),Tableau222[[#This Row],[DATE_FACTURE]]+Tableau222[[#This Row],[DELAIS]],IF(AND(Tableau222[[#This Row],[DATE_FICHE]]<>"",Tableau222[[#This Row],[DATE_FACTURE]]=""),Tableau222[[#This Row],[DATE_FICHE]]+Tableau222[[#This Row],[DELAIS]])) -> 45682 | W7: =+Tableau222[[#This Row],[MONTANT TTC]]-Tableau222[[#This Row],[MONTANT PAYÉ (FCFA)]] -> 270000
A8: SIM BETON | C8: 45682 | E8: FD250125-3 | G8: ENGAGEMENT PREVISIONNELLE | I8: TANON ANDRE | L8: ACHAT DE FOURNITURES | M8: ACHAT DE 2 VOYAGE SABLE | N8: USINE ABJ | O8: 170000 | P8: 0 | Q8: =+Tableau222[[#This Row],[MONTANT HT]]*Tableau222[[#This Row],[TAUX TVA]] -> 0 | R8: =+Tableau222[[#This Row],[MONTANT HT]]+Tableau222[[#This Row],[MONTANT TVA]] -> 170000 | T8: =+IF(OR(AND(Tableau222[[#This Row],[DATE_FICHE]]<>"",Tableau222[[#This Row],[DATE_FACTURE]]<>""),AND(Tableau222[[#This Row],[DATE_FICHE]]="",Tableau222[[#This Row],[DATE_FACTURE]]<>"")),Tableau222[[#This Row],[DATE_FACTURE]]+Tableau222[[#This Row],[DELAIS]],IF(AND(Tableau222[[#This Row],[DATE_FICHE]]<>"",Tableau222[[#This Row],[DATE_FACTURE]]=""),Tableau222[[#This Row],[DATE_FICHE]]+Tableau222[[#This Row],[DELAIS]])) -> 45682 | W8: =+Tableau222[[#This Row],[MONTANT TTC]]-Tableau222[[#This Row],[MONTANT PAYÉ (FCFA)]] -> 170000
A9: SIM BETON | C9: 45682 | E9: FD250125-4 | G9: ENGAGEMENT PREVISIONNELLE | I9: TANON ANDRE | L9: LOCATION | M9: LOCATION DE GRUE | N9: USINE BKE | O9: 150000 | P9: 0 | Q9: =+Tableau222[[#This Row],[MONTANT HT]]*Tableau222[[#This Row],[TAUX TVA]] -> 0 | R9: =+Tableau222[[#This Row],[MONTANT HT]]+Tableau222[[#This Row],[MONTANT TVA]] -> 150000 | T9: =+IF(OR(AND(Tableau222[[#This Row],[DATE_FICHE]]<>"",Tableau222[[#This Row],[DATE_FACTURE]]<>""),AND(Tableau222[[#This Row],[DATE_FICHE]]="",Tableau222[[#This Row],[DATE_FACTURE]]<>"")),Tableau222[[#This Row],[DATE_FACTURE]]+Tableau222[[#This Row],[DELAIS]],IF(AND(Tableau222[[#This Row],[DATE_FICHE]]<>"",Tableau222[[#This Row],[DATE_FACTURE]]=""),Tableau222[[#This Row],[DATE_FICHE]]+Tableau222[[#This Row],[DELAIS]])) -> 45682 | W9: =+Tableau222[[#This Row],[MONTANT TTC]]-Tableau222[[#This Row],[MONTANT PAYÉ (FCFA)]] -> 150000
A10: SIM BETON | C10: 45684 | E10: FD250127-1 | G10: ENGAGEMENT PREVISIONNELLE | I10: TANON ANDRE | L10: ACHAT DE PETIT MATERIEL | M10: ACHAT DE PINCEAU NIV MACON | N10: USINE MAN | O10: 8000 | P10: 0 | Q10: =+Tableau222[[#This Row],[MONTANT HT]]*Tableau222[[#This Row],[TAUX TVA]] -> 0 | R10: =+Tableau222[[#This Row],[MONTANT HT]]+Tableau222[[#This Row],[MONTANT TVA]] -> 8000 | T10: =+IF(OR(AND(Tableau222[[#This Row],[DATE_FICHE]]<>"",Tableau222[[#This Row],[DATE_FACTURE]]<>""),AND(Tableau222[[#This Row],[DATE_FICHE]]="",Tableau222[[#This Row],[DATE_FACTURE]]<>"")),Tableau222[[#This Row],[DATE_FACTURE]]+Tableau222[[#This Row],[DELAIS]],IF(AND(Tableau222[[#This Row],[DATE_FICHE]]<>"",Tableau222[[#This Row],[DATE_FACTURE]]=""),Tableau222[[#This Row],[DATE_FICHE]]+Tableau222[[#This Row],[DELAIS]])) -> 45684 | W10: =+Tableau222[[#This Row],[MONTANT TTC]]-Tableau222[[#This Row],[MONTANT PAYÉ (FCFA)]] -> 8000
A11: SIM BETON | C11: 45684 | E11: FD250127-2 | G11: ENGAGEMENT PREVISIONNELLE | I11: TANON ANDRE | L11: ACHAT DE FOURNITURES | M11: ACHAT DE BOULON, CLE,… | N11: USINE MAN | O11: 191000 | P11: 0 | Q11: =+Tableau222[[#This Row],[MONTANT HT]]*Tableau222[[#This Row],[TAUX TVA]] -> 0 | R11: =+Tableau222[[#This Row],[MONTANT HT]]+Tableau222[[#This Row],[MONTANT TVA]] -> 191000 | T11: =+IF(OR(AND(Tableau222[[#This Row],[DATE_FICHE]]<>"",Tableau222[[#This Row],[DATE_FACTURE]]<>""),AND(Tableau222[[#This Row],[DATE_FICHE]]="",Tableau222[[#This Row],[DATE_FACTURE]]<>"")),Tableau222[[#This Row],[DATE_FACTURE]]+Tableau222[[#This Row],[DELAIS]],IF(AND(Tableau222[[#This Row],[DATE_FICHE]]<>"",Tableau222[[#This Row],[DATE_FACTURE]]=""),Tableau222[[#This Row],[DATE_FICHE]]+Tableau222[[#This Row],[DELAIS]])) -> 45684 | W11: =+Tableau222[[#This Row],[MONTANT TTC]]-Tableau222[[#This Row],[MONTANT PAYÉ (FCFA)]] -> 191000
A12: SIM BETON | C12: 45684 | E12: FD250127-3 | G12: ENGAGEMENT PREVISIONNELLE | I12: SORO ETIENNE | L12: ACHAT DE FOURNITURES | M12: FRAIS DE PRODUCTION DU 27/01/25 AU 01/02/25 | N12: USINE ABJ | O12: 111500 | P12: 0 | Q12: =+Tableau222[[#This Row],[MONTANT HT]]*Tableau222[[#This Row],[TAUX TVA]] -> 0 | R12: =+Tableau222[[#This Row],[MONTANT HT]]+Tableau222[[#This Row],[MONTANT TVA]] -> 111500 | T12: =+IF(OR(AND(Tableau222[[#This Row],[DATE_FICHE]]<>"",Tableau222[[#This Row],[DATE_FACTURE]]<>""),AND(Tableau222[[#This Row],[DATE_FICHE]]="",Tableau222[[#This Row],[DATE_FACTURE]]<>"")),Tableau222[[#This Row],[DATE_FACTURE]]+Tableau222[[#This Row],[DELAIS]],IF(AND(Tableau222[[#This Row],[DATE_FICHE]]<>"",Tableau222[[#This Row],[DATE_FACTURE]]=""),Tableau222[[#This Row],[DATE_FICHE]]+Tableau222[[#This Row],[DELAIS]])) -> 45684 | W12: =+Tableau222[[#This Row],[MONTANT TTC]]-Tableau222[[#This Row],[MONTANT PAYÉ (FCFA)]] -> 111500
A13: SIM BETON | C13: 45684 | E13: FD250127-4 | G13: ENGAGEMENT PREVISIONNELLE | I13: SORO ETIENNE | L13: ACHAT DE FOURNITURES | M13: FRAIS DE PRODUCTION DU 27/01/25 AU 01/02/25 | N13: USINE BKE | O13: 147250 | P13: 0 | Q13: =+Tableau222[[#This Row],[MONTANT HT]]*Tableau222[[#This Row],[TAUX TVA]] -> 0 | R13: =+Tableau222[[#This Row],[MONTANT HT]]+Tableau222[[#This Row],[MONTANT TVA]] -> 147250 | T13: =+IF(OR(AND(Tableau222[[#This Row],[DATE_FICHE]]<>"",Tableau222[[#This Row],[DATE_FACTURE]]<>""),AND(Tableau222[[#This Row],[DATE_FICHE]]="",Tableau222[[#This Row],[DATE_FACTURE]]<>"")),Tableau222[[#This Row],[DATE_FACTURE]]+Tableau222[[#This Row],[DELAIS]],IF(AND(Tableau222[[#This Row],[DATE_FICHE]]<>"",Tableau222[[#This Row],[DATE_FACTURE]]=""),Tableau222[[#This Row],[DATE_FICHE]]+Tableau222[[#This Row],[DELAIS]])) -> 45684 | W13: =+Tableau222[[#This Row],[MONTANT TTC]]-Tableau222[[#This Row],[MONTANT PAYÉ (FCFA)]] -> 147250
A14: SIM GROUP | C14: 45684 | E14: FD250127-5 | G14: ENGAGEMENT PREVISIONNELLE | I14: KONAN N'DRI | L14: ACHAT DE PETIT MATERIEL | M14: ACHAT D UN TELEPHONE PORTABLE | N14: TRESORERIE | O14: 67000 | P14: 0 | Q14: =+Tableau222[[#This Row],[MONTANT HT]]*Tableau222[[#This Row],[TAUX TVA]] -> 0 | R14: =+Tableau222[[#This Row],[MONTANT HT]]+Tableau222[[#This Row],[MONTANT TVA]] -> 67000 | T14: =+IF(OR(AND(Tableau222[[#This Row],[DATE_FICHE]]<>"",Tableau222[[#This Row],[DATE_FACTURE]]<>""),AND(Tableau222[[#This Row],[DATE_FICHE]]="",Tableau222[[#This Row],[DATE_FACTURE]]<>"")),Tableau222[[#This Row],[DATE_FACTURE]]+Tableau222[[#This Row],[DELAIS]],IF(AND(Tableau222[[#This Row],[DATE_FICHE]]<>"",Tableau222[[#This Row],[DATE_FACTURE]]=""),Tableau222[[#This Row],[DATE_FICHE]]+Tableau222[[#This Row],[DELAIS]])) -> 45684 | W14: =+Tableau222[[#This Row],[MONTANT TTC]]-Tableau222[[#This Row],[MONTANT PAYÉ (FCFA)]] -> 67000
A15: SIM BETON | C15: 45684 | E15: FD250127-6 | G15: ENGAGEMENT PREVISIONNELLE | I15: GOSSAN P/C SORO | L15: MAIN ŒUVRE | M15: MO ARMATURIERS EQUIPE SEKOFOLE DU 06/01 -23/01/25 | N15: USINE ABJ | O15: 467500 | P15: 0 | Q15: =+Tableau222[[#This Row],[MONTANT HT]]*Tableau222[[#This Row],[TAUX TVA]] -> 0 | R15: =+Tableau222[[#This Row],[MONTANT HT]]+Tableau222[[#This Row],[MONTANT TVA]] -> 467500 | T15: =+IF(OR(AND(Tableau222[[#This Row],[DATE_FICHE]]<>"",Tableau222[[#This Row],[DATE_FACTURE]]<>""),AND(Tableau222[[#This Row],[DATE_FICHE]]="",Tableau222[[#This Row],[DATE_FACTURE]]<>"")),Tableau222[[#This Row],[DATE_FACTURE]]+Tableau222[[#This Row],[DELAIS]],IF(AND(Tableau222[[#This Row],[DATE_FICHE]]<>"",Tableau222[[#This Row],[DATE_FACTURE]]=""),Tableau222[[#This Row],[DATE_FICHE]]+Tableau222[[#This Row],[DELAIS]])) -> 45684 | W15: =+Tableau222[[#This Row],[MONTANT TTC]]-Tableau222[[#This Row],[MONTANT PAYÉ (FCFA)]] -> 467500
A16: SIM BETON | C16: 45684 | E16: FD250127-7 | G16: ENGAGEMENT PREVISIONNELLE | I16: GOSSAN P/C FOFANA | L16: MAIN ŒUVRE | M16: MO ARMATURIERS EQUIPE BEAN DU 08/01 -16/01/25 | N16: USINE BKE | O16: 265000 | P16: 0 | Q16: =+Tableau222[[#This Row],[MONTANT HT]]*Tableau222[[#This Row],[TAUX TVA]] -> 0 | R16: =+Tableau222[[#This Row],[MONTANT HT]]+Tableau222[[#This Row],[MONTANT TVA]] -> 265000 | T16: =+IF(OR(AND(Tableau222[[#This Row],[DATE_FICHE]]<>"",Tableau222[[#This Row],[DATE_FACTURE]]<>""),AND(Tableau222[[#This Row],[DATE_FICHE]]="",Tableau222[[#This Row],[DATE_FACTURE]]<>"")),Tableau222[[#This Row],[DATE_FACTURE]]+Tableau222[[#This Row],[DELAIS]],IF(AND(Tableau222[[#This Row],[DATE_FICHE]]<>"",Tableau222[[#This Row],[DATE_FACTURE]]=""),Tableau222[[#This Row],[DATE_FICHE]]+Tableau222[[#This Row],[DELAIS]])) -> 45684 | W16: =+Tableau222[[#This Row],[MONTANT TTC]]-Tableau222[[#This Row],[MONTANT PAYÉ (FCFA)]] -> 265000
A17: SIM BETON | C17: 45684 | E17: FD250127-8 | G17: ENGAGEMENT PREVISIONNELLE | I17: GOSSAN P/C ACHI | L17: MAIN ŒUVRE | M17: MO ARMATURIERS EQUIPE YAO DU 10/01 -23/01/25 | N17: USINE MAN | O17: 274000 | P17: 0 | Q17: =+Tableau222[[#This Row],[MONTANT HT]]*Tableau222[[#This Row],[TAUX TVA]] -> 0 | R17: =+Tableau222[[#This Row],[MONTANT HT]]+Tableau222[[#This Row],[MONTANT TVA]] -> 274000 | T17: =+IF(OR(AND(Tableau222[[#This Row],[DATE_FICHE]]<>"",Tableau222[[#This Row],[DATE_FACTURE]]<>""),AND(Tableau222[[#This Row],[DATE_FICHE]]="",Tableau222[[#This Row],[DATE_FACTURE]]<>"")),Tableau222[[#This Row],[DATE_FACTURE]]+Tableau222[[#This Row],[DELAIS]],IF(AND(Tableau222[[#This Row],[DATE_FICHE]]<>"",Tableau222[[#This Row],[DATE_FACTURE]]=""),Tableau222[[#This Row],[DATE_FICHE]]+Tableau222[[#This Row],[DELAIS]])) -> 45684 | W17: =+Tableau222[[#This Row],[MONTANT TTC]]-Tableau222[[#This Row],[MONTANT PAYÉ (FCFA)]] -> 274000
... A27: SIM BETON | C27: 45696 | E27: FD250208-5 | G27: ENGAGEMENT PREVISIONNELLE | I27: KONAN N'DRI | L27: EMPRUNT INTER CO | M27: PRÊT RECU DE TEXTIPRINT | N27: SIM BETON | O27: 500000 | P27: 0 | Q27: =+Tableau222[[#This Row],[MONTANT HT]]*Tableau222[[#This Row],[TAUX TVA]] -> 0 | R27: =+Tableau222[[#This Row],[MONTANT HT]]+Tableau222[[#This Row],[MONTANT TVA]] -> 500000 | T27: =+IF(OR(AND(Tableau222[[#This Row],[DATE_FICHE]]<>"",Tableau222[[#This Row],[DATE_FACTURE]]<>""),AND(Tableau222[[#This Row],[DATE_FICHE]]="",Tableau222[[#This Row],[DATE_FACTURE]]<>"")),Tableau222[[#This Row],[DATE_FACTURE]]+Tableau222[[#This Row],[DELAIS]],IF(AND(Tableau222[[#This Row],[DATE_FICHE]]<>"",Tableau222[[#This Row],[DATE_FACTURE]]=""),Tableau222[[#This Row],[DATE_FICHE]]+Tableau222[[#This Row],[DELAIS]])) -> 45696 | W27: =+Tableau222[[#This Row],[MONTANT TTC]]-Tableau222[[#This Row],[MONTANT PAYÉ (FCFA)]] -> 500000
A28: SIM BETON | C28: 45696 | E28: FD250208-6 | G28: ENGAGEMENT PREVISIONNELLE | I28: GOSSAN | L28: EMPRUNT | M28: EMPRUNT AUPRES DE L ADG | O28: 295000 | P28: 0 | Q28: =+Tableau222[[#This Row],[MONTANT HT]]*Tableau222[[#This Row],[TAUX TVA]] -> 0 | R28: =+Tableau222[[#This Row],[MONTANT HT]]+Tableau222[[#This Row],[MONTANT TVA]] -> 295000 | T28: =+IF(OR(AND(Tableau222[[#This Row],[DATE_FICHE]]<>"",Tableau222[[#This Row],[DATE_FACTURE]]<>""),AND(Tableau222[[#This Row],[DATE_FICHE]]="",Tableau222[[#This Row],[DATE_FACTURE]]<>"")),Tableau222[[#This Row],[DATE_FACTURE]]+Tableau222[[#This Row],[DELAIS]],IF(AND(Tableau222[[#This Row],[DATE_FICHE]]<>"",Tableau222[[#This Row],[DATE_FACTURE]]=""),Tableau222[[#This Row],[DATE_FICHE]]+Tableau222[[#This Row],[DELAIS]])) -> 45696 | W28: =+Tableau222[[#This Row],[MONTANT TTC]]-Tableau222[[#This Row],[MONTANT PAYÉ (FCFA)]] -> 295000
A29: SIM BETON | C29: 45698 | E29: FD250210-1 | G29: ENGAGEMENT PREVISIONNELLE | I29: YEO NOUGNON | L29: TRANSPORT | M29: TRANSPORT DE GRAVIER | N29: SIM BETON | O29: 180000 | P29: 0 | Q29: =+Tableau222[[#This Row],[MONTANT HT]]*Tableau222[[#This Row],[TAUX TVA]] -> 0 | R29: =+Tableau222[[#This Row],[MONTANT HT]]+Tableau222[[#This Row],[MONTANT TVA]] -> 180000 | T29: =+IF(OR(AND(Tableau222[[#This Row],[DATE_FICHE]]<>"",Tableau222[[#This Row],[DATE_FACTURE]]<>""),AND(Tableau222[[#This Row],[DATE_FICHE]]="",Tableau222[[#This Row],[DATE_FACTURE]]<>"")),Tableau222[[#This Row],[DATE_FACTURE]]+Tableau222[[#This Row],[DELAIS]],IF(AND(Tableau222[[#This Row],[DATE_FICHE]]<>"",Tableau222[[#This Row],[DATE_FACTURE]]=""),Tableau222[[#This Row],[DATE_FICHE]]+Tableau222[[#This Row],[DELAIS]])) -> 45698 | W29: =+Tableau222[[#This Row],[MONTANT TTC]]-Tableau222[[#This Row],[MONTANT PAYÉ (FCFA)]] -> 180000
A30: SIM BETON | C30: 45698 | E30: FD250210-2 | G30: ENGAGEMENT PREVISIONNELLE | I30: YEO NOUGNON | L30: ACHAT DE FOURNITURES | M30: FRAIS DE PRODUCTION DU 10/02/2025 AU 15/02/2025 | N30: SIM BETON | O30: 134250 | P30: 0 | Q30: =+Tableau222[[#This Row],[MONTANT HT]]*Tableau222[[#This Row],[TAUX TVA]] -> 0 | R30: =+Tableau222[[#This Row],[MONTANT HT]]+Tableau222[[#This Row],[MONTANT TVA]] -> 134250 | T30: =+IF(OR(AND(Tableau222[[#This Row],[DATE_FICHE]]<>"",Tableau222[[#This Row],[DATE_FACTURE]]<>""),AND(Tableau222[[#This Row],[DATE_FICHE]]="",Tableau222[[#This Row],[DATE_FACTURE]]<>"")),Tableau222[[#This Row],[DATE_FACTURE]]+Tableau222[[#This Row],[DELAIS]],IF(AND(Tableau222[[#This Row],[DATE_FICHE]]<>"",Tableau222[[#This Row],[DATE_FACTURE]]=""),Tableau222[[#This Row],[DATE_FICHE]]+Tableau222[[#This Row],[DELAIS]])) -> 45698 | W30: =+Tableau222[[#This Row],[MONTANT TTC]]-Tableau222[[#This Row],[MONTANT PAYÉ (FCFA)]] -> 134250
A31: SIM BETON | C31: 45698 | E31: FD250210-3 | G31: ENGAGEMENT PREVISIONNELLE | I31: YEO NOUGNON | L31: ACHAT DE FOURNITURES | M31: ACHAT DE VOYAGE DE SABLE | N31: SIM BETON | O31: 300000 | P31: 0 | Q31: =+Tableau222[[#This Row],[MONTANT HT]]*Tableau222[[#This Row],[TAUX TVA]] -> 0 | R31: =+Tableau222[[#This Row],[MONTANT HT]]+Tableau222[[#This Row],[MONTANT TVA]] -> 300000 | T31: =+IF(OR(AND(Tableau222[[#This Row],[DATE_FICHE]]<>"",Tableau222[[#This Row],[DATE_FACTURE]]<>""),AND(Tableau222[[#This Row],[DATE_FICHE]]="",Tableau222[[#This Row],[DATE_FACTURE]]<>"")),Tableau222[[#This Row],[DATE_FACTURE]]+Tableau222[[#This Row],[DELAIS]],IF(AND(Tableau222[[#This Row],[DATE_FICHE]]<>"",Tableau222[[#This Row],[DATE_FACTURE]]=""),Tableau222[[#This Row],[DATE_FICHE]]+Tableau222[[#This Row],[DELAIS]])) -> 45698 | W31: =+Tableau222[[#This Row],[MONTANT TTC]]-Tableau222[[#This Row],[MONTANT PAYÉ (FCFA)]] -> 300000
A32: SIM BETON | C32: 45698 | E32: FD250210-4 | G32: ENGAGEMENT PREVISIONNELLE | I32: YEO NOUGNON | L32: ACHAT DE FOURNITURES | M32: LOCATION GROUPE ELECTROGENE | N32: SIM BETON | O32: 75000 | P32: 0 | Q32: =+Tableau222[[#This Row],[MONTANT HT]]*Tableau222[[#This Row],[TAUX TVA]] -> 0 | R32: =+Tableau222[[#This Row],[MONTANT HT]]+Tableau222[[#This Row],[MONTANT TVA]] -> 75000 | T32: =+IF(OR(AND(Tableau222[[#This Row],[DATE_FICHE]]<>"",Tableau222[[#This Row],[DATE_FACTURE]]<>""),AND(Tableau222[[#This Row],[DATE_FICHE]]="",Tableau222[[#This Row],[DATE_FACTURE]]<>"")),Tableau222[[#This Row],[DATE_FACTURE]]+Tableau222[[#This Row],[DELAIS]],IF(AND(Tableau222[[#This Row],[DATE_FICHE]]<>"",Tableau222[[#This Row],[DATE_FACTURE]]=""),Tableau222[[#This Row],[DATE_FICHE]]+Tableau222[[#This Row],[DELAIS]])) -> 45698 | W32: =+Tableau222[[#This Row],[MONTANT TTC]]-Tableau222[[#This Row],[MONTANT PAYÉ (FCFA)]] -> 75000
A33: SIM BETON | C33: 45698 | E33: FD250210-5 | G33: ENGAGEMENT PREVISIONNELLE | I33: YEO DG | L33: EMPRUNT | M33: EMPRUNT AUPRES DU DG LOCATION ROYAL BEOUIN-BOUAKE | N33: SIM BETON | O33: 250000 | P33: 0 | Q33: =+Tableau222[[#This Row],[MONTANT HT]]*Tableau222[[#This Row],[TAUX TVA]] -> 0 | R33: =+Tableau222[[#This Row],[MONTANT HT]]+Tableau222[[#This Row],[MONTANT TVA]] -> 250000 | T33: =+IF(OR(AND(Tableau222[[#This Row],[DATE_FICHE]]<>"",Tableau222[[#This Row],[DATE_FACTURE]]<>""),AND(Tableau222[[#This Row],[DATE_FICHE]]="",Tableau222[[#This Row],[DATE_FACTURE]]<>"")),Tableau222[[#This Row],[DATE_FACTURE]]+Tableau222[[#This Row],[DELAIS]],IF(AND(Tableau222[[#This Row],[DATE_FICHE]]<>"",Tableau222[[#This Row],[DATE_FACTURE]]=""),Tableau222[[#This Row],[DATE_FICHE]]+Tableau222[[#This Row],[DELAIS]])) -> 45698 | W33: =+Tableau222[[#This Row],[MONTANT TTC]]-Tableau222[[#This Row],[MONTANT PAYÉ (FCFA)]] -> 250000
A34: SIM BETON | C34: 45698 | E34: FD250210-6 | G34: ENGAGEMENT PREVISIONNELLE | I34: AHUI SYNTHIA | L34: ACHAT DE FOURNITURES | M34: FRAIS DE CARBURANT POUR ROYAL | N34: SIM BETON | O34: 230000 | P34: 0 | Q34: =+Tableau222[[#This Row],[MONTANT HT]]*Tableau222[[#This Row],[TAUX TVA]] -> 0 | R34: =+Tableau222[[#This Row],[MONTANT HT]]+Tableau222[[#This Row],[MONTANT TVA]] -> 230000 | T34: =+IF(OR(AND(Tableau222[[#This Row],[DATE_FICHE]]<>"",Tableau222[[#This Row],[DATE_FACTURE]]<>""),AND(Tableau222[[#This Row],[DATE_FICHE]]="",Tableau222[[#This Row],[DATE_FACTURE]]<>"")),Tableau222[[#This Row],[DATE_FACTURE]]+Tableau222[[#This Row],[DELAIS]],IF(AND(Tableau222[[#This Row],[DATE_FICHE]]<>"",Tableau222[[#This Row],[DATE_FACTURE]]=""),Tableau222[[#This Row],[DATE_FICHE]]+Tableau222[[#This Row],[DELAIS]])) -> 45698 | W34: =+Tableau222[[#This Row],[MONTANT TTC]]-Tableau222[[#This Row],[MONTANT PAYÉ (FCFA)]] -> 230000
A35: SIM BETON | C35: 45698 | E35: FD250210-7 | G35: ENGAGEMENT PREVISIONNELLE | I35: BORIS MADOU | L35: ACHAT DE SERVICE | M35: ACHAT DE MO DES ARMATURES | N35: SIM BETON | O35: 100000 | P35: 0 | Q35: =+Tableau222[[#This Row],[MONTANT HT]]*Tableau222[[#This Row],[TAUX TVA]] -> 0 | R35: =+Tableau222[[#This Row],[MONTANT HT]]+Tableau222[[#This Row],[MONTANT TVA]] -> 100000 | T35: =+IF(OR(AND(Tableau222[[#This Row],[DATE_FICHE]]<>"",Tableau222[[#This Row],[DATE_FACTURE]]<>""),AND(Tableau222[[#This Row],[DATE_FICHE]]="",Tableau222[[#This Row],[DATE_FACTURE]]<>"")),Tableau222[[#This Row],[DATE_FACTURE]]+Tableau222[[#This Row],[DELAIS]],IF(AND(Tableau222[[#This Row],[DATE_FICHE]]<>"",Tableau222[[#This Row],[DATE_FACTURE]]=""),Tableau222[[#This Row],[DATE_FICHE]]+Tableau222[[#This Row],[DELAIS]])) -> 45698 | W35: =+Tableau222[[#This Row],[MONTANT TTC]]-Tableau222[[#This Row],[MONTANT PAYÉ (FCFA)]] -> 100000
A36: SIM GROUP | C36: 45698 | D36: 45644 | E36: FD250210-8 | F36: 120 | G36: DETTE REELLE | H36: FOURNISSEUR | I36: KONAN N'DRI | J36: CIE | K36: HG | L36: AUTRES ENERGIES ELECTRICITE | M36: CONSOMMATION ELECTRICITE 04/10/2024 AU 04/12/2024 | N36: SIM GROUP | O36: 322915 | P36: 0.18 | Q36: =+Tableau222[[#This Row],[MONTANT HT]]*Tableau222[[#This Row],[TAUX TVA]] -> 58124.7 | R36: =+Tableau222[[#This Row],[MONTANT HT]]+Tableau222[[#This Row],[MONTANT TVA]] -> 381039.7 | T36: =+IF(OR(AND(Tableau222[[#This Row],[DATE_FICHE]]<>"",Tableau222[[#This Row],[DATE_FACTURE]]<>""),AND(Tableau222[[#This Row],[DATE_FICHE]]="",Tableau222[[#This Row],[DATE_FACTURE]]<>"")),Tableau222[[#This Row],[DATE_FACTURE]]+Tableau222[[#This Row],[DELAIS]],IF(AND(Tableau222[[#This Row],[DATE_FICHE]]<>"",Tableau222[[#This Row],[DATE_FACTURE]]=""),Tableau222[[#This Row],[DATE_FICHE]]+Tableau222[[#This Row],[DELAIS]])) -> 45644 | W36: =+Tableau222[[#This Row],[MONTANT TTC]]-Tableau222[[#This Row],[MONTANT PAYÉ (FCFA)]] -> 381039.7
A37: SIM GROUP | C37: 45698 | D37: 45624 | E37: FD250210-9 | F37: 0211202401 | G37: DETTE REELLE | H37: FOURNISSEUR | I37: KONAN N'DRI | J37: SODECI | K37: HG | L37: AUTRES ENERGIES EAU | M37: CONSOMMATION EAU DES PERIODES DE SEPT, OCT ET NOV 2024 | N37: SIM GROUP | O37: 17875 | P37: 0.18 | Q37: =+Tableau222[[#This Row],[MONTANT HT]]*Tableau222[[#This Row],[TAUX TVA]] -> 3217.5 | R37: =+Tableau222[[#This Row],[MONTANT HT]]+Tableau222[[#This Row],[MONTANT TVA]] -> 21092.5 | T37: =+IF(OR(AND(Tableau222[[#This Row],[DATE_FICHE]]<>"",Tableau222[[#This Row],[DATE_FACTURE]]<>""),AND(Tableau222[[#This Row],[DATE_FICHE]]="",Tableau222[[#This Row],[DATE_FACTURE]]<>"")),Tableau222[[#This Row],[DATE_FACTURE]]+Tableau222[[#This Row],[DELAIS]],IF(AND(Tableau222[[#This Row],[DATE_FICHE]]<>"",Tableau222[[#This Row],[DATE_FACTURE]]=""),Tableau222[[#This Row],[DATE_FICHE]]+Tableau222[[#This Row],[DELAIS]])) -> 45624 | W37: =+Tableau222[[#This Row],[MONTANT TTC]]-Tableau222[[#This Row],[MONTANT PAYÉ (FCFA)]] -> 21092.5
A38: SIM BETON | C38: 45698 | E38: FD250210-10 | G38: ENGAGEMENT PREVISIONNELLE | H38: FOURNISSEUR | I38: KONAN N'DRI | K38: IG | L38: LOCATION | M38: LOCATION DE 02 CAMIONS | N38: SIM GROUP | O38: 350000 | P38: 0 | Q38: =+Tableau222[[#This Row],[MONTANT HT]]*Tableau222[[#This Row],[TAUX TVA]] -> 0 | R38: =+Tableau222[[#This Row],[MONTANT HT]]+Tableau222[[#This Row],[MONTANT TVA]] -> 350000 | T38: =+IF(OR(AND(Tableau222[[#This Row],[DATE_FICHE]]<>"",Tableau222[[#This Row],[DATE_FACTURE]]<>""),AND(Tableau222[[#This Row],[DATE_FICHE]]="",Tableau222[[#This Row],[DATE_FACTURE]]<>"")),Tableau222[[#This Row],[DATE_FACTURE]]+Tableau222[[#This Row],[DELAIS]],IF(AND(Tableau222[[#This Row],[DATE_FICHE]]<>"",Tableau222[[#This Row],[DATE_FACTURE]]=""),Tableau222[[#This Row],[DATE_FICHE]]+Tableau222[[#This Row],[DELAIS]])) -> 45698 | W38: =+Tableau222[[#This Row],[MONTANT TTC]]-Tableau222[[#This Row],[MONTANT PAYÉ (FCFA)]] -> 350000
A39: SIM BETON | C39: 45698 | E39: FD250210-11 | G39: ENGAGEMENT PREVISIONNELLE | I39: TANON ANDRE | L39: FOURNITURE DE BUREAU | M39: CARNET DE BL A 3 FEUILLETS | N39: SIM BETON | O39: 82600 | P39: 0 | Q39: =+Tableau222[[#This Row],[MONTANT HT]]*Tableau222[[#This Row],[TAUX TVA]] -> 0 | R39: =+Tableau222[[#This Row],[MONTANT HT]]+Tableau222[[#This Row],[MONTANT TVA]] -> 82600 | T39: =+IF(OR(AND(Tableau222[[#This Row],[DATE_FICHE]]<>"",Tableau222[[#This Row],[DATE_FACTURE]]<>""),AND(Tableau222[[#This Row],[DATE_FICHE]]="",Tableau222[[#This Row],[DATE_FACTURE]]<>"")),Tableau222[[#This Row],[DATE_FACTURE]]+Tableau222[[#This Row],[DELAIS]],IF(AND(Tableau222[[#This Row],[DATE_FICHE]]<>"",Tableau222[[#This Row],[DATE_FACTURE]]=""),Tableau222[[#This Row],[DATE_FICHE]]+Tableau222[[#This Row],[DELAIS]])) -> 45698 | W39: =+Tableau222[[#This Row],[MONTANT TTC]]-Tableau222[[#This Row],[MONTANT PAYÉ (FCFA)]] -> 82600
A40: SINERGIE RESEAU | B40: 45706 | C40: 45575 | E40: FD241010-1 | G40: ENGAGEMENT PREVISIONNELLE | H40: PERSONNEL | I40: GBANHOUN SANDRINE | J40: M YEO SOULEYMANE | K40: IG | L40: ACHAT DE SERVICE | M40: PRESTATION D'IMPLANTATION DE PBA DU 10/10/2024 | N40: CIC SAN PEDRO | O40: 200000 | P40: 0 | Q40: =+Tableau222[[#This Row],[MONTANT HT]]*Tableau222[[#This Row],[TAUX TVA]] -> 0 | R40: =+Tableau222[[#This Row],[MONTANT HT]]+Tableau222[[#This Row],[MONTANT TVA]] -> 200000 | T40: =+IF(OR(AND(Tableau222[[#This Row],[DATE_FICHE]]<>"",Tableau222[[#This Row],[DATE_FACTURE]]<>""),AND(Tableau222[[#This Row],[DATE_FICHE]]="",Tableau222[[#This Row],[DATE_FACTURE]]<>"")),Tableau222[[#This Row],[DATE_FACTURE]]+Tableau222[[#This Row],[DELAIS]],IF(AND(Tableau222[[#This Row],[DATE_FICHE]]<>"",Tableau222[[#This Row],[DATE_FACTURE]]=""),Tableau222[[#This Row],[DATE_FICHE]]+Tableau222[[#This Row],[DELAIS]])) -> 45575 | W40: =+Tableau222[[#This Row],[MONTANT TTC]]-Tableau222[[#This Row],[MONTANT PAYÉ (FCFA)]] -> 200000
A41: SIM BETON | C41: 45618 | E41: FD241122-1 | G41: ENGAGEMENT PREVISIONNELLE | I41: DOSSO MEDJOUA | K41: HG | L41: ACHAT DE SERVICE | M41: FOURNITURES ET CORRECTION DE MOULE | N41: USINE ABJ | O41: 13180000 | P41: 0 | Q41: =+Tableau222[[#This Row],[MONTANT HT]]*Tableau222[[#This Row],[TAUX TVA]] -> 0 | R41: =+Tableau222[[#This Row],[MONTANT HT]]+Tableau222[[#This Row],[MONTANT TVA]] -> 13180000 | T41: =+IF(OR(AND(Tableau222[[#This Row],[DATE_FICHE]]<>"",Tableau222[[#This Row],[DATE_FACTURE]]<>""),AND(Tableau222[[#This Row],[DATE_FICHE]]="",Tableau222[[#This Row],[DATE_FACTURE]]<>"")),Tableau222[[#This Row],[DATE_FACTURE]]+Tableau222[[#This Row],[DELAIS]],IF(AND(Tableau222[[#This Row],[DATE_FICHE]]<>"",Tableau222[[#This Row],[DATE_FACTURE]]=""),Tableau222[[#This Row],[DATE_FICHE]]+Tableau222[[#This Row],[DELAIS]])) -> 45618 | W41: =+Tableau222[[#This Row],[MONTANT TTC]]-Tableau222[[#This Row],[MONTANT PAYÉ (FCFA)]] -> 13180000
A42: SIM GROUP | B42: 45706 | D42: 45061 | F42: 0009 | G42: DETTE REELLE | H42: FOURNISSEUR | J42: EM'NISS CREATIV | K42: HG | L42: ACHAT DE SERVICE | M42: COMMUNITY MANAGEMENT MENSUEL | N42: SIM GROUP | O42: 225000 | P42: 0 | Q42: =+Tableau222[[#This Row],[MONTANT HT]]*Tableau222[[#This Row],[TAUX TVA]] -> 0 | R42: =+Tableau222[[#This Row],[MONTANT HT]]+Tableau222[[#This Row],[MONTANT TVA]] -> 225000 | T42: =+IF(OR(AND(Tableau222[[#This Row],[DATE_FICHE]]<>"",Tableau222[[#This Row],[DATE_FACTURE]]<>""),AND(Tableau222[[#This Row],[DATE_FICHE]]="",Tableau222[[#This Row],[DATE_FACTURE]]<>"")),Tableau222[[#This Row],[DATE_FACTURE]]+Tableau222[[#This Row],[DELAIS]],IF(AND(Tableau222[[#This Row],[DATE_FICHE]]<>"",Tableau222[[#This Row],[DATE_FACTURE]]=""),Tableau222[[#This Row],[DATE_FICHE]]+Tableau222[[#This Row],[DELAIS]])) -> 45061 | V42: 225000 | W42: =+Tableau222[[#This Row],[MONTANT TTC]]-Tableau222[[#This Row],[MONTANT PAYÉ (FCFA)]] -> 0
A43: SIM GROUP | B43: 45706 | D43: 45121 | F43: 0013 | G43: DETTE REELLE | H43: FOURNISSEUR | J43: EM'NISS CREATIV | K43: HG | L43: ACHAT DE SERVICE | M43: COMMUNITY MANAGEMENT MENSUEL | N43: SIM GROUP | O43: 500000 | P43: 0 | Q43: =+Tableau222[[#This Row],[MONTANT HT]]*Tableau222[[#This Row],[TAUX TVA]] -> 0 | R43: =+Tableau222[[#This Row],[MONTANT HT]]+Tableau222[[#This Row],[MONTANT TVA]] -> 500000 | T43: =+IF(OR(AND(Tableau222[[#This Row],[DATE_FICHE]]<>"",Tableau222[[#This Row],[DATE_FACTURE]]<>""),AND(Tableau222[[#This Row],[DATE_FICHE]]="",Tableau222[[#This Row],[DATE_FACTURE]]<>"")),Tableau222[[#This Row],[DATE_FACTURE]]+Tableau222[[#This Row],[DELAIS]],IF(AND(Tableau222[[#This Row],[DATE_FICHE]]<>"",Tableau222[[#This Row],[DATE_FACTURE]]=""),Tableau222[[#This Row],[DATE_FICHE]]+Tableau222[[#This Row],[DELAIS]])) -> 45121 | V43: 500000 | W43: =+Tableau222[[#This Row],[MONTANT TTC]]-Tableau222[[#This Row],[MONTANT PAYÉ (FCFA)]] -> 0
A44: SIM GROUP | B44: 45706 | D44: 45121 | F44: 0012 | G44: DETTE REELLE | H44: FOURNISSEUR | J44: EM'NISS CREATIV | K44: HG | L44: ACHAT DE SERVICE | M44: COMMUNITY MANAGEMENT MENSUEL | N44: SIM GROUP | O44: 500000 | P44: 0 | Q44: =+Tableau222[[#This Row],[MONTANT HT]]*Tableau222[[#This Row],[TAUX TVA]] -> 0 | R44: =+Tableau222[[#This Row],[MONTANT HT]]+Tableau222[[#This Row],[MONTANT TVA]] -> 500000 | T44: =+IF(OR(AND(Tableau222[[#This Row],[DATE_FICHE]]<>"",Tableau222[[#This Row],[DATE_FACTURE]]<>""),AND(Tableau222[[#This Row],[DATE_FICHE]]="",Tableau222[[#This Row],[DATE_FACTURE]]<>"")),Tableau222[[#This Row],[DATE_FACTURE]]+Tableau222[[#This Row],[DELAIS]],IF(AND(Tableau222[[#This Row],[DATE_FICHE]]<>"",Tableau222[[#This Row],[DATE_FACTURE]]=""),Tableau222[[#This Row],[DATE_FICHE]]+Tableau222[[#This Row],[DELAIS]])) -> 45121 | V44: 500000 | W44: =+Tableau222[[#This Row],[MONTANT TTC]]-Tableau222[[#This Row],[MONTANT PAYÉ (FCFA)]] -> 0
A45: SIM GROUP | B45: 45706 | D45: 45152 | F45: 0015 | G45: DETTE REELLE | H45: FOURNISSEUR | J45: EM'NISS CREATIV | K45: HG | L45: ACHAT DE SERVICE | M45: COMMUNICATION DIGITAL MENSUEL AOUT 2023 | N45: SIM GROUP | O45: 600000 | P45: 0 | Q45: =+Tableau222[[#This Row],[MONTANT HT]]*Tableau222[[#This Row],[TAUX TVA]] -> 0 | R45: =+Tableau222[[#This Row],[MONTANT HT]]+Tableau222[[#This Row],[MONTANT TVA]] -> 600000 | T45: =+IF(OR(AND(Tableau222[[#This Row],[DATE_FICHE]]<>"",Tableau222[[#This Row],[DATE_FACTURE]]<>""),AND(Tableau222[[#This Row],[DATE_FICHE]]="",Tableau222[[#This Row],[DATE_FACTURE]]<>"")),Tableau222[[#This Row],[DATE_FACTURE]]+Tableau222[[#This Row],[DELAIS]],IF(AND(Tableau222[[#This Row],[DATE_FICHE]]<>"",Tableau222[[#This Row],[DATE_FACTURE]]=""),Tableau222[[#This Row],[DATE_FICHE]]+Tableau222[[#This Row],[DELAIS]])) -> 45152 | V45: 275000 | W45: =+Tableau222[[#This Row],[MONTANT TTC]]-Tableau222[[#This Row],[MONTANT PAYÉ (FCFA)]] -> 325000
A46: SIM GROUP | B46: 45706 | D46: 45180 | F46: 0016 | G46: DETTE REELLE | H46: FOURNISSEUR | J46: EM'NISS CREATIV | K46: HG | L46: ACHAT DE SERVICE | M46: COMMUNICATION DIGITAL MENSUEL SEPTEMBRE 2023 | N46: SIM GROUP | O46: 500000 | P46: 0 | Q46: =+Tableau222[[#This Row],[MONTANT HT]]*Tableau222[[#This Row],[TAUX TVA]] -> 0 | R46: =+Tableau222[[#This Row],[MONTANT HT]]+Tableau222[[#This Row],[MONTANT TVA]] -> 500000 | T46: =+IF(OR(AND(Tableau222[[#This Row],[DATE_FICHE]]<>"",Tableau222[[#This Row],[DATE_FACTURE]]<>""),AND(Tableau222[[#This Row],[DATE_FICHE]]="",Tableau222[[#This Row],[DATE_FACTURE]]<>"")),Tableau222[[#This Row],[DATE_FACTURE]]+Tableau222[[#This Row],[DELAIS]],IF(AND(Tableau222[[#This Row],[DATE_FICHE]]<>"",Tableau222[[#This Row],[DATE_FACTURE]]=""),Tableau222[[#This Row],[DATE_FICHE]]+Tableau222[[#This Row],[DELAIS]])) -> 45180 | W46: =+Tableau222[[#This Row],[MONTANT TTC]]-Tableau222[[#This Row],[MONTANT PAYÉ (FCFA)]] -> 500000
A47: SIM GROUP | B47: 45706 | D47: 45210 | F47: 0021 | G47: DETTE REELLE | H47: FOURNISSEUR | J47: EM'NISS CREATIV | K47: HG | L47: ACHAT DE SERVICE | M47: COMMUNICATION DIGITAL MENSUEL OCTOBRE 2023 | N47: SIM GROUP | O47: 500000 | P47: 0 | Q47: =+Tableau222[[#This Row],[MONTANT HT]]*Tableau222[[#This Row],[TAUX TVA]] -> 0 | R47: =+Tableau222[[#This Row],[MONTANT HT]]+Tableau222[[#This Row],[MONTANT TVA]] -> 500000 | T47: =+IF(OR(AND(Tableau222[[#This Row],[DATE_FICHE]]<>"",Tableau222[[#This Row],[DATE_FACTURE]]<>""),AND(Tableau222[[#This Row],[DATE_FICHE]]="",Tableau222[[#This Row],[DATE_FACTURE]]<>"")),Tableau222[[#This Row],[DATE_FACTURE]]+Tableau222[[#This Row],[DELAIS]],IF(AND(Tableau222[[#This Row],[DATE_FICHE]]<>"",Tableau222[[#This Row],[DATE_FACTURE]]=""),Tableau222[[#This Row],[DATE_FICHE]]+Tableau222[[#This Row],[DELAIS]])) -> 45210 | W47: =+Tableau222[[#This Row],[MONTANT TTC]]-Tableau222[[#This Row],[MONTANT PAYÉ (FCFA)]] -> 500000
A48: SIM GROUP | B48: 45706 | D48: 45239 | F48: 0022 | G48: DETTE REELLE | H48: FOURNISSEUR | J48: EM'NISS CREATIV | K48: HG | L48: ACHAT DE SERVICE | M48: COMMUNICATION DIGITAL MENSUEL NOVEMBRE 2023 | N48: SIM GROUP | O48: 500000 | P48: 0 | Q48: =+Tableau222[[#This Row],[MONTANT HT]]*Tableau222[[#This Row],[TAUX TVA]] -> 0 | R48: =+Tableau222[[#This Row],[MONTANT HT]]+Tableau222[[#This Row],[MONTANT TVA]] -> 500000 | T48: =+IF(OR(AND(Tableau222[[#This Row],[DATE_FICHE]]<>"",Tableau222[[#This Row],[DATE_FACTURE]]<>""),AND(Tableau222[[#This Row],[DATE_FICHE]]="",Tableau222[[#This Row],[DATE_FACTURE]]<>"")),Tableau222[[#This Row],[DATE_FACTURE]]+Tableau222[[#This Row],[DELAIS]],IF(AND(Tableau222[[#This Row],[DATE_FICHE]]<>"",Tableau222[[#This Row],[DATE_FACTURE]]=""),Tableau222[[#This Row],[DATE_FICHE]]+Tableau222[[#This Row],[DELAIS]])) -> 45239 | W48: =+Tableau222[[#This Row],[MONTANT TTC]]-Tableau222[[#This Row],[MONTANT PAYÉ (FCFA)]] -> 500000
A49: SIM GROUP | B49: 45706 | D49: 45239 | F49: 0023 | G49: DETTE REELLE | H49: FOURNISSEUR | J49: EM'NISS CREATIV | K49: HG | L49: ACHAT DE SERVICE | M49: COMMUNICATION DIGITAL MENSUEL DECEMBRE 2023 | N49: SIM GROUP | O49: 500000 | P49: 0 | Q49: =+Tableau222[[#This Row],[MONTANT HT]]*Tableau222[[#This Row],[TAUX TVA]] -> 0 | R49: =+Tableau222[[#This Row],[MONTANT HT]]+Tableau222[[#This Row],[MONTANT TVA]] -> 500000 | T49: =+IF(OR(AND(Tableau222[[#This Row],[DATE_FICHE]]<>"",Tableau222[[#This Row],[DATE_FACTURE]]<>""),AND(Tableau222[[#This Row],[DATE_FICHE]]="",Tableau222[[#This Row],[DATE_FACTURE]]<>"")),Tableau222[[#This Row],[DATE_FACTURE]]+Tableau222[[#This Row],[DELAIS]],IF(AND(Tableau222[[#This Row],[DATE_FICHE]]<>"",Tableau222[[#This Row],[DATE_FACTURE]]=""),Tableau222[[#This Row],[DATE_FICHE]]+Tableau222[[#This Row],[DELAIS]])) -> 45239 | W49: =+Tableau222[[#This Row],[MONTANT TTC]]-Tableau222[[#This Row],[MONTANT PAYÉ (FCFA)]] -> 500000
A50: SIM GROUP | B50: 45706 | D50: 45299 | F50: 0024 | G50: DETTE REELLE | H50: FOURNISSEUR | J50: EM'NISS CREATIV | K50: HG | L50: ACHAT DE SERVICE | M50: COMMUNICATION DIGITAL MENSUEL JANVIER 2024 | N50: SIM GROUP | O50: 500000 | P50: 0 | Q50: =+Tableau222[[#This Row],[MONTANT HT]]*Tableau222[[#This Row],[TAUX TVA]] -> 0 | R50: =+Tableau222[[#This Row],[MONTANT HT]]+Tableau222[[#This Row],[MONTANT TVA]] -> 500000 | T50: =+IF(OR(AND(Tableau222[[#This Row],[DATE_FICHE]]<>"",Tableau222[[#This Row],[DATE_FACTURE]]<>""),AND(Tableau222[[#This Row],[DATE_FICHE]]="",Tableau222[[#This Row],[DATE_FACTURE]]<>"")),Tableau222[[#This Row],[DATE_FACTURE]]+Tableau222[[#This Row],[DELAIS]],IF(AND(Tableau222[[#This Row],[DATE_FICHE]]<>"",Tableau222[[#This Row],[DATE_FACTURE]]=""),Tableau222[[#This Row],[DATE_FICHE]]+Tableau222[[#This Row],[DELAIS]])) -> 45299 | W50: =+Tableau222[[#This Row],[MONTANT TTC]]-Tableau222[[#This Row],[MONTANT PAYÉ (FCFA)]] -> 500000
A51: SIM GROUP | B51: 45706 | D51: 45319 | F51: 0025 | G51: DETTE REELLE | H51: FOURNISSEUR | J51: EM'NISS CREATIV | K51: HG | L51: ACHAT DE SERVICE | M51: RENOUVELLEMENT HEBERGEMENT | N51: SIM GROUP | O51: 100000 | P51: 0 | Q51: =+Tableau222[[#This Row],[MONTANT HT]]*Tableau222[[#This Row],[TAUX TVA]] -> 0 | R51: =+Tableau222[[#This Row],[MONTANT HT]]+Tableau222[[#This Row],[MONTANT TVA]] -> 100000 | T51: =+IF(OR(AND(Tableau222[[#This Row],[DATE_FICHE]]<>"",Tableau222[[#This Row],[DATE_FACTURE]]<>""),AND(Tableau222[[#This Row],[DATE_FICHE]]="",Tableau222[[#This Row],[DATE_FACTURE]]<>"")),Tableau222[[#This Row],[DATE_FACTURE]]+Tableau222[[#This Row],[DELAIS]],IF(AND(Tableau222[[#This Row],[DATE_FICHE]]<>"",Tableau222[[#This Row],[DATE_FACTURE]]=""),Tableau222[[#This Row],[DATE_FICHE]]+Tableau222[[#This Row],[DELAIS]])) -> 45319 | V51: 100000 | W51: =+Tableau222[[#This Row],[MONTANT TTC]]-Tableau222[[#This Row],[MONTANT PAYÉ (FCFA)]] -> 0
A52: SINERGIE RESEAU | B52: 45706 | C52: 45568 | E52: R241003 | G52: DETTE REELLE | H52: PERSONNEL | I52: KOUAME SYLVIE | J52: ESMEL NIKITA | L52: ACHAT DE FOURNITURES | M52: ACHAT CARBURANT POUR LES VEHICULES POUR LA REALISATION DES TRAVAUX DE CAMUSAT | N52: SINERGIE | O52: 15150 | P52: 0 | Q52: =+Tableau222[[#This Row],[MONTANT HT]]*Tableau222[[#This Row],[TAUX TVA]] -> 0 | R52: =+Tableau222[[#This Row],[MONTANT HT]]+Tableau222[[#This Row],[MONTANT TVA]] -> 15150 | T52: =+IF(OR(AND(Tableau222[[#This Row],[DATE_FICHE]]<>"",Tableau222[[#This Row],[DATE_FACTURE]]<>""),AND(Tableau222[[#This Row],[DATE_FICHE]]="",Tableau222[[#This Row],[DATE_FACTURE]]<>"")),Tableau222[[#This Row],[DATE_FACTURE]]+Tableau222[[#This Row],[DELAIS]],IF(AND(Tableau222[[#This Row],[DATE_FICHE]]<>"",Tableau222[[#This Row],[DATE_FACTURE]]=""),Tableau222[[#This Row],[DATE_FICHE]]+Tableau222[[#This Row],[DELAIS]])) -> 45568 | W52: =+Tableau222[[#This Row],[MONTANT TTC]]-Tableau222[[#This Row],[MONTANT PAYÉ (FCFA)]] -> 15150
A53: SINERGIE RESEAU | B53: 45706 | C53: 45569 | G53: DETTE REELLE | H53: PRÊT INERCO | I53: KOUAME SYLVIE | J53: TEXTIRINT | K53: IG | L53: ACHAT DE FOURNITURES | M53: ACHAT DE 10 M, COLLIER, CARBURANT | N53: FTTH | O53: 18000 | P53: 0 | Q53: =+Tableau222[[#This Row],[MONTANT HT]]*Tableau222[[#This Row],[TAUX TVA]] -> 0 | R53: =+Tableau222[[#This Row],[MONTANT HT]]+Tableau222[[#This Row],[MONTANT TVA]] -> 18000 | T53: =+IF(OR(AND(Tableau222[[#This Row],[DATE_FICHE]]<>"",Tableau222[[#This Row],[DATE_FACTURE]]<>""),AND(Tableau222[[#This Row],[DATE_FICHE]]="",Tableau222[[#This Row],[DATE_FACTURE]]<>"")),Tableau222[[#This Row],[DATE_FACTURE]]+Tableau222[[#This Row],[DELAIS]],IF(AND(Tableau222[[#This Row],[DATE_FICHE]]<>"",Tableau222[[#This Row],[DATE_FACTURE]]=""),Tableau222[[#This Row],[DATE_FICHE]]+Tableau222[[#This Row],[DELAIS]])) -> 45569 | W53: =+Tableau222[[#This Row],[MONTANT TTC]]-Tableau222[[#This Row],[MONTANT PAYÉ (FCFA)]] -> 18000
A54: SINERGIE RESEAU | B54: 45706 | C54: 45624 | G54: DETTE REELLE | H54: FOURNISSEUR | I54: KOFFI LAURA | L54: ACHAT DE SERVICE | M54: ACHAT PRESTATION PM DU 28/11/2025 | N54: CIC PM | O54: 117665 | P54: 0 | Q54: =+Tableau222[[#This Row],[MONTANT HT]]*Tableau222[[#This Row],[TAUX TVA]] -> 0 | R54: =+Tableau222[[#This Row],[MONTANT HT]]+Tableau222[[#This Row],[MONTANT TVA]] -> 117665 | T54: =+IF(OR(AND(Tableau222[[#This Row],[DATE_FICHE]]<>"",Tableau222[[#This Row],[DATE_FACTURE]]<>""),AND(Tableau222[[#This Row],[DATE_FICHE]]="",Tableau222[[#This Row],[DATE_FACTURE]]<>"")),Tableau222[[#This Row],[DATE_FACTURE]]+Tableau222[[#This Row],[DELAIS]],IF(AND(Tableau222[[#This Row],[DATE_FICHE]]<>"",Tableau222[[#This Row],[DATE_FACTURE]]=""),Tableau222[[#This Row],[DATE_FICHE]]+Tableau222[[#This Row],[DELAIS]])) -> 45624 | V54: =36360+20000 -> 56360 | W54: =+Tableau222[[#This Row],[MONTANT TTC]]-Tableau222[[#This Row],[MONTANT PAYÉ (FCFA)]] -> 61305
A55: SINERGIE RESEAU | B55: 45706 | C55: 45573 | G55: DETTE REELLE | H55: PRÊT INERCO | I55: KOUAME SYLVIE | J55: TEXTIRINT | K55: IG | L55: ACHAT DE FOURNITURES | M55: ACHAT DE CARBURANT | N55: FTTH | O55: 15000 | P55: 0 | Q55: =+Tableau222[[#This Row],[MONTANT HT]]*Tableau222[[#This Row],[TAUX TVA]] -> 0 | R55: =+Tableau222[[#This Row],[MONTANT HT]]+Tableau222[[#This Row],[MONTANT TVA]] -> 15000 | T55: =+IF(OR(AND(Tableau222[[#This Row],[DATE_FICHE]]<>"",Tableau222[[#This Row],[DATE_FACTURE]]<>""),AND(Tableau222[[#This Row],[DATE_FICHE]]="",Tableau222[[#This Row],[DATE_FACTURE]]<>"")),Tableau222[[#This Row],[DATE_FACTURE]]+Tableau222[[#This Row],[DELAIS]],IF(AND(Tableau222[[#This Row],[DATE_FICHE]]<>"",Tableau222[[#This Row],[DATE_FACTURE]]=""),Tableau222[[#This Row],[DATE_FICHE]]+Tableau222[[#This Row],[DELAIS]])) -> 45573 | W55: =+Tableau222[[#This Row],[MONTANT TTC]]-Tableau222[[#This Row],[MONTANT PAYÉ (FCFA)]] -> 15000
A56: SINERGIE RESEAU | B56: 45706 | C56: 45575 | E56: FD241104-1 | G56: ENGAGEMENT PREVISIONNELLE | H56: PERSONNEL | I56: KOUAME SYLVIE | L56: ACHAT DE SERVICE | M56: ACHAT POUR PRESTATION INFRA FTTH DU 04/11/2024 | N56: CAMUSAT FTTH | O56: 22500 | P56: 0 | Q56: =+Tableau222[[#This Row],[MONTANT HT]]*Tableau222[[#This Row],[TAUX TVA]] -> 0 | R56: =+Tableau222[[#This Row],[MONTANT HT]]+Tableau222[[#This Row],[MONTANT TVA]] -> 22500 | T56: =+IF(OR(AND(Tableau222[[#This Row],[DATE_FICHE]]<>"",Tableau222[[#This Row],[DATE_FACTURE]]<>""),AND(Tableau222[[#This Row],[DATE_FICHE]]="",Tableau222[[#This Row],[DATE_FACTURE]]<>"")),Tableau222[[#This Row],[DATE_FACTURE]]+Tableau222[[#This Row],[DELAIS]],IF(AND(Tableau222[[#This Row],[DATE_FICHE]]<>"",Tableau222[[#This Row],[DATE_FACTURE]]=""),Tableau222[[#This Row],[DATE_FICHE]]+Tableau222[[#This Row],[DELAIS]])) -> 45575 | W56: =+Tableau222[[#This Row],[MONTANT TTC]]-Tableau222[[#This Row],[MONTANT PAYÉ (FCFA)]] -> 22500
A57: SINERGIE RESEAU | B57: 45706 | C57: 45586 | E57: FD241021-1 | G57: ENGAGEMENT PREVISIONNELLE | H57: PERSONNEL | I57: KOUAME SYLVIE | J57: MME TIKANA | L57: ACHAT DE SERVICE | M57: TRANSPORT ALLER PAR YANGO CARGO POUR PRESTATION | N57: CAMUSAT FTTH | O57: 15000 | P57: 0 | Q57: =+Tableau222[[#This Row],[MONTANT HT]]*Tableau222[[#This Row],[TAUX TVA]] -> 0 | R57: =+Tableau222[[#This Row],[MONTANT HT]]+Tableau222[[#This Row],[MONTANT TVA]] -> 15000 | T57: =+IF(OR(AND(Tableau222[[#This Row],[DATE_FICHE]]<>"",Tableau222[[#This Row],[DATE_FACTURE]]<>""),AND(Tableau222[[#This Row],[DATE_FICHE]]="",Tableau222[[#This Row],[DATE_FACTURE]]<>"")),Tableau222[[#This Row],[DATE_FACTURE]]+Tableau222[[#This Row],[DELAIS]],IF(AND(Tableau222[[#This Row],[DATE_FICHE]]<>"",Tableau222[[#This Row],[DATE_FACTURE]]=""),Tableau222[[#This Row],[DATE_FICHE]]+Tableau222[[#This Row],[DELAIS]])) -> 45586 | V57: 7000 | W57: =+Tableau222[[#This Row],[MONTANT TTC]]-Tableau222[[#This Row],[MONTANT PAYÉ (FCFA)]] -> 8000
A58: SINERGIE RESEAU | C58: 45586 | E58: FD241021-2 | G58: ENGAGEMENT PREVISIONNELLE | I58: TIKANA FATIMA | L58: ACHAT DE SERVICE | M58: ACHAT POUR PRESTATION PM DU 21/10/24 | N58: CIC PM | O58: 128000 | P58: 0 | Q58: =+Tableau222[[#This Row],[MONTANT HT]]*Tableau222[[#This Row],[TAUX TVA]] -> 0 | R58: =+Tableau222[[#This Row],[MONTANT HT]]+Tableau222[[#This Row],[MONTANT TVA]] -> 128000 | T58: =+IF(OR(AND(Tableau222[[#This Row],[DATE_FICHE]]<>"",Tableau222[[#This Row],[DATE_FACTURE]]<>""),AND(Tableau222[[#This Row],[DATE_FICHE]]="",Tableau222[[#This Row],[DATE_FACTURE]]<>"")),Tableau222[[#This Row],[DATE_FACTURE]]+Tableau222[[#This Row],[DELAIS]],IF(AND(Tableau222[[#This Row],[DATE_FICHE]]<>"",Tableau222[[#This Row],[DATE_FACTURE]]=""),Tableau222[[#This Row],[DATE_FICHE]]+Tableau222[[#This Row],[DELAIS]])) -> 45586 | W58: =+Tableau222[[#This Row],[MONTANT TTC]]-Tableau222[[#This Row],[MONTANT PAYÉ (FCFA)]] -> 128000
A59: SINERGIE RESEAU | C59: 45596 | E59: FD241031-3 | G59: ENGAGEMENT PREVISIONNELLE | I59: KOFFI LAURA | L59: ACHAT DE SERVICE | M59: ACHAT DE PRESTATION PM DU 31/10/24 | N59: CIC PM | O59: 115000 | P59: 0 | Q59: =+Tableau222[[#This Row],[MONTANT HT]]*Tableau222[[#This Row],[TAUX TVA]] -> 0 | R59: =+Tableau222[[#This Row],[MONTANT HT]]+Tableau222[[#This Row],[MONTANT TVA]] -> 115000 | T59: =+IF(OR(AND(Tableau222[[#This Row],[DATE_FICHE]]<>"",Tableau222[[#This Row],[DATE_FACTURE]]<>""),AND(Tableau222[[#This Row],[DATE_FICHE]]="",Tableau222[[#This Row],[DATE_FACTURE]]<>"")),Tableau222[[#This Row],[DATE_FACTURE]]+Tableau222[[#This Row],[DELAIS]],IF(AND(Tableau222[[#This Row],[DATE_FICHE]]<>"",Tableau222[[#This Row],[DATE_FACTURE]]=""),Tableau222[[#This Row],[DATE_FICHE]]+Tableau222[[#This Row],[DELAIS]])) -> 45596 | W59: =+Tableau222[[#This Row],[MONTANT TTC]]-Tableau222[[#This Row],[MONTANT PAYÉ (FCFA)]] -> 115000
A60: SINERGIE RESEAU | C60: 45617 | E60: FD241121-1 | G60: ENGAGEMENT PREVISIONNELLE | I60: KOFFI LAURA | L60: ACHAT DE SERVICE | M60: ACHAT DE PRESTATION PM DU 21/11/24 | N60: CIC PM | O60: 36000 | P60: 0 | Q60: =+Tableau222[[#This Row],[MONTANT HT]]*Tableau222[[#This Row],[TAUX TVA]] -> 0 | R60: =+Tableau222[[#This Row],[MONTANT HT]]+Tableau222[[#This Row],[MONTANT TVA]] -> 36000 | T60: =+IF(OR(AND(Tableau222[[#This Row],[DATE_FICHE]]<>"",Tableau222[[#This Row],[DATE_FACTURE]]<>""),AND(Tableau222[[#This Row],[DATE_FICHE]]="",Tableau222[[#This Row],[DATE_FACTURE]]<>"")),Tableau222[[#This Row],[DATE_FACTURE]]+Tableau222[[#This Row],[DELAIS]],IF(AND(Tableau222[[#This Row],[DATE_FICHE]]<>"",Tableau222[[#This Row],[DATE_FACTURE]]=""),Tableau222[[#This Row],[DATE_FICHE]]+Tableau222[[#This Row],[DELAIS]])) -> 45617 | W60: =+Tableau222[[#This Row],[MONTANT TTC]]-Tableau222[[#This Row],[MONTANT PAYÉ (FCFA)]] -> 36000
A61: SIGIB | C61: 45609 | E61: FD241113-1 | G61: ENGAGEMENT PREVISIONNELLE | I61: KONAN N'DRI | L61: FOURNITURE DE BUREAU | M61: ACHAT DE FACTURE NORMALISE | N61: SIGIB | O61: 218300 | P61: 0 | Q61: =+Tableau222[[#This Row],[MONTANT HT]]*Tableau222[[#This Row],[TAUX TVA]] -> 0 | R61: =+Tableau222[[#This Row],[MONTANT HT]]+Tableau222[[#This Row],[MONTANT TVA]] -> 218300 | T61: =+IF(OR(AND(Tableau222[[#This Row],[DATE_FICHE]]<>"",Tableau222[[#This Row],[DATE_FACTURE]]<>""),AND(Tableau222[[#This Row],[DATE_FICHE]]="",Tableau222[[#This Row],[DATE_FACTURE]]<>"")),Tableau222[[#This Row],[DATE_FACTURE]]+Tableau222[[#This Row],[DELAIS]],IF(AND(Tableau222[[#This Row],[DATE_FICHE]]<>"",Tableau222[[#This Row],[DATE_FACTURE]]=""),Tableau222[[#This Row],[DATE_FICHE]]+Tableau222[[#This Row],[DELAIS]])) -> 45609 | W61: =+Tableau222[[#This Row],[MONTANT TTC]]-Tableau222[[#This Row],[MONTANT PAYÉ (FCFA)]] -> 218300
A62: SINERGIE RESEAU | C62: 45573 | E62: FD241008-1 | G62: ENGAGEMENT PREVISIONNELLE | I62: KONAN N'DRI | L62: TRANSPORT | M62: TRANSPORT POUR LE RETRAIT DU BC N° 004 CIC | N62: SINERGIE | O62: 3500 | P62: 0 | Q62: =+Tableau222[[#This Row],[MONTANT HT]]*Tableau222[[#This Row],[TAUX TVA]] -> 0 | R62: =+Tableau222[[#This Row],[MONTANT HT]]+Tableau222[[#This Row],[MONTANT TVA]] -> 3500 | T62: =+IF(OR(AND(Tableau222[[#This Row],[DATE_FICHE]]<>"",Tableau222[[#This Row],[DATE_FACTURE]]<>""),AND(Tableau222[[#This Row],[DATE_FICHE]]="",Tableau222[[#This Row],[DATE_FACTURE]]<>"")),Tableau222[[#This Row],[DATE_FACTURE]]+Tableau222[[#This Row],[DELAIS]],IF(AND(Tableau222[[#This Row],[DATE_FICHE]]<>"",Tableau222[[#This Row],[DATE_FACTURE]]=""),Tableau222[[#This Row],[DATE_FICHE]]+Tableau222[[#This Row],[DELAIS]])) -> 45573 | W62: =+Tableau222[[#This Row],[MONTANT TTC]]-Tableau222[[#This Row],[MONTANT PAYÉ (FCFA)]] -> 3500
